Workbook

Sheet Справочники
A1: Справочники для выпадающих списков и шкал
A2: Используются на расчетных листах для унификации классификации, оценок и статусов.
A3: Шкала_1_5 | B3: Сегменты | C3: Тип_проблемы | D3: Тип_ценности | E3: Тип_ЦП | F3: Тип_цифрового_товара | G3: Единица_монетизации | H3: Периодичность | I3: Статус | J3: Да_нет | K3: Элемент_БМ | L3: Решение_проверки | M3: Приоритет
A4: 1 | B4: B2B | C4: Функциональная | D4: Экономия времени | E4: Устранение боли | F4: Веб-сервис | G4: Пользователь | H4: Разово | I4: Черновик | J4: Да | K4: Клиентские сегменты | L4: Проходят проверку | M4: Критический
A5: 2 | B5: B2C | C5: Экономическая | D5: Снижение затрат | E5: Усиление результата | F5: Мобильное приложение | G5: Рабочее место | H5: Ежемесячно | I5: Нужно дополнить | J5: Нет | K5: Ценностное предложение | L5: Требуется доработка | M5: Высокий
A6: 3 | B6: B2B2C | C6: Организационная | D6: Снижение риска | E6: Повышение удобства | F6: Личный кабинет | G6: Транзакция | H6: Ежеквартально | I6: Готово | K6: Каналы | L6: Недостаточно данных | M6: Средний
A7: 4 | B7: Государственный сектор | C7: Информационная | D7: Повышение точности | E7: Автоматизация процесса | F7: Платформа | G7: Проект | H7: Ежегодно | I7: Отклонить | K7: Отношения с клиентами | M7: Низкий
A8: 5 | B8: Смешанный сегмент | C8: Эмоциональная | D8: Рост дохода | E8: Новая возможность | F8: Расширение/модуль | G8: Объем данных | H8: По использованию | K8: Потоки доходов
C9: Техническая | D9: Контроль и прозрачность | E9: Дифференциация | F9: Прикладной программный интерфейс | G9: Операция | H9: Подписка | K9: Ключевые ресурсы
C10: Правовая/регуляторная | D10: Доступность | E10: Снижение барьера входа | F10: Цифровой контент | G10: Пакет функций | H10: Комиссия | K10: Ключевые виды деятельности
D11: Персонализация | F11: Аналитический сервис | G11: Результат/отчет | H11: Смешанная модель | K11: Ключевые партнеры
F12: Маркетплейс | G12: Доступ к аудитории | K12: Структура затрат

Sheet Инструкция
A1: Excel-шаблон к методике формулирования ценностного предложения и цифрового товара
A2: Книга предназначена для перехода от анализа проблем и конкурентов к проверяемому ценностному предложению, цифровому товару и единице монетизации.
A4: Раздел | B4: Что заполняется | C4: Результат
A5: 1. Исходные данные | B5: Фиксируются источники: отзывы, сайты конкурентов, страницы тарифов, описания функций, кейсы, часто задаваемые вопросы. | C5: Контролируемая база доказательств.
A6: 2. Проблемы клиентов | B6: Каждая проблема оценивается по частоте, интенсивности, срочности, незакрытости конкурентами, готовности платить и доказательности. | C6: Рейтинг проблем для выбора опорной проблемы.
A7: 3. Конкурентные решения | B7: По каждому конкуренту фиксируется, как он закрывает проблему и насколько убедительно оформляет свое решение. | C7: Понимание рыночного стандарта и пробелов.
A8: 4. Ценностные предложения | B8: Для выбранных проблем формулируется обещаемый результат, разрыв рынка и итоговая формулировка ценностного предложения. | C8: Готовая формула ценности для клиента.
A9: 5. Цифровой товар | B9: Ценностное предложение переводится в состав цифрового товара: функции, данные, сценарии использования и условия доступа. | C9: Проверяемое описание товара как носителя ценности.
A10: 6. Единица монетизации | B10: Определяется, за что именно платит клиент: пользователь, доступ, транзакция, операция, объем данных, результат, пакет функций. | C10: Экономическая единица бизнес-модели.
A11: 7. Связь с бизнес-моделью | B11: Проверяется, как товар и ценность связаны с клиентами, каналами, отношениями, ресурсами, доходами и затратами. | C11: Согласованная бизнес-модель.
A12: 8. Проверка связности | B12: Оценивается, не разорвана ли цепочка: проблема → ценность → товар → монетизация → бизнес-модель. | C12: Итоговое решение о готовности концепции.

Sheet Исходные данные
A1: Исходные данные анализа
A2: Единый реестр источников, на основании которых выделяются проблемы, конкурентные решения и признаки ценности.
A4: ID источника | B4: Дата сбора | C4: Тип источника | D4: Площадка/сайт | E4: Компания/товар | F4: Ссылка | G4: Фрагмент факта | H4: Какая проблема/решение подтверждается | I4: Достоверность 1–5 | J4: Комментарий
A5: SRC-001 | B5: 46282 | C5: Сайт конкурента | D5: plantuml.com | E5: PlantUML | F5: https://plantuml.com | G5: Бесплатный open-source DSL; цитата «No server. No tokens. No tracking»; UML, C4 частично; профилей IDEF0/IDEF3/DFD нет | H5: P-001: DaC-инструменты не покрывают структурные нотации | I5: 5 | J5: ЛР5, разд. 2
A6: SRC-002 | B6: 46282 | C6: Описание функций | D6: mermaid.js.org | E6: Mermaid | F6: https://mermaid.js.org | G6: Типы: flowchart, sequence, class, state, ER, Gantt, pie, git-graph; нативный рендер в GitHub/GitLab/Notion; IDEF нет | H6: P-001, P-007: рыночный стандарт «текст → диаграмма», нет IDEF/DFD | I6: 5 | J6: ЛР5, разд. 2
A7: SRC-003 | B7: 46282 | C7: Тарифы | D7: eraser.io/pricing | E7: Eraser.io | F7: https://www.eraser.io/pricing | G7: Free $0 → Starter $15–20 → Business $45–60 → Enterprise; AI-кредиты 3 → 40 → 250 → ∞ | H7: Единица монетизации рынка: подписка за место + лимит AI | I7: 5 | J7: ЛР5, разд. 2
A8: SRC-004 | B8: 46282 | C8: Описание функций | D8: eraser.io/ai-diagrams | E8: Eraser.io | F8: https://www.eraser.io/product/ai-diagrams | G8: Diagram-as-code + AI-генерация + канвас; история версий 90 дней → безлимит по тарифу | H8: P-003, P-005: история и AI как платные признаки | I8: 5 | J8: ЛР5, разд. 3
A9: SRC-005 | B9: 46288 | C9: Сайт конкурента | D9: d2lang.com | E9: D2 | F9: https://d2lang.com | G9: «A modern language that turns text to diagrams»; open-source, донаты Hack Club; UML class/sequence | H9: P-001: DaC без IDEF/DFD | I9: 5 | J9: ЛР5, разд. 2
A10: SRC-006 | B10: 46288 | C10: Сайт конкурента | D10: drawio.com | E10: draw.io | F10: https://www.drawio.com | G10: «No account required. No credit card»; open source Apache 2.0; GUI-ввод, проверка правил нотаций не заявлена | H10: P-001: графический редактор не проверяет правила нотации | I10: 4 | J10: Отсутствие функции — косвенный вывод
A11: SRC-007 | B11: 46288 | C11: Документация | D11: drawio.com/integrations | E11: draw.io | F11: https://www.drawio.com/integrations | G11: Интеграции: Google Drive, OneDrive, Confluence/Jira, GitHub, VS Code, Notion | H11: Рыночный стандарт: хранение во внешних сервисах | I11: 5 | J11: ЛР5, разд. 2
A12: SRC-008 | B12: 46282 | C12: Сообщество | D12: SimilarWeb | E12: PlantUML | F12: https://www.similarweb.com/website/plantuml.com | G12: ~507 тыс. визитов за период; Россия — 9,07 % трафика (1-е место среди стран) | H12: Русскоязычная аудитория DaC существует | I12: 4 | J12: ЛР2-3, разд. 2
A13: SRC-009 | B13: 46288 | C13: Сообщество | D13: SimilarWeb | E13: Eraser.io / draw.io | F13: https://www.similarweb.com | G13: eraser.io — 678,5 тыс. визитов; app.diagrams.net — 7,8 млн визитов | H13: Масштаб спроса на диаграммные инструменты | I13: 4 | J13: ЛР2-3, разд. 2
A14: SRC-010 | B14: 46282 | C14: Сообщество | D14: Google Trends | E14: PlantUML | F14: https://trends.google.com | G14: Индекс PlantUML 16 → 53 (19.09.2021 → 08.12.2024), рост ≈231 %; запрос «text to diagram ai» — Breakout | H14: Растущий спрос на «текст → диаграмма» и AI | I14: 4 | J14: ЛР1, разд. 3
A15: SRC-011 | B15: 46282 | C15: Описание функций | D15: Обзор аналогов | E15: Ramus / BPwin | F15: E:\VisualDSL-Platform\PROJECT_DOCUMENTATION\06_market_and_extras\00-competitive-analysis.md | G15: IDEF0/IDEF1X/IDEF3 в настольных GUI-средствах; устаревший UX; используются в курсах СНГ | H15: P-004: специализированные CASE ограничены | I15: 3 | J15: Вторичный источник проекта
A16: SRC-012 | B16: 46288 | C16: Документация | D16: Концепция NotaCode | E16: NotaCode | F16: E:\NotaCode\docs\business\01-project-concept.md | G16: Проблемы P-01…P-06: ручная раскладка, нет IDEF в DaC, правила не проверяются, CASE ограничены, нет связи текст↔изображение, нет истории | H16: Перечень проблем для карты проблем | I16: 3 | J16: Внутренний источник; требует подтверждения отзывами
... A18: SRC-014 | B18: 46282 | C18: FAQ | D18: ЛР5: Кано и Левитт | E18: Рынок | F18: ЛР5, разд. 3–5 | G18: Обязательные: DSL, браузерный рендер, GitHub; линейные: история версий; восхищающие: полный охват нотаций, AI | H18: Рыночный стандарт и зона отличия | I18: 4 | J18: ЛР5
A19: SRC-015 | C19: Отзывы | D19: G2 / Capterra / Reddit / Habr | E19: draw.io, Lucidchart, PlantUML, Mermaid, Ramus | F19: 🔲 ДОСНЯТЬ | G19: 🔲 ДОСНЯТЬ: ≥30 отзывов/высказываний о ручной раскладке, проверке правил, IDEF/DFD | H19: Подтверждение P-001…P-008 | J19: Требование методики: ≥30 отзывов
A20: SRC-016 | C20: Отзывы | D20: Опрос студентов (Google Forms) | E20: S-01 | F20: 🔲 ДОСНЯТЬ | G20: 🔲 ДОСНЯТЬ: опрос 20+ студентов ИИТ/ФКП: сколько времени уходит на диаграммы, были ли замечания по нотации | H20: Частота и последствия P-001 | J20: План проверки гипотезы H-01

Sheet Проблемы клиентов
A1: Анализ проблем клиентов
A2: Приоритет проблемы рассчитывается по частоте, интенсивности, срочности, незакрытости конкурентами, готовности платить и доказательности.
A4: ID проблемы | B4: Сегмент | C4: Тип проблемы | D4: Формулировка проблемы клиента | E4: Частота 1–5 | F4: Интенсивность 1–5 | G4: Срочность 1–5 | H4: Незакрытость конкурентами 1–5 | I4: Готовность платить 1–5 | J4: Доказательность 1–5 | K4: Индекс проблемы | L4: Приоритет | M4: Комментарий
A5: P-001 | B5: B2C | C5: Функциональная | D5: Студент технической специальности (S-01) тратит часы на ручное построение диаграмм IDEF0/IDEF3/DFD/ERD/UML и получает замечания за нарушение правил нотации: графические редакторы не проверяют правила, а DaC-инструменты не поддерживают IDEF/DFD | E5: 5 | F5: 5 | G5: 5 | H5: 5 | I5: 2 | J5: 4 | K5: =IF(COUNTA(E5:J5)=0,"",ROUND(((E5*0.18)+(F5*0.22)+(G5*0.18)+(H5*0.2)+(I5*0.14)+(J5*0.08))*20,0)) -> 90 | L5: =IF(K5="","",IF(K5>=80,"Критический",IF(K5>=65,"Высокий",IF(K5>=45,"Средний","Низкий")))) -> Критический | M5: Опорная проблема (интегральная P-01+P-02+P-03 концепции)
A6: P-002 | B6: B2B | C6: Информационная | D6: Аналитик (S-02) держит модели BPMN/IDEF0/DFD отдельно от требований в Git — модель и документация рассинхронизируются | E6: 3 | F6: 4 | G6: 3 | H6: 4 | I6: 4 | J6: 3 | K6: =IF(COUNTA(E6:J6)=0,"",ROUND(((E6*0.18)+(F6*0.22)+(G6*0.18)+(H6*0.2)+(I6*0.14)+(J6*0.08))*20,0)) -> 71 | L6: =IF(K6="","",IF(K6>=80,"Критический",IF(K6>=65,"Высокий",IF(K6>=45,"Средний","Низкий")))) -> Высокий | M6: Сегмент Pro
A7: P-003 | B7: B2B | C7: Техническая | D7: Для диаграмм в бинарных/XML-файлах редакторов нет построчного diff, истории и отката | E7: 3 | F7: 3 | G7: 2 | H7: 3 | I7: 4 | J7: 4 | K7: =IF(COUNTA(E7:J7)=0,"",ROUND(((E7*0.18)+(F7*0.22)+(G7*0.18)+(H7*0.2)+(I7*0.14)+(J7*0.08))*20,0)) -> 61 | L7: =IF(K7="","",IF(K7>=80,"Критический",IF(K7>=65,"Высокий",IF(K7>=45,"Средний","Низкий")))) -> Средний | M7: Частично закрыто Eraser.io (платно)
A8: P-004 | B8: B2C | C8: Экономическая | D8: Специализированные CASE-средства (Ramus, BPwin, Sparx EA) — настольные, платные, с устаревшим UX и без текстового представления | E8: 3 | F8: 3 | G8: 3 | H8: 4 | I8: 3 | J8: 3 | K8: =IF(COUNTA(E8:J8)=0,"",ROUND(((E8*0.18)+(F8*0.22)+(G8*0.18)+(H8*0.2)+(I8*0.14)+(J8*0.08))*20,0)) -> 64 | L8: =IF(K8="","",IF(K8>=80,"Критический",IF(K8>=65,"Высокий",IF(K8>=45,"Средний","Низкий")))) -> Средний
A9: P-005 | B9: B2C | C9: Функциональная | D9: Новичку сложно начать писать диаграмму кодом: нет примеров и подсказок по синтаксису и правилам нотации | E9: 4 | F9: 3 | G9: 4 | H9: 3 | I9: 2 | J9: 3 | K9: =IF(COUNTA(E9:J9)=0,"",ROUND(((E9*0.18)+(F9*0.22)+(G9*0.18)+(H9*0.2)+(I9*0.14)+(J9*0.08))*20,0)) -> 64 | L9: =IF(K9="","",IF(K9>=80,"Критический",IF(K9>=65,"Высокий",IF(K9>=45,"Средний","Низкий")))) -> Средний | M9: Закрывается шаблонами, документацией, AI
A10: P-006 | B10: B2C | C10: Информационная | D10: Неизвестно, какая строка описания соответствует элементу изображения — трудно найти место ошибки | E10: 4 | F10: 2 | G10: 2 | H10: 4 | I10: 2 | J10: 3 | K10: =IF(COUNTA(E10:J10)=0,"",ROUND(((E10*0.18)+(F10*0.22)+(G10*0.18)+(H10*0.2)+(I10*0.14)+(J10*0.08))*20,0)) -> 57 | L10: =IF(K10="","",IF(K10>=80,"Критический",IF(K10>=65,"Высокий",IF(K10>=45,"Средний","Низкий")))) -> Средний | M10: Отличие D-03
A11: P-007 | B11: B2B | C11: Организационная | D11: Архитектору (S-03) приходится держать разные инструменты для разных нотаций и вручную переносить диаграммы между форматами | E11: 3 | F11: 3 | G11: 2 | H11: 4 | I11: 4 | J11: 3 | K11: =IF(COUNTA(E11:J11)=0,"",ROUND(((E11*0.18)+(F11*0.22)+(G11*0.18)+(H11*0.2)+(I11*0.14)+(J11*0.08))*20,0)) -> 63 | L11: =IF(K11="","",IF(K11>=80,"Критический",IF(K11>=65,"Высокий",IF(K11>=45,"Средний","Низкий")))) -> Средний | M11: Экспорт PlantUML/Mermaid/XMI/DDL
A12: P-008 | B12: Смешанный сегмент | C12: Организационная | D12: Преподаватель (S-04) вручную проверяет соблюдение правил нотаций в работах студентов | E12: 3 | F12: 4 | G12: 4 | H12: 4 | I12: 2 | J12: 3 | K12: =IF(COUNTA(E12:J12)=0,"",ROUND(((E12*0.18)+(F12*0.22)+(G12*0.18)+(H12*0.2)+(I12*0.14)+(J12*0.08))*20,0)) -> 69 | L12: =IF(K12="","",IF(K12>=80,"Критический",IF(K12>=65,"Высокий",IF(K12>=45,"Средний","Низкий")))) -> Высокий | M12: Влияющее лицо для S-01
K13: =IF(COUNTA(E13:J13)=0,"",ROUND(((E13*0.18)+(F13*0.22)+(G13*0.18)+(H13*0.2)+(I13*0.14)+(J13*0.08))*20,0)) | L13: =IF(K13="","",IF(K13>=80,"Критический",IF(K13>=65,"Высокий",IF(K13>=45,"Средний","Низкий"))))
K14: =IF(COUNTA(E14:J14)=0,"",ROUND(((E14*0.18)+(F14*0.22)+(G14*0.18)+(H14*0.2)+(I14*0.14)+(J14*0.08))*20,0)) | L14: =IF(K14="","",IF(K14>=80,"Критический",IF(K14>=65,"Высокий",IF(K14>=45,"Средний","Низкий"))))
K15: =IF(COUNTA(E15:J15)=0,"",ROUND(((E15*0.18)+(F15*0.22)+(G15*0.18)+(H15*0.2)+(I15*0.14)+(J15*0.08))*20,0)) | L15: =IF(K15="","",IF(K15>=80,"Критический",IF(K15>=65,"Высокий",IF(K15>=45,"Средний","Низкий"))))
K16: =IF(COUNTA(E16:J16)=0,"",ROUND(((E16*0.18)+(F16*0.22)+(G16*0.18)+(H16*0.2)+(I16*0.14)+(J16*0.08))*20,0)) | L16: =IF(K16="","",IF(K16>=80,"Критический",IF(K16>=65,"Высокий",IF(K16>=45,"Средний","Низкий"))))
K17: =IF(COUNTA(E17:J17)=0,"",ROUND(((E17*0.18)+(F17*0.22)+(G17*0.18)+(H17*0.2)+(I17*0.14)+(J17*0.08))*20,0)) | L17: =IF(K17="","",IF(K17>=80,"Критический",IF(K17>=65,"Высокий",IF(K17>=45,"Средний","Низкий"))))
K18: =IF(COUNTA(E18:J18)=0,"",ROUND(((E18*0.18)+(F18*0.22)+(G18*0.18)+(H18*0.2)+(I18*0.14)+(J18*0.08))*20,0)) | L18: =IF(K18="","",IF(K18>=80,"Критический",IF(K18>=65,"Высокий",IF(K18>=45,"Средний","Низкий"))))
K19: =IF(COUNTA(E19:J19)=0,"",ROUND(((E19*0.18)+(F19*0.22)+(G19*0.18)+(H19*0.2)+(I19*0.14)+(J19*0.08))*20,0)) | L19: =IF(K19="","",IF(K19>=80,"Критический",IF(K19>=65,"Высокий",IF(K19>=45,"Средний","Низкий"))))
K20: =IF(COUNTA(E20:J20)=0,"",ROUND(((E20*0.18)+(F20*0.22)+(G20*0.18)+(H20*0.2)+(I20*0.14)+(J20*0.08))*20,0)) | L20: =IF(K20="","",IF(K20>=80,"Критический",IF(K20>=65,"Высокий",IF(K20>=45,"Средний","Низкий"))))
K21: =IF(COUNTA(E21:J21)=0,"",ROUND(((E21*0.18)+(F21*0.22)+(G21*0.18)+(H21*0.2)+(I21*0.14)+(J21*0.08))*20,0)) | L21: =IF(K21="","",IF(K21>=80,"Критический",IF(K21>=65,"Высокий",IF(K21>=45,"Средний","Низкий"))))
K22: =IF(COUNTA(E22:J22)=0,"",ROUND(((E22*0.18)+(F22*0.22)+(G22*0.18)+(H22*0.2)+(I22*0.14)+(J22*0.08))*20,0)) | L22: =IF(K22="","",IF(K22>=80,"Критический",IF(K22>=65,"Высокий",IF(K22>=45,"Средний","Низкий"))))
K23: =IF(COUNTA(E23:J23)=0,"",ROUND(((E23*0.18)+(F23*0.22)+(G23*0.18)+(H23*0.2)+(I23*0.14)+(J23*0.08))*20,0)) | L23: =IF(K23="","",IF(K23>=80,"Критический",IF(K23>=65,"Высокий",IF(K23>=45,"Средний","Низкий"))))
K24: =IF(COUNTA(E24:J24)=0,"",ROUND(((E24*0.18)+(F24*0.22)+(G24*0.18)+(H24*0.2)+(I24*0.14)+(J24*0.08))*20,0)) | L24: =IF(K24="","",IF(K24>=80,"Критический",IF(K24>=65,"Высокий",IF(K24>=45,"Средний","Низкий"))))
... K104: =IF(COUNTA(E104:J104)=0,"",ROUND(((E104*0.18)+(F104*0.22)+(G104*0.18)+(H104*0.2)+(I104*0.14)+(J104*0.08))*20,0)) | L104: =IF(K104="","",IF(K104>=80,"Критический",IF(K104>=65,"Высокий",IF(K104>=45,"Средний","Низкий"))))

Sheet Конкурентные решения
A1: Анализ конкурентных решений
A2: Лист показывает, какие проблемы конкуренты уже закрывают, где находится рыночный стандарт и где сохраняется пространство для дифференциации.
A4: Компания | B4: Сайт | C4: ID проблемы | D4: Как конкурент решает проблему | E4: Покрытие проблемы 1–5 | F4: Ясность обещания 1–5 | G4: Полнота товара 1–5 | H4: Удобство доступа 1–5 | I4: Доказательность 1–5 | J4: Индекс силы решения | K4: Уровень решения | L4: Комментарий
A5: draw.io | B5: https://www.drawio.com | C5: P-001 | D5: Библиотеки фигур UML/IDEF0/BPMN, ручная раскладка; правила нотаций не проверяются | E5: 2 | F5: 4 | G5: 3 | H5: 5 | I5: 4 | J5: =IF(COUNTA(E5:I5)=0,"",ROUND(((E5*0.25)+(F5*0.2)+(G5*0.2)+(H5*0.15)+(I5*0.2))*20,0)) -> 69 | K5: =IF(J5="","",IF(J5>=80,"Сильное решение",IF(J5>=60,"Рыночный стандарт",IF(J5>=40,"Частичное решение","Слабое решение")))) -> Рыночный стандарт | L5: Близкий конкурент (ЛР5: 67,5)
A6: PlantUML | B6: https://plantuml.com | C6: P-001 | D6: UML из текста с авто-раскладкой; IDEF0/IDEF3/DFD не поддерживаются, правила UML не валидируются | E6: 3 | F6: 4 | G6: 3 | H6: 5 | I6: 5 | J6: =IF(COUNTA(E6:I6)=0,"",ROUND(((E6*0.25)+(F6*0.2)+(G6*0.2)+(H6*0.15)+(I6*0.2))*20,0)) -> 78 | K6: =IF(J6="","",IF(J6>=80,"Сильное решение",IF(J6>=60,"Рыночный стандарт",IF(J6>=40,"Частичное решение","Слабое решение")))) -> Рыночный стандарт | L6: Прямой (ЛР5: 90,0)
A7: Mermaid | B7: https://mermaid.js.org | C7: P-001 | D7: Flowchart/ER/class из текста в Markdown; нет IDEF/DFD | E7: 2 | F7: 4 | G7: 3 | H7: 5 | I7: 5 | J7: =IF(COUNTA(E7:I7)=0,"",ROUND(((E7*0.25)+(F7*0.2)+(G7*0.2)+(H7*0.15)+(I7*0.2))*20,0)) -> 73 | K7: =IF(J7="","",IF(J7>=80,"Сильное решение",IF(J7>=60,"Рыночный стандарт",IF(J7>=40,"Частичное решение","Слабое решение")))) -> Рыночный стандарт | L7: Прямой (ЛР5: 90,0)
A8: Eraser.io | B8: https://www.eraser.io | C8: P-001 | D8: DaC + AI + канвас; нет IDEF/сетей Петри, правила нотаций не проверяются | E8: 3 | F8: 5 | G8: 4 | H8: 4 | I8: 4 | J8: =IF(COUNTA(E8:I8)=0,"",ROUND(((E8*0.25)+(F8*0.2)+(G8*0.2)+(H8*0.15)+(I8*0.2))*20,0)) -> 79 | K8: =IF(J8="","",IF(J8>=80,"Сильное решение",IF(J8>=60,"Рыночный стандарт",IF(J8>=40,"Частичное решение","Слабое решение")))) -> Рыночный стандарт | L8: Прямой (ЛР5: 93,0)
A9: D2 | B9: https://d2lang.com | C9: P-001 | D9: Декларативный DSL, 3 движка раскладки; нет структурных нотаций | E9: 2 | F9: 4 | G9: 3 | H9: 4 | I9: 4 | J9: =IF(COUNTA(E9:I9)=0,"",ROUND(((E9*0.25)+(F9*0.2)+(G9*0.2)+(H9*0.15)+(I9*0.2))*20,0)) -> 66 | K9: =IF(J9="","",IF(J9>=80,"Сильное решение",IF(J9>=60,"Рыночный стандарт",IF(J9>=40,"Частичное решение","Слабое решение")))) -> Рыночный стандарт | L9: Близкий (ЛР5: 79,5)
A10: Ramus Educational | B10: — | C10: P-001 | D10: IDEF0/IDEF3 с правилами методологии, но GUI-десктоп, без текста и Git | E10: 4 | F10: 3 | G10: 3 | H10: 2 | I10: 3 | J10: =IF(COUNTA(E10:I10)=0,"",ROUND(((E10*0.25)+(F10*0.2)+(G10*0.2)+(H10*0.15)+(I10*0.2))*20,0)) -> 62 | K10: =IF(J10="","",IF(J10>=80,"Сильное решение",IF(J10>=60,"Рыночный стандарт",IF(J10>=40,"Частичное решение","Слабое решение")))) -> Рыночный стандарт | L10: Специализированный CASE
A11: Eraser.io | B11: https://www.eraser.io/pricing | C11: P-003 | D11: История версий 90 дней → безлимит на платных тарифах | E11: 4 | F11: 4 | G11: 4 | H11: 4 | I11: 5 | J11: =IF(COUNTA(E11:I11)=0,"",ROUND(((E11*0.25)+(F11*0.2)+(G11*0.2)+(H11*0.15)+(I11*0.2))*20,0)) -> 84 | K11: =IF(J11="","",IF(J11>=80,"Сильное решение",IF(J11>=60,"Рыночный стандарт",IF(J11>=40,"Частичное решение","Слабое решение")))) -> Сильное решение | L11: Платный признак
A12: PlantUML | B12: https://plantuml.com | C12: P-003 | D12: История — только через внешний Git-репозиторий пользователя | E12: 3 | F12: 3 | G12: 3 | H12: 5 | I12: 4 | J12: =IF(COUNTA(E12:I12)=0,"",ROUND(((E12*0.25)+(F12*0.2)+(G12*0.2)+(H12*0.15)+(I12*0.2))*20,0)) -> 70 | K12: =IF(J12="","",IF(J12>=80,"Сильное решение",IF(J12>=60,"Рыночный стандарт",IF(J12>=40,"Частичное решение","Слабое решение")))) -> Рыночный стандарт
A13: draw.io | B13: https://www.drawio.com/integrations | C13: P-003 | D13: Версии через хранилище (Google Drive/Confluence), без построчного diff | E13: 3 | F13: 3 | G13: 3 | H13: 4 | I13: 4 | J13: =IF(COUNTA(E13:I13)=0,"",ROUND(((E13*0.25)+(F13*0.2)+(G13*0.2)+(H13*0.15)+(I13*0.2))*20,0)) -> 67 | K13: =IF(J13="","",IF(J13>=80,"Сильное решение",IF(J13>=60,"Рыночный стандарт",IF(J13>=40,"Частичное решение","Слабое решение")))) -> Рыночный стандарт
A14: Eraser.io | B14: https://www.eraser.io/product/ai-diagrams | C14: P-005 | D14: AI-генерация диаграммы по описанию снижает порог входа | E14: 4 | F14: 5 | G14: 4 | H14: 4 | I14: 4 | J14: =IF(COUNTA(E14:I14)=0,"",ROUND(((E14*0.25)+(F14*0.2)+(G14*0.2)+(H14*0.15)+(I14*0.2))*20,0)) -> 84 | K14: =IF(J14="","",IF(J14>=80,"Сильное решение",IF(J14>=60,"Рыночный стандарт",IF(J14>=40,"Частичное решение","Слабое решение")))) -> Сильное решение | L14: 3 AI-диаграммы на Free
A15: Mermaid | B15: https://mermaid.js.org | C15: P-007 | D15: Нативный рендер в GitHub/GitLab/Notion — один формат для документации | E15: 3 | F15: 4 | G15: 3 | H15: 5 | I15: 5 | J15: =IF(COUNTA(E15:I15)=0,"",ROUND(((E15*0.25)+(F15*0.2)+(G15*0.2)+(H15*0.15)+(I15*0.2))*20,0)) -> 78 | K15: =IF(J15="","",IF(J15>=80,"Сильное решение",IF(J15>=60,"Рыночный стандарт",IF(J15>=40,"Частичное решение","Слабое решение")))) -> Рыночный стандарт
A16: draw.io | B16: https://www.drawio.com | C16: P-006 | D16: Связи «текст ↔ элемент» нет (ввод графический) | E16: 1 | F16: 2 | G16: 1 | H16: 5 | I16: 3 | J16: =IF(COUNTA(E16:I16)=0,"",ROUND(((E16*0.25)+(F16*0.2)+(G16*0.2)+(H16*0.15)+(I16*0.2))*20,0)) -> 44 | K16: =IF(J16="","",IF(J16>=80,"Сильное решение",IF(J16>=60,"Рыночный стандарт",IF(J16>=40,"Частичное решение","Слабое решение")))) -> Частичное решение
J17: =IF(COUNTA(E17:I17)=0,"",ROUND(((E17*0.25)+(F17*0.2)+(G17*0.2)+(H17*0.15)+(I17*0.2))*20,0)) | K17: =IF(J17="","",IF(J17>=80,"Сильное решение",IF(J17>=60,"Рыночный стандарт",IF(J17>=40,"Частичное решение","Слабое решение"))))
J18: =IF(COUNTA(E18:I18)=0,"",ROUND(((E18*0.25)+(F18*0.2)+(G18*0.2)+(H18*0.15)+(I18*0.2))*20,0)) | K18: =IF(J18="","",IF(J18>=80,"Сильное решение",IF(J18>=60,"Рыночный стандарт",IF(J18>=40,"Частичное решение","Слабое решение"))))
J19: =IF(COUNTA(E19:I19)=0,"",ROUND(((E19*0.25)+(F19*0.2)+(G19*0.2)+(H19*0.15)+(I19*0.2))*20,0)) | K19: =IF(J19="","",IF(J19>=80,"Сильное решение",IF(J19>=60,"Рыночный стандарт",IF(J19>=40,"Частичное решение","Слабое решение"))))
J20: =IF(COUNTA(E20:I20)=0,"",ROUND(((E20*0.25)+(F20*0.2)+(G20*0.2)+(H20*0.15)+(I20*0.2))*20,0)) | K20: =IF(J20="","",IF(J20>=80,"Сильное решение",IF(J20>=60,"Рыночный стандарт",IF(J20>=40,"Частичное решение","Слабое решение"))))
J21: =IF(COUNTA(E21:I21)=0,"",ROUND(((E21*0.25)+(F21*0.2)+(G21*0.2)+(H21*0.15)+(I21*0.2))*20,0)) | K21: =IF(J21="","",IF(J21>=80,"Сильное решение",IF(J21>=60,"Рыночный стандарт",IF(J21>=40,"Частичное решение","Слабое решение"))))
J22: =IF(COUNTA(E22:I22)=0,"",ROUND(((E22*0.25)+(F22*0.2)+(G22*0.2)+(H22*0.15)+(I22*0.2))*20,0)) | K22: =IF(J22="","",IF(J22>=80,"Сильное решение",IF(J22>=60,"Рыночный стандарт",IF(J22>=40,"Частичное решение","Слабое решение"))))
J23: =IF(COUNTA(E23:I23)=0,"",ROUND(((E23*0.25)+(F23*0.2)+(G23*0.2)+(H23*0.15)+(I23*0.2))*20,0)) | K23: =IF(J23="","",IF(J23>=80,"Сильное решение",IF(J23>=60,"Рыночный стандарт",IF(J23>=40,"Частичное решение","Слабое решение"))))
J24: =IF(COUNTA(E24:I24)=0,"",ROUND(((E24*0.25)+(F24*0.2)+(G24*0.2)+(H24*0.15)+(I24*0.2))*20,0)) | K24: =IF(J24="","",IF(J24>=80,"Сильное решение",IF(J24>=60,"Рыночный стандарт",IF(J24>=40,"Частичное решение","Слабое решение"))))
J25: =IF(COUNTA(E25:I25)=0,"",ROUND(((E25*0.25)+(F25*0.2)+(G25*0.2)+(H25*0.15)+(I25*0.2))*20,0)) | K25: =IF(J25="","",IF(J25>=80,"Сильное решение",IF(J25>=60,"Рыночный стандарт",IF(J25>=40,"Частичное решение","Слабое решение"))))
J26: =IF(COUNTA(E26:I26)=0,"",ROUND(((E26*0.25)+(F26*0.2)+(G26*0.2)+(H26*0.15)+(I26*0.2))*20,0)) | K26: =IF(J26="","",IF(J26>=80,"Сильное решение",IF(J26>=60,"Рыночный стандарт",IF(J26>=40,"Частичное решение","Слабое решение"))))
J27: =IF(COUNTA(E27:I27)=0,"",ROUND(((E27*0.25)+(F27*0.2)+(G27*0.2)+(H27*0.15)+(I27*0.2))*20,0)) | K27: =IF(J27="","",IF(J27>=80,"Сильное решение",IF(J27>=60,"Рыночный стандарт",IF(J27>=40,"Частичное решение","Слабое решение"))))
J28: =IF(COUNTA(E28:I28)=0,"",ROUND(((E28*0.25)+(F28*0.2)+(G28*0.2)+(H28*0.15)+(I28*0.2))*20,0)) | K28: =IF(J28="","",IF(J28>=80,"Сильное решение",IF(J28>=60,"Рыночный стандарт",IF(J28>=40,"Частичное решение","Слабое решение"))))
... J104: =IF(COUNTA(E104:I104)=0,"",ROUND(((E104*0.25)+(F104*0.2)+(G104*0.2)+(H104*0.15)+(I104*0.2))*20,0)) | K104: =IF(J104="","",IF(J104>=80,"Сильное решение",IF(J104>=60,"Рыночный стандарт",IF(J104>=40,"Частичное решение","Слабое решение"))))

Sheet Ценностные предложения
A1: Формулирование ценностного предложения
A2: Ценностное предложение связывает опорную проблему клиента, конкурентный пробел и обещаемый измеримый результат.
A4: ID ЦП | B4: ID проблемы | C4: Сегмент | D4: Опорная проблема | E4: Конкурентный пробел | F4: Обещаемый результат | G4: Механизм создания ценности | H4: Формулировка ценностного предложения | I4: Тип ЦП | J4: Тип ценности | K4: Индекс проблемы | L4: Статус | M4: Комментарий
A5: VP-001 | B5: P-001 | C5: B2C | D5: Ручное построение диаграмм строгих нотаций и замечания за нарушение правил | E5: draw.io не проверяет правила; PlantUML/Mermaid/D2/Eraser не поддерживают IDEF0/IDEF3/DFD; Ramus — десктоп без текста | F5: Корректная по правилам нотации диаграмма за одну итерацию «код → Run → исправление» вместо ручной перерисовки | G5: Единый DSL + профили нотаций с валидацией (код правила, строка) + авто-раскладка elkjs + шаблоны | H5: Для студентов технических специальностей, которые выполняют лабораторные и курсовые с IDEF0/IDEF3/DFD/ERD/UML, NotaCode строит диаграмму из текста и до сдачи показывает нарушения правил нотации с номером строки, в отличие от draw.io (правила не проверяет) и PlantUML/Mermaid (IDEF/DFD нет) | I5: Устранение боли | J5: Экономия времени | K5: =IF(B5="","",IFERROR(INDEX('Проблемы клиентов'!$K$5:$K$104,MATCH(B5,'Проблемы клиентов'!$A$5:$A$104,0)),0)) -> 90 | L5: =IF(A5="","",IF(AND(B5<>"",F5<>"",G5<>"",H5<>"",I5<>"",J5<>""),"Готово","Нужно дополнить")) -> Готово | M5: Основное ЦП (Free)
A6: VP-002 | B6: P-002 | C6: B2B | D6: Модели процессов и данных живут отдельно от требований в Git | E6: Eraser.io синхронизирует с Git, но без IDEF/DFD; draw.io хранит XML без построчного diff | F6: Модель BPMN/IDEF0/DFD/ERD хранится как текст рядом с требованиями, с diff и откатом | G6: Текстовый DSL + история версий (коммиты, diff) + push в GitHub + экспорт BPMN XML/XMI/SQL DDL | H6: Для бизнес- и системных аналитиков NotaCode хранит модели процессов и данных как текст с историей версий и публикацией в GitHub, в отличие от графических редакторов, где модель и требования расходятся | I6: Автоматизация процесса | J6: Контроль и прозрачность | K6: =IF(B6="","",IFERROR(INDEX('Проблемы клиентов'!$K$5:$K$104,MATCH(B6,'Проблемы клиентов'!$A$5:$A$104,0)),0)) -> 71 | L6: =IF(A6="","",IF(AND(B6<>"",F6<>"",G6<>"",H6<>"",I6<>"",J6<>""),"Готово","Нужно дополнить")) -> Готово | M6: Расширенное ЦП (Pro)
A7: VP-003 | B7: P-007 | C7: B2B | D7: Разные инструменты и форматы для разных нотаций | E7: Каждый DaC-инструмент поддерживает свой формат и свой набор нотаций | F7: Один язык для UML/ERD/IDEF/DFD и конвертация в форматы аналогов | G7: Каталог нотаций + Conversion Service (PlantUML, Mermaid, D2, DOT, XMI, SQL DDL) | H7: Для архитекторов ПО NotaCode даёт один язык для всех нотаций и экспорт в PlantUML/Mermaid/XMI/SQL DDL без ручного переноса | I7: Дифференциация | J7: Экономия времени | K7: =IF(B7="","",IFERROR(INDEX('Проблемы клиентов'!$K$5:$K$104,MATCH(B7,'Проблемы клиентов'!$A$5:$A$104,0)),0)) -> 63 | L7: =IF(A7="","",IF(AND(B7<>"",F7<>"",G7<>"",H7<>"",I7<>"",J7<>""),"Готово","Нужно дополнить")) -> Готово | M7: Гипотеза, R3–R4
K8: =IF(B8="","",IFERROR(INDEX('Проблемы клиентов'!$K$5:$K$104,MATCH(B8,'Проблемы клиентов'!$A$5:$A$104,0)),0)) | L8: =IF(A8="","",IF(AND(B8<>"",F8<>"",G8<>"",H8<>"",I8<>"",J8<>""),"Готово","Нужно дополнить"))
K9: =IF(B9="","",IFERROR(INDEX('Проблемы клиентов'!$K$5:$K$104,MATCH(B9,'Проблемы клиентов'!$A$5:$A$104,0)),0)) | L9: =IF(A9="","",IF(AND(B9<>"",F9<>"",G9<>"",H9<>"",I9<>"",J9<>""),"Готово","Нужно дополнить"))
K10: =IF(B10="","",IFERROR(INDEX('Проблемы клиентов'!$K$5:$K$104,MATCH(B10,'Проблемы клиентов'!$A$5:$A$104,0)),0)) | L10: =IF(A10="","",IF(AND(B10<>"",F10<>"",G10<>"",H10<>"",I10<>"",J10<>""),"Готово","Нужно дополнить"))
K11: =IF(B11="","",IFERROR(INDEX('Проблемы клиентов'!$K$5:$K$104,MATCH(B11,'Проблемы клиентов'!$A$5:$A$104,0)),0)) | L11: =IF(A11="","",IF(AND(B11<>"",F11<>"",G11<>"",H11<>"",I11<>"",J11<>""),"Готово","Нужно дополнить"))
K12: =IF(B12="","",IFERROR(INDEX('Проблемы клиентов'!$K$5:$K$104,MATCH(B12,'Проблемы клиентов'!$A$5:$A$104,0)),0)) | L12: =IF(A12="","",IF(AND(B12<>"",F12<>"",G12<>"",H12<>"",I12<>"",J12<>""),"Готово","Нужно дополнить"))
K13: =IF(B13="","",IFERROR(INDEX('Проблемы клиентов'!$K$5:$K$104,MATCH(B13,'Проблемы клиентов'!$A$5:$A$104,0)),0)) | L13: =IF(A13="","",IF(AND(B13<>"",F13<>"",G13<>"",H13<>"",I13<>"",J13<>""),"Готово","Нужно дополнить"))
K14: =IF(B14="","",IFERROR(INDEX('Проблемы клиентов'!$K$5:$K$104,MATCH(B14,'Проблемы клиентов'!$A$5:$A$104,0)),0)) | L14: =IF(A14="","",IF(AND(B14<>"",F14<>"",G14<>"",H14<>"",I14<>"",J14<>""),"Готово","Нужно дополнить"))
K15: =IF(B15="","",IFERROR(INDEX('Проблемы клиентов'!$K$5:$K$104,MATCH(B15,'Проблемы клиентов'!$A$5:$A$104,0)),0)) | L15: =IF(A15="","",IF(AND(B15<>"",F15<>"",G15<>"",H15<>"",I15<>"",J15<>""),"Готово","Нужно дополнить"))
K16: =IF(B16="","",IFERROR(INDEX('Проблемы клиентов'!$K$5:$K$104,MATCH(B16,'Проблемы клиентов'!$A$5:$A$104,0)),0)) | L16: =IF(A16="","",IF(AND(B16<>"",F16<>"",G16<>"",H16<>"",I16<>"",J16<>""),"Готово","Нужно дополнить"))
K17: =IF(B17="","",IFERROR(INDEX('Проблемы клиентов'!$K$5:$K$104,MATCH(B17,'Проблемы клиентов'!$A$5:$A$104,0)),0)) | L17: =IF(A17="","",IF(AND(B17<>"",F17<>"",G17<>"",H17<>"",I17<>"",J17<>""),"Готово","Нужно дополнить"))
K18: =IF(B18="","",IFERROR(INDEX('Проблемы клиентов'!$K$5:$K$104,MATCH(B18,'Проблемы клиентов'!$A$5:$A$104,0)),0)) | L18: =IF(A18="","",IF(AND(B18<>"",F18<>"",G18<>"",H18<>"",I18<>"",J18<>""),"Готово","Нужно дополнить"))
K19: =IF(B19="","",IFERROR(INDEX('Проблемы клиентов'!$K$5:$K$104,MATCH(B19,'Проблемы клиентов'!$A$5:$A$104,0)),0)) | L19: =IF(A19="","",IF(AND(B19<>"",F19<>"",G19<>"",H19<>"",I19<>"",J19<>""),"Готово","Нужно дополнить"))
... K104: =IF(B104="","",IFERROR(INDEX('Проблемы клиентов'!$K$5:$K$104,MATCH(B104,'Проблемы клиентов'!$A$5:$A$104,0)),0)) | L104: =IF(A104="","",IF(AND(B104<>"",F104<>"",G104<>"",H104<>"",I104<>"",J104<>""),"Готово","Нужно дополнить"))

Sheet Цифровой товар
A1: Описание цифрового товара как носителя ценности
A2: На листе ценностное предложение переводится в состав цифрового товара, функции, пользовательский сценарий и условия доступа.
A4: ID товара | B4: ID ЦП | C4: Название цифрового товара | D4: Тип цифрового товара | E4: Клиентская задача | F4: Базовая функция | G4: Расширенные функции | H4: Данные/алгоритмы как часть ценности | I4: Условия доступа и использования | J4: Носитель ценности | K4: Индекс товарной оформленности | L4: Статус | M4: Комментарий
A5: PR-001 | B5: VP-001 | C5: NotaCode Free (Web-IDE) | D5: Веб-сервис | E5: Построить корректную диаграмму строгой нотации для учебной работы | F5: DSL-редактор + Run + холст + валидация правил волны 1 + шаблоны + экспорт SVG/PNG | G5: Кросс-подсветка строка↔элемент, история 20 версий, AI-заглушка/BYOK, GitHub push | H5: Профили нотаций (правила, коды правил), elkjs-раскладка, кэш анализа по хэшу | I5: Бесплатно: 5 проектов в облаке, 20 файлов в проекте, 20 версий; гостевой режим без регистрации | J5: =IF(A5="","",IF(AND(E5<>"",F5<>"",H5<>"",I5<>""),"Да","Нет")) -> Да | K5: =IF(A5="","",ROUND((COUNTA(E5:I5)/5)*100,0)) -> 100 | L5: =IF(A5="","",IF(K5>=80,"Готово",IF(K5>=50,"Нужно дополнить","Черновик"))) -> Готово | M5: Базовый уровень предложения
A6: PR-002 | B6: VP-002 | C6: NotaCode Pro | D6: Веб-сервис | E6: Вести модели процессов/данных как код с полной историей и экспортом в рабочие форматы | F6: Всё из Free без лимитов проектов + полная история, diff, откат | G6: Все форматы экспорта (BPMN XML, XMI, PNML, draw.io, PlantUML, Mermaid, D2, DOT, SQL DDL, PDF), автосинхронизация GitHub/Drive, Kroki | H6: Conversion Service, серверные AI-ключи с квотой (после MVP) | I6: Подписка 4 USD/мес или 40 USD/год на пользователя (допущение цены, концепция §6) | J6: =IF(A6="","",IF(AND(E6<>"",F6<>"",H6<>"",I6<>""),"Да","Нет")) -> Да | K6: =IF(A6="","",ROUND((COUNTA(E6:I6)/5)*100,0)) -> 100 | L6: =IF(A6="","",IF(K6>=80,"Готово",IF(K6>=50,"Нужно дополнить","Черновик"))) -> Готово | M6: Расширенный уровень
A7: PR-003 | B7: VP-003 | C7: NotaCode для кафедры (гипотеза) | D7: Платформа | E7: Выдавать студентам наборы шаблонов заданий и проверять правила нотации | F7: Наборы шаблонов заданий, публичные ссылки на примеры | G7: Групповые лицензии Pro, отчёт о нарушениях правил по группе | H7: Агрегированная диагностика по правилам нотации | I7: Индивидуальный договор с вузом (🔲 проверить спрос интервью с преподавателями) | J7: =IF(A7="","",IF(AND(E7<>"",F7<>"",H7<>"",I7<>""),"Да","Нет")) -> Да | K7: =IF(A7="","",ROUND((COUNTA(E7:I7)/5)*100,0)) -> 100 | L7: =IF(A7="","",IF(K7>=80,"Готово",IF(K7>=50,"Нужно дополнить","Черновик"))) -> Готово | M7: Предельный уровень, R3–R4
J8: =IF(A8="","",IF(AND(E8<>"",F8<>"",H8<>"",I8<>""),"Да","Нет")) | K8: =IF(A8="","",ROUND((COUNTA(E8:I8)/5)*100,0)) | L8: =IF(A8="","",IF(K8>=80,"Готово",IF(K8>=50,"Нужно дополнить","Черновик")))
J9: =IF(A9="","",IF(AND(E9<>"",F9<>"",H9<>"",I9<>""),"Да","Нет")) | K9: =IF(A9="","",ROUND((COUNTA(E9:I9)/5)*100,0)) | L9: =IF(A9="","",IF(K9>=80,"Готово",IF(K9>=50,"Нужно дополнить","Черновик")))
J10: =IF(A10="","",IF(AND(E10<>"",F10<>"",H10<>"",I10<>""),"Да","Нет")) | K10: =IF(A10="","",ROUND((COUNTA(E10:I10)/5)*100,0)) | L10: =IF(A10="","",IF(K10>=80,"Готово",IF(K10>=50,"Нужно дополнить","Черновик")))
J11: =IF(A11="","",IF(AND(E11<>"",F11<>"",H11<>"",I11<>""),"Да","Нет")) | K11: =IF(A11="","",ROUND((COUNTA(E11:I11)/5)*100,0)) | L11: =IF(A11="","",IF(K11>=80,"Готово",IF(K11>=50,"Нужно дополнить","Черновик")))
J12: =IF(A12="","",IF(AND(E12<>"",F12<>"",H12<>"",I12<>""),"Да","Нет")) | K12: =IF(A12="","",ROUND((COUNTA(E12:I12)/5)*100,0)) | L12: =IF(A12="","",IF(K12>=80,"Готово",IF(K12>=50,"Нужно дополнить","Черновик")))
J13: =IF(A13="","",IF(AND(E13<>"",F13<>"",H13<>"",I13<>""),"Да","Нет")) | K13: =IF(A13="","",ROUND((COUNTA(E13:I13)/5)*100,0)) | L13: =IF(A13="","",IF(K13>=80,"Готово",IF(K13>=50,"Нужно дополнить","Черновик")))
J14: =IF(A14="","",IF(AND(E14<>"",F14<>"",H14<>"",I14<>""),"Да","Нет")) | K14: =IF(A14="","",ROUND((COUNTA(E14:I14)/5)*100,0)) | L14: =IF(A14="","",IF(K14>=80,"Готово",IF(K14>=50,"Нужно дополнить","Черновик")))
J15: =IF(A15="","",IF(AND(E15<>"",F15<>"",H15<>"",I15<>""),"Да","Нет")) | K15: =IF(A15="","",ROUND((COUNTA(E15:I15)/5)*100,0)) | L15: =IF(A15="","",IF(K15>=80,"Готово",IF(K15>=50,"Нужно дополнить","Черновик")))
J16: =IF(A16="","",IF(AND(E16<>"",F16<>"",H16<>"",I16<>""),"Да","Нет")) | K16: =IF(A16="","",ROUND((COUNTA(E16:I16)/5)*100,0)) | L16: =IF(A16="","",IF(K16>=80,"Готово",IF(K16>=50,"Нужно дополнить","Черновик")))
J17: =IF(A17="","",IF(AND(E17<>"",F17<>"",H17<>"",I17<>""),"Да","Нет")) | K17: =IF(A17="","",ROUND((COUNTA(E17:I17)/5)*100,0)) | L17: =IF(A17="","",IF(K17>=80,"Готово",IF(K17>=50,"Нужно дополнить","Черновик")))
J18: =IF(A18="","",IF(AND(E18<>"",F18<>"",H18<>"",I18<>""),"Да","Нет")) | K18: =IF(A18="","",ROUND((COUNTA(E18:I18)/5)*100,0)) | L18: =IF(A18="","",IF(K18>=80,"Готово",IF(K18>=50,"Нужно дополнить","Черновик")))
J19: =IF(A19="","",IF(AND(E19<>"",F19<>"",H19<>"",I19<>""),"Да","Нет")) | K19: =IF(A19="","",ROUND((COUNTA(E19:I19)/5)*100,0)) | L19: =IF(A19="","",IF(K19>=80,"Готово",IF(K19>=50,"Нужно дополнить","Черновик")))
... J104: =IF(A104="","",IF(AND(E104<>"",F104<>"",H104<>"",I104<>""),"Да","Нет")) | K104: =IF(A104="","",ROUND((COUNTA(E104:I104)/5)*100,0)) | L104: =IF(A104="","",IF(K104>=80,"Готово",IF(K104>=50,"Нужно дополнить","Черновик")))

Sheet Единица монетизации
A1: Определение единицы монетизации
A2: Единица монетизации показывает, за что именно платит клиент и как цифровой товар становится источником выручки.
A4: ID монетизации | B4: ID товара | C4: Единица монетизации | D4: Что покупает клиент | E4: Периодичность | F4: Базовая цена | G4: Кол-во единиц в месяц | H4: Расчетная выручка | I4: Обоснование готовности платить | J4: Связь с ценностью 1–5 | K4: Простота тарификации 1–5 | L4: Повторяемость 1–5 | M4: Монетизационный потенциал | N4: Статус
A5: M-001 | B5: PR-002 | C5: Пользователь | D5: Pro-доступ на 1 месяц: снятие лимитов, полная история, все форматы экспорта | E5: Ежемесячно | F5: 4 | G5: 15 | H5: =IF(OR(F5="",G5=""),"",F5*G5) -> 60 | I5: Рыночный стандарт — подписка за место (Eraser.io $15–20); цена снижена под СНГ/студентов (концепция §6, допущение); 15 подписок = 500 активных Free × 4 % конверсии × доля помесячных (допущение) | J5: 4 | K5: 5 | L5: 4 | M5: =IF(COUNTA(J5:L5)=0,"",ROUND(((J5*0.4)+(K5*0.3)+(L5*0.3))*20,0)) -> 86 | N5: =IF(A5="","",IF(M5>=80,"Готово",IF(M5>=60,"Нужно дополнить",IF(M5>=40,"Черновик","Отклонить")))) -> Готово
A6: M-002 | B6: PR-002 | C6: Пользователь | D6: Pro-доступ на 12 месяцев со скидкой ≈17 % | E6: Ежегодно | F6: 40 | G6: 1 | H6: =IF(OR(F6="",G6=""),"",F6*G6) -> 40 | I6: Годовой тариф снижает отток; 1 годовая подписка в месяц — допущение | J6: 4 | K6: 4 | L6: 3 | M6: =IF(COUNTA(J6:L6)=0,"",ROUND(((J6*0.4)+(K6*0.3)+(L6*0.3))*20,0)) -> 74 | N6: =IF(A6="","",IF(M6>=80,"Готово",IF(M6>=60,"Нужно дополнить",IF(M6>=40,"Черновик","Отклонить")))) -> Нужно дополнить
A7: M-003 | B7: PR-003 | C7: Пакет функций | D7: Групповой доступ кафедры: шаблоны заданий + Pro для группы | E7: Ежегодно | H7: =IF(OR(F7="",G7=""),"",F7*G7) | I7: Гипотеза: платит вуз/кафедра; цена не определена — 🔲 интервью с 3 преподавателями | J7: 3 | K7: 3 | L7: 3 | M7: =IF(COUNTA(J7:L7)=0,"",ROUND(((J7*0.4)+(K7*0.3)+(L7*0.3))*20,0)) -> 60 | N7: =IF(A7="","",IF(M7>=80,"Готово",IF(M7>=60,"Нужно дополнить",IF(M7>=40,"Черновик","Отклонить")))) -> Нужно дополнить
H8: =IF(OR(F8="",G8=""),"",F8*G8) | M8: =IF(COUNTA(J8:L8)=0,"",ROUND(((J8*0.4)+(K8*0.3)+(L8*0.3))*20,0)) | N8: =IF(A8="","",IF(M8>=80,"Готово",IF(M8>=60,"Нужно дополнить",IF(M8>=40,"Черновик","Отклонить"))))
H9: =IF(OR(F9="",G9=""),"",F9*G9) | M9: =IF(COUNTA(J9:L9)=0,"",ROUND(((J9*0.4)+(K9*0.3)+(L9*0.3))*20,0)) | N9: =IF(A9="","",IF(M9>=80,"Готово",IF(M9>=60,"Нужно дополнить",IF(M9>=40,"Черновик","Отклонить"))))
H10: =IF(OR(F10="",G10=""),"",F10*G10) | M10: =IF(COUNTA(J10:L10)=0,"",ROUND(((J10*0.4)+(K10*0.3)+(L10*0.3))*20,0)) | N10: =IF(A10="","",IF(M10>=80,"Готово",IF(M10>=60,"Нужно дополнить",IF(M10>=40,"Черновик","Отклонить"))))
H11: =IF(OR(F11="",G11=""),"",F11*G11) | M11: =IF(COUNTA(J11:L11)=0,"",ROUND(((J11*0.4)+(K11*0.3)+(L11*0.3))*20,0)) | N11: =IF(A11="","",IF(M11>=80,"Готово",IF(M11>=60,"Нужно дополнить",IF(M11>=40,"Черновик","Отклонить"))))
H12: =IF(OR(F12="",G12=""),"",F12*G12) | M12: =IF(COUNTA(J12:L12)=0,"",ROUND(((J12*0.4)+(K12*0.3)+(L12*0.3))*20,0)) | N12: =IF(A12="","",IF(M12>=80,"Готово",IF(M12>=60,"Нужно дополнить",IF(M12>=40,"Черновик","Отклонить"))))
H13: =IF(OR(F13="",G13=""),"",F13*G13) | M13: =IF(COUNTA(J13:L13)=0,"",ROUND(((J13*0.4)+(K13*0.3)+(L13*0.3))*20,0)) | N13: =IF(A13="","",IF(M13>=80,"Готово",IF(M13>=60,"Нужно дополнить",IF(M13>=40,"Черновик","Отклонить"))))
H14: =IF(OR(F14="",G14=""),"",F14*G14) | M14: =IF(COUNTA(J14:L14)=0,"",ROUND(((J14*0.4)+(K14*0.3)+(L14*0.3))*20,0)) | N14: =IF(A14="","",IF(M14>=80,"Готово",IF(M14>=60,"Нужно дополнить",IF(M14>=40,"Черновик","Отклонить"))))
H15: =IF(OR(F15="",G15=""),"",F15*G15) | M15: =IF(COUNTA(J15:L15)=0,"",ROUND(((J15*0.4)+(K15*0.3)+(L15*0.3))*20,0)) | N15: =IF(A15="","",IF(M15>=80,"Готово",IF(M15>=60,"Нужно дополнить",IF(M15>=40,"Черновик","Отклонить"))))
H16: =IF(OR(F16="",G16=""),"",F16*G16) | M16: =IF(COUNTA(J16:L16)=0,"",ROUND(((J16*0.4)+(K16*0.3)+(L16*0.3))*20,0)) | N16: =IF(A16="","",IF(M16>=80,"Готово",IF(M16>=60,"Нужно дополнить",IF(M16>=40,"Черновик","Отклонить"))))
H17: =IF(OR(F17="",G17=""),"",F17*G17) | M17: =IF(COUNTA(J17:L17)=0,"",ROUND(((J17*0.4)+(K17*0.3)+(L17*0.3))*20,0)) | N17: =IF(A17="","",IF(M17>=80,"Готово",IF(M17>=60,"Нужно дополнить",IF(M17>=40,"Черновик","Отклонить"))))
H18: =IF(OR(F18="",G18=""),"",F18*G18) | M18: =IF(COUNTA(J18:L18)=0,"",ROUND(((J18*0.4)+(K18*0.3)+(L18*0.3))*20,0)) | N18: =IF(A18="","",IF(M18>=80,"Готово",IF(M18>=60,"Нужно дополнить",IF(M18>=40,"Черновик","Отклонить"))))
H19: =IF(OR(F19="",G19=""),"",F19*G19) | M19: =IF(COUNTA(J19:L19)=0,"",ROUND(((J19*0.4)+(K19*0.3)+(L19*0.3))*20,0)) | N19: =IF(A19="","",IF(M19>=80,"Готово",IF(M19>=60,"Нужно дополнить",IF(M19>=40,"Черновик","Отклонить"))))
... H104: =IF(OR(F104="",G104=""),"",F104*G104) | M104: =IF(COUNTA(J104:L104)=0,"",ROUND(((J104*0.4)+(K104*0.3)+(L104*0.3))*20,0)) | N104: =IF(A104="","",IF(M104>=80,"Готово",IF(M104>=60,"Нужно дополнить",IF(M104>=40,"Черновик","Отклонить"))))

Sheet Бизнес-модель
A1: Связь цифрового товара с бизнес-моделью
A2: Лист фиксирует, как ценностное предложение, цифровой товар и монетизация превращаются в элементы бизнес-модели.
A4: ID модели | B4: ID товара | C4: Клиентские сегменты | D4: Ценностное предложение | E4: Каналы | F4: Отношения с клиентами | G4: Потоки доходов | H4: Ключевые ресурсы | I4: Ключевые виды деятельности | J4: Ключевые партнеры | K4: Структура затрат | L4: Индекс полноты бизнес-модели | M4: Комментарий
A5: BM-001 | B5: PR-002 | C5: S-01 студенты технических специальностей (первичный, Free); S-02 аналитики и S-03 архитекторы (Pro); S-04 преподаватели (влияние) | D5: Корректная диаграмма строгой нотации из текста с проверкой правил, историей и экспортом | E5: Органический поиск (IDEF0/DFD/«diagram as code»), GitHub, рекомендации преподавателей, сообщества студентов | F5: Самообслуживание: шаблоны, документация, AI-помощник; сообщество (чат) | G5: Freemium: Pro 4 USD/мес или 40 USD/год; лимиты Free — проекты, версии, форматы | H5: Грамматика DSL, каталог и профили нотаций, Web IDE, модель версий | I5: Разработка профилей нотаций волнами, поддержка документации и шаблонов, контроль качества (100 % покрытие) | J5: LLM-провайдеры (бесплатные квоты), GitHub/Google Drive API, хостинг (Netlify, Render, Neon), платёжный провайдер РБ | K5: Разработка (≈610 ч), инфраструктура 0 на бесплатных тарифах, переменные — LLM API после MVP | L5: =IF(A5="","",ROUND((COUNTA(C5:K5)/9)*100,0)) -> 100 | M5: Полная модель (9 из 9 блоков)
L6: =IF(A6="","",ROUND((COUNTA(C6:K6)/9)*100,0))
L7: =IF(A7="","",ROUND((COUNTA(C7:K7)/9)*100,0))
L8: =IF(A8="","",ROUND((COUNTA(C8:K8)/9)*100,0))
L9: =IF(A9="","",ROUND((COUNTA(C9:K9)/9)*100,0))
L10: =IF(A10="","",ROUND((COUNTA(C10:K10)/9)*100,0))
L11: =IF(A11="","",ROUND((COUNTA(C11:K11)/9)*100,0))
L12: =IF(A12="","",ROUND((COUNTA(C12:K12)/9)*100,0))
L13: =IF(A13="","",ROUND((COUNTA(C13:K13)/9)*100,0))
L14: =IF(A14="","",ROUND((COUNTA(C14:K14)/9)*100,0))
L15: =IF(A15="","",ROUND((COUNTA(C15:K15)/9)*100,0))
L16: =IF(A16="","",ROUND((COUNTA(C16:K16)/9)*100,0))
L17: =IF(A17="","",ROUND((COUNTA(C17:K17)/9)*100,0))
... L104: =IF(A104="","",ROUND((COUNTA(C104:K104)/9)*100,0))

Sheet Проверка связности
A1: Проверка связности: проблема → ценность → товар → монетизация → бизнес-модель
A2: Итоговая проверка нужна для выявления разрывов между выбранной проблемой, обещанной ценностью, цифровым товаром и экономикой бизнес-модели.
A4: ID проверки | B4: ID проблемы | C4: ID ЦП | D4: ID товара | E4: ID монетизации | F4: ID модели | G4: Индекс связности | H4: Решение | I4: Главный разрыв | J4: Что доработать
A5: CHK-001 | B5: P-001 | C5: VP-001 | D5: PR-001 | E5: M-001 | F5: BM-001 | G5: =IF(A5="","",ROUND((IFERROR(INDEX('Проблемы клиентов'!$K$5:$K$104,MATCH(B5,'Проблемы клиентов'!$A$5:$A$104,0)),0)*0.3+IFERROR(INDEX('Ценностные предложения'!$K$5:$K$104,MATCH(C5,'Ценностные предложения'!$A$5:$A$104,0)),0)*0.15+IFERROR(INDEX('Цифровой товар'!$K$5:$K$104,MATCH(D5,'Цифровой товар'!$A$5:$A$104,0)),0)*0.2+IFERROR(INDEX('Единица монетизации'!$M$5:$M$104,MATCH(E5,'Единица монетизации'!$A$5:$A$104,0)),0)*0.2+IFERROR(INDEX('Бизнес-модель'!$L$5:$L$104,MATCH(F5,'Бизнес-модель'!$A$5:$A$104,0)),0)*0.15),0)) -> 93 | H5: =IF(G5="","",IF(G5>=75,"Проходят проверку",IF(G5>=55,"Требуется доработка","Недостаточно данных"))) -> Проходят проверку | I5: Сегмент S-01 почти не платит: товар Free, а монетизация — Pro для S-02/S-03 | J5: Проверить конверсию S-01 → Pro после выпуска (студенты-старшекурсники, дипломники)
A6: CHK-002 | B6: P-002 | C6: VP-002 | D6: PR-002 | E6: M-001 | F6: BM-001 | G6: =IF(A6="","",ROUND((IFERROR(INDEX('Проблемы клиентов'!$K$5:$K$104,MATCH(B6,'Проблемы клиентов'!$A$5:$A$104,0)),0)*0.3+IFERROR(INDEX('Ценностные предложения'!$K$5:$K$104,MATCH(C6,'Ценностные предложения'!$A$5:$A$104,0)),0)*0.15+IFERROR(INDEX('Цифровой товар'!$K$5:$K$104,MATCH(D6,'Цифровой товар'!$A$5:$A$104,0)),0)*0.2+IFERROR(INDEX('Единица монетизации'!$M$5:$M$104,MATCH(E6,'Единица монетизации'!$A$5:$A$104,0)),0)*0.2+IFERROR(INDEX('Бизнес-модель'!$L$5:$L$104,MATCH(F6,'Бизнес-модель'!$A$5:$A$104,0)),0)*0.15),0)) -> 84 | H6: =IF(G6="","",IF(G6>=75,"Проходят проверку",IF(G6>=55,"Требуется доработка","Недостаточно данных"))) -> Проходят проверку | I6: Нет подтверждения готовности аналитиков платить 4 USD | J6: Интервью с 5 аналитиками, тест страницы тарифов (заявка «Хочу Pro»)
A7: CHK-003 | B7: P-007 | C7: VP-003 | D7: PR-003 | E7: M-003 | F7: BM-001 | G7: =IF(A7="","",ROUND((IFERROR(INDEX('Проблемы клиентов'!$K$5:$K$104,MATCH(B7,'Проблемы клиентов'!$A$5:$A$104,0)),0)*0.3+IFERROR(INDEX('Ценностные предложения'!$K$5:$K$104,MATCH(C7,'Ценностные предложения'!$A$5:$A$104,0)),0)*0.15+IFERROR(INDEX('Цифровой товар'!$K$5:$K$104,MATCH(D7,'Цифровой товар'!$A$5:$A$104,0)),0)*0.2+IFERROR(INDEX('Единица монетизации'!$M$5:$M$104,MATCH(E7,'Единица монетизации'!$A$5:$A$104,0)),0)*0.2+IFERROR(INDEX('Бизнес-модель'!$L$5:$L$104,MATCH(F7,'Бизнес-модель'!$A$5:$A$104,0)),0)*0.15),0)) -> 75 | H7: =IF(G7="","",IF(G7>=75,"Проходят проверку",IF(G7>=55,"Требуется доработка","Недостаточно данных"))) -> Проходят проверку | I7: Цена кафедрального тарифа не определена | J7: Интервью с преподавателями S-04
G8: =IF(A8="","",ROUND((IFERROR(INDEX('Проблемы клиентов'!$K$5:$K$104,MATCH(B8,'Проблемы клиентов'!$A$5:$A$104,0)),0)*0.3+IFERROR(INDEX('Ценностные предложения'!$K$5:$K$104,MATCH(C8,'Ценностные предложения'!$A$5:$A$104,0)),0)*0.15+IFERROR(INDEX('Цифровой товар'!$K$5:$K$104,MATCH(D8,'Цифровой товар'!$A$5:$A$104,0)),0)*0.2+IFERROR(INDEX('Единица монетизации'!$M$5:$M$104,MATCH(E8,'Единица монетизации'!$A$5:$A$104,0)),0)*0.2+IFERROR(INDEX('Бизнес-модель'!$L$5:$L$104,MATCH(F8,'Бизнес-модель'!$A$5:$A$104,0)),0)*0.15),0)) | H8: =IF(G8="","",IF(G8>=75,"Проходят проверку",IF(G8>=55,"Требуется доработка","Недостаточно данных")))
G9: =IF(A9="","",ROUND((IFERROR(INDEX('Проблемы клиентов'!$K$5:$K$104,MATCH(B9,'Проблемы клиентов'!$A$5:$A$104,0)),0)*0.3+IFERROR(INDEX('Ценностные предложения'!$K$5:$K$104,MATCH(C9,'Ценностные предложения'!$A$5:$A$104,0)),0)*0.15+IFERROR(INDEX('Цифровой товар'!$K$5:$K$104,MATCH(D9,'Цифровой товар'!$A$5:$A$104,0)),0)*0.2+IFERROR(INDEX('Единица монетизации'!$M$5:$M$104,MATCH(E9,'Единица монетизации'!$A$5:$A$104,0)),0)*0.2+IFERROR(INDEX('Бизнес-модель'!$L$5:$L$104,MATCH(F9,'Бизнес-модель'!$A$5:$A$104,0)),0)*0.15),0)) | H9: =IF(G9="","",IF(G9>=75,"Проходят проверку",IF(G9>=55,"Требуется доработка","Недостаточно данных")))
G10: =IF(A10="","",ROUND((IFERROR(INDEX('Проблемы клиентов'!$K$5:$K$104,MATCH(B10,'Проблемы клиентов'!$A$5:$A$104,0)),0)*0.3+IFERROR(INDEX('Ценностные предложения'!$K$5:$K$104,MATCH(C10,'Ценностные предложения'!$A$5:$A$104,0)),0)*0.15+IFERROR(INDEX('Цифровой товар'!$K$5:$K$104,MATCH(D10,'Цифровой товар'!$A$5:$A$104,0)),0)*0.2+IFERROR(INDEX('Единица монетизации'!$M$5:$M$104,MATCH(E10,'Единица монетизации'!$A$5:$A$104,0)),0)*0.2+IFERROR(INDEX('Бизнес-модель'!$L$5:$L$104,MATCH(F10,'Бизнес-модель'!$A$5:$A$104,0)),0)*0.15),0)) | H10: =IF(G10="","",IF(G10>=75,"Проходят проверку",IF(G10>=55,"Требуется доработка","Недостаточно данных")))
G11: =IF(A11="","",ROUND((IFERROR(INDEX('Проблемы клиентов'!$K$5:$K$104,MATCH(B11,'Проблемы клиентов'!$A$5:$A$104,0)),0)*0.3+IFERROR(INDEX('Ценностные предложения'!$K$5:$K$104,MATCH(C11,'Ценностные предложения'!$A$5:$A$104,0)),0)*0.15+IFERROR(INDEX('Цифровой товар'!$K$5:$K$104,MATCH(D11,'Цифровой товар'!$A$5:$A$104,0)),0)*0.2+IFERROR(INDEX('Единица монетизации'!$M$5:$M$104,MATCH(E11,'Единица монетизации'!$A$5:$A$104,0)),0)*0.2+IFERROR(INDEX('Бизнес-модель'!$L$5:$L$104,MATCH(F11,'Бизнес-модель'!$A$5:$A$104,0)),0)*0.15),0)) | H11: =IF(G11="","",IF(G11>=75,"Проходят проверку",IF(G11>=55,"Требуется доработка","Недостаточно данных")))
G12: =IF(A12="","",ROUND((IFERROR(INDEX('Проблемы клиентов'!$K$5:$K$104,MATCH(B12,'Проблемы клиентов'!$A$5:$A$104,0)),0)*0.3+IFERROR(INDEX('Ценностные предложения'!$K$5:$K$104,MATCH(C12,'Ценностные предложения'!$A$5:$A$104,0)),0)*0.15+IFERROR(INDEX('Цифровой товар'!$K$5:$K$104,MATCH(D12,'Цифровой товар'!$A$5:$A$104,0)),0)*0.2+IFERROR(INDEX('Единица монетизации'!$M$5:$M$104,MATCH(E12,'Единица монетизации'!$A$5:$A$104,0)),0)*0.2+IFERROR(INDEX('Бизнес-модель'!$L$5:$L$104,MATCH(F12,'Бизнес-модель'!$A$5:$A$104,0)),0)*0.15),0)) | H12: =IF(G12="","",IF(G12>=75,"Проходят проверку",IF(G12>=55,"Требуется доработка","Недостаточно данных")))
G13: =IF(A13="","",ROUND((IFERROR(INDEX('Проблемы клиентов'!$K$5:$K$104,MATCH(B13,'Проблемы клиентов'!$A$5:$A$104,0)),0)*0.3+IFERROR(INDEX('Ценностные предложения'!$K$5:$K$104,MATCH(C13,'Ценностные предложения'!$A$5:$A$104,0)),0)*0.15+IFERROR(INDEX('Цифровой товар'!$K$5:$K$104,MATCH(D13,'Цифровой товар'!$A$5:$A$104,0)),0)*0.2+IFERROR(INDEX('Единица монетизации'!$M$5:$M$104,MATCH(E13,'Единица монетизации'!$A$5:$A$104,0)),0)*0.2+IFERROR(INDEX('Бизнес-модель'!$L$5:$L$104,MATCH(F13,'Бизнес-модель'!$A$5:$A$104,0)),0)*0.15),0)) | H13: =IF(G13="","",IF(G13>=75,"Проходят проверку",IF(G13>=55,"Требуется доработка","Недостаточно данных")))
G14: =IF(A14="","",ROUND((IFERROR(INDEX('Проблемы клиентов'!$K$5:$K$104,MATCH(B14,'Проблемы клиентов'!$A$5:$A$104,0)),0)*0.3+IFERROR(INDEX('Ценностные предложения'!$K$5:$K$104,MATCH(C14,'Ценностные предложения'!$A$5:$A$104,0)),0)*0.15+IFERROR(INDEX('Цифровой товар'!$K$5:$K$104,MATCH(D14,'Цифровой товар'!$A$5:$A$104,0)),0)*0.2+IFERROR(INDEX('Единица монетизации'!$M$5:$M$104,MATCH(E14,'Единица монетизации'!$A$5:$A$104,0)),0)*0.2+IFERROR(INDEX('Бизнес-модель'!$L$5:$L$104,MATCH(F14,'Бизнес-модель'!$A$5:$A$104,0)),0)*0.15),0)) | H14: =IF(G14="","",IF(G14>=75,"Проходят проверку",IF(G14>=55,"Требуется доработка","Недостаточно данных")))
G15: =IF(A15="","",ROUND((IFERROR(INDEX('Проблемы клиентов'!$K$5:$K$104,MATCH(B15,'Проблемы клиентов'!$A$5:$A$104,0)),0)*0.3+IFERROR(INDEX('Ценностные предложения'!$K$5:$K$104,MATCH(C15,'Ценностные предложения'!$A$5:$A$104,0)),0)*0.15+IFERROR(INDEX('Цифровой товар'!$K$5:$K$104,MATCH(D15,'Цифровой товар'!$A$5:$A$104,0)),0)*0.2+IFERROR(INDEX('Единица монетизации'!$M$5:$M$104,MATCH(E15,'Единица монетизации'!$A$5:$A$104,0)),0)*0.2+IFERROR(INDEX('Бизнес-модель'!$L$5:$L$104,MATCH(F15,'Бизнес-модель'!$A$5:$A$104,0)),0)*0.15),0)) | H15: =IF(G15="","",IF(G15>=75,"Проходят проверку",IF(G15>=55,"Требуется доработка","Недостаточно данных")))
G16: =IF(A16="","",ROUND((IFERROR(INDEX('Проблемы клиентов'!$K$5:$K$104,MATCH(B16,'Проблемы клиентов'!$A$5:$A$104,0)),0)*0.3+IFERROR(INDEX('Ценностные предложения'!$K$5:$K$104,MATCH(C16,'Ценностные предложения'!$A$5:$A$104,0)),0)*0.15+IFERROR(INDEX('Цифровой товар'!$K$5:$K$104,MATCH(D16,'Цифровой товар'!$A$5:$A$104,0)),0)*0.2+IFERROR(INDEX('Единица монетизации'!$M$5:$M$104,MATCH(E16,'Единица монетизации'!$A$5:$A$104,0)),0)*0.2+IFERROR(INDEX('Бизнес-модель'!$L$5:$L$104,MATCH(F16,'Бизнес-модель'!$A$5:$A$104,0)),0)*0.15),0)) | H16: =IF(G16="","",IF(G16>=75,"Проходят проверку",IF(G16>=55,"Требуется доработка","Недостаточно данных")))
G17: =IF(A17="","",ROUND((IFERROR(INDEX('Проблемы клиентов'!$K$5:$K$104,MATCH(B17,'Проблемы клиентов'!$A$5:$A$104,0)),0)*0.3+IFERROR(INDEX('Ценностные предложения'!$K$5:$K$104,MATCH(C17,'Ценностные предложения'!$A$5:$A$104,0)),0)*0.15+IFERROR(INDEX('Цифровой товар'!$K$5:$K$104,MATCH(D17,'Цифровой товар'!$A$5:$A$104,0)),0)*0.2+IFERROR(INDEX('Единица монетизации'!$M$5:$M$104,MATCH(E17,'Единица монетизации'!$A$5:$A$104,0)),0)*0.2+IFERROR(INDEX('Бизнес-модель'!$L$5:$L$104,MATCH(F17,'Бизнес-модель'!$A$5:$A$104,0)),0)*0.15),0)) | H17: =IF(G17="","",IF(G17>=75,"Проходят проверку",IF(G17>=55,"Требуется доработка","Недостаточно данных")))
G18: =IF(A18="","",ROUND((IFERROR(INDEX('Проблемы клиентов'!$K$5:$K$104,MATCH(B18,'Проблемы клиентов'!$A$5:$A$104,0)),0)*0.3+IFERROR(INDEX('Ценностные предложения'!$K$5:$K$104,MATCH(C18,'Ценностные предложения'!$A$5:$A$104,0)),0)*0.15+IFERROR(INDEX('Цифровой товар'!$K$5:$K$104,MATCH(D18,'Цифровой товар'!$A$5:$A$104,0)),0)*0.2+IFERROR(INDEX('Единица монетизации'!$M$5:$M$104,MATCH(E18,'Единица монетизации'!$A$5:$A$104,0)),0)*0.2+IFERROR(INDEX('Бизнес-модель'!$L$5:$L$104,MATCH(F18,'Бизнес-модель'!$A$5:$A$104,0)),0)*0.15),0)) | H18: =IF(G18="","",IF(G18>=75,"Проходят проверку",IF(G18>=55,"Требуется доработка","Недостаточно данных")))
G19: =IF(A19="","",ROUND((IFERROR(INDEX('Проблемы клиентов'!$K$5:$K$104,MATCH(B19,'Проблемы клиентов'!$A$5:$A$104,0)),0)*0.3+IFERROR(INDEX('Ценностные предложения'!$K$5:$K$104,MATCH(C19,'Ценностные предложения'!$A$5:$A$104,0)),0)*0.15+IFERROR(INDEX('Цифровой товар'!$K$5:$K$104,MATCH(D19,'Цифровой товар'!$A$5:$A$104,0)),0)*0.2+IFERROR(INDEX('Единица монетизации'!$M$5:$M$104,MATCH(E19,'Единица монетизации'!$A$5:$A$104,0)),0)*0.2+IFERROR(INDEX('Бизнес-модель'!$L$5:$L$104,MATCH(F19,'Бизнес-модель'!$A$5:$A$104,0)),0)*0.15),0)) | H19: =IF(G19="","",IF(G19>=75,"Проходят проверку",IF(G19>=55,"Требуется доработка","Недостаточно данных")))
... G104: =IF(A104="","",ROUND((IFERROR(INDEX('Проблемы клиентов'!$K$5:$K$104,MATCH(B104,'Проблемы клиентов'!$A$5:$A$104,0)),0)*0.3+IFERROR(INDEX('Ценностные предложения'!$K$5:$K$104,MATCH(C104,'Ценностные предложения'!$A$5:$A$104,0)),0)*0.15+IFERROR(INDEX('Цифровой товар'!$K$5:$K$104,MATCH(D104,'Цифровой товар'!$A$5:$A$104,0)),0)*0.2+IFERROR(INDEX('Единица монетизации'!$M$5:$M$104,MATCH(E104,'Единица монетизации'!$A$5:$A$104,0)),0)*0.2+IFERROR(INDEX('Бизнес-модель'!$L$5:$L$104,MATCH(F104,'Бизнес-модель'!$A$5:$A$104,0)),0)*0.15),0)) | H104: =IF(G104="","",IF(G104>=75,"Проходят проверку",IF(G104>=55,"Требуется доработка","Недостаточно данных")))

Sheet Дашборд
A1: Сводный дашборд разработки ценностного предложения и цифрового товара
A2: Расчетные показатели обновляются после заполнения рабочих листов.
A4: Показатель | B4: Значение | C4: Интерпретация | E4: Приоритет проблемы | F4: Количество | G4: Доля
A5: Количество выявленных проблем | B5: =COUNTIF('Проблемы клиентов'!$A$5:$A$104,"<>") -> 8 | C5: Объем базы проблем для выбора опорной проблемы. | E5: Критический | F5: =COUNTIF('Проблемы клиентов'!$L$5:$L$104,E5) -> 1 | G5: =IFERROR(F5/SUM($F$5:$F$8),0) -> 0.125
A6: Максимальный индекс проблемы | B6: =IFERROR(MAX('Проблемы клиентов'!$K$5:$K$104),0) -> 90 | C6: Наиболее значимая проблема по текущей оценке. | E6: Высокий | F6: =COUNTIF('Проблемы клиентов'!$L$5:$L$104,E6) -> 2 | G6: =IFERROR(F6/SUM($F$5:$F$8),0) -> 0.25
A7: Готовых ценностных предложений | B7: =COUNTIF('Ценностные предложения'!$L$5:$L$104,"Готово") -> 3 | C7: Количество формулировок, прошедших минимальную проверку полноты. | E7: Средний | F7: =COUNTIF('Проблемы клиентов'!$L$5:$L$104,E7) -> 5 | G7: =IFERROR(F7/SUM($F$5:$F$8),0) -> 0.625
A8: Готовых цифровых товаров | B8: =COUNTIF('Цифровой товар'!$L$5:$L$104,"Готово") -> 3 | C8: Количество описаний товара с достаточной оформленностью. | E8: Низкий | F8: =COUNTIF('Проблемы клиентов'!$L$5:$L$104,E8) -> 0 | G8: =IFERROR(F8/SUM($F$5:$F$8),0) -> 0
A9: Средний индекс связности | B9: =IFERROR(ROUND(AVERAGE('Проверка связности'!$G$5:$G$104),0),0) -> 84 | C9: Согласованность цепочки проблема → ценность → товар → монетизация → бизнес-модель.
A10: Расчетная выручка по заполненным единицам | B10: =IFERROR(SUM('Единица монетизации'!$H$5:$H$104),0) -> 100 | C10: Сумма расчетной месячной выручки по листу монетизации.
E11: Решение проверки | F11: Количество | G11: Доля
E12: Проходят проверку | F12: =COUNTIF('Проверка связности'!$H$5:$H$104,E12) -> 3 | G12: =IFERROR(F12/SUM($F$12:$F$14),0) -> 1
E13: Требуется доработка | F13: =COUNTIF('Проверка связности'!$H$5:$H$104,E13) -> 0 | G13: =IFERROR(F13/SUM($F$12:$F$14),0) -> 0
E14: Недостаточно данных | F14: =COUNTIF('Проверка связности'!$H$5:$H$104,E14) -> 0 | G14: =IFERROR(F14/SUM($F$12:$F$14),0) -> 0
