Workbook

Sheet Инструкция
A1: Шаблон деления разработки сайта или мобильного приложения на первый и последующие релизы
A3: Назначение файла | B3: Помочь разделить разработку цифрового товара на первый релиз и последующие релизы так, чтобы быстро и экономно выйти на рынок, но не разрушить ценностное предложение, удержание и потенциал роста аудитории.
A4: Логика работы | B4: 1) перенесите выводы всех предыдущих анализов в лист «Банк_анализа»; 2) опишите страницы, экраны, функции, интеграции и контентные блоки в листе «Реестр_единиц»; 3) заполните баллы 1–5; 4) используйте расчетный рекомендованный релиз; 5) проверьте первый релиз на целостность ценности и монетизации.
A5: Принцип первого релиза | B5: Первый релиз должен содержать минимальный набор, который позволяет пользователю получить заявленную ценность, бизнесу — проверить спрос и монетизацию, а продукту — собрать данные для следующего роста.
A6: Что нельзя переносить из первого релиза | B6: Нельзя переносить элементы, без которых пользователь не достигает ключевого результата, невозможно проверить основную гипотезу, не работает единица монетизации, не собирается критически важная обратная связь или разрывается основной пользовательский сценарий.
A7: Как читать расчет | B7: Рекомендованный релиз формируется по баллам: связь с ценностным предложением, критичность для первого дохода, удержание, рост, доказательность, рыночный стандарт, быстрота и дешевизна реализации, технический риск и риск потери ценности при переносе.
A8: Редактируемые поля | B8: Желтые поля предназначены для ввода. Зеленые поля являются расчетными. Справочники и выпадающие списки находятся на листе «Справочники».
A10: Шаг | B10: Действие | C10: Результат
A11: 1 | B11: Собрать выводы из анализа проблем, отзывов, конкурентов, ценностного предложения, цифрового товара, Канвас, сценариев и страниц/экранов. | C11: Единый банк доказанных оснований для решений по релизам.
A12: 2 | B12: Разложить будущий сайт или приложение на интерфейсные и функциональные единицы. | C12: Перечень кандидатов на включение в релизы.
A13: 3 | B13: Оценить каждую единицу по шкалам 1–5. | C13: Сравнимые баллы для быстрого и обоснованного выбора состава первого релиза.
A14: 4 | B14: Проверить, не нарушается ли ценностное предложение, монетизация, удержание и рост при переносе части функций. | C14: Сбалансированный первый релиз без избыточной разработки.
A15: 5 | B15: Сформировать дорожную карту последующих релизов. | C15: Последовательность развития продукта после выхода на рынок.

Sheet Банк_анализа
A1: ID вывода | B1: Вид анализа | C1: Объект анализа | D1: Ключевой вывод | E1: Проблема / потребность | F1: Пользовательский сегмент | G1: Доказательство | H1: Источник / ссылка | I1: Достоверность 1–5 | J1: Значимость 1–5 | K1: Вывод для релизов | L1: Связанная единица разработки
A2: A-001 | B2: Анализ проблем | C2: Карта проблем 6.1 | D2: Опорная P-001 (ИПП 4,35) | E2: Корректная диаграмма до сдачи | F2: S-01 студенты | G2: 8 проблем, индекс шаблона 90 | H2: ЛР6 6.1 | I2: 3 | J2: 5 | K2: Ядро R1 — редактор + валидация | L2: RU-001…RU-006
A3: A-002 | B3: Анализ конкурентов по сайтам | C3: Прямые конкуренты | D3: Стандарт: DSL, браузерный рендер, GitHub, экспорт, шаблоны, Free | E3: Не отстать от стандарта | F3: Все | G3: ЛР5, 4 прямых | H3: Сайты конкурентов | I3: 5 | J3: 5 | K3: Стандарт — в R1 | L3: RU-007, RU-013, RU-015
A4: A-003 | B4: Классификация конкурентов | C4: Уровни конкуренции | D4: Eraser.io 93,0 — эталон AI + история | E4: Отличие без AI-гонки | F4: S-02/S-03 | G4: ЛР5 разд. 1 | H4: ЛР5 | I4: 4 | J4: 4 | K4: AI в R1 — заглушка, серверный AI — R4 | L4: RU-009, RU-034
A5: A-004 | B5: Ценностное предложение | C5: VP-001 | D5: Ценность — проверка правил с номером строки | E5: Сдать без замечаний | F5: S-01 | G5: ИКЦП 3,83 | H5: ЛР6 6.1 | I5: 4 | J5: 5 | K5: Problems и подсветка — в R1 | L5: RU-005, RU-006
A6: A-005 | B6: Канвас | C6: Потоки доходов | D6: Самый слабый блок (42 %) | E6: Проверить готовность платить | F6: S-02/S-03 | G6: Индекс доказательности | H6: ЛР6 6.2 | I6: 4 | J6: 5 | K6: Тарифы + заявка в R1; оплата — R2 | L6: RU-018, RU-025
A7: A-006 | B7: Пользовательские сценарии | C7: S-004, S-007 | D7: Ключевой сценарий: шаблон → DSL → Run → Problems → OK → Save/Export | E7: Результат без помощи | F7: S-01 | G7: Паспорта сценариев | H7: ЛР6 6.3 | I7: 5 | J7: 5 | K7: Все шаги сценария — в R1 | L7: RU-001…RU-015
A8: A-007 | B8: Страницы и экраны | C8: P1-состав | D8: P1: лендинг, тарифы, IDE, Problems, сохранение, экспорт, документация | E8: Цепочка ценность → оплата → поддержка | F8: Все | G8: Приоритизация 6.4 | H8: ЛР6 6.4 | I8: 4 | J8: 5 | K8: Экраны P1 — в R1 | L8: RU-017, RU-018
A9: A-008 | B9: Анализ отзывов | C9: Отзывы | D9: 🔲 ДОСНЯТЬ | E9: — | F9: S-01 | G9: — | H9: 🔲 | I9: 1 | J9: 4 | K9: Проверить приоритет onboarding после R1 | L9: RU-021
A10: A-009 | B10: Цифровой товар | C10: Лимиты Free | D10: 5 проектов, 20 версий, SVG/PNG | E10: Граница бесплатного | F10: S-01 | G10: Концепция §6 | H10: 01-project-concept.md | I10: 3 | J10: 5 | K10: Лимиты реализуются в R1 | L10: RU-011, RU-016
A11: A-010 | B11: Канвас | C11: Партнёры | D11: Платёжный провайдер РБ не выбран (R-24) | E11: Приём оплаты | F11: S-02/S-03 | G11: Риск R-24 | H11: Концепция | I11: 4 | J11: 5 | K11: Оплата — R2 | L11: RU-025

Sheet Реестр_единиц
A1: ID | B1: Тип единицы | C1: Название единицы разработки | D1: Роль / сегмент | E1: Связанный сценарий | F1: Блок Канвас | G1: Связь с ценностным предложением 1–5 | H1: Критичность для первого дохода 1–5 | I1: Потенциал удержания 1–5 | J1: Потенциал роста аудитории 1–5 | K1: Доказательность 1–5 | L1: Рыночный стандарт 1–5 | M1: Быстрота реализации 1–5 | N1: Дешевизна реализации 1–5 | O1: Технический риск 1–5 | P1: Риск потери ценности при переносе 1–5 | Q1: Балл первого релиза | R1: Балл следующих релизов | S1: Рекомендованный релиз | T1: Решение | U1: Обоснование
A2: RU-001 | B2: Функция | C2: Редактор DSL (Monaco, подсветка, подсказки) | D2: Активный пользователь | E2: S-004 | F2: Ценностное предложение | G2: 5 | H2: 4 | I2: 4 | J2: 3 | K2: 4 | L2: 5 | M2: 3 | N2: 3 | O2: 2 | P2: 5 | Q2: =IF(A2="","",ROUND((G2*0.18)+(H2*0.15)+(I2*0.12)+(J2*0.08)+(K2*0.13)+(L2*0.1)+(M2*0.12)+(N2*0.12)-(O2*0.07)+(P2*0.1),2)) -> 4.32 | R2: =IF(A2="","",ROUND((I2*0.16)+(J2*0.2)+(K2*0.12)+(L2*0.1)+((6-M2)*0.08)+((6-N2)*0.08)+(O2*0.06)+(P2*0.14)+(G2*0.06),2)) -> 3.82 | S2: =IF(A2="","",IF(AND(G2>=4,H2>=4,K2>=3,P2>=4),"Первый релиз",IF(Q2>=3.7,"Первый релиз",IF(R2>=3.6,"Следующий релиз","Не включать / проверить")))) -> Первый релиз | T2: =IF(A2="","",IF(S2="Первый релиз","Включить в минимальный рыночный выпуск",IF(S2="Следующий релиз","Запланировать после проверки первого релиза","Оставить как гипотезу / проверить позже"))) -> Включить в минимальный рыночный выпуск | U2: Ядро товара
A3: RU-002 | B3: Функция | C3: Разбор DSL и диагностика (Language Service) | D3: Активный пользователь | E3: S-004 | F3: Ключевые ресурсы | G3: 5 | H3: 4 | I3: 4 | J3: 3 | K3: 4 | L3: 5 | M3: 1 | N3: 1 | O3: 3 | P3: 5 | Q3: =IF(A3="","",ROUND((G3*0.18)+(H3*0.15)+(I3*0.12)+(J3*0.08)+(K3*0.13)+(L3*0.1)+(M3*0.12)+(N3*0.12)-(O3*0.07)+(P3*0.1),2)) -> 3.77 | R3: =IF(A3="","",ROUND((I3*0.16)+(J3*0.2)+(K3*0.12)+(L3*0.1)+((6-M3)*0.08)+((6-N3)*0.08)+(O3*0.06)+(P3*0.14)+(G3*0.06),2)) -> 4.2 | S3: =IF(A3="","",IF(AND(G3>=4,H3>=4,K3>=3,P3>=4),"Первый релиз",IF(Q3>=3.7,"Первый релиз",IF(R3>=3.6,"Следующий релиз","Не включать / проверить")))) -> Первый релиз | T3: =IF(A3="","",IF(S3="Первый релиз","Включить в минимальный рыночный выпуск",IF(S3="Следующий релиз","Запланировать после проверки первого релиза","Оставить как гипотезу / проверить позже"))) -> Включить в минимальный рыночный выпуск | U3: Ядро; упростить: восстановление после ошибок — базовое
A4: RU-003 | B4: Функция | C4: Профили нотаций волны 1 с валидацией правил | D4: Активный пользователь | E4: S-004 | F4: Ценностное предложение | G4: 5 | H4: 4 | I4: 4 | J4: 4 | K4: 4 | L4: 2 | M4: 1 | N4: 1 | O4: 4 | P4: 5 | Q4: =IF(A4="","",ROUND((G4*0.18)+(H4*0.15)+(I4*0.12)+(J4*0.08)+(K4*0.13)+(L4*0.1)+(M4*0.12)+(N4*0.12)-(O4*0.07)+(P4*0.1),2)) -> 3.48 | R4: =IF(A4="","",ROUND((I4*0.16)+(J4*0.2)+(K4*0.12)+(L4*0.1)+((6-M4)*0.08)+((6-N4)*0.08)+(O4*0.06)+(P4*0.14)+(G4*0.06),2)) -> 4.16 | S4: =IF(A4="","",IF(AND(G4>=4,H4>=4,K4>=3,P4>=4),"Первый релиз",IF(Q4>=3.7,"Первый релиз",IF(R4>=3.6,"Следующий релиз","Не включать / проверить")))) -> Первый релиз | T4: =IF(A4="","",IF(S4="Первый релиз","Включить в минимальный рыночный выпуск",IF(S4="Следующий релиз","Запланировать после проверки первого релиза","Оставить как гипотезу / проверить позже"))) -> Включить в минимальный рыночный выпуск | U4: Отличие D-01/D-02; упростить: по одной нотации за спринт S4–S7
A5: RU-004 | B5: Функция | C5: Холст SVG + elkjs, pan/zoom, сетка | D5: Новый пользователь | E5: S-003 | F5: Ценностное предложение | G5: 5 | H5: 3 | I5: 4 | J5: 3 | K5: 4 | L5: 5 | M5: 2 | N5: 2 | O5: 3 | P5: 5 | Q5: =IF(A5="","",ROUND((G5*0.18)+(H5*0.15)+(I5*0.12)+(J5*0.08)+(K5*0.13)+(L5*0.1)+(M5*0.12)+(N5*0.12)-(O5*0.07)+(P5*0.1),2)) -> 3.86 | R5: =IF(A5="","",ROUND((I5*0.16)+(J5*0.2)+(K5*0.12)+(L5*0.1)+((6-M5)*0.08)+((6-N5)*0.08)+(O5*0.06)+(P5*0.14)+(G5*0.06),2)) -> 4.04 | S5: =IF(A5="","",IF(AND(G5>=4,H5>=4,K5>=3,P5>=4),"Первый релиз",IF(Q5>=3.7,"Первый релиз",IF(R5>=3.6,"Следующий релиз","Не включать / проверить")))) -> Первый релиз | T5: =IF(A5="","",IF(S5="Первый релиз","Включить в минимальный рыночный выпуск",IF(S5="Следующий релиз","Запланировать после проверки первого релиза","Оставить как гипотезу / проверить позже"))) -> Включить в минимальный рыночный выпуск | U5: Без холста нет результата
A6: RU-005 | B6: Функция | C6: Кросс-подсветка строка ↔ элемент | D6: Активный пользователь | E6: S-008 | F6: Ценностное предложение | G6: 4 | H6: 2 | I6: 3 | J6: 3 | K6: 4 | L6: 2 | M6: 3 | N6: 3 | O6: 2 | P6: 4 | Q6: =IF(A6="","",ROUND((G6*0.18)+(H6*0.15)+(I6*0.12)+(J6*0.08)+(K6*0.13)+(L6*0.1)+(M6*0.12)+(N6*0.12)-(O6*0.07)+(P6*0.1),2)) -> 3.32 | R6: =IF(A6="","",ROUND((I6*0.16)+(J6*0.2)+(K6*0.12)+(L6*0.1)+((6-M6)*0.08)+((6-N6)*0.08)+(O6*0.06)+(P6*0.14)+(G6*0.06),2)) -> 3.16 | S6: =IF(A6="","",IF(AND(G6>=4,H6>=4,K6>=3,P6>=4),"Первый релиз",IF(Q6>=3.7,"Первый релиз",IF(R6>=3.6,"Следующий релиз","Не включать / проверить")))) -> Не включать / проверить | T6: =IF(A6="","",IF(S6="Первый релиз","Включить в минимальный рыночный выпуск",IF(S6="Следующий релиз","Запланировать после проверки первого релиза","Оставить как гипотезу / проверить позже"))) -> Оставить как гипотезу / проверить позже | U6: Шаблон: «Не включать / проверить» (балл R1 3,48 < 3,7) → R2; в agile-plan Must — пересмотр PO
A7: RU-006 | B7: Экран приложения | C7: Terminal/Problems + тосты Error/Warning/OK | D7: Активный пользователь | E7: S-008 | F7: Отношения с клиентами | G7: 5 | H7: 3 | I7: 4 | J7: 2 | K7: 4 | L7: 4 | M7: 4 | N7: 4 | O7: 1 | P7: 5 | Q7: =IF(A7="","",ROUND((G7*0.18)+(H7*0.15)+(I7*0.12)+(J7*0.08)+(K7*0.13)+(L7*0.1)+(M7*0.12)+(N7*0.12)-(O7*0.07)+(P7*0.1),2)) -> 4.3 | R7: =IF(A7="","",ROUND((I7*0.16)+(J7*0.2)+(K7*0.12)+(L7*0.1)+((6-M7)*0.08)+((6-N7)*0.08)+(O7*0.06)+(P7*0.14)+(G7*0.06),2)) -> 3.3 | S7: =IF(A7="","",IF(AND(G7>=4,H7>=4,K7>=3,P7>=4),"Первый релиз",IF(Q7>=3.7,"Первый релиз",IF(R7>=3.6,"Следующий релиз","Не включать / проверить")))) -> Первый релиз | T7: =IF(A7="","",IF(S7="Первый релиз","Включить в минимальный рыночный выпуск",IF(S7="Следующий релиз","Запланировать после проверки первого релиза","Оставить как гипотезу / проверить позже"))) -> Включить в минимальный рыночный выпуск | U7: Носитель ценности «проверка правил»
A8: RU-007 | B8: Контентный блок | C8: Шаблоны нотаций (просмотр, копирование) | D8: Новый пользователь | E8: S-003 | F8: Отношения с клиентами | G8: 4 | H8: 3 | I8: 4 | J8: 4 | K8: 5 | L8: 5 | M8: 5 | N8: 5 | O8: 1 | P8: 4 | Q8: =IF(A8="","",ROUND((G8*0.18)+(H8*0.15)+(I8*0.12)+(J8*0.08)+(K8*0.13)+(L8*0.1)+(M8*0.12)+(N8*0.12)-(O8*0.07)+(P8*0.1),2)) -> 4.65 | R8: =IF(A8="","",ROUND((I8*0.16)+(J8*0.2)+(K8*0.12)+(L8*0.1)+((6-M8)*0.08)+((6-N8)*0.08)+(O8*0.06)+(P8*0.14)+(G8*0.06),2)) -> 3.56 | S8: =IF(A8="","",IF(AND(G8>=4,H8>=4,K8>=3,P8>=4),"Первый релиз",IF(Q8>=3.7,"Первый релиз",IF(R8>=3.6,"Следующий релиз","Не включать / проверить")))) -> Первый релиз | T8: =IF(A8="","",IF(S8="Первый релиз","Включить в минимальный рыночный выпуск",IF(S8="Следующий релиз","Запланировать после проверки первого релиза","Оставить как гипотезу / проверить позже"))) -> Включить в минимальный рыночный выпуск | U8: Первая ценность без обучения
A9: RU-008 | B9: Контентный блок | C9: Вкладка документации (синтаксис + теория) | D9: Новый пользователь | E9: S-009 | F9: Отношения с клиентами | G9: 4 | H9: 2 | I9: 4 | J9: 3 | K9: 4 | L9: 5 | M9: 4 | N9: 4 | O9: 1 | P9: 4 | Q9: =IF(A9="","",ROUND((G9*0.18)+(H9*0.15)+(I9*0.12)+(J9*0.08)+(K9*0.13)+(L9*0.1)+(M9*0.12)+(N9*0.12)-(O9*0.07)+(P9*0.1),2)) -> 4.05 | R9: =IF(A9="","",ROUND((I9*0.16)+(J9*0.2)+(K9*0.12)+(L9*0.1)+((6-M9)*0.08)+((6-N9)*0.08)+(O9*0.06)+(P9*0.14)+(G9*0.06),2)) -> 3.4 | S9: =IF(A9="","",IF(AND(G9>=4,H9>=4,K9>=3,P9>=4),"Первый релиз",IF(Q9>=3.7,"Первый релиз",IF(R9>=3.6,"Следующий релиз","Не включать / проверить")))) -> Первый релиз | T9: =IF(A9="","",IF(S9="Первый релиз","Включить в минимальный рыночный выпуск",IF(S9="Следующий релиз","Запланировать после проверки первого релиза","Оставить как гипотезу / проверить позже"))) -> Включить в минимальный рыночный выпуск | U9: Самообслуживание
A10: RU-009 | B10: Функция | C10: AI-ассистент: заглушка + BYOK, 4 режима | D10: Активный пользователь | E10: S-010 | F10: Ключевые партнеры | G10: 4 | H10: 2 | I10: 3 | J10: 4 | K10: 3 | L10: 3 | M10: 3 | N10: 3 | O10: 3 | P10: 2 | Q10: =IF(A10="","",ROUND((G10*0.18)+(H10*0.15)+(I10*0.12)+(J10*0.08)+(K10*0.13)+(L10*0.1)+(M10*0.12)+(N10*0.12)-(O10*0.07)+(P10*0.1),2)) -> 3.1 | R10: =IF(A10="","",ROUND((I10*0.16)+(J10*0.2)+(K10*0.12)+(L10*0.1)+((6-M10)*0.08)+((6-N10)*0.08)+(O10*0.06)+(P10*0.14)+(G10*0.06),2)) -> 3.12 | S10: =IF(A10="","",IF(AND(G10>=4,H10>=4,K10>=3,P10>=4),"Первый релиз",IF(Q10>=3.7,"Первый релиз",IF(R10>=3.6,"Следующий релиз","Не включать / проверить")))) -> Не включать / проверить | T10: =IF(A10="","",IF(S10="Первый релиз","Включить в минимальный рыночный выпуск",IF(S10="Следующий релиз","Запланировать после проверки первого релиза","Оставить как гипотезу / проверить позже"))) -> Оставить как гипотезу / проверить позже | U10: Шаблон: «Не включать / проверить» → R2; в agile-plan Must (заглушка) — пересмотр PO
A11: RU-010 | B11: Форма | C11: Вход и регистрация (JWT, OAuth) | D11: Новый пользователь | E11: S-005 | F11: Отношения с клиентами | G11: 3 | H11: 4 | I11: 4 | J11: 2 | K11: 5 | L11: 5 | M11: 4 | N11: 4 | O11: 2 | P11: 4 | Q11: =IF(A11="","",ROUND((G11*0.18)+(H11*0.15)+(I11*0.12)+(J11*0.08)+(K11*0.13)+(L11*0.1)+(M11*0.12)+(N11*0.12)-(O11*0.07)+(P11*0.1),2)) -> 4.15 | R11: =IF(A11="","",ROUND((I11*0.16)+(J11*0.2)+(K11*0.12)+(L11*0.1)+((6-M11)*0.08)+((6-N11)*0.08)+(O11*0.06)+(P11*0.14)+(G11*0.06),2)) -> 3.32 | S11: =IF(A11="","",IF(AND(G11>=4,H11>=4,K11>=3,P11>=4),"Первый релиз",IF(Q11>=3.7,"Первый релиз",IF(R11>=3.6,"Следующий релиз","Не включать / проверить")))) -> Первый релиз | T11: =IF(A11="","",IF(S11="Первый релиз","Включить в минимальный рыночный выпуск",IF(S11="Следующий релиз","Запланировать после проверки первого релиза","Оставить как гипотезу / проверить позже"))) -> Включить в минимальный рыночный выпуск | U11: Нужен для сохранения в БД (Must) и лимитов Free
A12: RU-011 | B12: Функция | C12: Сохранение в БД аккаунта (лимит Free 5 проектов) | D12: Активный пользователь | E12: S-005 | F12: Потоки доходов | G12: 4 | H12: 5 | I12: 5 | J12: 2 | K12: 4 | L12: 4 | M12: 3 | N12: 3 | O12: 2 | P12: 5 | Q12: =IF(A12="","",ROUND((G12*0.18)+(H12*0.15)+(I12*0.12)+(J12*0.08)+(K12*0.13)+(L12*0.1)+(M12*0.12)+(N12*0.12)-(O12*0.07)+(P12*0.1),2)) -> 4.23 | R12: =IF(A12="","",ROUND((I12*0.16)+(J12*0.2)+(K12*0.12)+(L12*0.1)+((6-M12)*0.08)+((6-N12)*0.08)+(O12*0.06)+(P12*0.14)+(G12*0.06),2)) -> 3.62 | S12: =IF(A12="","",IF(AND(G12>=4,H12>=4,K12>=3,P12>=4),"Первый релиз",IF(Q12>=3.7,"Первый релиз",IF(R12>=3.6,"Следующий релиз","Не включать / проверить")))) -> Первый релиз | T12: =IF(A12="","",IF(S12="Первый релиз","Включить в минимальный рыночный выпуск",IF(S12="Следующий релиз","Запланировать после проверки первого релиза","Оставить как гипотезу / проверить позже"))) -> Включить в минимальный рыночный выпуск | U12: Удержание + тарифный ограничитель
A13: RU-012 | B13: Функция | C13: Сохранение на устройство | D13: Активный пользователь | E13: S-005 | F13: Ценностное предложение | G13: 4 | H13: 2 | I13: 3 | J13: 1 | K13: 5 | L13: 5 | M13: 5 | N13: 5 | O13: 1 | P13: 4 | Q13: =IF(A13="","",ROUND((G13*0.18)+(H13*0.15)+(I13*0.12)+(J13*0.08)+(K13*0.13)+(L13*0.1)+(M13*0.12)+(N13*0.12)-(O13*0.07)+(P13*0.1),2)) -> 4.14 | R13: =IF(A13="","",ROUND((I13*0.16)+(J13*0.2)+(K13*0.12)+(L13*0.1)+((6-M13)*0.08)+((6-N13)*0.08)+(O13*0.06)+(P13*0.14)+(G13*0.06),2)) -> 2.8 | S13: =IF(A13="","",IF(AND(G13>=4,H13>=4,K13>=3,P13>=4),"Первый релиз",IF(Q13>=3.7,"Первый релиз",IF(R13>=3.6,"Следующий релиз","Не включать / проверить")))) -> Первый релиз | T13: =IF(A13="","",IF(S13="Первый релиз","Включить в минимальный рыночный выпуск",IF(S13="Следующий релиз","Запланировать после проверки первого релиза","Оставить как гипотезу / проверить позже"))) -> Включить в минимальный рыночный выпуск | U13: Работа гостя без аккаунта
... A39: RU-038 | B39: Функция | C39: Совместное редактирование в реальном времени | D39: Платящий клиент | E39: S-004 | F39: Ценностное предложение | G39: 2 | H39: 2 | I39: 3 | J39: 3 | K39: 2 | L39: 2 | M39: 1 | N39: 1 | O39: 5 | P39: 1 | Q39: =IF(A39="","",ROUND((G39*0.18)+(H39*0.15)+(I39*0.12)+(J39*0.08)+(K39*0.13)+(L39*0.1)+(M39*0.12)+(N39*0.12)-(O39*0.07)+(P39*0.1),2)) -> 1.71 | R39: =IF(A39="","",ROUND((I39*0.16)+(J39*0.2)+(K39*0.12)+(L39*0.1)+((6-M39)*0.08)+((6-N39)*0.08)+(O39*0.06)+(P39*0.14)+(G39*0.06),2)) -> 2.88 | S39: =IF(A39="","",IF(AND(G39>=4,H39>=4,K39>=3,P39>=4),"Первый релиз",IF(Q39>=3.7,"Первый релиз",IF(R39>=3.6,"Следующий релиз","Не включать / проверить")))) -> Не включать / проверить | T39: =IF(A39="","",IF(S39="Первый релиз","Включить в минимальный рыночный выпуск",IF(S39="Следующий релиз","Запланировать после проверки первого релиза","Оставить как гипотезу / проверить позже"))) -> Оставить как гипотезу / проверить позже | U39: Won't; вне ближайшего цикла
Q40: =IF(A40="","",ROUND((G40*0.18)+(H40*0.15)+(I40*0.12)+(J40*0.08)+(K40*0.13)+(L40*0.1)+(M40*0.12)+(N40*0.12)-(O40*0.07)+(P40*0.1),2)) | R40: =IF(A40="","",ROUND((I40*0.16)+(J40*0.2)+(K40*0.12)+(L40*0.1)+((6-M40)*0.08)+((6-N40)*0.08)+(O40*0.06)+(P40*0.14)+(G40*0.06),2)) | S40: =IF(A40="","",IF(AND(G40>=4,H40>=4,K40>=3,P40>=4),"Первый релиз",IF(Q40>=3.7,"Первый релиз",IF(R40>=3.6,"Следующий релиз","Не включать / проверить")))) | T40: =IF(A40="","",IF(S40="Первый релиз","Включить в минимальный рыночный выпуск",IF(S40="Следующий релиз","Запланировать после проверки первого релиза","Оставить как гипотезу / проверить позже")))
Q41: =IF(A41="","",ROUND((G41*0.18)+(H41*0.15)+(I41*0.12)+(J41*0.08)+(K41*0.13)+(L41*0.1)+(M41*0.12)+(N41*0.12)-(O41*0.07)+(P41*0.1),2)) | R41: =IF(A41="","",ROUND((I41*0.16)+(J41*0.2)+(K41*0.12)+(L41*0.1)+((6-M41)*0.08)+((6-N41)*0.08)+(O41*0.06)+(P41*0.14)+(G41*0.06),2)) | S41: =IF(A41="","",IF(AND(G41>=4,H41>=4,K41>=3,P41>=4),"Первый релиз",IF(Q41>=3.7,"Первый релиз",IF(R41>=3.6,"Следующий релиз","Не включать / проверить")))) | T41: =IF(A41="","",IF(S41="Первый релиз","Включить в минимальный рыночный выпуск",IF(S41="Следующий релиз","Запланировать после проверки первого релиза","Оставить как гипотезу / проверить позже")))
Q42: =IF(A42="","",ROUND((G42*0.18)+(H42*0.15)+(I42*0.12)+(J42*0.08)+(K42*0.13)+(L42*0.1)+(M42*0.12)+(N42*0.12)-(O42*0.07)+(P42*0.1),2)) | R42: =IF(A42="","",ROUND((I42*0.16)+(J42*0.2)+(K42*0.12)+(L42*0.1)+((6-M42)*0.08)+((6-N42)*0.08)+(O42*0.06)+(P42*0.14)+(G42*0.06),2)) | S42: =IF(A42="","",IF(AND(G42>=4,H42>=4,K42>=3,P42>=4),"Первый релиз",IF(Q42>=3.7,"Первый релиз",IF(R42>=3.6,"Следующий релиз","Не включать / проверить")))) | T42: =IF(A42="","",IF(S42="Первый релиз","Включить в минимальный рыночный выпуск",IF(S42="Следующий релиз","Запланировать после проверки первого релиза","Оставить как гипотезу / проверить позже")))
Q43: =IF(A43="","",ROUND((G43*0.18)+(H43*0.15)+(I43*0.12)+(J43*0.08)+(K43*0.13)+(L43*0.1)+(M43*0.12)+(N43*0.12)-(O43*0.07)+(P43*0.1),2)) | R43: =IF(A43="","",ROUND((I43*0.16)+(J43*0.2)+(K43*0.12)+(L43*0.1)+((6-M43)*0.08)+((6-N43)*0.08)+(O43*0.06)+(P43*0.14)+(G43*0.06),2)) | S43: =IF(A43="","",IF(AND(G43>=4,H43>=4,K43>=3,P43>=4),"Первый релиз",IF(Q43>=3.7,"Первый релиз",IF(R43>=3.6,"Следующий релиз","Не включать / проверить")))) | T43: =IF(A43="","",IF(S43="Первый релиз","Включить в минимальный рыночный выпуск",IF(S43="Следующий релиз","Запланировать после проверки первого релиза","Оставить как гипотезу / проверить позже")))
Q44: =IF(A44="","",ROUND((G44*0.18)+(H44*0.15)+(I44*0.12)+(J44*0.08)+(K44*0.13)+(L44*0.1)+(M44*0.12)+(N44*0.12)-(O44*0.07)+(P44*0.1),2)) | R44: =IF(A44="","",ROUND((I44*0.16)+(J44*0.2)+(K44*0.12)+(L44*0.1)+((6-M44)*0.08)+((6-N44)*0.08)+(O44*0.06)+(P44*0.14)+(G44*0.06),2)) | S44: =IF(A44="","",IF(AND(G44>=4,H44>=4,K44>=3,P44>=4),"Первый релиз",IF(Q44>=3.7,"Первый релиз",IF(R44>=3.6,"Следующий релиз","Не включать / проверить")))) | T44: =IF(A44="","",IF(S44="Первый релиз","Включить в минимальный рыночный выпуск",IF(S44="Следующий релиз","Запланировать после проверки первого релиза","Оставить как гипотезу / проверить позже")))
Q45: =IF(A45="","",ROUND((G45*0.18)+(H45*0.15)+(I45*0.12)+(J45*0.08)+(K45*0.13)+(L45*0.1)+(M45*0.12)+(N45*0.12)-(O45*0.07)+(P45*0.1),2)) | R45: =IF(A45="","",ROUND((I45*0.16)+(J45*0.2)+(K45*0.12)+(L45*0.1)+((6-M45)*0.08)+((6-N45)*0.08)+(O45*0.06)+(P45*0.14)+(G45*0.06),2)) | S45: =IF(A45="","",IF(AND(G45>=4,H45>=4,K45>=3,P45>=4),"Первый релиз",IF(Q45>=3.7,"Первый релиз",IF(R45>=3.6,"Следующий релиз","Не включать / проверить")))) | T45: =IF(A45="","",IF(S45="Первый релиз","Включить в минимальный рыночный выпуск",IF(S45="Следующий релиз","Запланировать после проверки первого релиза","Оставить как гипотезу / проверить позже")))
Q46: =IF(A46="","",ROUND((G46*0.18)+(H46*0.15)+(I46*0.12)+(J46*0.08)+(K46*0.13)+(L46*0.1)+(M46*0.12)+(N46*0.12)-(O46*0.07)+(P46*0.1),2)) | R46: =IF(A46="","",ROUND((I46*0.16)+(J46*0.2)+(K46*0.12)+(L46*0.1)+((6-M46)*0.08)+((6-N46)*0.08)+(O46*0.06)+(P46*0.14)+(G46*0.06),2)) | S46: =IF(A46="","",IF(AND(G46>=4,H46>=4,K46>=3,P46>=4),"Первый релиз",IF(Q46>=3.7,"Первый релиз",IF(R46>=3.6,"Следующий релиз","Не включать / проверить")))) | T46: =IF(A46="","",IF(S46="Первый релиз","Включить в минимальный рыночный выпуск",IF(S46="Следующий релиз","Запланировать после проверки первого релиза","Оставить как гипотезу / проверить позже")))
Q47: =IF(A47="","",ROUND((G47*0.18)+(H47*0.15)+(I47*0.12)+(J47*0.08)+(K47*0.13)+(L47*0.1)+(M47*0.12)+(N47*0.12)-(O47*0.07)+(P47*0.1),2)) | R47: =IF(A47="","",ROUND((I47*0.16)+(J47*0.2)+(K47*0.12)+(L47*0.1)+((6-M47)*0.08)+((6-N47)*0.08)+(O47*0.06)+(P47*0.14)+(G47*0.06),2)) | S47: =IF(A47="","",IF(AND(G47>=4,H47>=4,K47>=3,P47>=4),"Первый релиз",IF(Q47>=3.7,"Первый релиз",IF(R47>=3.6,"Следующий релиз","Не включать / проверить")))) | T47: =IF(A47="","",IF(S47="Первый релиз","Включить в минимальный рыночный выпуск",IF(S47="Следующий релиз","Запланировать после проверки первого релиза","Оставить как гипотезу / проверить позже")))
Q48: =IF(A48="","",ROUND((G48*0.18)+(H48*0.15)+(I48*0.12)+(J48*0.08)+(K48*0.13)+(L48*0.1)+(M48*0.12)+(N48*0.12)-(O48*0.07)+(P48*0.1),2)) | R48: =IF(A48="","",ROUND((I48*0.16)+(J48*0.2)+(K48*0.12)+(L48*0.1)+((6-M48)*0.08)+((6-N48)*0.08)+(O48*0.06)+(P48*0.14)+(G48*0.06),2)) | S48: =IF(A48="","",IF(AND(G48>=4,H48>=4,K48>=3,P48>=4),"Первый релиз",IF(Q48>=3.7,"Первый релиз",IF(R48>=3.6,"Следующий релиз","Не включать / проверить")))) | T48: =IF(A48="","",IF(S48="Первый релиз","Включить в минимальный рыночный выпуск",IF(S48="Следующий релиз","Запланировать после проверки первого релиза","Оставить как гипотезу / проверить позже")))
Q49: =IF(A49="","",ROUND((G49*0.18)+(H49*0.15)+(I49*0.12)+(J49*0.08)+(K49*0.13)+(L49*0.1)+(M49*0.12)+(N49*0.12)-(O49*0.07)+(P49*0.1),2)) | R49: =IF(A49="","",ROUND((I49*0.16)+(J49*0.2)+(K49*0.12)+(L49*0.1)+((6-M49)*0.08)+((6-N49)*0.08)+(O49*0.06)+(P49*0.14)+(G49*0.06),2)) | S49: =IF(A49="","",IF(AND(G49>=4,H49>=4,K49>=3,P49>=4),"Первый релиз",IF(Q49>=3.7,"Первый релиз",IF(R49>=3.6,"Следующий релиз","Не включать / проверить")))) | T49: =IF(A49="","",IF(S49="Первый релиз","Включить в минимальный рыночный выпуск",IF(S49="Следующий релиз","Запланировать после проверки первого релиза","Оставить как гипотезу / проверить позже")))
Q50: =IF(A50="","",ROUND((G50*0.18)+(H50*0.15)+(I50*0.12)+(J50*0.08)+(K50*0.13)+(L50*0.1)+(M50*0.12)+(N50*0.12)-(O50*0.07)+(P50*0.1),2)) | R50: =IF(A50="","",ROUND((I50*0.16)+(J50*0.2)+(K50*0.12)+(L50*0.1)+((6-M50)*0.08)+((6-N50)*0.08)+(O50*0.06)+(P50*0.14)+(G50*0.06),2)) | S50: =IF(A50="","",IF(AND(G50>=4,H50>=4,K50>=3,P50>=4),"Первый релиз",IF(Q50>=3.7,"Первый релиз",IF(R50>=3.6,"Следующий релиз","Не включать / проверить")))) | T50: =IF(A50="","",IF(S50="Первый релиз","Включить в минимальный рыночный выпуск",IF(S50="Следующий релиз","Запланировать после проверки первого релиза","Оставить как гипотезу / проверить позже")))
Q51: =IF(A51="","",ROUND((G51*0.18)+(H51*0.15)+(I51*0.12)+(J51*0.08)+(K51*0.13)+(L51*0.1)+(M51*0.12)+(N51*0.12)-(O51*0.07)+(P51*0.1),2)) | R51: =IF(A51="","",ROUND((I51*0.16)+(J51*0.2)+(K51*0.12)+(L51*0.1)+((6-M51)*0.08)+((6-N51)*0.08)+(O51*0.06)+(P51*0.14)+(G51*0.06),2)) | S51: =IF(A51="","",IF(AND(G51>=4,H51>=4,K51>=3,P51>=4),"Первый релиз",IF(Q51>=3.7,"Первый релиз",IF(R51>=3.6,"Следующий релиз","Не включать / проверить")))) | T51: =IF(A51="","",IF(S51="Первый релиз","Включить в минимальный рыночный выпуск",IF(S51="Следующий релиз","Запланировать после проверки первого релиза","Оставить как гипотезу / проверить позже")))
... Q101: =IF(A101="","",ROUND((G101*0.18)+(H101*0.15)+(I101*0.12)+(J101*0.08)+(K101*0.13)+(L101*0.1)+(M101*0.12)+(N101*0.12)-(O101*0.07)+(P101*0.1),2)) | R101: =IF(A101="","",ROUND((I101*0.16)+(J101*0.2)+(K101*0.12)+(L101*0.1)+((6-M101)*0.08)+((6-N101)*0.08)+(O101*0.06)+(P101*0.14)+(G101*0.06),2)) | S101: =IF(A101="","",IF(AND(G101>=4,H101>=4,K101>=3,P101>=4),"Первый релиз",IF(Q101>=3.7,"Первый релиз",IF(R101>=3.6,"Следующий релиз","Не включать / проверить")))) | T101: =IF(A101="","",IF(S101="Первый релиз","Включить в минимальный рыночный выпуск",IF(S101="Следующий релиз","Запланировать после проверки первого релиза","Оставить как гипотезу / проверить позже")))

Sheet Оценка_релизов
A1: Сводная оценка состава релизов
A3: Релиз | B3: Количество единиц | C3: Средний балл первого релиза | D3: Средняя доказательность | E3: Средняя связь с ценностью | F3: Средняя критичность дохода | G3: Среднее удержание | H3: Средний рост | I3: Средний технический риск | J3: Интерпретация
A4: Первый релиз | B4: =COUNTIF(Реестр_единиц!$S$2:$S$101,A4) -> 16 | C4: =IFERROR(AVERAGEIF(Реестр_единиц!$S$2:$S$101,A4,Реестр_единиц!$Q$2:$Q$101),0) -> 4.124375 | D4: =IFERROR(AVERAGEIF(Реестр_единиц!$S$2:$S$101,A4,Реестр_единиц!$K$2:$K$101),0) -> 4.375 | E4: =IFERROR(AVERAGEIF(Реестр_единиц!$S$2:$S$101,A4,Реестр_единиц!$G$2:$G$101),0) -> 4.25 | F4: =IFERROR(AVERAGEIF(Реестр_единиц!$S$2:$S$101,A4,Реестр_единиц!$H$2:$H$101),0) -> 3.5 | G4: =IFERROR(AVERAGEIF(Реестр_единиц!$S$2:$S$101,A4,Реестр_единиц!$I$2:$I$101),0) -> 3.6875 | H4: =IFERROR(AVERAGEIF(Реестр_единиц!$S$2:$S$101,A4,Реестр_единиц!$J$2:$J$101),0) -> 3 | I4: =IFERROR(AVERAGEIF(Реестр_единиц!$S$2:$S$101,A4,Реестр_единиц!$O$2:$O$101),0) -> 1.9375 | J4: =IF(B4=0,"Нет выбранных единиц",IF(AND(E4>=4,D4>=3.5),"Состав достаточно обоснован","Требуется дополнительная проверка")) -> Состав достаточно обоснован
A5: Следующий релиз | B5: =COUNTIF(Реестр_единиц!$S$2:$S$101,A5) -> 1 | C5: =IFERROR(AVERAGEIF(Реестр_единиц!$S$2:$S$101,A5,Реестр_единиц!$Q$2:$Q$101),0) -> 2.8 | D5: =IFERROR(AVERAGEIF(Реестр_единиц!$S$2:$S$101,A5,Реестр_единиц!$K$2:$K$101),0) -> 3 | E5: =IFERROR(AVERAGEIF(Реестр_единиц!$S$2:$S$101,A5,Реестр_единиц!$G$2:$G$101),0) -> 4 | F5: =IFERROR(AVERAGEIF(Реестр_единиц!$S$2:$S$101,A5,Реестр_единиц!$H$2:$H$101),0) -> 3 | G5: =IFERROR(AVERAGEIF(Реестр_единиц!$S$2:$S$101,A5,Реестр_единиц!$I$2:$I$101),0) -> 3 | H5: =IFERROR(AVERAGEIF(Реестр_единиц!$S$2:$S$101,A5,Реестр_единиц!$J$2:$J$101),0) -> 4 | I5: =IFERROR(AVERAGEIF(Реестр_единиц!$S$2:$S$101,A5,Реестр_единиц!$O$2:$O$101),0) -> 4 | J5: =IF(B5=0,"Нет выбранных единиц",IF(AND(E5>=4,D5>=3.5),"Состав достаточно обоснован","Требуется дополнительная проверка")) -> Требуется дополнительная проверка
A6: Не включать / проверить | B6: =COUNTIF(Реестр_единиц!$S$2:$S$101,A6) -> 21 | C6: =IFERROR(AVERAGEIF(Реестр_единиц!$S$2:$S$101,A6,Реестр_единиц!$Q$2:$Q$101),0) -> 2.7333333 | D6: =IFERROR(AVERAGEIF(Реестр_единиц!$S$2:$S$101,A6,Реестр_единиц!$K$2:$K$101),0) -> 2.9047619 | E6: =IFERROR(AVERAGEIF(Реестр_единиц!$S$2:$S$101,A6,Реестр_единиц!$G$2:$G$101),0) -> 2.952381 | F6: =IFERROR(AVERAGEIF(Реестр_единиц!$S$2:$S$101,A6,Реестр_единиц!$H$2:$H$101),0) -> 2.1428571 | G6: =IFERROR(AVERAGEIF(Реестр_единиц!$S$2:$S$101,A6,Реестр_единиц!$I$2:$I$101),0) -> 2.8095238 | H6: =IFERROR(AVERAGEIF(Реестр_единиц!$S$2:$S$101,A6,Реестр_единиц!$J$2:$J$101),0) -> 2.952381 | I6: =IFERROR(AVERAGEIF(Реестр_единиц!$S$2:$S$101,A6,Реестр_единиц!$O$2:$O$101),0) -> 2.7619048 | J6: =IF(B6=0,"Нет выбранных единиц",IF(AND(E6>=4,D6>=3.5),"Состав достаточно обоснован","Требуется дополнительная проверка")) -> Требуется дополнительная проверка

Sheet Первый_релиз
A1: План первого релиза: быстрый и экономный выход на рынок без разрушения ценности
A3: ID | B3: Единица первого релиза | C3: Зачем нужна в первом релизе | D3: Проверяемая гипотеза | E3: Минимальная реализация | F3: Критерий готовности | G3: Метрика после запуска | H3: Ответственный
A4: FR-001 | B4: Ядро: редактор + разбор + профили волны 1 + холст + Problems (RU-001…004, RU-006) | C4: Даёт ключевой результат — корректную диаграмму | D4: Студент проходит S-004 до OK без помощи | E4: 7 нотаций волны 1, по одной за спринт; автоисправлений нет | F4: Сценарий S-004 проходит e2e на каждой нотации | G4: Доля Run OK ≤ 3 итераций | H4: Хаджинова К. (PO/разработчик)
A5: FR-002 | B5: Шаблоны + документация (RU-007, RU-008) | C5: Снижает отказ до первой ценности | D5: Шаблон ускоряет первый Run | E5: Один шаблон на тип диаграммы, статьи из каталога | F5: Шаблоны проходят валидатор в CI | G5: Активация ≤ 10 мин | H5: Хаджинова К.
A6: FR-003 | B6: Сохранение БД/устройство, GitHub push, экспорт SVG/PNG/XML, история 20 версий (RU-010…016) | C6: Результат наружу и повод вернуться | D6: Пользователи возвращаются к проекту | E6: Ручной push; Drive — R2 | F6: Сохранение и экспорт без потери данных | G6: Возврат D7, экспортов на пользователя | H6: Хаджинова К.
A7: FR-004 | B7: Лендинг + тарифы + заявка «Хочу Pro» + модалка лимита (RU-017, RU-018) | C7: Проверка монетизации без провайдера оплаты | D7: ≥ 3 % Free оставят заявку (H-02) | E7: Статичная страница + форма заявки | F7: Лимит → тарифы → заявка работает | G7: Заявки ÷ упоры в лимит | H7: Хаджинова К.
A8: FR-005 | B8: Аналитика + обратная связь + правовые документы (RU-019, RU-020) | C8: Измерение поведения и законность | D8: События дают решение о R2 | E8: События Run/экспорт/лимит/заявка; форма в статус-баре | F8: События видны в отчёте | G8: Покрытие событиями ключевых шагов 100 % | H8: Хаджинова К.

Sheet Следующие_релизы
A1: План последующих релизов: развитие удержания, роста и операционной эффективности
A3: ID | B3: Релиз | C3: Единица развития | D3: Основание переноса | E3: Условие включения | F3: Ожидаемый эффект | G3: Связанная метрика | H3: Зависимости | I3: Комментарий
A4: NR-001 | B4: Релиз 2 | C4: Оплата Pro (RU-025) | D4: Нет провайдера РБ; нужны данные заявок R1 | E4: Заявки ≥ 3 % Free; провайдер выбран | F4: Поток доходов | G4: Выручка, конверсия | H4: RU-018, R-24
A5: NR-002 | B5: Релиз 2 | C5: Кросс-подсветка, AI-заглушка/BYOK, onboarding, quick fix, undo/redo (RU-005, RU-009, RU-021…023) | D5: Нужны данные об ошибках R1 | E5: Топ-10 ошибок R1 известны | F5: Снижение отказов | G5: Активация, D7 | H5: RU-006
A6: NR-003 | B6: Релиз 2 | C6: Google Drive, центр уведомлений, PWA, импорт (RU-014, RU-024, RU-026, RU-027) | D6: ИРП 1,3–1,85; не обязательны для ядра | E6: Запросы пользователей | F6: Удержание | G6: Повторное использование | H6: RU-013
A7: NR-004 | B7: Релиз 3 | C7: Публичные ссылки, кабинет преподавателя, RU/EN, реферал (RU-028…030, RU-033) | D7: Рост без удержания теряет аудиторию | E7: D7 ≥ 25 % | F7: Рост аудитории | G7: Новые пользователи по ссылкам | H7: R2
A8: NR-005 | B8: Релиз 3 | C8: Волна 2 нотаций и Pro-форматы экспорта (RU-031, RU-032) | D8: Высокая сложность; для S-02/S-03 | E8: Оплаты Pro идут | F8: Глубина ценности Pro | G8: ARPPU, доля Pro | H8: Каталог нотаций
A9: NR-006 | B9: Релиз 4 | C9: Серверный AI, волна 3, Kroki, изображение → DSL (RU-034…037) | D9: Переменные затраты и сложность | E9: Понятна юнит-экономика | F9: Расширение продукта | G9: Маржа на Pro | H9: R3

Sheet Дорожная_карта
A1: Дорожная карта релизов
A3: Релиз | B3: Цель релиза | C3: Состав | D3: Ключевая гипотеза | E3: Что измеряем | F3: Критерий перехода к следующему релизу | G3: Ограничение бюджета / срока | H3: Риски | I3: Решение по запуску | J3: Дата начала | K3: Дата окончания
A4: Релиз 0 (подготовительный) | B4: Данные, прототип, правила, аналитика | C4: Требования, архитектура, ADR, мокапы, карта сценариев, walking skeleton, CI, план событий, тексты тарифов и правовых документов | D4: Прототип подтверждает сценарий S-004 | E4: Готовность skeleton, покрытие 100 % | F4: Skeleton web → gateway → language работает | G4: S0; бюджет 0 | H4: Объём распределённой системы | I4: Выполнен частично (S0) | J4: 46286 | K4: 46299
A5: Первый релиз (R1, MVP) | B5: Проверить ЦП и готовность к целевому действию | C5: RU-001…RU-004, RU-006…RU-008, RU-010…RU-013, RU-015…RU-020 (17 единиц: 16 по расчёту шаблона + RU-020) | D5: Студенты получают корректную диаграмму и возвращаются; ≥ 3 % Free оставляют заявку Pro | E5: Активация, Run OK, D7, экспорт, заявки Pro | F5: Контрольный лист R1 пройден; H-02 и H-05 измерены | G5: S1–S10, MVP к 06.12.2026; бюджет 0 | H5: Не успеть волну 1 → упростить по нотациям | I5: Запуск при прохождении контрольного листа | J5: 46293 | K5: 46362
A6: Релиз 2 | B6: Удержание, качество, запуск оплаты Pro | C6: RU-005, RU-009, RU-014, RU-021…RU-027 | D6: Подсветка, AI-заглушка, onboarding и quick fix снижают отказы; оплата подтверждает цену | E6: D7, D30, конверсия в оплату | F6: D7 ≥ 25 %, есть оплаты Pro | G6: Январь–февраль 2027 (допущение) | H6: Провайдер оплаты РБ | I6: После данных R1 | J6: 46398 | K6: 46446
A7: Релиз 3 | B7: Рост аудитории | C7: RU-028…RU-033 | D7: Преподаватели и ссылки приводят студентов | E7: Новые пользователи по каналам, доля Pro | F7: Подтверждён масштабируемый канал | G7: Март–май 2027 (допущение) | H7: Рост без удержания | I7: После подтверждения удержания | J7: 46447 | K7: 46538
A8: Релиз 4 | B8: Расширение продукта | C8: RU-034…RU-037 | D8: Серверный AI и волна 3 повышают ARPPU | E8: ARPPU, маржа, затраты LLM | F8: Юнит-экономика положительна | G8: Июнь–сентябрь 2027 (допущение) | H8: Затраты LLM | I8: После понимания экономики | J8: 46539 | K8: 46660

Sheet Проверка_ценности
A1: Контрольный лист: первый релиз сохраняет ценностное предложение, монетизацию, удержание и рост
A3: Блок проверки | B3: Контрольный вопрос | C3: Оценка 1–5 | D3: Доказательство | E3: Риск при низкой оценке | F3: Решение | G3: Что добавить / изменить | H3: Ответственный | I3: Статус
A4: Ценность | B4: Может ли пользователь получить обещанный результат в R1? | C4: 5 | D4: RU-001…006: сценарий S-004 целиком | E4: R1 не подтвердит ЦП | F4: Оставить в первом релизе | H4: Хаджинова К. | I4: Готово
A5: Проблема | B5: Закрывает ли R1 опорную проблему P-001? | C5: 4 | D5: Валидация волны 1; отзывы — 🔲 | E5: Проверка второстепенной гипотезы | F5: Подтвердить отзывами и опросом | G5: Опрос H-01 | H5: Хаджинова К. | I5: В работе
A6: Монетизация | B6: Есть ли единица монетизации или целевое действие? | C6: 4 | D6: Тарифы + заявка «Хочу Pro» + лимиты Free | E6: Нельзя проверить бизнес-модель | F6: Включить заявку; оплата — R2 | H6: Хаджинова К. | I6: Готово
A7: Удержание | B7: Есть ли механизм возврата? | C7: 4 | D7: Сохранение в аккаунт, история 20 версий, GitHub | E7: Привлечёт, но не удержит | F7: Оставить | G7: Напоминание о проекте — R2 | H7: Хаджинова К. | I7: Готово
A8: Рост | B8: Собираются ли данные для решений? | C8: 4 | D8: События аналитики + обратная связь | E8: R2 без фактов | F8: Включить минимальную аналитику | H8: Хаджинова К. | I8: Готово
A9: Экономичность | B9: Не включены ли дорогие функции? | C9: 4 | D9: Серверный AI, волны 2–3, Drive, оплата — перенесены | E9: Перерасход до проверки спроса | F9: Перенести тяжёлые функции | H9: Хаджинова К. | I9: Готово

Sheet Риски_зависимости
A1: Риски, зависимости и условия переноса функций между релизами
A3: ID | B3: Единица / решение | C3: Риск | D3: Тип риска | E3: Вероятность 1–5 | F3: Влияние 1–5 | G3: Индекс риска | H3: Митигирующее действие | I3: Связанный релиз | J3: Ответственный
A4: R-001 | B4: Профили нотаций волны 1 | C4: Не успеть все 7 нотаций к S10 | D4: Срок | E4: 3 | F4: 5 | G4: =IF(A4="","",E4*F4) -> 15 | H4: Упростить: приоритет UML class, ERD, IDEF0; остальное — по готовности | I4: Первый релиз | J4: Хаджинова К.
A5: R-002 | B5: Заявка вместо оплаты | C5: Заявка не отражает реальную готовность платить | D5: Монетизация | E5: 4 | F5: 3 | G5: =IF(A5="","",E5*F5) -> 12 | H5: Спросить сумму и способ оплаты в форме; оплата в R2 | I5: Первый релиз | J5: Хаджинова К.
A6: R-003 | B6: Платёжный провайдер РБ | C6: Нет провайдера для приёма USD/BYN | D6: Монетизация | E6: 3 | F6: 4 | G6: =IF(A6="","",E6*F6) -> 12 | H6: Выбрать провайдера до R2 (R-24) | I6: Следующий релиз | J6: Хаджинова К.
A7: R-004 | B7: Перенос Google Drive | C7: Часть S-01 хранит работы в Drive | D7: Удержание | E7: 2 | F7: 2 | G7: =IF(A7="","",E7*F7) -> 4 | H7: Экспорт на устройство + ручная загрузка; Drive в R2 | I7: Следующий релиз | J7: Хаджинова К.
A8: R-005 | B8: Аналитика | C8: Сбор событий нарушит приватность | D8: Данные | E8: 2 | F8: 4 | G8: =IF(A8="","",E8*F8) -> 8 | H8: Анонимные события, политика конфиденциальности (RU-020) | I8: Первый релиз | J8: Хаджинова К.
A9: R-006 | B9: AI-заглушка | C9: Пользователь разочаруется заглушкой | D9: Ценность | E9: 3 | F9: 2 | G9: =IF(A9="","",E9*F9) -> 6 | H9: Честная подпись «демо», BYOK | I9: Первый релиз | J9: Хаджинова К.
A10: R-007 | B10: Серверный AI | C10: Затраты LLM растут быстрее выручки | D10: Стоимость | E10: 3 | F10: 4 | G10: =IF(A10="","",E10*F10) -> 12 | H10: Квоты Redis token bucket; только Pro; R4 | I10: Бэклог | J10: Хаджинова К.
A11: R-008 | B11: Лабы съедают время продукта | C11: Срыв спринтов продукта | D11: Срок | E11: 4 | F11: 4 | G11: =IF(A11="","",E11*F11) -> 16 | H11: Лаба = часть продукта; дорожка Expedite (agile-plan §12) | I11: Первый релиз | J11: Хаджинова К.
G12: =IF(A12="","",E12*F12)
G13: =IF(A13="","",E13*F13)
G14: =IF(A14="","",E14*F14)
G15: =IF(A15="","",E15*F15)
G16: =IF(A16="","",E16*F16)
G17: =IF(A17="","",E17*F17)
G18: =IF(A18="","",E18*F18)
G19: =IF(A19="","",E19*F19)
G20: =IF(A20="","",E20*F20)
G21: =IF(A21="","",E21*F21)
G22: =IF(A22="","",E22*F22)
G23: =IF(A23="","",E23*F23)
... G100: =IF(A100="","",E100*F100)

Sheet Дашборд
A1: Дашборд готовности релизного плана
A3: Показатель | B3: Значение | C3: Интерпретация | E3: Релиз | F3: Количество
A4: Всего единиц разработки | B4: =COUNTA(Реестр_единиц!$A$2:$A$101) -> 38 | C4: Количество страниц, экранов, функций, интеграций и контентных блоков в реестре | E4: Первый релиз | F4: =COUNTIF(Реестр_единиц!$S$2:$S$101,E4) -> 16
A5: Единиц в первом релизе | B5: =COUNTIF(Реестр_единиц!$S$2:$S$101,"Первый релиз") -> 16 | C5: Объем минимального рыночного выпуска | E5: Следующий релиз | F5: =COUNTIF(Реестр_единиц!$S$2:$S$101,E5) -> 1
A6: Средний балл первого релиза | B6: =IFERROR(AVERAGEIF(Реестр_единиц!$S$2:$S$101,"Первый релиз",Реестр_единиц!$Q$2:$Q$101),0) -> 4.124375 | C6: Насколько первый релиз сочетает ценность, скорость и экономичность | E6: Не включать / проверить | F6: =COUNTIF(Реестр_единиц!$S$2:$S$101,E6) -> 21
A7: Средняя связь с ценностным предложением в первом релизе | B7: =IFERROR(AVERAGEIF(Реестр_единиц!$S$2:$S$101,"Первый релиз",Реестр_единиц!$G$2:$G$101),0) -> 4.25 | C7: Должна быть высокой, иначе первый релиз теряет смысл
A8: Средний риск первого релиза | B8: =IFERROR(AVERAGEIF(Реестр_единиц!$S$2:$S$101,"Первый релиз",Реестр_единиц!$O$2:$O$101),0) -> 1.9375 | C8: Чем ниже, тем проще старт
A9: Средняя оценка контрольного листа ценности | B9: =IFERROR(AVERAGE(Проверка_ценности!$C$4:$C$80),0) -> 4.1666667 | C9: Показывает, насколько сохранены ценность, монетизация, удержание и рост
A12: Критерий | B12: Средняя оценка первого релиза
A13: Ценность | B13: =IFERROR(AVERAGEIF(Реестр_единиц!$S$2:$S$101,"Первый релиз",Реестр_единиц!$G$2:$G$101),0) -> 4.25
A14: Доход | B14: =IFERROR(AVERAGEIF(Реестр_единиц!$S$2:$S$101,"Первый релиз",Реестр_единиц!$H$2:$H$101),0) -> 3.5
A15: Удержание | B15: =IFERROR(AVERAGEIF(Реестр_единиц!$S$2:$S$101,"Первый релиз",Реестр_единиц!$I$2:$I$101),0) -> 3.6875
A16: Рост | B16: =IFERROR(AVERAGEIF(Реестр_единиц!$S$2:$S$101,"Первый релиз",Реестр_единиц!$J$2:$J$101),0) -> 3
A17: Доказательность | B17: =IFERROR(AVERAGEIF(Реестр_единиц!$S$2:$S$101,"Первый релиз",Реестр_единиц!$K$2:$K$101),0) -> 4.375
A18: Быстрота | B18: =IFERROR(AVERAGEIF(Реестр_единиц!$S$2:$S$101,"Первый релиз",Реестр_единиц!$M$2:$M$101),0) -> 3.4375
A19: Дешевизна | B19: =IFERROR(AVERAGEIF(Реестр_единиц!$S$2:$S$101,"Первый релиз",Реестр_единиц!$N$2:$N$101),0) -> 3.4375

Sheet Справочники
A1: Справочники для выпадающих списков и шкал оценки
A3: Вид анализа | B3: Статус | C3: Тип единицы | D3: Блок Канвас | E3: Рекомендованный релиз | F3: Шкала | G3: Тип риска | H3: Тип метрики
A4: Анализ проблем | B4: Не начато | C4: Страница сайта | D4: Потребительские сегменты | E4: Первый релиз | F4: 1 — очень низко | G4: Ценность | H4: Активация
A5: Анализ отзывов | B5: В работе | C5: Экран приложения | D5: Ценностное предложение | E5: Следующий релиз | F5: 2 — низко | G5: Данные | H5: Конверсия
A6: Анализ конкурентов по сайтам | B6: Готово | C6: Функция | D6: Каналы | E6: Не включать / проверить | F6: 3 — средне | G6: Стоимость | H6: Удержание
A7: Классификация конкурентов | B7: Требует решения | C7: Интеграция | D7: Отношения с клиентами | F7: 4 — высоко | G7: Срок | H7: Повторное использование
A8: Ценностное предложение | C8: Контентный блок | D8: Потоки доходов | F8: 5 — очень высоко | G8: Технология | H8: Рост аудитории
A9: Цифровой товар | C9: Форма | D9: Ключевые ресурсы | G9: Монетизация | H9: Выручка
A10: Канвас | C10: Административная функция | D10: Ключевые виды деятельности | G10: Удержание | H10: Обращения в поддержку
A11: Пользовательские сценарии | C11: Аналитика | D11: Ключевые партнеры | G11: Рост | H11: Стоимость привлечения
A12: Страницы и экраны | D12: Структура затрат | H12: Срок реализации
