Workbook

Sheet 00_Инструкция
A1: Методика сборки бизнес-модели по Канвас: рабочий Excel-шаблон
A3: Назначение файла
A4: Книга предназначена для перевода результатов анализа конкурентов, отзывов, уровней конкуренции, цифрового товара, ценностного предложения и монетизации в связанную бизнес-модель по шаблону Канвас. Заполняются желтые поля; зеленые поля рассчитываются автоматически
A7: Этап | B7: Что заполнить | C7: Где заполнять | D7: Что получится | E7: Контроль качества
A8: 1 | B8: Внести выводы из всех предыдущих видов анализа | C8: 01_Данные_анализа | D8: Единый банк фактов и доказательств | E8: Каждый вывод должен иметь источник, блок Канвас и оценку достоверности
A9: 2 | B9: Заполнить 9 блоков Канвас | C9: 02_Канвас | D9: Черновик бизнес-модели | E9: По каждому блоку должны быть формулировка, доказательства, оценка полноты и риска
A10: 3 | B10: Детализировать сегменты, проблемы и ценность | C10: 03_Сегменты; 04_Ценность_товар | D10: Связка «клиент – проблема – ценность – цифровой товар» | E10: Не должно быть ценности без подтвержденной проблемы
A11: 4 | B11: Описать каналы, отношения и монетизацию | C11: 05_Каналы_отношения; 06_Монетизация | D11: Механизм привлечения, продажи, удержания и получения дохода | E11: Единица монетизации должна быть связана с воспринимаемой ценностью
A12: 5 | B12: Собрать операционную и затратную часть | C12: 07_Операционная_основа; 08_Затраты | D12: Основания выполнения обещания ценности | E12: Ключевые ресурсы и действия должны поддерживать ценностное предложение
A13: 6 | B13: Проверить связность бизнес-модели | C13: 09_Проверка_связности | D13: Карта слабых мест бизнес-модели | E13: Разрывы переводятся в задачи проверки или доработки
A14: 7 | B14: Сформировать итоговый паспорт | C14: 10_Паспорт; 11_Дашборд | D14: Итоговое описание бизнес-модели и сводные показатели | E14: Паспорт используется для презентации и управленческого обсуждения

Sheet 01_Данные_анализа
A1: Единый банк выводов из всех видов анализа
A2: ID | B2: Источник анализа | C2: Объект анализа | D2: Компания / товар | E2: Ссылка или место фиксации | F2: Факт / наблюдение | G2: Вывод для бизнес-модели | H2: Блок Канвас | I2: Достоверность 1-5 | J2: Актуальность 1-5 | K2: Приоритет 1-5 | L2: Индекс доказательности | M2: Статус использования | N2: Комментарий
A3: 1 | B3: Анализ сайтов конкурентов | C3: Тарифы | D3: Mermaid Chart | E3: https://mermaid.ai/pricing/ | F3: Basic Free (до 6 диаграмм, 15 ИИ-кредитов), Plus 10 у.е., Premium 20 у.е. за пользователя в месяц, Enterprise | G3: Тариф за пользователя; Free ограничен лимитами | H3: Потоки доходов | I3: 5 | J3: 5 | K3: 5 | L3: =IF(COUNTA(B3:K3)=0,"",ROUND(AVERAGE(I3:K3),2)) -> 5 | M3: Готово | N3: Данные ЛР1-ЛР5, снимок 30.09-01.10.2026
A4: 2 | B4: Анализ сайтов конкурентов | C4: Тарифы | D4: Lucidchart | E4: https://lucid.app/pricing/lucidchart | F4: Free: 3 документа, 75 фигур; Individual 9 у.е., Team 10 у.е.; пробный период 7 дней | G4: Free ограничен числом документов; платная подписка от 9 у.е. в месяц | H4: Потоки доходов | I4: 5 | J4: 5 | K4: 5 | L4: =IF(COUNTA(B4:K4)=0,"",ROUND(AVERAGE(I4:K4),2)) -> 5 | M4: Готово | N4: Данные ЛР1-ЛР5, снимок 30.09-01.10.2026
A5: 3 | B5: Анализ сайтов конкурентов | C5: Тарифы | D5: Eraser | E5: https://www.eraser.io/pricing | F5: Free 0 у.е. (3 ИИ-диаграммы), Starter 15 у.е., Business 45 у.е.; лимиты ИИ по тарифам | G5: Лимиты ИИ используются как тарифный ограничитель | H5: Потоки доходов | I5: 5 | J5: 5 | K5: 4 | L5: =IF(COUNTA(B5:K5)=0,"",ROUND(AVERAGE(I5:K5),2)) -> 4.67 | M5: Готово | N5: Данные ЛР1-ЛР5, снимок 30.09-01.10.2026
A6: 4 | B6: Анализ сайтов конкурентов | C6: Тарифы | D6: Whimsical | E6: https://whimsical.com/pricing | F6: Free: 50 объектов в месяц, водяной знак; Pro 10 у.е., Business 20 у.е. за редактора | G6: Free ограничен объёмом и водяным знаком | H6: Потоки доходов | I6: 5 | J6: 5 | K6: 3 | L6: =IF(COUNTA(B6:K6)=0,"",ROUND(AVERAGE(I6:K6),2)) -> 4.33 | M6: Готово | N6: Данные ЛР1-ЛР5, снимок 30.09-01.10.2026
A7: 5 | B7: Анализ сайтов конкурентов | C7: Тарифы | D7: Storm | E7: https://stormbpmn.com/pricing | F7: Бесплатный Персональный тариф, Команда 1 200 руб., Бизнес 4 720 руб., on-prem от 990 тыс. руб. в год | G7: На русском языке с рублёвыми тарифами найден только Storm | H7: Клиентские сегменты | I7: 5 | J7: 5 | K7: 4 | L7: =IF(COUNTA(B7:K7)=0,"",ROUND(AVERAGE(I7:K7),2)) -> 4.67 | M7: Готово | N7: Данные ЛР1-ЛР5, снимок 30.09-01.10.2026
A8: 6 | B8: Анализ сайтов конкурентов | C8: Главная страница | D8: draw.io | E8: https://www.drawio.com/ | F8: Бесплатное приложение с открытым кодом, без enterprise-тарифа, 100M+ пользователей | G8: Бесплатный доступ - стандарт рынка | H8: Ценностное предложение | I8: 4 | J8: 5 | K8: 5 | L8: =IF(COUNTA(B8:K8)=0,"",ROUND(AVERAGE(I8:K8),2)) -> 4.67 | M8: Готово | N8: Данные ЛР1-ЛР5, снимок 30.09-01.10.2026
A9: 7 | B9: Анализ цифрового товара по Левитту | C9: ЛР5, лист 03_Левитт | D9: 8 конкурентов | E9: ЛР5_Анализ_конкурентов/Excel/analiz_konkurentov_Levitt_Kano_NotaCode.xlsx | F9: Бесплатный доступ и экспорт - у 8 из 8; UML - у 4 из 8; ERD - у 6 из 8; документация - у 6 из 8 | G9: Минимальная конфигурация товара: Free, экспорт, UML, ERD, документация | H9: Ценностное предложение | I9: 4 | J9: 5 | K9: 5 | L9: =IF(COUNTA(B9:K9)=0,"",ROUND(AVERAGE(I9:K9),2)) -> 4.67 | M9: Готово | N9: Данные ЛР1-ЛР5, снимок 30.09-01.10.2026
A10: 8 | B10: Классификация требований по Кано | C10: ЛР5, лист 04_Кано | D10: 8 конкурентов | E10: ЛР5_Анализ_конкурентов/Excel/analiz_konkurentov_Levitt_Kano_NotaCode.xlsx | F10: IDEF0, DFD и сети Петри на сайтах 8 конкурентов не найдены; UML, BPMN и ERD вместе - только у Lucidchart | G10: Зона отличия: полный набор нотаций проекта | H10: Ценностное предложение | I10: 4 | J10: 5 | K10: 5 | L10: =IF(COUNTA(B10:K10)=0,"",ROUND(AVERAGE(I10:K10),2)) -> 4.67 | M10: Готово | N10: Данные ЛР1-ЛР5, снимок 30.09-01.10.2026
A11: 9 | B11: Анализ бизнес-моделей конкурентов | C11: ЛР5, лист 10_Стандарт | D11: 8 конкурентов | E11: ЛР5_Анализ_конкурентов/Excel/analiz_biznes_modeli_konkurentov_NotaCode.xlsx | F11: Условно-бесплатная модель у 5 из 8, бесплатный открытый код у 3 из 8 | G11: Модель freemium соответствует рынку | H11: Потоки доходов | I11: 4 | J11: 5 | K11: 5 | L11: =IF(COUNTA(B11:K11)=0,"",ROUND(AVERAGE(I11:K11),2)) -> 4.67 | M11: Готово | N11: Данные ЛР1-ЛР5, снимок 30.09-01.10.2026
A12: 10 | B12: Анализ бизнес-моделей конкурентов | C12: ЛР5, лист 10_Стандарт | D12: 8 конкурентов | E12: ЛР5_Анализ_конкурентов/Excel/analiz_biznes_modeli_konkurentov_NotaCode.xlsx | F12: Независимые отзывы у 7 из 8, раздел безопасности и документация у 6 из 8 | G12: Доверие строится отзывами, документацией и разделом безопасности | H12: Отношения с клиентами | I12: 4 | J12: 5 | K12: 4 | L12: =IF(COUNTA(B12:K12)=0,"",ROUND(AVERAGE(I12:K12),2)) -> 4.33 | M12: Готово | N12: Данные ЛР1-ЛР5, снимок 30.09-01.10.2026
A13: 11 | B13: Анализ бизнес-моделей конкурентов | C13: ЛР5, лист 10_Стандарт | D13: 8 конкурентов | E13: ЛР5_Анализ_конкурентов/Excel/analiz_biznes_modeli_konkurentov_NotaCode.xlsx | F13: Интеграции у 8 из 8, API у 5 из 8, открытый код у 3 из 8 | G13: Партнёрские интеграции и API - часть товара | H13: Ключевые партнеры | I13: 4 | J13: 5 | K13: 3 | L13: =IF(COUNTA(B13:K13)=0,"",ROUND(AVERAGE(I13:K13),2)) -> 4 | M13: Готово | N13: Данные ЛР1-ЛР5, снимок 30.09-01.10.2026
A14: 12 | B14: Анализ бизнес-моделей конкурентов | C14: Каналы Similarweb Pro | D14: PlantUML | E14: https://pro.similarweb.com | F14: Органический поиск 47,25 %, прямые заходы 38,11 % (июнь - август 2026) | G14: Основной канал привлечения текстовых инструментов - поиск | H14: Каналы | I14: 4 | J14: 4 | K14: 5 | L14: =IF(COUNTA(B14:K14)=0,"",ROUND(AVERAGE(I14:K14),2)) -> 4.33 | M14: Готово | N14: Данные ЛР1-ЛР5, снимок 30.09-01.10.2026
... A26: 24 | B26: Экспертная оценка | C26: Деятельность | D26: NotaCode | E26: нет ссылки (экспертная оценка) | F26: Разработка и поддержка движка нотаций, документация, продвижение | G26: Деятельность определена по ресурсам и каналам | H26: Ключевые виды деятельности | I26: 2 | J26: 4 | K26: 4 | L26: =IF(COUNTA(B26:K26)=0,"",ROUND(AVERAGE(I26:K26),2)) -> 3.33 | M26: Гипотеза | N26: Данные ЛР1-ЛР5, снимок 30.09-01.10.2026

Sheet 02_Канвас
A1: Шаблон Канвас: вопросы, источники ответов и рабочие формулировки
A2: Блок Канвас | B2: Ключевые вопросы | C2: Источники ответов из анализа | D2: Рабочая формулировка | E2: Доказательства | F2: Достоверность 1-5 | G2: Полнота 1-5 | H2: Риск ошибки 1-5 | I2: Что проверить | J2: Итоговый статус
A3: Клиентские сегменты | B3: Кто является целевым пользователем и покупателем? Какие сегменты имеют подтвержденную проблему и платежеспособность? | C3: Анализ отзывов; классификация уровней конкуренции; анализ сайтов конкурентов; сегментные сигналы из 03_Сегменты | D3: Сегмент: студенты технических специальностей (Free) и аналитики и разработчики ПО (Pro) в Беларуси, затем в России и СНГ, которые сталкиваются с отсутствием единого инструмента для нотаций UML, BPMN, ERD, IDEF0, DFD и оценивают решение по цене, набору нотаций и экспорту | E3: 229,0 тыс. студентов (ЛР1); 8 из 8 конкурентов дают бесплатный доступ; опрос 27 студентов | F3: 4 | G3: 4 | H3: 2 | I3: Интервью с аналитиками ПО; доля готовых платить | J3: =IF(COUNTA(D3:E3)=0,"Не заполнено",IF(AND(F3>=4,G3>=4,H3<=2),"Готово",IF(OR(F3<3,G3<3,H3>=4),"Требует доработки","Проверить"))) -> Готово
A4: Ценностное предложение | B4: Какую проблему решает продукт? В чем измеримая польза? Почему это лучше или точнее существующих решений? | C4: Анализ проблем и отзывов; конкурентные преимущества; модель Левитта; Кано; 04_Ценность_товар | D4: Для студентов и аналитиков ПО, которым нужны диаграммы UML, BPMN, ERD, IDEF0 и DFD, NotaCode - веб-IDE «диаграммы как код» - даёт диаграмму в любой нотации проекта из текста в одном инструменте, в отличие от текстовых языков без визуального редактора и платных редакторов с оплатой за пользователя | E4: ЛР5: IDEF0, DFD, сети Петри не найдены у 8 конкурентов; полный набор UML, BPMN, ERD только у Lucidchart; индекс проблемы 74 | F4: 4 | G4: 4 | H4: 3 | I4: Проверка спроса на нотации IDEF0, DFD; тест понятности ЦП | J4: =IF(COUNTA(D4:E4)=0,"Не заполнено",IF(AND(F4>=4,G4>=4,H4<=2),"Готово",IF(OR(F4<3,G4<3,H4>=4),"Требует доработки","Проверить"))) -> Проверить
A5: Каналы | B5: Где клиент узнает о продукте, оценивает его, покупает, подключается и получает поддержку? | C5: Сайты конкурентов; воронки; страницы тарифов; страницы продукта; рекламные посадочные страницы; 05_Каналы_отношения | D5: Основной канал: поиск Google и Яндекс на этапе осведомлённости; сайт с открытой ценой и документацией на этапе оценки; вспомогательный канал: вузы и сообщества разработчиков | E5: Органический поиск 47,25 % (PlantUML) и 58,56 % (Mermaid) трафика; открытая страница тарифов у 5 из 8 | F5: 4 | G5: 4 | H5: 3 | I5: Тест посадочной страницы; стоимость привлечения | J5: =IF(COUNTA(D5:E5)=0,"Не заполнено",IF(AND(F5>=4,G5>=4,H5<=2),"Готово",IF(OR(F5<3,G5<3,H5>=4),"Требует доработки","Проверить"))) -> Проверить
A6: Отношения с клиентами | B6: Как компания привлекает, обучает, сопровождает, удерживает и возвращает клиента? | C6: Сайт конкурента; справочные центры; демо; база знаний; поддержка; отзывы; 05_Каналы_отношения | D6: Самообслуживание: бесплатный уровень, документация, примеры; сообщество на этапах использования и удержания | E6: Документация у 6 из 8 конкурентов, отзывы у 7 из 8 | F6: 3 | G6: 4 | H6: 3 | I6: Нагрузка на поддержку; потребность в обучающих материалах | J6: =IF(COUNTA(D6:E6)=0,"Не заполнено",IF(AND(F6>=4,G6>=4,H6<=2),"Готово",IF(OR(F6<3,G6<3,H6>=4),"Требует доработки","Проверить"))) -> Проверить
A7: Потоки доходов | B7: За что именно платит клиент? Какова единица монетизации? Как цена связана с ценностью? | C7: Страницы тарифов; условия подписки; анализ монетизации; 06_Монетизация | D7: Основной поток: подписка Pro 40 у.е. в год (48 у.е. при цене 4 у.е. в месяц, 4 x 12) за пользователя; Free без оплаты; тарифный ограничитель - функции и лимиты | E7: Условно-бесплатная модель у 5 из 8; тарифы 9-20 у.е. в месяц; SAM около 65 375 у.е.; опрос: 18 из 27 готовы платить; KPI проекта: конверсия Free в Pro 3 %, ARPPU 4 у.е. | F7: 3 | G7: 4 | H7: 3 | I7: Проверка цены Pro и границы Free на реальных клиентах | J7: =IF(COUNTA(D7:E7)=0,"Не заполнено",IF(AND(F7>=4,G7>=4,H7<=2),"Готово",IF(OR(F7<3,G7<3,H7>=4),"Требует доработки","Проверить"))) -> Проверить
A8: Ключевые ресурсы | B8: Какие активы необходимы для создания, доставки и защиты ценности? | C8: Анализ цифрового товара; технологические требования; вакансии; документация; 07_Операционная_основа | D8: Ключевой ресурс: собственный движок нотаций и ИИ-ассистент в PWA, нужен для создания и поставки ценности; подтверждение - состав продукта (ЛР4, 6.1) | E8: Документация NotaCode: один разработчик с ИИ-ассистентом, около 610 ч; ресурсы конкурентов: сообщество и бренд | F8: 2 | G8: 3 | H8: 3 | I8: Оценка трудозатрат движка по нотациям | J8: =IF(COUNTA(D8:E8)=0,"Не заполнено",IF(AND(F8>=4,G8>=4,H8<=2),"Готово",IF(OR(F8<3,G8<3,H8>=4),"Требует доработки","Проверить"))) -> Требует доработки
A9: Ключевые виды деятельности | B9: Какие процессы должны выполняться регулярно, чтобы ценностное предложение было реализовано? | C9: Функциональность продукта; пользовательский сценарий; операционные процессы; 07_Операционная_основа | D9: Ключевой процесс: разработка и поддержка движка нотаций, документация и продвижение; обеспечивает качество диаграмм и привлечение, связан с движком нотаций | E9: Практика конкурентов: документация, обновления, интеграции | F9: 2 | G9: 3 | H9: 3 | I9: План развития и объём поддержки | J9: =IF(COUNTA(D9:E9)=0,"Не заполнено",IF(AND(F9>=4,G9>=4,H9<=2),"Готово",IF(OR(F9<3,G9<3,H9>=4),"Требует доработки","Проверить"))) -> Требует доработки
A10: Ключевые партнеры | B10: Какие внешние участники нужны для технологии, продаж, данных, платежей, интеграций или доверия? | C10: Интеграции на сайтах; партнерские страницы; платежные цепочки; технологические поставщики; 07_Операционная_основа | D10: Партнёры: вузы (доступ к студентам), платёжный провайдер, ИИ-провайдер, облачная инфраструктура; причины - доступ, скорость, интеграция | E10: Интеграции у 8 из 8 конкурентов; API у 5 из 8 | F10: 2 | G10: 3 | H10: 3 | I10: Договорённости с вузами и провайдерами | J10: =IF(COUNTA(D10:E10)=0,"Не заполнено",IF(AND(F10>=4,G10>=4,H10<=2),"Готово",IF(OR(F10<3,G10<3,H10>=4),"Требует доработки","Проверить"))) -> Требует доработки
A11: Структура затрат | B11: Какие затраты прямо связаны с созданием цифрового товара, привлечением клиента и поддержанием сервиса? | C11: Операционная основа; монетизация; инфраструктура; маркетинг; разработка; 08_Затраты | D11: Ключевые затраты: разработка (постоянные), облачная инфраструктура (полупеременные), ИИ-вызовы (переменные), поддержка и продвижение | E11: Лимиты ИИ в тарифах Eraser и Mermaid Chart; ЛР4 (поставщики); концепция NotaCode: бюджет инфраструктуры MVP 0, бесплатные тарифы хостинга | F11: 2 | G11: 3 | H11: 4 | I11: Расчёт экономики на пользователя | J11: =IF(COUNTA(D11:E11)=0,"Не заполнено",IF(AND(F11>=4,G11>=4,H11<=2),"Готово",IF(OR(F11<3,G11<3,H11>=4),"Требует доработки","Проверить"))) -> Требует доработки

Sheet 03_Сегменты
A1: Клиентские сегменты и подтвержденные проблемы
A2: ID сегмента | B2: Сегмент | C2: Задача клиента | D2: Ключевая проблема | E2: Доказательства | F2: Сила боли 1-5 | G2: Рыночный сигнал 1-5 | H2: Платежеспособность 1-5 | I2: Доступность канала 1-5 | J2: Индекс приоритета | K2: Статус
A3: S-001 | B3: Студенты технических специальностей | C3: Построить диаграмму к проекту или учебной работе | D3: Нет единого бесплатного инструмента для всех нотаций; сложность текстовых языков | E3: 229,0 тыс. студентов (ЛР1); опрос 27 студентов; 8 из 8 конкурентов дают бесплатный доступ | F3: 4 | G3: 4 | H3: 2 | I3: 4 | J3: =IF(COUNTA(B3:I3)=0,"",ROUND(AVERAGE(F3:I3),2)) -> 3.5 | K3: =IF(J3="","",IF(J3>=4,"Приоритетный",IF(J3>=3,"Перспективный","Низкий приоритет"))) -> Перспективный
A4: S-002 | B4: Аналитики и разработчики ПО | C4: Описать и согласовать модель процессов и данных | D4: Платные редакторы тарифицируются за пользователя от 9 у.е. в месяц; IDEF0 и DFD не поддерживаются | E4: Тарифы Lucidchart, Mermaid Chart, Eraser; ЛР5 | F4: 3 | G4: 4 | H4: 4 | I4: 3 | J4: =IF(COUNTA(B4:I4)=0,"",ROUND(AVERAGE(F4:I4),2)) -> 3.5 | K4: =IF(J4="","",IF(J4>=4,"Приоритетный",IF(J4>=3,"Перспективный","Низкий приоритет"))) -> Перспективный
A5: 3 | B5: Преподаватели технических специальностей | C5: Создать наглядные диаграммы для учебного курса или методического материала | D5: Нет единого бесплатного инструмента для всех нотаций (UML, IDEF0, DFD) в учебных и методических целях | E5: 229,0 тыс. студентов техвузов (ЛР1); спрос по IDEF0 и DFD (SRC-001); IDEF0/DFD отсутствует у 8 из 8 конкурентов (SRC-015) | F5: 3 | G5: 3 | H5: 3 | I5: 3 | J5: =IF(COUNTA(B5:I5)=0,"",ROUND(AVERAGE(F5:I5),2)) -> 3 | K5: =IF(J5="","",IF(J5>=4,"Приоритетный",IF(J5>=3,"Перспективный","Низкий приоритет"))) -> Перспективный
A6: 4 | B6: Команды аналитиков и разработчиков малых IT-компаний | C6: Документировать и согласовывать архитектуру системы и бизнес-процессы в единой среде | D6: Платные редакторы тарифицируются за пользователя от 9 до 20 у.е. в месяц; высокая стоимость для небольших команд | E6: Тарифы Lucidchart 9–10 у.е., Mermaid Chart 10–20 у.е. (SRC-007, SRC-008); G2 Lucidchart 4,5 (8 988 отзывов) (SRC-006) | F6: 3 | G6: 4 | H6: 4 | I6: 3 | J6: =IF(COUNTA(B6:I6)=0,"",ROUND(AVERAGE(F6:I6),2)) -> 3.5 | K6: =IF(J6="","",IF(J6>=4,"Приоритетный",IF(J6>=3,"Перспективный","Низкий приоритет"))) -> Перспективный

Sheet 04_Ценность_товар
A1: Ценностное предложение и цифровой товар как носитель ценности
A2: ID | B2: ID проблемы / сегмента | C2: Формулировка проблемы | D2: Текущая альтернатива клиента | E2: Желаемый результат | F2: Формулировка ценностного предложения | G2: Цифровой товар | H2: Тип цифрового товара | I2: Ядро товара | J2: Реальный товар | K2: Расширенный товар | L2: Класс требования по Кано | M2: Дифференциация 1-5 | N2: Доказательность 1-5 | O2: Связь с монетизацией 1-5 | P2: Индекс готовности | Q2: Статус
A3: V-001 | B3: P-002 / S-001 | C3: Нет единого инструмента для всех нотаций проекта | D3: Несколько инструментов: draw.io, PlantUML, Lucidchart; IDEF0 и DFD не поддерживаются | E3: Диаграмма в любой нотации проекта из текста в одном бесплатном инструменте | F3: Для студентов и аналитиков ПО NotaCode даёт диаграмму в любой нотации проекта из текста в одном инструменте без установки | G3: NotaCode - веб-IDE (PWA) | H3: Веб-платформа | I3: Построение диаграмм из текстового описания | J3: Редактор для UML, BPMN 2.0, ERD, IDEF0, DFD, сетей Петри; Free и Pro | K3: ИИ-ассистент, экспорт, документация, потенциально API и интеграции | L3: Привлекательное | M3: 4 | N3: 3 | O3: 4 | P3: =IF(COUNTA(B3:O3)=0,"",ROUND(AVERAGE(M3:O3),2)) -> 3.67 | Q3: =IF(P3="","",IF(P3>=4,"Готово",IF(P3>=3,"Проверить","Доработать"))) -> Проверить
A4: V-002 | B4: P-001 / S-001 | C4: Освоение текстовых языков (PlantUML, Mermaid) отнимает время | D4: Документация и ИИ-генерация (Mermaid Chart, Eraser) | E4: Получить корректную диаграмму без изучения всего синтаксиса | F4: Для студентов NotaCode снижает порог входа в диаграммы как код за счёт редактора и ИИ-ассистента | G4: NotaCode - веб-IDE (PWA) | H4: Веб-платформа | I4: Текст и визуализация в одном окне | J4: Редактор с ИИ-ассистентом и примерами | K4: Шаблоны и подсказки (подтвердить составом MVP) | L4: Линейное | M4: 3 | N4: 3 | O4: 3 | P4: =IF(COUNTA(B4:O4)=0,"",ROUND(AVERAGE(M4:O4),2)) -> 3 | Q4: =IF(P4="","",IF(P4>=4,"Готово",IF(P4>=3,"Проверить","Доработать"))) -> Проверить
A5: 3 | B5: P-003 / S-002 | C5: Платные редакторы тарифицируются за пользователя от 9 до 20 у.е. в месяц; бесплатные ограничены 3–6 документами или диаграммами | D5: Платные Lucidchart 9–10 у.е., Mermaid Chart 10–20 у.е.; бесплатный draw.io без IDEF0 и DFD | E5: Получить полнофункциональный инструмент бесплатно без лимитов по нотациям | F5: Для аналитиков и разработчиков ПО NotaCode предоставляет бесплатный доступ ко всем нотациям, в отличие от платных редакторов с оплатой за пользователя, потому что уровень Free включает весь набор нотаций без ограничений | G5: NotaCode – веб-IDE (PWA) | H5: Веб-платформа | I5: Бесплатный доступ без ограничений по нотациям | J5: Редактор для всех нотаций на уровне Free | K5: Pro-подписка 40 у.е. в год (расширенный экспорт, история версий) | L5: Базовое требование | M5: 3 | N5: 4 | O5: 3 | P5: =IF(COUNTA(B5:O5)=0,"",ROUND(AVERAGE(M5:O5),2)) -> 3.33 | Q5: =IF(P5="","",IF(P5>=4,"Готово",IF(P5>=3,"Проверить","Доработать"))) -> Проверить
A6: 4 | B6: P-004 / S-001 | C6: Совместная работа и экспорт – ожидаемый минимум: коллаборация важна 26 из 27 опрошенных, экспорт PNG – 27 из 27, SVG – 18 из 27 | D6: draw.io и Miro поддерживают коллаборацию, но не охватывают IDEF0, DFD и сети Петри | E6: Экспортировать диаграмму в нужном формате и работать в команде без дополнительных инструментов | F6: Для студентов и аналитиков NotaCode обеспечивает экспорт SVG и PNG и совместный доступ в одном инструменте, потому что базовые форматы экспорта включены в Free | G6: NotaCode – веб-IDE (PWA) | H6: Веб-платформа | I6: Экспорт SVG и PNG | J6: Редактор с экспортом и совместным доступом к проекту | K6: Расширенный экспорт Pro: BPMN XML, XMI, PNML, draw.io, PlantUML, Mermaid, D2, DOT | L6: Базовое требование | M6: 3 | N6: 3 | O6: 3 | P6: =IF(COUNTA(B6:O6)=0,"",ROUND(AVERAGE(M6:O6),2)) -> 3 | Q6: =IF(P6="","",IF(P6>=4,"Готово",IF(P6>=3,"Проверить","Доработать"))) -> Проверить

Sheet 05_Каналы_отношения
A1: Каналы, сценарий продаж и отношения с клиентами
A2: ID | B2: Этап канала | C2: Сегмент | D2: Канал / точка контакта | E2: Роль в воронке | F2: Конкурентный стандарт | G2: Пригодность 1-5 | H2: Затратность/риск 1-5 | I2: Доказательность 1-5 | J2: Индекс приоритета | K2: Решение
A3: CH-001 | B3: Осведомленность | C3: Студенты и аналитики | D3: Поиск Google и Яндекс | E3: Привлечение | F3: Органический поиск 47-59 % трафика у текстовых инструментов | G3: 5 | H3: 2 | I3: 4 | J3: =IF(COUNTA(B3:I3)=0,"",ROUND(AVERAGE(G3,6-H3,I3),2)) -> 4.33 | K3: =IF(J3="","",IF(J3>=4,"Включить",IF(J3>=3,"Проверить","Не основной"))) -> Включить
A4: CH-002 | B4: Оценка | C4: Студенты и аналитики | D4: Сайт с открытой ценой и документацией | E4: Оценка | F4: Страница тарифов у 5 из 8, документация у 6 из 8 | G4: 5 | H4: 2 | I4: 4 | J4: =IF(COUNTA(B4:I4)=0,"",ROUND(AVERAGE(G4,6-H4,I4),2)) -> 4.33 | K4: =IF(J4="","",IF(J4>=4,"Включить",IF(J4>=3,"Проверить","Не основной"))) -> Включить
A5: CH-003 | B5: Подключение | C5: Студенты | D5: Регистрация в бесплатном уровне | E5: Активация | F5: Регистрация или Free-тариф у 8 из 8 | G5: 5 | H5: 1 | I5: 4 | J5: =IF(COUNTA(B5:I5)=0,"",ROUND(AVERAGE(G5,6-H5,I5),2)) -> 4.67 | K5: =IF(J5="","",IF(J5>=4,"Включить",IF(J5>=3,"Проверить","Не основной"))) -> Включить
A6: CH-004 | B6: Использование | C6: Студенты и аналитики | D6: Документация и примеры в продукте | E6: Удержание | F6: Документация у 6 из 8 | G6: 4 | H6: 2 | I6: 4 | J6: =IF(COUNTA(B6:I6)=0,"",ROUND(AVERAGE(G6,6-H6,I6),2)) -> 4 | K6: =IF(J6="","",IF(J6>=4,"Включить",IF(J6>=3,"Проверить","Не основной"))) -> Включить
A7: CH-005 | B7: Осведомленность | C7: Студенты | D7: Вузы и преподаватели | E7: Привлечение | F7: Канал через вузы (ЛР1, ЛР4); договорённостей нет | G7: 4 | H7: 3 | I7: 2 | J7: =IF(COUNTA(B7:I7)=0,"",ROUND(AVERAGE(G7,6-H7,I7),2)) -> 3 | K7: =IF(J7="","",IF(J7>=4,"Включить",IF(J7>=3,"Проверить","Не основной"))) -> Проверить

Sheet 06_Монетизация
A1: Единица монетизации и потоки доходов
A2: ID | B2: Единица монетизации | C2: Событие оплаты | D2: Метрика учета | E2: Логика цены | F2: Тип потока доходов | G2: Сигналы конкурентов | H2: Связь с ценностью | I2: Готовность платить 1-5 | J2: Измеримость 1-5 | K2: Повторяемость дохода 1-5 | L2: Доказательность 1-5 | M2: Индекс монетизации | N2: Статус
A3: MO-001 | B3: Пользователь Pro (подписка на год) | C3: Оплата годовой подписки | D3: Число активных платящих пользователей | E3: 40 у.е. в год (48 у.е. при 4 x 12); ниже тарифов конкурентов от 9 у.е. в месяц | F3: Подписка | G3: Mermaid Chart, Lucidchart, Eraser, Whimsical: подписка за пользователя | H3: Расширенные возможности и снятие лимитов Free | I3: 3 | J3: 4 | K3: 4 | L3: 4 | M3: =IF(COUNTA(B3:L3)=0,"",ROUND(AVERAGE(I3:L3),2)) -> 3.75 | N3: =IF(M3="","",IF(M3>=4,"Основная гипотеза",IF(M3>=3,"Требует проверки","Слабая гипотеза"))) -> Требует проверки
A4: MO-002 | B4: Бесплатный пользователь (Free) | C4: Регистрация | D4: Число зарегистрированных | E4: 0 у.е.; ограничения по функциям | F4: Фримиум | G4: Free или бесплатный открытый код у 8 из 8 | H4: Вход в продукт и аудитория | I4: 4 | J4: 5 | K4: 2 | L4: 4 | M4: =IF(COUNTA(B4:L4)=0,"",ROUND(AVERAGE(I4:L4),2)) -> 3.75 | N4: =IF(M4="","",IF(M4>=4,"Основная гипотеза",IF(M4>=3,"Требует проверки","Слабая гипотеза"))) -> Требует проверки
A5: MO-003 | B5: Лимит ИИ-вызовов | C5: Исчерпание лимита | D5: Число ИИ-диаграмм в месяц | E5: Лимиты по тарифам (гипотеза по Eraser и Mermaid Chart) | F5: Плата за объем использования | G5: Eraser: 3, 40, 250 ИИ-диаграмм; Mermaid Chart: 15, 300, 2000 кредитов | H5: Контроль переменных затрат ИИ | I5: 3 | J5: 4 | K5: 3 | L5: 4 | M5: =IF(COUNTA(B5:L5)=0,"",ROUND(AVERAGE(I5:L5),2)) -> 3.5 | N5: =IF(M5="","",IF(M5>=4,"Основная гипотеза",IF(M5>=3,"Требует проверки","Слабая гипотеза"))) -> Требует проверки
A6: MO-004 | B6: Организация (корпоративный тариф) | C6: Договор | D6: Число мест | E6: По запросу (отложено) | F6: Плата за пользователя | G6: Enterprise у 4 из 8 конкурентов | H6: Командное использование | I6: 2 | J6: 3 | K6: 4 | L6: 3 | M6: =IF(COUNTA(B6:L6)=0,"",ROUND(AVERAGE(I6:L6),2)) -> 3 | N6: =IF(M6="","",IF(M6>=4,"Основная гипотеза",IF(M6>=3,"Требует проверки","Слабая гипотеза"))) -> Требует проверки

Sheet 07_Операционная_основа
A1: Ключевые ресурсы, виды деятельности и партнеры
A2: ID | B2: Блок | C2: Элемент | D2: Описание | E2: Как поддерживает ценность / товар | F2: Источник | G2: Критичность 1-5 | H2: Доступность 1-5 | I2: Затратное влияние 1-5 | J2: Подход к обеспечению | K2: Операционный приоритет
A3: OP-001 | B3: Ключевые ресурсы | C3: Движок нотаций и ИИ-ассистент | D3: Разбор текста и построение диаграмм UML, BPMN, ERD, IDEF0, DFD, сетей Петри | E3: Создаёт и поставляет ценность | F3: Описание проекта (ЛР4) | G3: 5 | H3: 3 | I3: 4 | J3: Создать внутри | K3: =IF(COUNTA(B3:J3)=0,"",ROUND(AVERAGE(G3,6-H3,I3),2)) -> 4
A4: OP-002 | B4: Ключевые ресурсы | C4: PWA, домен, репозиторий | D4: Доставка продукта в браузере | E4: Доступ без установки | F4: Описание проекта (ЛР4) | G4: 4 | H4: 4 | I4: 3 | J4: Создать внутри | K4: =IF(COUNTA(B4:J4)=0,"",ROUND(AVERAGE(G4,6-H4,I4),2)) -> 3
A5: OP-003 | B5: Ключевые виды деятельности | C5: Разработка и поддержка нотаций | D5: Развитие поддержки нотаций, исправление ошибок | E5: Качество диаграмм | F5: Практика конкурентов | G5: 5 | H5: 3 | I5: 4 | J5: Создать внутри | K5: =IF(COUNTA(B5:J5)=0,"",ROUND(AVERAGE(G5,6-H5,I5),2)) -> 4
A6: OP-004 | B6: Ключевые виды деятельности | C6: Документация и примеры | D6: Обучение пользователей | E6: Снижает порог входа | F6: Документация у 6 из 8 конкурентов | G6: 4 | H6: 4 | I6: 2 | J6: Создать внутри | K6: =IF(COUNTA(B6:J6)=0,"",ROUND(AVERAGE(G6,6-H6,I6),2)) -> 2.67
A7: OP-005 | B7: Ключевые виды деятельности | C7: Продвижение | D7: Поиск, сайт, вузы | E7: Осведомлённость | F7: Similarweb: поиск 47-59 % | G7: 4 | H7: 4 | I7: 3 | J7: Создать внутри | K7: =IF(COUNTA(B7:J7)=0,"",ROUND(AVERAGE(G7,6-H7,I7),2)) -> 3
A8: OP-006 | B8: Ключевые партнеры | C8: Вузы | D8: Доступ к студентам | E8: Канал привлечения | F8: ЛР1, ЛР4 | G8: 3 | H8: 3 | I8: 2 | J8: Получить через партнера | K8: =IF(COUNTA(B8:J8)=0,"",ROUND(AVERAGE(G8,6-H8,I8),2)) -> 2.67
A9: OP-007 | B9: Ключевые партнеры | C9: Платёжный провайдер | D9: Приём платежей Pro | E9: Монетизация | F9: Практика подписок | G9: 4 | H9: 4 | I9: 2 | J9: Купить готовое решение | K9: =IF(COUNTA(B9:J9)=0,"",ROUND(AVERAGE(G9,6-H9,I9),2)) -> 2.67
A10: OP-008 | B10: Ключевые партнеры | C10: ИИ-провайдер и облако | D10: ИИ-ассистент и хостинг | E10: Скорость запуска | F10: Лимиты ИИ у Eraser, Mermaid Chart | G10: 4 | H10: 4 | I10: 4 | J10: Арендовать сервис | K10: =IF(COUNTA(B10:J10)=0,"",ROUND(AVERAGE(G10,6-H10,I10),2)) -> 3.33

Sheet 08_Затраты
A1: Структура затрат и драйверы затрат
A2: ID | B2: Статья затрат | C2: Связанный ресурс / деятельность | D2: Тип затрат | E2: Драйвер затрат | F2: Этап развития | G2: Доказательство / основание | H2: Влияние на экономику 1-5 | I2: Уверенность 1-5 | J2: Управляемость 1-5 | K2: Приоритет контроля
A3: CO-001 | B3: Разработка и поддержка нотаций | C3: Движок нотаций | D3: Постоянные | E3: Число нотаций и функций | F3: Разработка | G3: Практика проектов; оценка | H3: 5 | I3: 3 | J3: 3 | K3: =IF(COUNTA(B3:J3)=0,"",ROUND(AVERAGE(H3,I3,6-J3),2)) -> 3.67
A4: CO-002 | B4: Облачная инфраструктура | C4: PWA, домен | D4: Инфраструктурные | E4: Число пользователей | F4: Запуск | G4: Практика SaaS | H4: 3 | I4: 3 | J4: 4 | K4: =IF(COUNTA(B4:J4)=0,"",ROUND(AVERAGE(H4,I4,6-J4),2)) -> 2.67
A5: CO-003 | B5: ИИ-вызовы | C5: ИИ-ассистент | D5: Переменные | E5: Число ИИ-запросов | F5: Рост | G5: Лимиты ИИ у Eraser, Mermaid Chart | H5: 4 | I5: 3 | J5: 3 | K5: =IF(COUNTA(B5:J5)=0,"",ROUND(AVERAGE(H5,I5,6-J5),2)) -> 3.33
A6: CO-004 | B6: Поддержка и документация | C6: Документация | D6: Операционные | E6: Число пользователей | F6: Рост | G6: Документация у 6 из 8 | H6: 3 | I6: 3 | J6: 4 | K6: =IF(COUNTA(B6:J6)=0,"",ROUND(AVERAGE(H6,I6,6-J6),2)) -> 2.67
A7: CO-005 | B7: Продвижение | C7: Поиск, вузы | D7: Маркетинговые | E7: Стоимость привлечения | F7: Запуск | G7: Similarweb (поиск) | H7: 4 | I7: 2 | J7: 3 | K7: =IF(COUNTA(B7:J7)=0,"",ROUND(AVERAGE(H7,I7,6-J7),2)) -> 3

Sheet 09_Проверка_связности
A1: Проверка связности бизнес-модели
A2: № | B2: Контрольный вопрос | C2: Где искать ответ | D2: Доказательство / ссылка на вывод | E2: Оценка 1-5 | F2: Результат | G2: Что доработать
A3: 1 | B3: Есть ли у выбранного сегмента подтвержденная проблема? | C3: 03_Сегменты; 01_Данные_анализа | D3: Сегмент студентов: 229,0 тыс.; сила боли подтверждена опросом и ЛР5 | E3: 4 | F3: =IF(E3="","Не оценено",IF(E3>=4,"Подтверждено",IF(E3>=3,"Нужна проверка","Риск разрыва"))) -> Подтверждено | G3: Интервью с аналитиками
A4: 2 | B4: Связано ли ценностное предложение с наиболее приоритетной проблемой? | C4: 04_Ценность_товар; 02_Канвас | D4: ЦП связана с проблемой P-002 (индекс 74) | E4: 4 | F4: =IF(E4="","Не оценено",IF(E4>=4,"Подтверждено",IF(E4>=3,"Нужна проверка","Риск разрыва"))) -> Подтверждено | G4: Проверить формулировку на клиентах
A5: 3 | B5: Описан ли цифровой товар как конкретная единица ценности, а не как общая идея? | C5: 04_Ценность_товар | D5: Товар описан (6.1, PR-001): состав, нотации, условия Free и Pro | E5: 4 | F5: =IF(E5="","Не оценено",IF(E5>=4,"Подтверждено",IF(E5>=3,"Нужна проверка","Риск разрыва"))) -> Подтверждено | G5: Уточнить формат экспорта
A6: 4 | B6: Понятно ли, за какую единицу клиент платит? | C6: 06_Монетизация | D6: Единица - пользователь, годовая подписка Pro | E6: 4 | F6: =IF(E6="","Не оценено",IF(E6>=4,"Подтверждено",IF(E6>=3,"Нужна проверка","Риск разрыва"))) -> Подтверждено | G6: Проверить цену
A7: 5 | B7: Каналы соответствуют сегменту и этапам принятия решения? | C7: 05_Каналы_отношения | D7: Поиск и сайт соответствуют сегменту (Similarweb) | E7: 4 | F7: =IF(E7="","Не оценено",IF(E7>=4,"Подтверждено",IF(E7>=3,"Нужна проверка","Риск разрыва"))) -> Подтверждено | G7: Проверить вузовский канал
A8: 6 | B8: Механика отношений с клиентом поддерживает удержание и повторное использование? | C8: 05_Каналы_отношения; 02_Канвас | D8: Самообслуживание подходит для простого товара | E8: 3 | F8: =IF(E8="","Не оценено",IF(E8>=4,"Подтверждено",IF(E8>=3,"Нужна проверка","Риск разрыва"))) -> Нужна проверка | G8: Оценить нагрузку поддержки
A9: 7 | B9: Ключевые ресурсы достаточны для выполнения обещания ценности? | C9: 07_Операционная_основа | D9: Ресурсы описаны как гипотезы | E9: 3 | F9: =IF(E9="","Не оценено",IF(E9>=4,"Подтверждено",IF(E9>=3,"Нужна проверка","Риск разрыва"))) -> Нужна проверка | G9: Подтвердить ресурс движка
A10: 8 | B10: Ключевые виды деятельности прямо связаны с созданием и доставкой цифрового товара? | C10: 07_Операционная_основа | D10: Процессы выведены из ресурсов и каналов | E10: 3 | F10: =IF(E10="","Не оценено",IF(E10>=4,"Подтверждено",IF(E10>=3,"Нужна проверка","Риск разрыва"))) -> Нужна проверка | G10: Подтвердить план развития
A11: 9 | B11: Партнеры закрывают реальные технологические, рыночные или операционные ограничения? | C11: 07_Операционная_основа | D11: Партнёры не подтверждены договорами | E11: 2 | F11: =IF(E11="","Не оценено",IF(E11>=4,"Подтверждено",IF(E11>=3,"Нужна проверка","Риск разрыва"))) -> Риск разрыва | G11: Заключить или найти партнёров
A12: 10 | B12: Структура затрат соответствует выбранной модели монетизации? | C12: 08_Затраты; 06_Монетизация | D12: Затраты описаны качественно | E12: 3 | F12: =IF(E12="","Не оценено",IF(E12>=4,"Подтверждено",IF(E12>=3,"Нужна проверка","Риск разрыва"))) -> Нужна проверка | G12: Рассчитать экономику
A13: 11 | B13: Есть ли отличие от прямых конкурентов, которое можно проверить через факты? | C13: 01_Данные_анализа; 04_Ценность_товар | D13: Отличие: IDEF0, DFD, сети Петри у конкурентов не найдены | E13: 4 | F13: =IF(E13="","Не оценено",IF(E13>=4,"Подтверждено",IF(E13>=3,"Нужна проверка","Риск разрыва"))) -> Подтверждено | G13: Проверить значимость для клиентов
A14: 12 | B14: Не противоречат ли блоки Канвас друг другу? | C14: 02_Канвас; 10_Паспорт | D14: Противоречий между блоками не выявлено, блоки 8-11 - гипотезы | E14: 3 | F14: =IF(E14="","Не оценено",IF(E14>=4,"Подтверждено",IF(E14>=3,"Нужна проверка","Риск разрыва"))) -> Нужна проверка | G14: Повторить проверку после интервью

Sheet 10_Паспорт
A1: Итоговый паспорт бизнес-модели
A2: Раздел паспорта | B2: Итоговая формулировка | C2: Основной источник | D2: Контрольный вопрос | E2: Статус
A3: Целевой клиентский сегмент | B3: =IFERROR(INDEX('02_Канвас'!$D$3:$D$11,MATCH("Клиентские сегменты",'02_Канвас'!$A$3:$A$11,0)),"") -> Сегмент: студенты технических специальностей (Free) и аналитики и разработчики ПО (Pro) в Беларуси, затем в России и СНГ, которые сталкиваются с отсутствием единого инструмента для нотаций UML, BPMN, ERD, IDEF0, DFD и оценивают решение по цене, набору нотаций и экспорту | C3: 02_Канвас / 03_Сегменты | D3: Кому именно создается ценность? | E3: =IF(B3="","Не заполнено","Заполнено") -> Заполнено
A4: Проблема клиента | B4: Студенты и аналитики ПО не имеют единого инструмента для всех нотаций проекта (UML, BPMN, ERD, IDEF0, DFD, сети Петри): IDEF0, DFD и сети Петри не найдены у 8 конкурентов, UML, BPMN и ERD вместе - только у Lucidchart (ЛР5); индекс проблемы 74 | C4: 03_Сегменты / 04_Ценность_товар | D4: Какая проблема подтверждена отзывами, сайтами и конкурентным анализом? | E4: =IF(B4="","Не заполнено","Заполнено") -> Заполнено
A5: Ценностное предложение | B5: =IFERROR(INDEX('02_Канвас'!$D$3:$D$11,MATCH("Ценностное предложение",'02_Канвас'!$A$3:$A$11,0)),"") -> Для студентов и аналитиков ПО, которым нужны диаграммы UML, BPMN, ERD, IDEF0 и DFD, NotaCode - веб-IDE «диаграммы как код» - даёт диаграмму в любой нотации проекта из текста в одном инструменте, в отличие от текстовых языков без визуального редактора и платных редакторов с оплатой за пользователя | C5: 02_Канвас / 04_Ценность_товар | D5: Какой результат получает клиент и почему это важно? | E5: =IF(B5="","Не заполнено","Заполнено") -> Заполнено
A6: Цифровой товар | B6: Веб-платформа: редактор диаграмм «как код» для UML, BPMN 2.0, ERD, IDEF0, DFD и сетей Петри с ИИ-ассистентом, экспортом и документацией; уровни Free и Pro | C6: 04_Ценность_товар | D6: Что именно продается или предоставляется клиенту? | E6: =IF(B6="","Не заполнено","Заполнено") -> Заполнено
A7: Единица монетизации | B7: Клиент платит за пользователя Pro (подписка на год); Free без оплаты; лимиты ИИ - гипотеза ограничителя | C7: 06_Монетизация | D7: За какую единицу ценности платит клиент? | E7: =IF(B7="","Не заполнено","Заполнено") -> Заполнено
A8: Каналы | B8: =IFERROR(INDEX('02_Канвас'!$D$3:$D$11,MATCH("Каналы",'02_Канвас'!$A$3:$A$11,0)),"") -> Основной канал: поиск Google и Яндекс на этапе осведомлённости; сайт с открытой ценой и документацией на этапе оценки; вспомогательный канал: вузы и сообщества разработчиков | C8: 02_Канвас / 05_Каналы_отношения | D8: Как клиент узнает, оценивает, покупает и использует продукт? | E8: =IF(B8="","Не заполнено","Заполнено") -> Заполнено
A9: Отношения с клиентами | B9: =IFERROR(INDEX('02_Канвас'!$D$3:$D$11,MATCH("Отношения с клиентами",'02_Канвас'!$A$3:$A$11,0)),"") -> Самообслуживание: бесплатный уровень, документация, примеры; сообщество на этапах использования и удержания | C9: 02_Канвас / 05_Каналы_отношения | D9: Как обеспечивается сопровождение, удержание и повторное использование? | E9: =IF(B9="","Не заполнено","Заполнено") -> Заполнено
A10: Потоки доходов | B10: =IFERROR(INDEX('02_Канвас'!$D$3:$D$11,MATCH("Потоки доходов",'02_Канвас'!$A$3:$A$11,0)),"") -> Основной поток: подписка Pro 40 у.е. в год (48 у.е. при цене 4 у.е. в месяц, 4 x 12) за пользователя; Free без оплаты; тарифный ограничитель - функции и лимиты | C10: 02_Канвас / 06_Монетизация | D10: Какие денежные потоки образует продукт? | E10: =IF(B10="","Не заполнено","Заполнено") -> Заполнено
A11: Ключевые ресурсы | B11: =IFERROR(INDEX('02_Канвас'!$D$3:$D$11,MATCH("Ключевые ресурсы",'02_Канвас'!$A$3:$A$11,0)),"") -> Ключевой ресурс: собственный движок нотаций и ИИ-ассистент в PWA, нужен для создания и поставки ценности; подтверждение - состав продукта (ЛР4, 6.1) | C11: 02_Канвас / 07_Операционная_основа | D11: Какие ресурсы критичны для выполнения обещания ценности? | E11: =IF(B11="","Не заполнено","Заполнено") -> Заполнено
A12: Ключевые виды деятельности | B12: =IFERROR(INDEX('02_Канвас'!$D$3:$D$11,MATCH("Ключевые виды деятельности",'02_Канвас'!$A$3:$A$11,0)),"") -> Ключевой процесс: разработка и поддержка движка нотаций, документация и продвижение; обеспечивает качество диаграмм и привлечение, связан с движком нотаций | C12: 02_Канвас / 07_Операционная_основа | D12: Какие процессы создают и доставляют ценность? | E12: =IF(B12="","Не заполнено","Заполнено") -> Заполнено
A13: Ключевые партнеры | B13: =IFERROR(INDEX('02_Канвас'!$D$3:$D$11,MATCH("Ключевые партнеры",'02_Канвас'!$A$3:$A$11,0)),"") -> Партнёры: вузы (доступ к студентам), платёжный провайдер, ИИ-провайдер, облачная инфраструктура; причины - доступ, скорость, интеграция | C13: 02_Канвас / 07_Операционная_основа | D13: Какие внешние участники нужны для модели? | E13: =IF(B13="","Не заполнено","Заполнено") -> Заполнено
A14: Структура затрат | B14: =IFERROR(INDEX('02_Канвас'!$D$3:$D$11,MATCH("Структура затрат",'02_Канвас'!$A$3:$A$11,0)),"") -> Ключевые затраты: разработка (постоянные), облачная инфраструктура (полупеременные), ИИ-вызовы (переменные), поддержка и продвижение | C14: 02_Канвас / 08_Затраты | D14: Какие затраты определяют экономику модели? | E14: =IF(B14="","Не заполнено","Заполнено") -> Заполнено
A15: Главное конкурентное отличие | B15: Полный набор нотаций проекта, включая IDEF0, DFD и сети Петри, в одном бесплатном инструменте (у 8 конкурентов не найден) | C15: 01_Данные_анализа / 04_Ценность_товар | D15: Чем модель отличается от прямых и близких конкурентов? | E15: =IF(B15="","Не заполнено","Заполнено") -> Заполнено
A16: Ключевая гипотеза для проверки | B16: Цена Pro 40 у.е. в год приемлема для аналитиков, а Free достаточен для привлечения студентов; проверить опросом и интервью | C16: 09_Проверка_связности | D16: Какая гипотеза создает наибольший риск ошибки? | E16: =IF(B16="","Не заполнено","Заполнено") -> Заполнено

Sheet 11_Дашборд
A1: Сводный дашборд готовности бизнес-модели
A3: Показатель | B3: Значение
A4: Полнота заполнения Канвас | B4: =IFERROR(AVERAGE('02_Канвас'!G3:G11)/5,0) -> 0.71111111
A5: Средняя доказательность Канвас | B5: =IFERROR(AVERAGE('02_Канвас'!F3:F11)/5,0) -> 0.57777778
A6: Контроль риска Канвас | B6: =IFERROR(1-AVERAGE('02_Канвас'!H3:H11)/5,0) -> 0.4
A7: Доля готовых блоков Канвас | B7: =IFERROR(COUNTIF('02_Канвас'!J3:J11,"Готово")/9,0) -> 0.11111111
A8: Количество зафиксированных выводов анализа | B8: =COUNTA('01_Данные_анализа'!F3:F26) -> 24
A9: Доля подтвержденных проверок связности | B9: =IFERROR(COUNTIF('09_Проверка_связности'!F3:F14,"Подтверждено")/COUNTA('09_Проверка_связности'!A3:A14),0) -> 0.5
A11: Блок Канвас | B11: Достоверность | C11: Полнота | D11: Риск | E11: Статус
A12: ='02_Канвас'!A3 -> Клиентские сегменты | B12: ='02_Канвас'!F3 -> 4 | C12: ='02_Канвас'!G3 -> 4 | D12: ='02_Канвас'!H3 -> 2 | E12: ='02_Канвас'!J3 -> Готово
A13: ='02_Канвас'!A4 -> Ценностное предложение | B13: ='02_Канвас'!F4 -> 4 | C13: ='02_Канвас'!G4 -> 4 | D13: ='02_Канвас'!H4 -> 3 | E13: ='02_Канвас'!J4 -> Проверить
A14: ='02_Канвас'!A5 -> Каналы | B14: ='02_Канвас'!F5 -> 4 | C14: ='02_Канвас'!G5 -> 4 | D14: ='02_Канвас'!H5 -> 3 | E14: ='02_Канвас'!J5 -> Проверить
A15: ='02_Канвас'!A6 -> Отношения с клиентами | B15: ='02_Канвас'!F6 -> 3 | C15: ='02_Канвас'!G6 -> 4 | D15: ='02_Канвас'!H6 -> 3 | E15: ='02_Канвас'!J6 -> Проверить
A16: ='02_Канвас'!A7 -> Потоки доходов | B16: ='02_Канвас'!F7 -> 3 | C16: ='02_Канвас'!G7 -> 4 | D16: ='02_Канвас'!H7 -> 3 | E16: ='02_Канвас'!J7 -> Проверить
A17: ='02_Канвас'!A8 -> Ключевые ресурсы | B17: ='02_Канвас'!F8 -> 2 | C17: ='02_Канвас'!G8 -> 3 | D17: ='02_Канвас'!H8 -> 3 | E17: ='02_Канвас'!J8 -> Требует доработки
A18: ='02_Канвас'!A9 -> Ключевые виды деятельности | B18: ='02_Канвас'!F9 -> 2 | C18: ='02_Канвас'!G9 -> 3 | D18: ='02_Канвас'!H9 -> 3 | E18: ='02_Канвас'!J9 -> Требует доработки
A19: ='02_Канвас'!A10 -> Ключевые партнеры | B19: ='02_Канвас'!F10 -> 2 | C19: ='02_Канвас'!G10 -> 3 | D19: ='02_Канвас'!H10 -> 3 | E19: ='02_Канвас'!J10 -> Требует доработки
A20: ='02_Канвас'!A11 -> Структура затрат | B20: ='02_Канвас'!F11 -> 2 | C20: ='02_Канвас'!G11 -> 3 | D20: ='02_Канвас'!H11 -> 4 | E20: ='02_Канвас'!J11 -> Требует доработки
A23: Итоговая интерпретация | B23: Правило | C23: Результат
A24: Высокая готовность | B24: Все KPI не ниже 80% | C24: =IF(AND(B4>=0.8,B5>=0.8,B6>=0.8,B7>=0.8,B9>=0.8),"Да","Нет") -> Нет
A25: Средняя готовность | B25: Большинство KPI не ниже 60% | C25: =IF(AND(B4>=0.6,B5>=0.6,B6>=0.6,B7>=0.6,B9>=0.6),"Да","Нет") -> Нет
A26: Низкая готовность | B26: Есть критичные пробелы в Канвас или связности | C26: =IF(OR(B4<0.6,B5<0.6,B6<0.6,B9<0.6),"Да","Нет") -> Да
A27: Рекомендуемое действие | B27: Сначала закрыть блоки со статусом «Требует доработки» | C27: =IF(C24="Да","Можно оформлять итоговую бизнес-модель",IF(C25="Да","Нужна точечная проверка гипотез","Нужна доработка исходных данных и связности")) -> Нужна доработка исходных данных и связности

Sheet 12_Справочники
A1: Справочники для выпадающих списков и шкал оценки
A2: Тип источника анализа | B2: Блок Канвас | C2: Оценка 1-5 | D2: Статус | E2: Тип цифрового товара | F2: Класс требования по Кано | G2: Тип потока доходов | H2: Тип затрат | I2: Этап канала | J2: Подход к обеспечению | K2: Уровень конкуренции
A3: Анализ сайтов конкурентов | B3: Клиентские сегменты | C3: 1 | D3: Не заполнено | E3: Программный сервис | F3: Обязательное | G3: Подписка | H3: Постоянные | I3: Осведомленность | J3: Создать внутри | K3: Прямой конкурент
A4: Анализ бизнес-моделей конкурентов | B4: Ценностное предложение | C4: 2 | D4: Проверить | E4: Мобильное приложение | F4: Линейное | G4: Разовая продажа доступа | H4: Переменные | I4: Оценка | J4: Купить готовое решение | K4: Близкий конкурент
A5: Анализ цифрового товара по Левитту | B5: Каналы | C5: 3 | D5: Готово | E5: Веб-платформа | F5: Восхищающее | G5: Комиссия за транзакцию | H5: Полупеременные | I5: Покупка | J5: Арендовать сервис | K5: Косвенный конкурент
A6: Классификация требований по Кано | B6: Отношения с клиентами | C6: 4 | D6: Требует доработки | E6: Цифровой контент | F6: Безразличное | G6: Плата за пользователя | H6: Инфраструктурные | I6: Подключение | J6: Получить через партнера | K6: Заменитель
A7: Анализ отзывов | B7: Потоки доходов | C7: 5 | D7: Исключить | E7: Доступ к данным | F7: Обратное | G7: Плата за объем использования | H7: Маркетинговые | I7: Использование | J7: Передать на подряд | K7: Смежный игрок
A8: Классификация уровней конкуренции | B8: Ключевые ресурсы | D8: Гипотеза | E8: Автоматизированная услуга | F8: Сомнительное | G8: Фримиум | H8: Разработческие | I8: Удержание | K8: Источник лучшей практики
A9: Анализ ценностного предложения | B9: Ключевые виды деятельности | E9: Подписка на функциональность | G9: Лицензия | H9: Операционные | I9: Поддержка
A10: Анализ монетизации | B10: Ключевые партнеры | E10: Расширение или модуль | G10: Платное сопровождение | H10: Партнерские | I10: Повторная покупка
A11: Экспертная оценка | B11: Структура затрат | G11: Реклама
A12: Финансовая гипотеза | G12: Партнерская комиссия
A13: Анализ спроса | B13: Потоки доходов | C13: 5 | D13: Проверить | E13: Аналитический сервис | F13: Привлекательное | G13: Плата за использование | H13: Смешанные | I13: Использование | J13: Получить через партнера | K13: Нет конкурентов
A14: Опрос потребителей | B14: Ключевые ресурсы | D14: Готово | E14: Цифровой контент | F14: Безразличное | G14: Фримиум | H14: Разовые | I14: Повторное использование | J14: Арендовать сервис
A15: Документация проекта | B15: Ключевые виды деятельности | D15: Не заполнено | E15: Расширение/модуль | G15: Смешанная модель | I15: Адвокация
A16: Анализ трафика | B16: Ключевые партнеры | E16: Прикладной программный интерфейс
B17: Структура затрат | E17: Маркетплейс
B18: Отношения с клиентами

Sheet Журнал_6_2
A1: Журнал рабочей копии: источники, правила, ограничения
A3: Раздел | B3: Код | C3: Содержание
A4: Источники | B4: И-1 | C4: Банк выводов из 24 записей: ЛР1-ЛР5 и методика 6.1; страницы конкурентов просмотрены 01.10.2026
A5: Правило | B5: П-1 | C5: Блоки 8-11 (ресурсы, деятельность, партнёры, затраты) основаны на экспертных гипотезах и косвенных признаках, доказательность 2; в статусе «Гипотеза»
A6: Правило | B6: П-2 | C6: Оценки 1-5 экспертные. Статусы и индексы - формулы шаблона
A7: Ограничения | B7: О-1 | C7: Спрос не проверен на реальных клиентах; продукт до MVP; опрос студентов пробный, по условным профилям. Планируется собрать: интервью, тест посадочной страницы, расчёт экономики на пользователя, договорённости с вузами и провайдерами
