Workbook

Sheet 13_Справочники
A1: Справочники для раскрывающихся списков
A2: Используйте эти значения в рабочих листах, чтобы результаты можно было сопоставлять между конкурентами
A3: Тип конкурента | B3: Приоритет | C3: Статус анализа | D3: Элемент бизнес-модели | E3: Уровень доказательности | F3: Модель монетизации | G3: Тип воронки | H3: Классификация практики | I3: Тип преимущества
A4: прямой | B4: высокий | C4: не начат | D4: целевые сегменты | E4: 1 | F4: подписка | G4: самостоятельная покупка | H4: рыночный стандарт | I4: товарное
A5: косвенный | B5: средний | C5: в работе | D5: ценностное предложение | E5: 2 | F5: разовая покупка | G5: заявка на консультацию | H5: формирующийся стандарт | I5: ценовое
A6: заменитель | B6: низкий | C6: требует проверки | D6: цифровой товар | E6: 3 | F6: комиссия | G6: демонстрация продукта | H6: зона дифференциации | I6: канальное
A7: эталон лучшей практики | C7: завершен | D7: каналы | E7: 4 | F7: транзакционная оплата | G7: регистрация | H7: нишевой признак | I7: технологическое
A8: смежная модель | D8: отношения с клиентами | E8: 5 | F8: условно-бесплатная модель | G8: пробный доступ | H8: слабый сигнал | I8: данные
D9: потоки доходов | F9: лицензия | G9: контентная воронка | I9: партнерское
D10: ключевые ресурсы | F10: реклама | G10: корпоративные продажи | I10: брендовое
D11: ключевые виды деятельности | F11: оплата за использование | G11: маркетплейс | I11: сервисное
D12: ключевые партнеры | F12: пакетная продажа | I12: операционное
D13: структура затрат | F13: смешанная
D14: данные и сетевые эффекты
D15: масштабирование

Sheet 01_Инструкция
A1: Методика анализа бизнес-модели конкурентов по их сайтам
A2: Рабочая книга предназначена для восстановления бизнес-модели конкурента по публичным данным сайта: продукт, ценность, монетизация, каналы, ресурсы, партнерства, данные, масштабируемость и конкурентные преимущества
A4: Этап | B4: Что сделать | C4: Где заполнять | D4: Результат | F4: Шкала | G4: Интерпретация
A5: 1. Сформировать контур анализа | B5: Внести список конкурентов, тип конкурента, географию, сегмент, приоритет и статус анализа | C5: 02_Конкуренты | D5: Единый перечень объектов наблюдения | F5: 1 | G5: Слабый косвенный признак: предположение без прямого подтверждения на сайте
A6: 2. Собрать факты с сайтов | B6: Фиксировать URL, раздел сайта, наблюдаемый факт, элемент бизнес-модели, уровень доказательности и вывод | C6: 03_Факты_сайта | D6: Проверяемая база фактов, на которой строятся гипотезы | F6: 2 | G6: Косвенное подтверждение: факт есть, но связь с блоком бизнес-модели неочевидна
A7: 3. Восстановить бизнес-модель | B7: По каждому конкуренту заполнить блоки бизнес-модели: сегменты, ценность, цифровой товар, каналы, отношения, доходы, ресурсы, деятельность, партнеры, издержки, данные | C7: 04_Бизнес_модель | D7: Профиль бизнес-модели конкурента с оценкой полноты и доказательности | F7: 3 | G7: Достаточное подтверждение: факт прямо указывает на элемент бизнес-модели
A8: 4. Уточнить товар и ценность | B8: Разложить предложение на ядро цифрового товара, ожидаемый уровень, расширенный уровень, потенциальное развитие и клиентский результат | C8: 05_Товар_ценность | D8: Понимание того, что фактически продается и за счет чего создается ценность | F8: 4 | G8: Сильное подтверждение: несколько страниц или блоков сайта подтверждают один вывод
A9: 5. Оценить монетизацию | B9: Зафиксировать признаки ценовой модели, тарифы, пробный доступ, ограничения, платежные условия и логику получения выручки | C9: 06_Монетизация | D9: Вывод о потоках доходов и зрелости коммерческой модели | F9: 5 | G9: Высокая доказательность: прямое описание, тариф, оферта, демонстрация, кейс или документация подтверждают вывод
A10: 6. Описать каналы и воронку | B10: Выявить источники привлечения, точки конверсии, призывы к действию, контент, регистрацию, демонстрацию, заявки и продажи | C10: 07_Каналы | D10: Понимание способа выхода на рынок и механики превращения посетителя в клиента
A11: 7. Описать операционную основу | B11: Оценить ресурсы, процессы, данные, интеграции, партнеров, поддержку, признаки масштабируемости и операционных ограничений | C11: 08_Операц_модель | D11: Оценка устойчивости и воспроизводимости бизнес-модели
A12: 8. Сравнить конкурентов | B12: Поставить оценки по ключевым блокам, использовать веса и получить итоговый индекс силы бизнес-модели | C12: 09_Матрица | D12: Рейтинг бизнес-моделей конкурентов
A13: 9. Определить рыночный стандарт | B13: Сгруппировать повторяющиеся практики и рассчитать долю конкурентов, у которых они присутствуют | C13: 10_Стандарт | D13: Отделение обязательного рыночного минимума от зон дифференциации
A14: 10. Сформулировать преимущества | B14: Выделить преимущества конкурентов и оценить силу, трудность копирования, коммерческую значимость и доказательность | C14: 11_Преимущества | D14: Список проверяемых преимуществ и угроз
A15: 11. Подготовить итог | B15: Использовать сводный лист для контроля заполнения, рейтинга и общей интерпретации | C15: 12_Сводка | D15: Сводная картина рынка и рекомендации к дальнейшему анализу

Sheet 02_Конкуренты
A1: Реестр конкурентов
A2: Заполняется первым. Один конкурент – одна строка. ID используется во всех остальных листах
A3: ID | B3: Название конкурента | C3: Сайт | D3: Сегмент | E3: Тип конкурента | F3: География | G3: Приоритет | H3: Статус анализа | I3: Дата фиксации | J3: Ответственный | K3: Примечание
A4: C01 | B4: PlantUML | C4: plantuml.com | D4: Разработчики, студенты, архитекторы ПО | E4: прямой | F4: Весь мир (английский язык) | G4: высокий | H4: завершен | I4: 01.10.2026 | J4: К. А. Хаджинова | K4: Профиль построен по просмотренным страницам; блоки деятельности, партнёров, затрат и сетевых эффектов - косвенные признаки и гипотезы
A5: C02 | B5: Mermaid (библиотека) | C5: mermaid.js.org | D5: Разработчики, авторы технической документации | E5: косвенный | F5: Весь мир (английский язык) | G5: высокий | H5: завершен | I5: 01.10.2026 | J5: К. А. Хаджинова | K5: Профиль построен по просмотренным страницам; блоки деятельности, партнёров, затрат и сетевых эффектов - косвенные признаки и гипотезы
A6: C03 | B6: Mermaid Chart | C6: mermaidchart.com | D6: Команды разработки и документации | E6: косвенный | F6: Весь мир (США, Великобритания, Япония в топ-странах) | G6: высокий | H6: завершен | I6: 01.10.2026 | J6: К. А. Хаджинова | K6: Профиль построен по просмотренным страницам; блоки деятельности, партнёров, затрат и сетевых эффектов - косвенные признаки и гипотезы
A7: C04 | B7: Storm (StormBPMN) | C7: stormbpmn.com | D7: Процессные аналитики, русскоязычный рынок | E7: смежная модель | F7: Россия и СНГ (Россия 62,99 %, Беларусь 2,49 %) | G7: средний | H7: завершен | I7: 01.10.2026 | J7: К. А. Хаджинова | K7: Профиль построен по просмотренным страницам; блоки деятельности, партнёров, затрат и сетевых эффектов - косвенные признаки и гипотезы
A8: C05 | B8: draw.io (diagrams.net) | C8: app.diagrams.net | D8: Студенты, разработчики, команды | E8: косвенный | F8: Весь мир (США, Индонезия, Индия, Китай, Россия) | G8: высокий | H8: завершен | I8: 01.10.2026 | J8: К. А. Хаджинова | K8: Профиль построен по просмотренным страницам; блоки деятельности, партнёров, затрат и сетевых эффектов - косвенные признаки и гипотезы
A9: C06 | B9: Lucidchart | C9: lucidchart.com | D9: Команды, бизнес-пользователи | E9: косвенный | F9: Весь мир (США, Мексика, Бразилия в топ-странах) | G9: средний | H9: завершен | I9: 01.10.2026 | J9: К. А. Хаджинова | K9: Профиль построен по просмотренным страницам; блоки деятельности, партнёров, затрат и сетевых эффектов - косвенные признаки и гипотезы
A10: C07 | B10: Eraser | C10: eraser.io | D10: Инженерные команды, разработчики | E10: косвенный | F10: Весь мир | G10: высокий | H10: завершен | I10: 01.10.2026 | J10: К. А. Хаджинова | K10: Профиль построен по просмотренным страницам; блоки деятельности, партнёров, затрат и сетевых эффектов - косвенные признаки и гипотезы
A11: C08 | B11: Whimsical | C11: whimsical.com | D11: Команды продуктов | E11: заменитель | F11: Весь мир | G11: низкий | H11: завершен | I11: 01.10.2026 | J11: К. А. Хаджинова | K11: Профиль построен по просмотренным страницам; блоки деятельности, партнёров, затрат и сетевых эффектов - косвенные признаки и гипотезы

Sheet 03_Факты_сайта
A1: Факты, извлеченные с сайтов конкурентов
A2: Каждый вывод по бизнес-модели должен иметь источник: URL, наблюдаемый факт и уровень доказательности
A3: Факт_ID | B3: ID конкурента | C3: Название | D3: Раздел сайта | E3: URL | F3: Блок/страница | G3: Наблюдаемый факт | H3: Элемент бизнес-модели | I3: Доказательность 1-5 | J3: Дата фиксации | K3: Цитата/скриншот | L3: Аналитический вывод
A4: F001 | B4: C01 | C4: =IF($B4="","",IFERROR(VLOOKUP($B4,'02_Конкуренты'!$A$4:$B$11,2,FALSE),"не найдено")) -> PlantUML | D4: Главная страница | E4: https://plantuml.com/ | F4: Заголовок и описание | G4: Обещание: «Open-source tool that uses simple textual descriptions to draw beautiful UML diagrams» | H4: ценностное предложение | I4: 4 | J4: 01.10.2026 | K4: главная страница, 01.10.2026
A5: F002 | B5: C01 | C5: =IF($B5="","",IFERROR(VLOOKUP($B5,'02_Конкуренты'!$A$4:$B$11,2,FALSE),"не найдено")) -> PlantUML | D5: Главная страница | E5: https://plantuml.com/ | F5: Состав товара | G5: Построение UML-диаграмм из текстового описания, экспорт PNG, LaTeX, EPS, SVG | H5: цифровой товар | I5: 4 | J5: 01.10.2026 | K5: страницы сайта, ЛР4
A6: F003 | B6: C01 | C6: =IF($B6="","",IFERROR(VLOOKUP($B6,'02_Конкуренты'!$A$4:$B$11,2,FALSE),"не найдено")) -> PlantUML | D6: Тарифы | E6: https://plantuml.com/ | F6: Тарифная таблица | G6: открытый код, бесплатно (ЛР1, табл. 42) | H6: потоки доходов | I6: 4 | J6: 01.10.2026 | K6: страница тарифов или лицензия
A7: F004 | B7: C01 | C7: =IF($B7="","",IFERROR(VLOOKUP($B7,'02_Конкуренты'!$A$4:$B$11,2,FALSE),"не найдено")) -> PlantUML | D7: Similarweb Pro | E7: https://plantuml.com/ | F7: Каналы | G7: прямые заходы 38,11 %; органический поиск 47,25 %; рефералы 5,91 %; соцсети органика 3,62 %; ИИ-ассистенты 4,42 %; e-mail 0,60 % (Similarweb Pro, Jun-Aug 2026, весь мир, снимок 30.09.2026) | H7: каналы | I7: 3 | J7: 01.10.2026 | K7: Similarweb Pro (ЛР4)
A8: F005 | B8: C01 | C8: =IF($B8="","",IFERROR(VLOOKUP($B8,'02_Конкуренты'!$A$4:$B$11,2,FALSE),"не найдено")) -> PlantUML | D8: GitHub | E8: https://github.com/plantuml/plantuml | F8: Репозиторий | G8: plantuml/plantuml: 13 346 звёзд, лицензия LGPL-3.0 | H8: ключевые ресурсы | I8: 5 | J8: 01.10.2026 | K8: GitHub API, 30.09.2026
A9: F006 | B9: C01 | C9: =IF($B9="","",IFERROR(VLOOKUP($B9,'02_Конкуренты'!$A$4:$B$11,2,FALSE),"не найдено")) -> PlantUML | D9: Страницы сайта | E9: https://plantuml.com/ | F9: Описание диаграммы текстом (DSL) | G9: Признак найден на просмотренных страницах: описание диаграммы текстом (dsl) | H9: цифровой товар | I9: 4 | J9: 01.10.2026 | K9: Главные страницы PlantUML, Mermaid, Mermaid Chart; «Diagram-as-code» в тарифе Free Eraser;
A10: F007 | B10: C01 | C10: =IF($B10="","",IFERROR(VLOOKUP($B10,'02_Конкуренты'!$A$4:$B$11,2,FALSE),"не найдено")) -> PlantUML | D10: Страницы сайта | E10: https://plantuml.com/ | F10: Интеграции с другими сервисами | G10: Признак найден на просмотренных страницах: интеграции с другими сервисами | H10: ключевые партнеры | I10: 3 | J10: 01.10.2026 | K10: Разделы и упоминания интеграций на страницах 8 из 8 конкурентов
A11: F008 | B11: C01 | C11: =IF($B11="","",IFERROR(VLOOKUP($B11,'02_Конкуренты'!$A$4:$B$11,2,FALSE),"не найдено")) -> PlantUML | D11: Страницы сайта | E11: https://plantuml.com/ | F11: Открытый код и сообщество | G11: Признак найден на просмотренных страницах: открытый код и сообщество | H11: ключевые ресурсы | I11: 3 | J11: 01.10.2026 | K11: GitHub API, 30.09.2026; лицензия Apache 2.0 у draw.io
A12: F009 | B12: C01 | C12: =IF($B12="","",IFERROR(VLOOKUP($B12,'02_Конкуренты'!$A$4:$B$11,2,FALSE),"не найдено")) -> PlantUML | D12: Страницы сайта | E12: https://plantuml.com/ | F12: Экспорт диаграмм (PNG, SVG, PDF и др.) | G12: Признак найден на просмотренных страницах: экспорт диаграмм (png, svg, pdf и др.) | H12: цифровой товар | I12: 4 | J12: 01.10.2026 | K12: Экспорт упомянут на страницах 8 из 8 конкурентов (PNG, SVG, PDF, DOCX у Storm, Visio у Luc
A13: F010 | B13: C01 | C13: =IF($B13="","",IFERROR(VLOOKUP($B13,'02_Конкуренты'!$A$4:$B$11,2,FALSE),"не найдено")) -> PlantUML | D13: Страницы сайта | E13: https://plantuml.com/ | F13: Документация и руководства | G13: Признак найден на просмотренных страницах: документация и руководства | H13: отношения с клиентами | I13: 4 | J13: 01.10.2026 | K13: PlantUML Language Reference Guide; Mermaid User Guide; docs.mermaidchart.com; docs.eraser
A14: F011 | B14: C01 | C14: =IF($B14="","",IFERROR(VLOOKUP($B14,'02_Конкуренты'!$A$4:$B$11,2,FALSE),"не найдено")) -> PlantUML | D14: Страницы сайта | E14: https://plantuml.com/ | F14: Диаграммы UML | G14: Признак найден на просмотренных страницах: диаграммы uml | H14: цифровой товар | I14: 4 | J14: 01.10.2026 | K14: Страницы class-diagram (PlantUML, Mermaid); UML в описании draw.io; UML-шаблоны Lucidchart
A15: F012 | B15: C01 | C15: =IF($B15="","",IFERROR(VLOOKUP($B15,'02_Конкуренты'!$A$4:$B$11,2,FALSE),"не найдено")) -> PlantUML | D15: Страницы сайта | E15: https://plantuml.com/ | F15: Диаграммы ERD | G15: Признак найден на просмотренных страницах: диаграммы erd | H15: цифровой товар | I15: 4 | J15: 01.10.2026 | K15: Страницы entityRelationshipDiagram (Mermaid), ie-diagram (PlantUML); ER в описании draw.io
... A148: F145 | B148: C08 | C148: =IF($B148="","",IFERROR(VLOOKUP($B148,'02_Конкуренты'!$A$4:$B$11,2,FALSE),"не найдено")) -> Whimsical | D148: Страницы сайта | E148: https://whimsical.com/ | F148: Настольное приложение | G148: Признак найден на просмотренных страницах: настольное приложение | H148: цифровой товар | I148: 3 | J148: 01.10.2026 | K148: Загрузка PlantUML; drawio-desktop (GitHub); Desktop app в таблице тарифов Whimsical

Sheet 04_Бизнес_модель
A1: Профиль бизнес-модели конкурента
A2: Заполняется на основе фактов с сайта. Полнота и доказательность рассчитываются автоматически
A3: ID конкурента | B3: Название | C3: Целевые сегменты | D3: Ценностное предложение | E3: Цифровой товар | F3: Каналы | G3: Отношения с клиентами | H3: Потоки доходов | I3: Ключевые ресурсы | J3: Ключевые виды деятельности | K3: Ключевые партнеры | L3: Структура затрат | M3: Данные и сетевые эффекты | N3: Главная гипотеза бизнес-модели | O3: Полнота профиля | P3: Средняя доказательность | Q3: Качество профиля
A4: C01 | B4: =IF($A4="","",IFERROR(VLOOKUP($A4,'02_Конкуренты'!$A$4:$B$11,2,FALSE),"не найдено")) -> PlantUML | C4: Разработчики, студенты, архитекторы ПО | D4: «Open-source tool that uses simple textual descriptions to draw beautiful UML diagrams» | E4: Построение UML-диаграмм из текстового описания, экспорт PNG, LaTeX, EPS, SVG; описание диаграммы текстом (dsl), бесплатный доступ или free-тариф, интеграции с другими сервисами, открытый код и сообщество, независимые отзывы и оценки, экспорт диаграмм (png, svg, pdf и др.), документация и руководства, диаграммы uml | F4: прямые заходы 38,11 %; органический поиск 47,25 %; рефералы 5,91 %; соцсети органика 3,62 %; ИИ-ассистенты 4,42 %; e-mail 0,60 % (Similarweb Pro, Jun-Aug 2026, весь мир, снимок 30.09.2026) | G4: оценки расширений: VS Marketplace jebbs.plantuml 4,72 (105), JetBrains plantuml4idea 4,63 (102); G2 и Trustpilot: карточка не найдена | H4: открытый код, бесплатно (ЛР1, табл. 42) | I4: plantuml/plantuml: 13 346 звёзд | J4: Разработка языка и серверной части, выпуск релизов (страница загрузки), документация | K4: Интеграции в вики, редакторы, IDE и языки программирования (страница running) | L4: Признаки: разработка сообщества и серверы; ИИ-расходов на сайте нет | M4: Сообщество на GitHub (13 346 звёзд), форумы | N4: Гипотеза (для проверки): ценность - диаграммы из текста; доход не из продажи самого инструмента | O4: =IF($A4="","",COUNTA($C4:$N4)/12) -> 1 | P4: =IF($A4="","",IFERROR(AVERAGEIF('03_Факты_сайта'!$B$4:$B$148,$A4,'03_Факты_сайта'!$I$4:$I$148),0)) -> 3.7142857 | Q4: =IF($A4="","",IF($O4<0.5,"недостаточно данных",IF($P4<3,"низкая доказательность",IF($O4>=0.85,"готов к сравнению","требует дополнения")))) -> готов к сравнению
A5: C02 | B5: =IF($A5="","",IFERROR(VLOOKUP($A5,'02_Конкуренты'!$A$4:$B$11,2,FALSE),"не найдено")) -> Mermaid (библиотека) | C5: Разработчики, авторы технической документации | D5: «Create diagrams and visualizations using text and code» | E5: Диаграммы и визуализации из текста и кода (JavaScript-библиотека); описание диаграммы текстом (dsl), бесплатный доступ или free-тариф, интеграции с другими сервисами, api или платформа разработчика, открытый код и сообщество, независимые отзывы и оценки, экспорт диаграмм (png, svg, pdf и др.), документация и руководства | F5: прямые заходы 22,18 %; органический поиск 58,56 %; рефералы 16,50 %; соцсети органика 1,25 %; ИИ-ассистенты 1,23 %; e-mail 0,22 %; платный поиск 0,01 % (Similarweb Pro, Jun-Aug 2026, весь мир, снимок 30.09.2026) | G5: оценки расширений: VS Marketplace (bierner.markdown-mermaid 60, vstirbu 27, tomoyukim 17) и JetBrains Mermaid 2,96 (65) | H5: открытый код (MIT); платные планы у Mermaid Chart | I5: mermaid-js/mermaid: 90 489 звёзд; mermaid-js/mermaid-live-editor: 6 836 звёзд | J5: Развитие библиотеки, экосистемы и документации | K5: Интеграции сообщества: редакторы, вики, платформы (страница integrations-community) | L5: Признаки: разработка сообщества; платные планы вынесены в Mermaid Chart | M5: Сообщество: 90 489 звёзд GitHub, плагины | N5: Гипотеза (для проверки): ядро открытого стандарта, монетизация вынесена в Mermaid Chart | O5: =IF($A5="","",COUNTA($C5:$N5)/12) -> 1 | P5: =IF($A5="","",IFERROR(AVERAGEIF('03_Факты_сайта'!$B$4:$B$148,$A5,'03_Факты_сайта'!$I$4:$I$148),0)) -> 3.7857143 | Q5: =IF($A5="","",IF($O5<0.5,"недостаточно данных",IF($P5<3,"низкая доказательность",IF($O5>=0.85,"готов к сравнению","требует дополнения")))) -> готов к сравнению
A6: C03 | B6: =IF($A6="","",IFERROR(VLOOKUP($A6,'02_Конкуренты'!$A$4:$B$11,2,FALSE),"не найдено")) -> Mermaid Chart | C6: Команды разработки и документации | D6: «Create diagrams, flowcharts, and documentation with Mermaid»; «You already think in systems» | E6: Облачный редактор диаграмм Mermaid с тарифами Free, Plus, Premium; описание диаграммы текстом (dsl), бесплатный доступ или free-тариф, платная подписка по тарифным уровням, открытая страница тарифов, корпоративный тариф (enterprise или on-prem), скидка или цена при годовой оплате, бесплатные гости или зрители, ии-генерация или ии-помощник | F6: прямые заходы 39,97 %; органический поиск 32,54 %; рефералы 10,32 %; соцсети органика 6,05 %; ИИ-ассистенты 1,62 %; e-mail 2,52 %; платный поиск 1,62 % (Similarweb Pro, Jun-Aug 2026, весь мир, снимок 30.09.2026) | G6: G2 (карточка Mermaid) 4,8 (16); Trustpilot 3,5 (3); Product Hunt 4,8 (26) | H6: Basic Free (до 6 диаграмм, 15 ИИ-кредитов); Plus 10 у.е. (300 кредитов); Premium 20 у.е. (2 000 кредитов, зрители без оплаты) за пользователя в месяц при оплате за год; Enterprise по запросу | I6: Команда продукта и облачная инфраструктура (по описанию сайта) | J6: Развитие облачного редактора, ИИ-функций, документации | K6: Плагины и интеграции (меню Product), экосистема Mermaid.js | L6: Признак: лимиты ИИ-кредитов указывают на стоимость ИИ-вызовов | M6: Совместная работа и общий доступ; 5M пользователей и 200k компаний по заявлению сайта | N6: Гипотеза (для проверки): облачный сервис над открытым стандартом: доход от тарифов за пользователя | O6: =IF($A6="","",COUNTA($C6:$N6)/12) -> 1 | P6: =IF($A6="","",IFERROR(AVERAGEIF('03_Факты_сайта'!$B$4:$B$148,$A6,'03_Факты_сайта'!$I$4:$I$148),0)) -> 3.952381 | Q6: =IF($A6="","",IF($O6<0.5,"недостаточно данных",IF($P6<3,"низкая доказательность",IF($O6>=0.85,"готов к сравнению","требует дополнения")))) -> готов к сравнению
A7: C04 | B7: =IF($A7="","",IFERROR(VLOOKUP($A7,'02_Конкуренты'!$A$4:$B$11,2,FALSE),"не найдено")) -> Storm (StormBPMN) | C7: Процессные аналитики, русскоязычный рынок | D7: «Соберите все процессы компании»; «Одна платформа - девять модулей процессного управления» | E7: Платформа из семи модулей: редактор, реестр, архитектура, оргструктура, опросы, ИИ, симуляция; бесплатный доступ или free-тариф, платная подписка по тарифным уровням, открытая страница тарифов, корпоративный тариф (enterprise или on-prem), скидка или цена при годовой оплате, бесплатные гости или зрители, ии-генерация или ии-помощник, интеграции с другими сервисами | F7: прямые заходы 57,33 %; органический поиск 20,91 %; рефералы 10,72 %; соцсети органика 2,59 %; ИИ-ассистенты 1,74 %; e-mail 3,78 %; платный поиск 1,32 % (Similarweb Pro, Jun-Aug 2026, весь мир, снимок 30.09.2026) | G7: Заявление сайта: «Нам доверяют больше 1 000 клиентов» | H7: Персональный 0 руб. (до 50 моделей); Команда 1 200 руб. (1 500 руб. помесячно) за пользователя в месяц; Бизнес 4 720 руб. (5 900 руб.); Enterprise на сервере заказчика от 990 тыс. руб. в год (страница тарифов, 01.10.2026) | I7: Команда продукта и облачная инфраструктура (по описанию сайта) | J7: Развитие девяти модулей платформы, ИИ-ассистента, MCP; продажи и внедрение on-prem | K7: MCP-интеграции, API в Enterprise | L7: Признаки: безлимитный ИИ в облачных тарифах, on-prem для крупных клиентов | M7: Связи процессов, реестр, оргструктура и база знаний внутри платформы; более 1 000 клиентов | N7: Гипотеза (для проверки): платформа процессного управления для русскоязычного рынка: доход от тарифов в рублях и on-prem | O7: =IF($A7="","",COUNTA($C7:$N7)/12) -> 1 | P7: =IF($A7="","",IFERROR(AVERAGEIF('03_Факты_сайта'!$B$4:$B$148,$A7,'03_Факты_сайта'!$I$4:$I$148),0)) -> 3.8571429 | Q7: =IF($A7="","",IF($O7<0.5,"недостаточно данных",IF($P7<3,"низкая доказательность",IF($O7>=0.85,"готов к сравнению","требует дополнения")))) -> готов к сравнению
A8: C05 | B8: =IF($A8="","",IFERROR(VLOOKUP($A8,'02_Конкуренты'!$A$4:$B$11,2,FALSE),"не найдено")) -> draw.io (diagrams.net) | C8: Студенты, разработчики, команды | D8: «Security-first diagramming for teams»; «Free, open source diagramming application with 100M+ users» | E8: Бесплатный онлайн-редактор блок-схем, UML, ER и других диаграмм; бесплатный доступ или free-тариф, интеграции с другими сервисами, открытый код и сообщество, независимые отзывы и оценки, данные о числе пользователей или клиентов на сайте, раздел или упоминание о безопасности и приватности, вход и личный кабинет, совместная работа в реальном времени | F8: прямые заходы 68,39 %; органический поиск 13,96 %; рефералы 9,72 %; соцсети органика 2,07 %; ИИ-ассистенты 2,68 %; e-mail 1,19 %; платный поиск 0,02 % (Similarweb Pro, Jun-Aug 2026, весь мир, снимок 30.09.2026) | G8: Capterra 4,6 (773); Trustpilot draw.io 3,4 (11) и diagrams.net 3,8 (2); Atlassian Marketplace draw.io Diagrams 4,8 (1 205) | H8: полностью бесплатный, открытый код (Apache 2.0) (ЛР1, табл. 42) | I8: jgraph/drawio: 8 502 звёзд; jgraph/drawio-desktop: 63 351 звёзд | J8: Развитие приложения, интеграций и встраивания; документация | K8: Google Drive, Microsoft SharePoint и OneDrive, Atlassian Confluence и Jira, GitHub, VS Code, Notion | L8: Признак: «Not VC-funded», нет enterprise-тарифа | M8: Данные у пользователя («we cannot access it»); совместимость файлов с 2005 г. | N8: Гипотеза (для проверки): бесплатный массовый инструмент: привлекает аудиторию, монетизация на сайте не показана | O8: =IF($A8="","",COUNTA($C8:$N8)/12) -> 1 | P8: =IF($A8="","",IFERROR(AVERAGEIF('03_Факты_сайта'!$B$4:$B$148,$A8,'03_Факты_сайта'!$I$4:$I$148),0)) -> 3.625 | Q8: =IF($A8="","",IF($O8<0.5,"недостаточно данных",IF($P8<3,"низкая доказательность",IF($O8>=0.85,"готов к сравнению","требует дополнения")))) -> готов к сравнению
A9: C06 | B9: =IF($A9="","",IFERROR(VLOOKUP($A9,'02_Конкуренты'!$A$4:$B$11,2,FALSE),"не найдено")) -> Lucidchart | C9: Команды, бизнес-пользователи | D9: «Diagramming powered by intelligence»: диаграммы с ИИ, данными и автоматизацией | E9: Облачный редактор диаграмм с тарифами Free, Individual, Team, Enterprise; описание диаграммы текстом (dsl), бесплатный доступ или free-тариф, платная подписка по тарифным уровням, открытая страница тарифов, корпоративный тариф (enterprise или on-prem), скидка или цена при годовой оплате, пробный период платного тарифа, ии-генерация или ии-помощник | F9: прямые заходы 11,33 %; органический поиск 55,95 %; рефералы 2,71 %; соцсети органика 1,34 %; ИИ-ассистенты 2,10 %; e-mail 0,20 %; платный поиск 22,55 % (Similarweb Pro, Jun-Aug 2026, весь мир, снимок 30.09.2026) | G9: G2 4,5 (8 988); Capterra/GetApp/Software Advice 4,5 (2 264); Trustpilot lucidchart.com 1,5 (116) | H9: Free (3 документа, 75 фигур, 100 шаблонов); Individual 9 у.е.; Team 10 у.е. за пользователя в месяц при оплате за год; Enterprise по запросу; пробный период 7 дней | I9: Команда продукта и облачная инфраструктура (по описанию сайта) | J9: Развитие продукта, ИИ, платформы разработчика, продажи Enterprise | K9: Microsoft 365, Confluence, Jira, LeanIX, Ardoq, Salesforce | L9: Признаки: ИИ, поддержка, учебный центр, Enterprise Shield | M9: Совместная работа, шаблоны, связывание данных; Fortune 500 по заявлению сайта | N9: Гипотеза (для проверки): облачный сервис с лестницей тарифов Free, Individual, Team, Enterprise | O9: =IF($A9="","",COUNTA($C9:$N9)/12) -> 1 | P9: =IF($A9="","",IFERROR(AVERAGEIF('03_Факты_сайта'!$B$4:$B$148,$A9,'03_Факты_сайта'!$I$4:$I$148),0)) -> 3.9583333 | Q9: =IF($A9="","",IF($O9<0.5,"недостаточно данных",IF($P9<3,"низкая доказательность",IF($O9>=0.85,"готов к сравнению","требует дополнения")))) -> готов к сравнению
A10: C07 | B10: =IF($A10="","",IFERROR(VLOOKUP($A10,'02_Конкуренты'!$A$4:$B$11,2,FALSE),"не найдено")) -> Eraser | C10: Инженерные команды, разработчики | D10: «AI for diagrams that matter»; «Create technical diagrams using AI» | E10: Создание технических диаграмм с помощью ИИ; описание диаграммы текстом (dsl), бесплатный доступ или free-тариф, платная подписка по тарифным уровням, открытая страница тарифов, корпоративный тариф (enterprise или on-prem), скидка или цена при годовой оплате, бесплатные гости или зрители, ии-генерация или ии-помощник | F10: Вход и документация на сайте; данные Similarweb по домену не получены | G10: Product Hunt 4,9 (10); расширение VS Code 4,8 (5) | H10: Free (0 у.е.; 3 файла, 3 ИИ-диаграммы); Starter 15 у.е. (20 у.е. при помесячной оплате); Business 45 у.е. (60 у.е.); Enterprise по запросу; цены за участника в месяц (страница тарифов, 01.10.2026) | I10: Команда продукта и облачная инфраструктура (по описанию сайта) | J10: Развитие ИИ-генерации диаграмм, интеграций, API | K10: GitHub, Notion, Confluence, VS Code | L10: Признак: лимиты ИИ-диаграмм по тарифам указывают на стоимость ИИ | M10: Совместная работа, гости без оплаты; история версий по тарифам | N10: Гипотеза (для проверки): подписка вокруг ИИ-генерации и diagram-as-code для технических команд | O10: =IF($A10="","",COUNTA($C10:$N10)/12) -> 1 | P10: =IF($A10="","",IFERROR(AVERAGEIF('03_Факты_сайта'!$B$4:$B$148,$A10,'03_Факты_сайта'!$I$4:$I$148),0)) -> 4 | Q10: =IF($A10="","",IF($O10<0.5,"недостаточно данных",IF($P10<3,"низкая доказательность",IF($O10>=0.85,"готов к сравнению","требует дополнения")))) -> готов к сравнению
A11: C08 | B11: =IF($A11="","",IFERROR(VLOOKUP($A11,'02_Конкуренты'!$A$4:$B$11,2,FALSE),"не найдено")) -> Whimsical | C11: Команды продуктов | D11: «The whiteboard for product builders»: диаграммы, схемы интерфейсов, документы | E11: Редактор диаграмм, схем интерфейсов и документов; тарифы Free, Pro, Business (страница тарифов, 01.10.2026); бесплатный доступ или free-тариф, платная подписка по тарифным уровням, открытая страница тарифов, бесплатные гости или зрители, ии-генерация или ии-помощник, интеграции с другими сервисами, независимые отзывы и оценки, раздел или упоминание о безопасности и приватности | F11: Вход и документация на сайте; данные Similarweb по домену не получены | G11: Capterra 4,7 (59) | H11: Free (0 у.е.; 50 объектов доски и 50 блоков документа в месяц, водяной знак при экспорте); Pro 10 у.е., Business 20 у.е. за редактора в месяц (страница тарифов, 01.10.2026) | I11: Команда продукта и облачная инфраструктура (по описанию сайта) | J11: Развитие доски, диаграмм, документов и ИИ | K11: Интеграции указаны на сайте (число не проверялось) | L11: Признаки: хранилище и история версий по тарифам, ИИ | M11: Совместная работа, гости и зрители без ограничений | N11: Гипотеза (для проверки): подписка для продуктовых команд: доход от платных мест редакторов | O11: =IF($A11="","",COUNTA($C11:$N11)/12) -> 1 | P11: =IF($A11="","",IFERROR(AVERAGEIF('03_Факты_сайта'!$B$4:$B$148,$A11,'03_Факты_сайта'!$I$4:$I$148),0)) -> 4 | Q11: =IF($A11="","",IF($O11<0.5,"недостаточно данных",IF($P11<3,"низкая доказательность",IF($O11>=0.85,"готов к сравнению","требует дополнения")))) -> готов к сравнению
B12: =IF($A12="","",IFERROR(VLOOKUP($A12,'02_Конкуренты'!$A$4:$B$11,2,FALSE),"не найдено")) | O12: =IF($A12="","",COUNTA($C12:$N12)/12) | P12: =IF($A12="","",IFERROR(AVERAGEIF('03_Факты_сайта'!$B$4:$B$148,$A12,'03_Факты_сайта'!$I$4:$I$148),0)) | Q12: =IF($A12="","",IF($O12<0.5,"недостаточно данных",IF($P12<3,"низкая доказательность",IF($O12>=0.85,"готов к сравнению","требует дополнения"))))
B13: =IF($A13="","",IFERROR(VLOOKUP($A13,'02_Конкуренты'!$A$4:$B$11,2,FALSE),"не найдено")) | O13: =IF($A13="","",COUNTA($C13:$N13)/12) | P13: =IF($A13="","",IFERROR(AVERAGEIF('03_Факты_сайта'!$B$4:$B$148,$A13,'03_Факты_сайта'!$I$4:$I$148),0)) | Q13: =IF($A13="","",IF($O13<0.5,"недостаточно данных",IF($P13<3,"низкая доказательность",IF($O13>=0.85,"готов к сравнению","требует дополнения"))))
B14: =IF($A14="","",IFERROR(VLOOKUP($A14,'02_Конкуренты'!$A$4:$B$11,2,FALSE),"не найдено")) | O14: =IF($A14="","",COUNTA($C14:$N14)/12) | P14: =IF($A14="","",IFERROR(AVERAGEIF('03_Факты_сайта'!$B$4:$B$148,$A14,'03_Факты_сайта'!$I$4:$I$148),0)) | Q14: =IF($A14="","",IF($O14<0.5,"недостаточно данных",IF($P14<3,"низкая доказательность",IF($O14>=0.85,"готов к сравнению","требует дополнения"))))
B15: =IF($A15="","",IFERROR(VLOOKUP($A15,'02_Конкуренты'!$A$4:$B$11,2,FALSE),"не найдено")) | O15: =IF($A15="","",COUNTA($C15:$N15)/12) | P15: =IF($A15="","",IFERROR(AVERAGEIF('03_Факты_сайта'!$B$4:$B$148,$A15,'03_Факты_сайта'!$I$4:$I$148),0)) | Q15: =IF($A15="","",IF($O15<0.5,"недостаточно данных",IF($P15<3,"низкая доказательность",IF($O15>=0.85,"готов к сравнению","требует дополнения"))))
B16: =IF($A16="","",IFERROR(VLOOKUP($A16,'02_Конкуренты'!$A$4:$B$11,2,FALSE),"не найдено")) | O16: =IF($A16="","",COUNTA($C16:$N16)/12) | P16: =IF($A16="","",IFERROR(AVERAGEIF('03_Факты_сайта'!$B$4:$B$148,$A16,'03_Факты_сайта'!$I$4:$I$148),0)) | Q16: =IF($A16="","",IF($O16<0.5,"недостаточно данных",IF($P16<3,"низкая доказательность",IF($O16>=0.85,"готов к сравнению","требует дополнения"))))
B17: =IF($A17="","",IFERROR(VLOOKUP($A17,'02_Конкуренты'!$A$4:$B$11,2,FALSE),"не найдено")) | O17: =IF($A17="","",COUNTA($C17:$N17)/12) | P17: =IF($A17="","",IFERROR(AVERAGEIF('03_Факты_сайта'!$B$4:$B$148,$A17,'03_Факты_сайта'!$I$4:$I$148),0)) | Q17: =IF($A17="","",IF($O17<0.5,"недостаточно данных",IF($P17<3,"низкая доказательность",IF($O17>=0.85,"готов к сравнению","требует дополнения"))))
B18: =IF($A18="","",IFERROR(VLOOKUP($A18,'02_Конкуренты'!$A$4:$B$11,2,FALSE),"не найдено")) | O18: =IF($A18="","",COUNTA($C18:$N18)/12) | P18: =IF($A18="","",IFERROR(AVERAGEIF('03_Факты_сайта'!$B$4:$B$148,$A18,'03_Факты_сайта'!$I$4:$I$148),0)) | Q18: =IF($A18="","",IF($O18<0.5,"недостаточно данных",IF($P18<3,"низкая доказательность",IF($O18>=0.85,"готов к сравнению","требует дополнения"))))
B19: =IF($A19="","",IFERROR(VLOOKUP($A19,'02_Конкуренты'!$A$4:$B$11,2,FALSE),"не найдено")) | O19: =IF($A19="","",COUNTA($C19:$N19)/12) | P19: =IF($A19="","",IFERROR(AVERAGEIF('03_Факты_сайта'!$B$4:$B$148,$A19,'03_Факты_сайта'!$I$4:$I$148),0)) | Q19: =IF($A19="","",IF($O19<0.5,"недостаточно данных",IF($P19<3,"низкая доказательность",IF($O19>=0.85,"готов к сравнению","требует дополнения"))))
B20: =IF($A20="","",IFERROR(VLOOKUP($A20,'02_Конкуренты'!$A$4:$B$11,2,FALSE),"не найдено")) | O20: =IF($A20="","",COUNTA($C20:$N20)/12) | P20: =IF($A20="","",IFERROR(AVERAGEIF('03_Факты_сайта'!$B$4:$B$148,$A20,'03_Факты_сайта'!$I$4:$I$148),0)) | Q20: =IF($A20="","",IF($O20<0.5,"недостаточно данных",IF($P20<3,"низкая доказательность",IF($O20>=0.85,"готов к сравнению","требует дополнения"))))
B21: =IF($A21="","",IFERROR(VLOOKUP($A21,'02_Конкуренты'!$A$4:$B$11,2,FALSE),"не найдено")) | O21: =IF($A21="","",COUNTA($C21:$N21)/12) | P21: =IF($A21="","",IFERROR(AVERAGEIF('03_Факты_сайта'!$B$4:$B$148,$A21,'03_Факты_сайта'!$I$4:$I$148),0)) | Q21: =IF($A21="","",IF($O21<0.5,"недостаточно данных",IF($P21<3,"низкая доказательность",IF($O21>=0.85,"готов к сравнению","требует дополнения"))))
B22: =IF($A22="","",IFERROR(VLOOKUP($A22,'02_Конкуренты'!$A$4:$B$11,2,FALSE),"не найдено")) | O22: =IF($A22="","",COUNTA($C22:$N22)/12) | P22: =IF($A22="","",IFERROR(AVERAGEIF('03_Факты_сайта'!$B$4:$B$148,$A22,'03_Факты_сайта'!$I$4:$I$148),0)) | Q22: =IF($A22="","",IF($O22<0.5,"недостаточно данных",IF($P22<3,"низкая доказательность",IF($O22>=0.85,"готов к сравнению","требует дополнения"))))
B23: =IF($A23="","",IFERROR(VLOOKUP($A23,'02_Конкуренты'!$A$4:$B$11,2,FALSE),"не найдено")) | O23: =IF($A23="","",COUNTA($C23:$N23)/12) | P23: =IF($A23="","",IFERROR(AVERAGEIF('03_Факты_сайта'!$B$4:$B$148,$A23,'03_Факты_сайта'!$I$4:$I$148),0)) | Q23: =IF($A23="","",IF($O23<0.5,"недостаточно данных",IF($P23<3,"низкая доказательность",IF($O23>=0.85,"готов к сравнению","требует дополнения"))))
... B203: =IF($A203="","",IFERROR(VLOOKUP($A203,'02_Конкуренты'!$A$4:$B$11,2,FALSE),"не найдено")) | O203: =IF($A203="","",COUNTA($C203:$N203)/12) | P203: =IF($A203="","",IFERROR(AVERAGEIF('03_Факты_сайта'!$B$4:$B$148,$A203,'03_Факты_сайта'!$I$4:$I$148),0)) | Q203: =IF($A203="","",IF($O203<0.5,"недостаточно данных",IF($P203<3,"низкая доказательность",IF($O203>=0.85,"готов к сравнению","требует дополнения"))))
A205: Примечание: сначала заполните ID конкурента, затем восстановите блоки бизнес-модели на основе листа 03_Факты_сайта. Не заполняйте гипотезу без ссылок на доказательства

Sheet 05_Товар_ценность
A1: Цифровой товар и ценностное предложение
A2: Лист помогает отделить сам цифровой товар от упаковки, сервиса, каналов продажи и обещаний на сайте
A3: ID конкурента | B3: Название | C3: Ядро цифрового товара | D3: Базовое предложение | E3: Ожидаемый уровень | F3: Расширенный уровень | G3: Потенциальное развитие | H3: Клиентская проблема | I3: Клиентский результат | J3: Задача клиента | K3: Отличие от рынка | L3: Подтверждающие страницы | M3: Вывод о роли товара в бизнес-модели
A4: C01 | B4: =IF($A4="","",IFERROR(VLOOKUP($A4,'02_Конкуренты'!$A$4:$B$11,2,FALSE),"не найдено")) -> PlantUML | C4: Диаграммы UML из текста | D4: Построение UML-диаграмм из текстового описания, экспорт PNG, LaTeX, EPS, SVG | E4: Экспорт, документация, интеграции | F4: Шаблоны, совместная работа, ИИ, API по тарифам | G4: Признаки развития на просмотренных страницах не найдены | H4: Создание UML-диаграмм требует специальных инструментов и ручного рисования | I4: Диаграммы строятся из текста автоматически – без рисования и без лицензии | J4: Разработчики, студенты, архитекторы ПО | K4: ценность - диаграммы из текста; доход не из продажи самого инструмента | L4: https://plantuml.com/ | M4: Открытая библиотека и сервер; монетизация не из продажи инструмента, а через сервисы и поддержку
A5: C02 | B5: =IF($A5="","",IFERROR(VLOOKUP($A5,'02_Конкуренты'!$A$4:$B$11,2,FALSE),"не найдено")) -> Mermaid (библиотека) | C5: Диаграммы из текста и кода | D5: Диаграммы и визуализации из текста и кода (JavaScript-библиотека) | E5: Экспорт, документация, интеграции | F5: Шаблоны, совместная работа, ИИ, API по тарифам | G5: Признаки развития на просмотренных страницах не найдены | H5: Диаграммы в документации и коде устаревают и плохо интегрируются с текстом | I5: Диаграммы встраиваются прямо в Markdown и код; обновляются вместе с документацией | J5: Разработчики, авторы технической документации | K5: ядро открытого стандарта, монетизация вынесена в Mermaid Chart | L5: https://mermaid.js.org/ | M5: Открытая JS-библиотека; ядро – бесплатный стандарт; доход выведен в Mermaid Chart и корпоративные контракты
A6: C03 | B6: =IF($A6="","",IFERROR(VLOOKUP($A6,'02_Конкуренты'!$A$4:$B$11,2,FALSE),"не найдено")) -> Mermaid Chart | C6: Облачный редактор Mermaid | D6: Облачный редактор диаграмм Mermaid с тарифами Free, Plus, Premium | E6: Экспорт, документация, интеграции | F6: Шаблоны, совместная работа, ИИ, API по тарифам | G6: MCP-интеграция (Storm) | H6: Нет удобного облачного хранения и совместной работы над Mermaid-диаграммами | I6: Облачное хранение, совместное редактирование и управление доступом к Mermaid-диаграммам | J6: Команды разработки и документации | K6: облачный сервис над открытым стандартом: доход от тарифов за пользователя | L6: https://www.mermaidchart.com/ | M6: SaaS-надстройка над открытым Mermaid; доход от тарифов Free, Plus, Premium за пользователя
A7: C04 | B7: =IF($A7="","",IFERROR(VLOOKUP($A7,'02_Конкуренты'!$A$4:$B$11,2,FALSE),"не найдено")) -> Storm (StormBPMN) | C7: Моделирование и управление процессами | D7: Платформа из семи модулей: редактор, реестр, архитектура, оргструктура, опросы, ИИ, симуляция | E7: Экспорт, документация, интеграции | F7: Шаблоны, совместная работа, ИИ, API по тарифам | G7: MCP-интеграция (Storm) | H7: Нет единой русскоязычной платформы для моделирования процессов, реестров и оргструктуры | I7: Семь модулей в одной платформе: от BPMN-редактора до симуляции и ИИ-советника | J7: Процессные аналитики, русскоязычный рынок | K7: платформа процессного управления для русскоязычного рынка: доход от тарифов в рублях и on-prem | L7: https://stormbpmn.com/ | M7: Комплексная BPM-платформа для русскоязычного рынка; доход от SaaS-подписки и on-prem Enterprise
A8: C05 | B8: =IF($A8="","",IFERROR(VLOOKUP($A8,'02_Конкуренты'!$A$4:$B$11,2,FALSE),"не найдено")) -> draw.io (diagrams.net) | C8: Бесплатный редактор диаграмм | D8: Бесплатный онлайн-редактор блок-схем, UML, ER и других диаграмм | E8: Экспорт, документация, интеграции | F8: Шаблоны, совместная работа, ИИ, API по тарифам | G8: Признаки развития на просмотренных страницах не найдены | H8: Профессиональные инструменты для диаграмм дорогие или требуют установки | I8: Профессиональные диаграммы в браузере – бесплатно, без регистрации, с экспортом | J8: Студенты, разработчики, команды | K8: бесплатный массовый инструмент: привлекает аудиторию, монетизация на сайте не показана | L8: https://app.diagrams.net/ | M8: Бесплатный массовый инструмент; монетизация на сайте не показана; вероятно – корпоративные интеграции
A9: C06 | B9: =IF($A9="","",IFERROR(VLOOKUP($A9,'02_Конкуренты'!$A$4:$B$11,2,FALSE),"не найдено")) -> Lucidchart | C9: Облачный редактор диаграмм с ИИ | D9: Облачный редактор диаграмм с тарифами Free, Individual, Team, Enterprise | E9: Экспорт, документация, интеграции | F9: Шаблоны, совместная работа, ИИ, API по тарифам | G9: MCP-интеграция (Storm) | H9: Корпоративным командам нужен масштабируемый инструмент с управлением доступом и интеграциями | I9: Корпоративная визуализация с ИИ, шаблонами, SSO и интеграциями для Enterprise | J9: Команды, бизнес-пользователи | K9: облачный сервис с лестницей тарифов Free, Individual, Team, Enterprise | L9: https://www.lucidchart.com/ | M9: Enterprise SaaS с лестницей тарифов Free–Individual–Team–Enterprise; доход от платных мест и контрактов
A10: C07 | B10: =IF($A10="","",IFERROR(VLOOKUP($A10,'02_Конкуренты'!$A$4:$B$11,2,FALSE),"не найдено")) -> Eraser | C10: ИИ-генерация технических диаграмм | D10: Создание технических диаграмм с помощью ИИ | E10: Экспорт, документация, интеграции | F10: Шаблоны, совместная работа, ИИ, API по тарифам | G10: MCP-интеграция (Storm) | H10: Создание технических диаграмм вручную занимает много времени у инженерных команд | I10: Технические диаграммы генерируются ИИ из описания или кода за секунды | J10: Инженерные команды, разработчики | K10: подписка вокруг ИИ-генерации и diagram-as-code для технических команд | L10: https://www.eraser.io/ | M10: ИИ-первый подход к diagram-as-code; доход от подписок Free, Pro, Enterprise
A11: C08 | B11: =IF($A11="","",IFERROR(VLOOKUP($A11,'02_Конкуренты'!$A$4:$B$11,2,FALSE),"не найдено")) -> Whimsical | C11: Доска, диаграммы и документы | D11: Редактор диаграмм, схем интерфейсов и документов; тарифы Free, Pro, Business (страница тарифов, 01.10.2026) | E11: Экспорт, документация, интеграции | F11: Шаблоны, совместная работа, ИИ, API по тарифам | G11: Признаки развития на просмотренных страницах не найдены | H11: Продуктовым командам нужно единое пространство для вайрфреймов, диаграмм и документов | I11: Единое рабочее пространство: флоучарты, вайрфреймы, майндкарты и документы в одном месте | J11: Команды продуктов | K11: подписка для продуктовых команд: доход от платных мест редакторов | L11: https://whimsical.com/ | M11: Многофункциональный редактор для продуктовых команд; доход от платных мест редакторов (Free, Pro, Business)

Sheet 06_Монетизация
A1: Монетизация и потоки доходов
A2: Фиксируются признаки получения выручки: тарифы, пробный доступ, условия оплаты, ограничения и коммерческая логика
A3: ID конкурента | B3: Название | C3: Модель монетизации | D3: Страница с тарифами/ценой | E3: Наличие бесплатного уровня | F3: Пробный доступ | G3: Тарифные уровни | H3: Единица оплаты | I3: Ограничения тарифа | J3: Платежная периодичность | K3: Признаки корпоративных продаж | L3: Прозрачность цены 1-5 | M3: Гибкость модели 1-5 | N3: Вывод о потоках доходов
A4: C01 | B4: =IF($A4="","",IFERROR(VLOOKUP($A4,'02_Конкуренты'!$A$4:$B$11,2,FALSE),"не найдено")) -> PlantUML | C4: лицензия | D4: https://plantuml.com/ | E4: да | F4: не найден на просмотренных страницах | G4: Бесплатно | H4: не применимо | I4: Нет единицы оплаты | J4: нет платежей | K4: не найдены | L4: 4 | M4: 2 | N4: Нет прямых доходов на сайте: ценность создаёт аудиторию и сообщество
A5: C02 | B5: =IF($A5="","",IFERROR(VLOOKUP($A5,'02_Конкуренты'!$A$4:$B$11,2,FALSE),"не найдено")) -> Mermaid (библиотека) | C5: лицензия | D5: https://mermaid.js.org/ | E5: да | F5: не найден на просмотренных страницах | G5: Бесплатно | H5: не применимо | I5: Нет единицы оплаты | J5: нет платежей | K5: не найдены | L5: 5 | M5: 2 | N5: Нет прямых доходов на сайте: ценность создаёт аудиторию и сообщество
A6: C03 | B6: =IF($A6="","",IFERROR(VLOOKUP($A6,'02_Конкуренты'!$A$4:$B$11,2,FALSE),"не найдено")) -> Mermaid Chart | C6: условно-бесплатная модель | D6: https://mermaid.ai/pricing/ | E6: да | F6: не найден на просмотренных страницах | G6: Basic Free, Plus 10 у.е., Premium 20 у.е., Enterprise | H6: за пользователя в месяц | I6: Basic: до 6 диаграмм, 15 ИИ-кредитов | J6: при оплате за год | K6: Enterprise: SSO, менеджер по успеху клиента, договор | L6: 5 | M6: 4 | N6: Подписка за пользователя; зрители без оплаты; ИИ-кредиты по тарифам
A7: C04 | B7: =IF($A7="","",IFERROR(VLOOKUP($A7,'02_Конкуренты'!$A$4:$B$11,2,FALSE),"не найдено")) -> Storm (StormBPMN) | C7: условно-бесплатная модель | D7: https://stormbpmn.com/pricing | E7: да | F7: кнопка «Попробовать всё» в тарифе Бизнес | G7: Персональный 0, Команда 1 200 руб., Бизнес 4 720 руб., Enterprise от 990 тыс. руб. в год | H7: за пользователя в месяц | I7: Персональный: до 50 моделей, 5 раз делиться процессами | J7: месяц или год (скидка 20 %) | K7: Enterprise on-prem: SSO, API, аудит, ИБ | L7: 5 | M7: 5 | N7: Бесплатный старт и рост до on-prem: потоки от подписок и корпоративных договоров
A8: C05 | B8: =IF($A8="","",IFERROR(VLOOKUP($A8,'02_Конкуренты'!$A$4:$B$11,2,FALSE),"не найдено")) -> draw.io (diagrams.net) | C8: лицензия | D8: https://app.diagrams.net/ | E8: да | F8: не найден на просмотренных страницах | G8: Бесплатно | H8: не применимо | I8: Нет единицы оплаты | J8: нет платежей | K8: не найдены | L8: 5 | M8: 2 | N8: Нет прямых доходов на сайте: ценность создаёт аудиторию и сообщество
A9: C06 | B9: =IF($A9="","",IFERROR(VLOOKUP($A9,'02_Конкуренты'!$A$4:$B$11,2,FALSE),"не найдено")) -> Lucidchart | C9: условно-бесплатная модель | D9: https://lucid.app/pricing/lucidchart | E9: да | F9: 7 дней | G9: Free, Individual 9 у.е., Team 10 у.е., Enterprise | H9: за пользователя в месяц | I9: Free: 3 документа, 75 фигур на документ | J9: при оплате за год | K9: Enterprise: SAML, Enterprise Shield, Salesforce | L9: 4 | M9: 4 | N9: Подписка за место с пробным периодом и Enterprise
A10: C07 | B10: =IF($A10="","",IFERROR(VLOOKUP($A10,'02_Конкуренты'!$A$4:$B$11,2,FALSE),"не найдено")) -> Eraser | C10: условно-бесплатная модель | D10: https://www.eraser.io/pricing | E10: да | F10: не найден на просмотренных страницах | G10: Free 0, Starter 15 у.е., Business 45 у.е., Enterprise | H10: за участника в месяц | I10: Free: 3 файла, 3 ИИ-диаграммы | J10: год (15 и 45 у.е.) или месяц (20 и 60 у.е.) | K10: Enterprise: гибкое развёртывание, менеджер по успеху клиента | L10: 5 | M10: 4 | N10: Подписка за участника с лимитами ИИ
A11: C08 | B11: =IF($A11="","",IFERROR(VLOOKUP($A11,'02_Конкуренты'!$A$4:$B$11,2,FALSE),"не найдено")) -> Whimsical | C11: условно-бесплатная модель | D11: https://whimsical.com/pricing | E11: да | F11: не найден на просмотренных страницах | G11: Free 0, Pro 10 у.е., Business 20 у.е. | H11: за редактора в месяц | I11: Free: 50 объектов доски и 50 блоков документа в месяц | J11: месячная цена за редактора | K11: Business с кнопкой «Contact sales», SAML SSO | L11: 5 | M11: 4 | N11: Подписка за редактора, зрители бесплатно

Sheet 07_Каналы
A1: Каналы, воронка и механика продаж
A2: Анализируется, как сайт превращает посетителя в пользователя, лид или покупателя
A3: ID конкурента | B3: Название | C3: Главные каналы привлечения | D3: Контентная стратегия | E3: Поисковая видимость по сайту | F3: Призыв к действию | G3: Первичная конверсия | H3: Тип воронки | I3: Регистрация/заявка | J3: Демонстрация/пробный доступ | K3: Доверительные элементы | L3: Сложность пути клиента 1-5 | M3: Сила воронки 1-5 | N3: Вывод о рынке и каналах
A4: C01 | B4: =IF($A4="","",IFERROR(VLOOKUP($A4,'02_Конкуренты'!$A$4:$B$11,2,FALSE),"не найдено")) -> PlantUML | C4: прямые заходы 38,11 %; органический поиск 47,25 %; рефералы 5,91 %; соцсети органика 3,62 %; ИИ-ассистенты 4,42 %; e-mail 0,60 % (Similarweb Pro, Jun-Aug 2026, весь мир, снимок 30.09.2026) | D4: Документация, примеры, блог на сайте | E4: Органический поиск 47,25 % трафика (Similarweb Pro) | F4: Онлайн-сервер без призыва к регистрации; ссылки на загрузку | G4: не требуется | H4: контентная воронка | I4: не требуется | J4: онлайн-сервер без регистрации | K4: оценки расширений: VS Marketplace jebbs.plantuml 4,72 (105), JetBrains plantuml4idea 4,63 (102); G2 и Trustpilot: карточка не найдена | L4: 1 | M4: 2 | N4: Путь клиента: вход без регистрации; тип воронки - контентная воронка
A5: C02 | B5: =IF($A5="","",IFERROR(VLOOKUP($A5,'02_Конкуренты'!$A$4:$B$11,2,FALSE),"не найдено")) -> Mermaid (библиотека) | C5: прямые заходы 22,18 %; органический поиск 58,56 %; рефералы 16,50 %; соцсети органика 1,25 %; ИИ-ассистенты 1,23 %; e-mail 0,22 %; платный поиск 0,01 % (Similarweb Pro, Jun-Aug 2026, весь мир, снимок 30.09.2026) | D5: Документация, примеры, блог на сайте | E5: Органический поиск 58,56 % трафика (Similarweb Pro) | F5: «Get started», документация, живой редактор | G5: не требуется для библиотеки | H5: контентная воронка | I5: не требуется для библиотеки | J5: Mermaid Live Editor | K5: оценки расширений: VS Marketplace (bierner.markdown-mermaid 60, vstirbu 27, tomoyukim 17) и JetBrains Mermaid 2,96 (65) | L5: 2 | M5: 3 | N5: Путь клиента: регистрация или заявка; тип воронки - контентная воронка
A6: C03 | B6: =IF($A6="","",IFERROR(VLOOKUP($A6,'02_Конкуренты'!$A$4:$B$11,2,FALSE),"не найдено")) -> Mermaid Chart | C6: прямые заходы 39,97 %; органический поиск 32,54 %; рефералы 10,32 %; соцсети органика 6,05 %; ИИ-ассистенты 1,62 %; e-mail 2,52 %; платный поиск 1,62 % (Similarweb Pro, Jun-Aug 2026, весь мир, снимок 30.09.2026) | D6: Документация, примеры, блог на сайте | E6: Органический поиск 32,54 % трафика (Similarweb Pro) | F6: «Start free», «Contact sales» | G6: регистрация для Free | H6: регистрация | I6: регистрация для Free | J6: Free (до 6 диаграмм) | K6: G2 (карточка Mermaid) 4,8 (16); Trustpilot 3,5 (3); Product Hunt 4,8 (26) | L6: 2 | M6: 4 | N6: Путь клиента: регистрация или заявка; тип воронки - регистрация
A7: C04 | B7: =IF($A7="","",IFERROR(VLOOKUP($A7,'02_Конкуренты'!$A$4:$B$11,2,FALSE),"не найдено")) -> Storm (StormBPMN) | C7: прямые заходы 57,33 %; органический поиск 20,91 %; рефералы 10,72 %; соцсети органика 2,59 %; ИИ-ассистенты 1,74 %; e-mail 3,78 %; платный поиск 1,32 % (Similarweb Pro, Jun-Aug 2026, весь мир, снимок 30.09.2026) | D7: Документация, примеры, блог на сайте | E7: Органический поиск 20,91 % трафика (Similarweb Pro) | F7: «Начать бесплатно», «Рассчитать для команды», «Обсудить on-prem» | G7: регистрация для Персонального | H7: корпоративные продажи | I7: регистрация для Персонального | J7: бесплатный тариф, «Попробовать всё» (Бизнес) | K7: «Нам доверяют больше 1 000 клиентов» | L7: 2 | M7: 4 | N7: Путь клиента: регистрация или заявка; тип воронки - корпоративные продажи
A8: C05 | B8: =IF($A8="","",IFERROR(VLOOKUP($A8,'02_Конкуренты'!$A$4:$B$11,2,FALSE),"не найдено")) -> draw.io (diagrams.net) | C8: прямые заходы 68,39 %; органический поиск 13,96 %; рефералы 9,72 %; соцсети органика 2,07 %; ИИ-ассистенты 2,68 %; e-mail 1,19 %; платный поиск 0,02 % (Similarweb Pro, Jun-Aug 2026, весь мир, снимок 30.09.2026) | D8: Документация, примеры, блог на сайте | E8: Органический поиск 13,96 % трафика (Similarweb Pro) | F8: Открыть приложение; «Embed»; GitHub | G8: не требуется | H8: самостоятельная покупка | I8: не требуется | J8: приложение без регистрации | K8: Capterra 4,6 (773); Trustpilot draw.io 3,4 (11) и diagrams.net 3,8 (2); Atlassian Marketplace draw.io Diagrams 4,8 (1 205) | L8: 1 | M8: 4 | N8: Путь клиента: вход без регистрации; тип воронки - самостоятельная покупка
A9: C06 | B9: =IF($A9="","",IFERROR(VLOOKUP($A9,'02_Конкуренты'!$A$4:$B$11,2,FALSE),"не найдено")) -> Lucidchart | C9: прямые заходы 11,33 %; органический поиск 55,95 %; рефералы 2,71 %; соцсети органика 1,34 %; ИИ-ассистенты 2,10 %; e-mail 0,20 %; платный поиск 22,55 % (Similarweb Pro, Jun-Aug 2026, весь мир, снимок 30.09.2026) | D9: Документация, примеры, блог на сайте | E9: Органический поиск 55,95 % трафика (Similarweb Pro) | F9: «Sign up free», вход через Google и Microsoft | G9: регистрация | H9: пробный доступ | I9: регистрация | J9: Free; пробный период 7 дней платных тарифов | K9: G2 4,5 (8 988); Capterra/GetApp/Software Advice 4,5 (2 264); Trustpilot lucidchart.com 1,5 (116) | L9: 2 | M9: 5 | N9: Путь клиента: регистрация или заявка; тип воронки - пробный доступ
A10: C07 | B10: =IF($A10="","",IFERROR(VLOOKUP($A10,'02_Конкуренты'!$A$4:$B$11,2,FALSE),"не найдено")) -> Eraser | C10: Данные Similarweb Pro по домену не получены | D10: Документация, примеры, блог на сайте | E10: Данные Similarweb по домену не получены | F10: «Try Eraser», «Get started for free» | G10: регистрация | H10: регистрация | I10: регистрация | J10: Free (3 файла) | K10: Product Hunt 4,9 (10); расширение VS Code 4,8 (5) | L10: 2 | M10: 4 | N10: Путь клиента: регистрация или заявка; тип воронки - регистрация
A11: C08 | B11: =IF($A11="","",IFERROR(VLOOKUP($A11,'02_Конкуренты'!$A$4:$B$11,2,FALSE),"не найдено")) -> Whimsical | C11: Данные Similarweb Pro по домену не получены | D11: Страницы шаблонов и ИИ | E11: Данные Similarweb по домену не получены | F11: «Get started», «Contact sales» (Business) | G11: регистрация | H11: регистрация | I11: регистрация | J11: Free (50 объектов) | K11: Capterra 4,7 (59) | L11: 2 | M11: 4 | N11: Путь клиента: регистрация или заявка; тип воронки - регистрация

Sheet 08_Операц_модель
A1: Операционная основа бизнес-модели
A2: Лист фиксирует, за счет каких ресурсов, процессов, партнерств и данных конкурент поддерживает цифровой товар
A3: ID конкурента | B3: Название | C3: Ключевые ресурсы | D3: Ключевые процессы | E3: Технологические признаки на сайте | F3: Использование данных | G3: Интеграции | H3: Партнеры | I3: Поддержка и сервис | J3: Признаки структуры затрат | K3: Масштабируемость 1-5 | L3: Трудность копирования 1-5 | M3: Операционный риск | N3: Вывод об устойчивости модели
A4: C01 | B4: =IF($A4="","",IFERROR(VLOOKUP($A4,'02_Конкуренты'!$A$4:$B$11,2,FALSE),"не найдено")) -> PlantUML | C4: Сообщество разработчиков, домен с 2010 г. | D4: Выпуск релизов, поддержка форумов | E4: Серверный рендеринг на Java; языковой справочник | F4: Диаграммы обрабатываются на сервере проекта | G4: Интеграции в вики, редакторы, IDE и языки программирования (страница running) | H4: Интеграции в вики, редакторы, IDE и языки программирования (страница running) | I4: FAQ, форум | J4: Признаки: разработка сообщества и серверы; ИИ-расходов на сайте нет | K4: 3 | L4: 2 | M4: Низкая монетизация | N4: Устойчив за счёт сообщества, не за счёт доходов
A5: C02 | B5: =IF($A5="","",IFERROR(VLOOKUP($A5,'02_Конкуренты'!$A$4:$B$11,2,FALSE),"не найдено")) -> Mermaid (библиотека) | C5: Сообщество (90 489 звёзд), команда проекта | D5: Релизы библиотеки, развитие экосистемы | E5: JavaScript-библиотека | F5: Рендеринг в браузере | G5: Интеграции сообщества: редакторы, вики, платформы (страница integrations-community) | H5: Интеграции сообщества: редакторы, вики, платформы (страница integrations-community) | I5: Документация, сообщество | J5: Признаки: разработка сообщества; платные планы вынесены в Mermaid Chart | K5: 4 | L5: 3 | M5: Зависимость от Mermaid Chart в финансировании | N5: Устойчив за счёт экосистемы
A6: C03 | B6: =IF($A6="","",IFERROR(VLOOKUP($A6,'02_Конкуренты'!$A$4:$B$11,2,FALSE),"не найдено")) -> Mermaid Chart | C6: Команда Mermaid, облако, ИИ | D6: Развитие редактора и ИИ-функций | E6: Облачный редактор, ИИ, API | F6: Данные пользователей в облаке | G6: Плагины и интеграции (меню Product), экосистема Mermaid.js | H6: Плагины и интеграции (меню Product), экосистема Mermaid.js | I6: Документация, контакты продаж | J6: Признак: лимиты ИИ-кредитов указывают на стоимость ИИ-вызовов | K6: 4 | L6: 3 | M6: Расходы на ИИ | N6: Устойчив при росте платных мест
A7: C04 | B7: =IF($A7="","",IFERROR(VLOOKUP($A7,'02_Конкуренты'!$A$4:$B$11,2,FALSE),"не найдено")) -> Storm (StormBPMN) | C7: Платформа из девяти модулей, база клиентов (более 1 000) | D7: Продажи, внедрение, развитие модулей | E7: BPMN-редактор, ИИ, симуляция DES, MCP | F7: Модели процессов, реестр, оргструктура, опросы | G7: MCP-интеграции, API в Enterprise | H7: MCP-интеграции, API в Enterprise | I7: База знаний; Enterprise: аудит и ИБ | J7: Признаки: безлимитный ИИ в облачных тарифах, on-prem для крупных клиентов | K7: 3 | L7: 4 | M7: Зависимость от русскоязычного рынка | N7: Модель устойчива у корпоративных клиентов
A8: C05 | B8: =IF($A8="","",IFERROR(VLOOKUP($A8,'02_Конкуренты'!$A$4:$B$11,2,FALSE),"не найдено")) -> draw.io (diagrams.net) | C8: Репозитории (63 351 звезда desktop), независимая частная компания | D8: Развитие приложения и интеграций | E8: Приложение на JavaScript, desktop, плагины | F8: Данные хранятся у пользователя | G8: Google Drive, Microsoft SharePoint и OneDrive, Atlassian Confluence и Jira, GitHub, VS Code, Notion | H8: Google Drive, Microsoft SharePoint и OneDrive, Atlassian Confluence и Jira, GitHub, VS Code, Notion | I8: Документация, GitHub | J8: Признак: «Not VC-funded», нет enterprise-тарифа | K8: 5 | L8: 3 | M8: Неясная монетизация на сайте | N8: Очень устойчив за счёт аудитории и независимости
A9: C06 | B9: =IF($A9="","",IFERROR(VLOOKUP($A9,'02_Конкуренты'!$A$4:$B$11,2,FALSE),"не найдено")) -> Lucidchart | C9: Команда и инфраструктура Lucid, платформа, бренд | D9: Продажи Enterprise, развитие ИИ и платформы | E9: Облако, ИИ, платформа разработчика, интеграции | F9: Связывание данных, импорт данных | G9: Microsoft 365, Confluence, Jira, LeanIX, Ardoq, Salesforce | H9: Microsoft 365, Confluence, Jira, LeanIX, Ardoq, Salesforce | I9: Учебный центр, поддержка, Enterprise Shield | J9: Признаки: ИИ, поддержка, учебный центр, Enterprise Shield | K9: 5 | L9: 5 | M9: Высокая зависимость от платных мест | N9: Устойчив: широкий продукт и Enterprise
A10: C07 | B10: =IF($A10="","",IFERROR(VLOOKUP($A10,'02_Конкуренты'!$A$4:$B$11,2,FALSE),"не найдено")) -> Eraser | C10: Команда продукта, ИИ-инфраструктура | D10: Развитие ИИ и интеграций | E10: ИИ-генерация, diagram-as-code, API | F10: Данные в облаке, лимиты ИИ | G10: GitHub, Notion, Confluence, VS Code | H10: GitHub, Notion, Confluence, VS Code | I10: Документация docs.eraser.io | J10: Признак: лимиты ИИ-диаграмм по тарифам указывают на стоимость ИИ | K10: 4 | L10: 3 | M10: Расходы на ИИ при росте | N10: Умеренно устойчив; зависит от ИИ-расходов
A11: C08 | B11: =IF($A11="","",IFERROR(VLOOKUP($A11,'02_Конкуренты'!$A$4:$B$11,2,FALSE),"не найдено")) -> Whimsical | C11: Команда продукта, бренд | D11: Развитие доски, диаграмм, документов | E11: Облако, desktop, ИИ | F11: Данные в облаке, история версий | G11: Интеграции указаны на сайте (число не проверялось) | H11: Интеграции указаны на сайте (число не проверялось) | I11: Раздел support, страница Security | J11: Признаки: хранилище и история версий по тарифам, ИИ | K11: 4 | L11: 2 | M11: Сильная конкуренция универсальных досок | N11: Устойчив у продуктовых команд

Sheet 09_Матрица
A1: Сравнительная матрица бизнес-моделей
A2: Вес | C2: 0.08 | D2: 0.13 | E2: 0.1 | F2: 0.09 | G2: 0.06 | H2: 0.12 | I2: 0.08 | J2: 0.06 | K2: 0.1 | L2: 0.09 | M2: 0.09
A3: ID конкурента | B3: Название | C3: Сегменты | D3: Ценность | E3: Товар | F3: Каналы | G3: Отношения | H3: Доходы | I3: Ресурсы | J3: Партнеры | K3: Данные/сеть | L3: Масштаб | M3: Защищенность | N3: Индекс силы | O3: Доказательность | P3: Полнота | Q3: Итог с учетом надежности
A4: C01 | B4: =IF($A4="","",IFERROR(VLOOKUP($A4,'02_Конкуренты'!$A$4:$B$11,2,FALSE),"не найдено")) -> PlantUML | C4: 3 | D4: 4 | E4: 4 | F4: 3 | G4: 2 | H4: 2 | I4: 3 | J4: 4 | K4: 3 | L4: 3 | M4: 4 | N4: =IF($A4="","",SUMPRODUCT($C4:$M4,$C$2:$M$2)/SUM($C$2:$M$2)) -> 3.2 | O4: =IF($A4="","",IFERROR(VLOOKUP($A4,'04_Бизнес_модель'!$A$4:$P$203,16,FALSE),0)) -> 3.7142857 | P4: =IF($A4="","",IFERROR(VLOOKUP($A4,'04_Бизнес_модель'!$A$4:$O$203,15,FALSE),0)) -> 1 | Q4: =IF($A4="","",$N4*0.6+$O4*0.25+$P4*5*0.15) -> 3.5985714
A5: C02 | B5: =IF($A5="","",IFERROR(VLOOKUP($A5,'02_Конкуренты'!$A$4:$B$11,2,FALSE),"не найдено")) -> Mermaid (библиотека) | C5: 3 | D5: 4 | E5: 4 | F5: 3 | G5: 3 | H5: 2 | I5: 4 | J5: 4 | K5: 4 | L5: 4 | M5: 4 | N5: =IF($A5="","",SUMPRODUCT($C5:$M5,$C$2:$M$2)/SUM($C$2:$M$2)) -> 3.53 | O5: =IF($A5="","",IFERROR(VLOOKUP($A5,'04_Бизнес_модель'!$A$4:$P$203,16,FALSE),0)) -> 3.7857143 | P5: =IF($A5="","",IFERROR(VLOOKUP($A5,'04_Бизнес_модель'!$A$4:$O$203,15,FALSE),0)) -> 1 | Q5: =IF($A5="","",$N5*0.6+$O5*0.25+$P5*5*0.15) -> 3.8144286
A6: C03 | B6: =IF($A6="","",IFERROR(VLOOKUP($A6,'02_Конкуренты'!$A$4:$B$11,2,FALSE),"не найдено")) -> Mermaid Chart | C6: 4 | D6: 4 | E6: 4 | F6: 4 | G6: 4 | H6: 4 | I6: 3 | J6: 4 | K6: 3 | L6: 4 | M6: 3 | N6: =IF($A6="","",SUMPRODUCT($C6:$M6,$C$2:$M$2)/SUM($C$2:$M$2)) -> 3.73 | O6: =IF($A6="","",IFERROR(VLOOKUP($A6,'04_Бизнес_модель'!$A$4:$P$203,16,FALSE),0)) -> 3.952381 | P6: =IF($A6="","",IFERROR(VLOOKUP($A6,'04_Бизнес_модель'!$A$4:$O$203,15,FALSE),0)) -> 1 | Q6: =IF($A6="","",$N6*0.6+$O6*0.25+$P6*5*0.15) -> 3.9760952
A7: C04 | B7: =IF($A7="","",IFERROR(VLOOKUP($A7,'02_Конкуренты'!$A$4:$B$11,2,FALSE),"не найдено")) -> Storm (StormBPMN) | C7: 4 | D7: 4 | E7: 5 | F7: 4 | G7: 4 | H7: 5 | I7: 3 | J7: 3 | K7: 3 | L7: 4 | M7: 3 | N7: =IF($A7="","",SUMPRODUCT($C7:$M7,$C$2:$M$2)/SUM($C$2:$M$2)) -> 3.89 | O7: =IF($A7="","",IFERROR(VLOOKUP($A7,'04_Бизнес_модель'!$A$4:$P$203,16,FALSE),0)) -> 3.8571429 | P7: =IF($A7="","",IFERROR(VLOOKUP($A7,'04_Бизнес_модель'!$A$4:$O$203,15,FALSE),0)) -> 1 | Q7: =IF($A7="","",$N7*0.6+$O7*0.25+$P7*5*0.15) -> 4.0482857
A8: C05 | B8: =IF($A8="","",IFERROR(VLOOKUP($A8,'02_Конкуренты'!$A$4:$B$11,2,FALSE),"не найдено")) -> draw.io (diagrams.net) | C8: 4 | D8: 5 | E8: 4 | F8: 3 | G8: 3 | H8: 2 | I8: 4 | J8: 5 | K8: 4 | L8: 5 | M8: 4 | N8: =IF($A8="","",SUMPRODUCT($C8:$M8,$C$2:$M$2)/SUM($C$2:$M$2)) -> 3.89 | O8: =IF($A8="","",IFERROR(VLOOKUP($A8,'04_Бизнес_модель'!$A$4:$P$203,16,FALSE),0)) -> 3.625 | P8: =IF($A8="","",IFERROR(VLOOKUP($A8,'04_Бизнес_модель'!$A$4:$O$203,15,FALSE),0)) -> 1 | Q8: =IF($A8="","",$N8*0.6+$O8*0.25+$P8*5*0.15) -> 3.99025
A9: C06 | B9: =IF($A9="","",IFERROR(VLOOKUP($A9,'02_Конкуренты'!$A$4:$B$11,2,FALSE),"не найдено")) -> Lucidchart | C9: 4 | D9: 4 | E9: 5 | F9: 5 | G9: 4 | H9: 5 | I9: 5 | J9: 5 | K9: 4 | L9: 5 | M9: 5 | N9: =IF($A9="","",SUMPRODUCT($C9:$M9,$C$2:$M$2)/SUM($C$2:$M$2)) -> 4.63 | O9: =IF($A9="","",IFERROR(VLOOKUP($A9,'04_Бизнес_модель'!$A$4:$P$203,16,FALSE),0)) -> 3.9583333 | P9: =IF($A9="","",IFERROR(VLOOKUP($A9,'04_Бизнес_модель'!$A$4:$O$203,15,FALSE),0)) -> 1 | Q9: =IF($A9="","",$N9*0.6+$O9*0.25+$P9*5*0.15) -> 4.5175833
A10: C07 | B10: =IF($A10="","",IFERROR(VLOOKUP($A10,'02_Конкуренты'!$A$4:$B$11,2,FALSE),"не найдено")) -> Eraser | C10: 4 | D10: 4 | E10: 4 | F10: 4 | G10: 4 | H10: 5 | I10: 3 | J10: 4 | K10: 3 | L10: 3 | M10: 3 | N10: =IF($A10="","",SUMPRODUCT($C10:$M10,$C$2:$M$2)/SUM($C$2:$M$2)) -> 3.76 | O10: =IF($A10="","",IFERROR(VLOOKUP($A10,'04_Бизнес_модель'!$A$4:$P$203,16,FALSE),0)) -> 4 | P10: =IF($A10="","",IFERROR(VLOOKUP($A10,'04_Бизнес_модель'!$A$4:$O$203,15,FALSE),0)) -> 1 | Q10: =IF($A10="","",$N10*0.6+$O10*0.25+$P10*5*0.15) -> 4.006
A11: C08 | B11: =IF($A11="","",IFERROR(VLOOKUP($A11,'02_Конкуренты'!$A$4:$B$11,2,FALSE),"не найдено")) -> Whimsical | C11: 3 | D11: 4 | E11: 4 | F11: 4 | G11: 4 | H11: 5 | I11: 3 | J11: 3 | K11: 3 | L11: 3 | M11: 3 | N11: =IF($A11="","",SUMPRODUCT($C11:$M11,$C$2:$M$2)/SUM($C$2:$M$2)) -> 3.62 | O11: =IF($A11="","",IFERROR(VLOOKUP($A11,'04_Бизнес_модель'!$A$4:$P$203,16,FALSE),0)) -> 4 | P11: =IF($A11="","",IFERROR(VLOOKUP($A11,'04_Бизнес_модель'!$A$4:$O$203,15,FALSE),0)) -> 1 | Q11: =IF($A11="","",$N11*0.6+$O11*0.25+$P11*5*0.15) -> 3.922

Sheet 10_Стандарт
A1: Определение рыночного стандарта бизнес-модели
A2: Повторяющиеся практики отделяются от настоящих конкурентных преимуществ. Порог стандарта можно корректировать в методике, базово используется 70%
A3: Практика/элемент | B3: Блок бизнес-модели | C3: Описание признака | D3: Кол-во конкурентов с признаком | E3: Доля конкурентов | F3: Статус | G3: Управленческий вывод | H3: Подтверждающие URL/факты
A4: Бесплатный доступ или Free-тариф | B4: потоки доходов | C4: Начать работу без оплаты | D4: 8 | E4: =IF($D4="","",IFERROR($D4/'12_Сводка'!$B$5,0)) -> 1 | F4: =IF($A4="","",IF($E4>=0.7,"рыночный стандарт",IF($E4>=0.4,"формирующийся стандарт",IF($E4>=0.2,"зона дифференциации","слабый сигнал")))) -> рыночный стандарт | G4: =IF($A4="","",IF($F4="рыночный стандарт","необходимо включить в минимально приемлемое предложение",IF($F4="формирующийся стандарт","проверить значимость для клиента и вероятность закрепления",IF($F4="зона дифференциации","может использоваться как поле позиционирования","не использовать без дополнительной проверки")))) -> необходимо включить в минимально приемлемое предложение | H4: Открытый код или тариф Free на страницах 8 из 8 конкурентов
A5: Платная подписка по тарифным уровням | B5: потоки доходов | C5: Получить расширенные возможности за оплату | D5: 5 | E5: =IF($D5="","",IFERROR($D5/'12_Сводка'!$B$5,0)) -> 0.625 | F5: =IF($A5="","",IF($E5>=0.7,"рыночный стандарт",IF($E5>=0.4,"формирующийся стандарт",IF($E5>=0.2,"зона дифференциации","слабый сигнал")))) -> формирующийся стандарт | G5: =IF($A5="","",IF($F5="рыночный стандарт","необходимо включить в минимально приемлемое предложение",IF($F5="формирующийся стандарт","проверить значимость для клиента и вероятность закрепления",IF($F5="зона дифференциации","может использоваться как поле позиционирования","не использовать без дополнительной проверки")))) -> проверить значимость для клиента и вероятность закрепления | H5: Страницы тарифов Mermaid Chart, Storm, Lucidchart, Eraser, Whimsical
A6: Открытая страница тарифов | B6: потоки доходов | C6: Понять цену и состав тарифа до регистрации | D6: 5 | E6: =IF($D6="","",IFERROR($D6/'12_Сводка'!$B$5,0)) -> 0.625 | F6: =IF($A6="","",IF($E6>=0.7,"рыночный стандарт",IF($E6>=0.4,"формирующийся стандарт",IF($E6>=0.2,"зона дифференциации","слабый сигнал")))) -> формирующийся стандарт | G6: =IF($A6="","",IF($F6="рыночный стандарт","необходимо включить в минимально приемлемое предложение",IF($F6="формирующийся стандарт","проверить значимость для клиента и вероятность закрепления",IF($F6="зона дифференциации","может использоваться как поле позиционирования","не использовать без дополнительной проверки")))) -> проверить значимость для клиента и вероятность закрепления | H6: Страницы тарифов (01.10.2026)
A7: Корпоративный тариф (Enterprise или on-prem) | B7: потоки доходов | C7: Подключить организацию целиком | D7: 4 | E7: =IF($D7="","",IFERROR($D7/'12_Сводка'!$B$5,0)) -> 0.5 | F7: =IF($A7="","",IF($E7>=0.7,"рыночный стандарт",IF($E7>=0.4,"формирующийся стандарт",IF($E7>=0.2,"зона дифференциации","слабый сигнал")))) -> формирующийся стандарт | G7: =IF($A7="","",IF($F7="рыночный стандарт","необходимо включить в минимально приемлемое предложение",IF($F7="формирующийся стандарт","проверить значимость для клиента и вероятность закрепления",IF($F7="зона дифференциации","может использоваться как поле позиционирования","не использовать без дополнительной проверки")))) -> проверить значимость для клиента и вероятность закрепления | H7: Enterprise по запросу на страницах тарифов; Storm: on-prem от 990 тыс. руб. в год
A8: Скидка или цена при годовой оплате | B8: потоки доходов | C8: Снизить стоимость при долгом использовании | D8: 4 | E8: =IF($D8="","",IFERROR($D8/'12_Сводка'!$B$5,0)) -> 0.5 | F8: =IF($A8="","",IF($E8>=0.7,"рыночный стандарт",IF($E8>=0.4,"формирующийся стандарт",IF($E8>=0.2,"зона дифференциации","слабый сигнал")))) -> формирующийся стандарт | G8: =IF($A8="","",IF($F8="рыночный стандарт","необходимо включить в минимально приемлемое предложение",IF($F8="формирующийся стандарт","проверить значимость для клиента и вероятность закрепления",IF($F8="зона дифференциации","может использоваться как поле позиционирования","не использовать без дополнительной проверки")))) -> проверить значимость для клиента и вероятность закрепления | H8: Цены «billed annually» (Mermaid Chart, Lucidchart, Eraser), скидка 20 % (Storm)
A9: Пробный период платного тарифа | B9: потоки доходов | C9: Проверить платные функции до оплаты | D9: 1 | E9: =IF($D9="","",IFERROR($D9/'12_Сводка'!$B$5,0)) -> 0.125 | F9: =IF($A9="","",IF($E9>=0.7,"рыночный стандарт",IF($E9>=0.4,"формирующийся стандарт",IF($E9>=0.2,"зона дифференциации","слабый сигнал")))) -> слабый сигнал | G9: =IF($A9="","",IF($F9="рыночный стандарт","необходимо включить в минимально приемлемое предложение",IF($F9="формирующийся стандарт","проверить значимость для клиента и вероятность закрепления",IF($F9="зона дифференциации","может использоваться как поле позиционирования","не использовать без дополнительной проверки")))) -> не использовать без дополнительной проверки | H9: FAQ Lucidchart: пробный период 7 дней
A10: Бесплатные гости или зрители | B10: отношения с клиентами | C10: Показать диаграмму без оплаты за каждого читателя | D10: 4 | E10: =IF($D10="","",IFERROR($D10/'12_Сводка'!$B$5,0)) -> 0.5 | F10: =IF($A10="","",IF($E10>=0.7,"рыночный стандарт",IF($E10>=0.4,"формирующийся стандарт",IF($E10>=0.2,"зона дифференциации","слабый сигнал")))) -> формирующийся стандарт | G10: =IF($A10="","",IF($F10="рыночный стандарт","необходимо включить в минимально приемлемое предложение",IF($F10="формирующийся стандарт","проверить значимость для клиента и вероятность закрепления",IF($F10="зона дифференциации","может использоваться как поле позиционирования","не использовать без дополнительной проверки")))) -> проверить значимость для клиента и вероятность закрепления | H10: Unlimited viewer seats (Mermaid Chart Premium); 100 гостей на участника (Storm); unlimited guests (Eraser, Whimsical)
A11: Интеграции с другими сервисами | B11: ключевые партнеры | C11: Встроить инструмент в рабочие процессы | D11: 8 | E11: =IF($D11="","",IFERROR($D11/'12_Сводка'!$B$5,0)) -> 1 | F11: =IF($A11="","",IF($E11>=0.7,"рыночный стандарт",IF($E11>=0.4,"формирующийся стандарт",IF($E11>=0.2,"зона дифференциации","слабый сигнал")))) -> рыночный стандарт | G11: =IF($A11="","",IF($F11="рыночный стандарт","необходимо включить в минимально приемлемое предложение",IF($F11="формирующийся стандарт","проверить значимость для клиента и вероятность закрепления",IF($F11="зона дифференциации","может использоваться как поле позиционирования","не использовать без дополнительной проверки")))) -> необходимо включить в минимально приемлемое предложение | H11: Разделы и упоминания интеграций на страницах 8 из 8 конкурентов
A12: API или платформа разработчика | B12: цифровой товар | C12: Автоматизировать генерацию диаграмм | D12: 5 | E12: =IF($D12="","",IFERROR($D12/'12_Сводка'!$B$5,0)) -> 0.625 | F12: =IF($A12="","",IF($E12>=0.7,"рыночный стандарт",IF($E12>=0.4,"формирующийся стандарт",IF($E12>=0.2,"зона дифференциации","слабый сигнал")))) -> формирующийся стандарт | G12: =IF($A12="","",IF($F12="рыночный стандарт","необходимо включить в минимально приемлемое предложение",IF($F12="формирующийся стандарт","проверить значимость для клиента и вероятность закрепления",IF($F12="зона дифференциации","может использоваться как поле позиционирования","не использовать без дополнительной проверки")))) -> проверить значимость для клиента и вероятность закрепления | H12: API Mermaid; пункт API в меню Mermaid Chart; API в Enterprise Storm; Developer platform Lucidchart; API calls Eraser
A13: ИИ-генерация или ИИ-помощник | B13: цифровой товар | C13: Ускорить создание диаграммы по описанию | D13: 5 | E13: =IF($D13="","",IFERROR($D13/'12_Сводка'!$B$5,0)) -> 0.625 | F13: =IF($A13="","",IF($E13>=0.7,"рыночный стандарт",IF($E13>=0.4,"формирующийся стандарт",IF($E13>=0.2,"зона дифференциации","слабый сигнал")))) -> формирующийся стандарт | G13: =IF($A13="","",IF($F13="рыночный стандарт","необходимо включить в минимально приемлемое предложение",IF($F13="формирующийся стандарт","проверить значимость для клиента и вероятность закрепления",IF($F13="зона дифференциации","может использоваться как поле позиционирования","не использовать без дополнительной проверки")))) -> проверить значимость для клиента и вероятность закрепления | H13: ИИ-кредиты (Mermaid Chart); ИИ-ассистент (Storm); Lucid AI; Eraser AI; ИИ в Whimsical
A14: Единый вход SSO или SAML | B14: потоки доходов | C14: Подключить корпоративную учётную запись | D14: 5 | E14: =IF($D14="","",IFERROR($D14/'12_Сводка'!$B$5,0)) -> 0.625 | F14: =IF($A14="","",IF($E14>=0.7,"рыночный стандарт",IF($E14>=0.4,"формирующийся стандарт",IF($E14>=0.2,"зона дифференциации","слабый сигнал")))) -> формирующийся стандарт | G14: =IF($A14="","",IF($F14="рыночный стандарт","необходимо включить в минимально приемлемое предложение",IF($F14="формирующийся стандарт","проверить значимость для клиента и вероятность закрепления",IF($F14="зона дифференциации","может использоваться как поле позиционирования","не использовать без дополнительной проверки")))) -> проверить значимость для клиента и вероятность закрепления | H14: SSO или SAML в старших тарифах
A15: Открытый код и сообщество | B15: ключевые ресурсы | C15: Доверять инструменту и расширять его | D15: 3 | E15: =IF($D15="","",IFERROR($D15/'12_Сводка'!$B$5,0)) -> 0.375 | F15: =IF($A15="","",IF($E15>=0.7,"рыночный стандарт",IF($E15>=0.4,"формирующийся стандарт",IF($E15>=0.2,"зона дифференциации","слабый сигнал")))) -> зона дифференциации | G15: =IF($A15="","",IF($F15="рыночный стандарт","необходимо включить в минимально приемлемое предложение",IF($F15="формирующийся стандарт","проверить значимость для клиента и вероятность закрепления",IF($F15="зона дифференциации","может использоваться как поле позиционирования","не использовать без дополнительной проверки")))) -> может использоваться как поле позиционирования | H15: GitHub API, 30.09.2026; лицензия Apache 2.0 у draw.io
... A22: Русскоязычный интерфейс и тарифы в рублях | B22: целевые сегменты | C22: Работать на русском языке и платить в рублях | D22: 1 | E22: =IF($D22="","",IFERROR($D22/'12_Сводка'!$B$5,0)) -> 0.125 | F22: =IF($A22="","",IF($E22>=0.7,"рыночный стандарт",IF($E22>=0.4,"формирующийся стандарт",IF($E22>=0.2,"зона дифференциации","слабый сигнал")))) -> слабый сигнал | G22: =IF($A22="","",IF($F22="рыночный стандарт","необходимо включить в минимально приемлемое предложение",IF($F22="формирующийся стандарт","проверить значимость для клиента и вероятность закрепления",IF($F22="зона дифференциации","может использоваться как поле позиционирования","не использовать без дополнительной проверки")))) -> не использовать без дополнительной проверки | H22: Сайт и тарифы Storm на русском языке, цены в рублях

Sheet 11_Преимущества
A1: Конкурентные преимущества по бизнес-модели
A2: Оцениваются только преимущества, которые подтверждаются публичными фактами сайта или устойчивой совокупностью признаков
A3: ID конкурента | B3: Название | C3: Гипотеза преимущества | D3: Тип преимущества | E3: Связанный блок бизнес-модели | F3: Подтверждающие страницы | G3: Сила 1-5 | H3: Трудность копирования 1-5 | I3: Коммерческая значимость 1-5 | J3: Доказательность 1-5 | K3: Итоговый балл | L3: Интерпретация | M3: Риск для нашей модели
A4: C07 | B4: =IF($A4="","",IFERROR(VLOOKUP($A4,'02_Конкуренты'!$A$4:$B$11,2,FALSE),"не найдено")) -> Eraser | C4: Тарифы с лимитами ИИ-диаграмм и diagram-as-code в бесплатном тарифе | D4: товарное | E4: цифровой товар | F4: eraser.io/pricing | G4: 4 | H4: 3 | I4: 4 | J4: 5 | K4: =IF($A4="","",$G4*0.3+$H4*0.25+$I4*0.25+$J4*0.2) -> 3.95 | L4: =IF($A4="","",IF($K4>=4,"сильное преимущество",IF($K4>=3,"умеренное преимущество",IF($K4>=2,"слабое преимущество","недостаточно подтверждений")))) -> умеренное преимущество | M4: ИИ-генерация диаграмм обесценивает текстовый подход; необходим сопоставимый ИИ-функционал в NotaCode
A5: C04 | B5: =IF($A5="","",IFERROR(VLOOKUP($A5,'02_Конкуренты'!$A$4:$B$11,2,FALSE),"не найдено")) -> Storm (StormBPMN) | C5: Бесплатный тариф с безлимитным ИИ и тарифы в рублях; on-prem | D5: ценовое | E5: потоки доходов | F5: stormbpmn.com/pricing | G5: 4 | H5: 4 | I5: 4 | J5: 5 | K5: =IF($A5="","",$G5*0.3+$H5*0.25+$I5*0.25+$J5*0.2) -> 4.2 | L5: =IF($A5="","",IF($K5>=4,"сильное преимущество",IF($K5>=3,"умеренное преимущество",IF($K5>=2,"слабое преимущество","недостаточно подтверждений")))) -> сильное преимущество | M5: On-prem и рублевые тарифы перехватывают корпоративный русскоязычный сегмент; NotaCode нужен аналог
A6: C06 | B6: =IF($A6="","",IFERROR(VLOOKUP($A6,'02_Конкуренты'!$A$4:$B$11,2,FALSE),"не найдено")) -> Lucidchart | C6: Лестница тарифов с пробным периодом и Enterprise Shield | D6: товарное | E6: потоки доходов | F6: lucid.app/pricing/lucidchart | G6: 5 | H6: 5 | I6: 5 | J6: 5 | K6: =IF($A6="","",$G6*0.3+$H6*0.25+$I6*0.25+$J6*0.2) -> 5 | L6: =IF($A6="","",IF($K6>=4,"сильное преимущество",IF($K6>=3,"умеренное преимущество",IF($K6>=2,"слабое преимущество","недостаточно подтверждений")))) -> сильное преимущество | M6: Enterprise-лестница с SSO и Shield сложна для повторения на старте; риск потери крупных клиентов
A7: C05 | B7: =IF($A7="","",IFERROR(VLOOKUP($A7,'02_Конкуренты'!$A$4:$B$11,2,FALSE),"не найдено")) -> draw.io (diagrams.net) | C7: Бесплатное приложение без enterprise-тарифа и данные у пользователя | D7: брендовое | E7: ценностное предложение | F7: drawio.com | G7: 4 | H7: 4 | I7: 4 | J7: 4 | K7: =IF($A7="","",$G7*0.3+$H7*0.25+$I7*0.25+$J7*0.2) -> 4 | L7: =IF($A7="","",IF($K7>=4,"сильное преимущество",IF($K7>=3,"умеренное преимущество",IF($K7>=2,"слабое преимущество","недостаточно подтверждений")))) -> сильное преимущество | M7: Бесплатность без ограничений удерживает пользователей без бюджета; NotaCode должен обосновать платность
A8: C02 | B8: =IF($A8="","",IFERROR(VLOOKUP($A8,'02_Конкуренты'!$A$4:$B$11,2,FALSE),"не найдено")) -> Mermaid (библиотека) | C8: Экосистема интеграций и сообщество 90 489 звёзд | D8: партнерское | E8: ключевые партнеры | F8: mermaid.js.org/ecosystem | G8: 5 | H8: 4 | I8: 3 | J8: 5 | K8: =IF($A8="","",$G8*0.3+$H8*0.25+$I8*0.25+$J8*0.2) -> 4.25 | L8: =IF($A8="","",IF($K8>=4,"сильное преимущество",IF($K8>=3,"умеренное преимущество",IF($K8>=2,"слабое преимущество","недостаточно подтверждений")))) -> сильное преимущество | M8: Экосистема 90К звезд формирует отраслевой стандарт; NotaCode нужна совместимость с Mermaid-синтаксисом
A9: C03 | B9: =IF($A9="","",IFERROR(VLOOKUP($A9,'02_Конкуренты'!$A$4:$B$11,2,FALSE),"не найдено")) -> Mermaid Chart | C9: Зрители без оплаты и четыре ясных тарифа | D9: ценовое | E9: потоки доходов | F9: mermaid.ai/pricing | G9: 4 | H9: 3 | I9: 4 | J9: 5 | K9: =IF($A9="","",$G9*0.3+$H9*0.25+$I9*0.25+$J9*0.2) -> 3.95 | L9: =IF($A9="","",IF($K9>=4,"сильное преимущество",IF($K9>=3,"умеренное преимущество",IF($K9>=2,"слабое преимущество","недостаточно подтверждений")))) -> умеренное преимущество | M9: Схожая модель зрителей без оплаты; прямой конкурент в сегменте diagram-as-code с облачным хранением
A10: C08 | B10: =IF($A10="","",IFERROR(VLOOKUP($A10,'02_Конкуренты'!$A$4:$B$11,2,FALSE),"не найдено")) -> Whimsical | C10: Гости и зрители без ограничений на всех тарифах | D10: ценовое | E10: отношения с клиентами | F10: whimsical.com/pricing | G10: 3 | H10: 3 | I10: 3 | J10: 5 | K10: =IF($A10="","",$G10*0.3+$H10*0.25+$I10*0.25+$J10*0.2) -> 3.4 | L10: =IF($A10="","",IF($K10>=4,"сильное преимущество",IF($K10>=3,"умеренное преимущество",IF($K10>=2,"слабое преимущество","недостаточно подтверждений")))) -> умеренное преимущество | M10: Низкий риск: иной целевой сегмент (продуктовые команды); пересечение только по вайрфреймам
A11: C01 | B11: =IF($A11="","",IFERROR(VLOOKUP($A11,'02_Конкуренты'!$A$4:$B$11,2,FALSE),"не найдено")) -> PlantUML | C11: Многолетний стандарт для UML из текста, запуск на своём сервере | D11: технологическое | E11: ключевые ресурсы | F11: plantuml.com/running | G11: 4 | H11: 2 | I11: 4 | J11: 4 | K11: =IF($A11="","",$G11*0.3+$H11*0.25+$I11*0.25+$J11*0.2) -> 3.5 | L11: =IF($A11="","",IF($K11>=4,"сильное преимущество",IF($K11>=3,"умеренное преимущество",IF($K11>=2,"слабое преимущество","недостаточно подтверждений")))) -> умеренное преимущество | M11: Сетевой эффект многолетнего стандарта сложно переломить; выгоднее поддерживать PlantUML-синтаксис

Sheet 12_Сводка
A1: Сводка анализа бизнес-моделей конкурентов
A2: Контроль заполнения, надежности выводов и рейтинга бизнес-моделей. Данные подтягиваются из рабочих листов
A4: Показатель | B4: Значение | C4: Интерпретация | E4: Рейтинг конкурентов
A5: Конкурентов в реестре | B5: =COUNTA('02_Конкуренты'!$A$4:$A$11) -> 8 | C5: Сколько объектов анализа внесено на лист 02_Конкуренты | E5: Место | F5: Конкурент | G5: Итоговый балл
A6: Конкурентов со статусом «завершен» | B6: =COUNTIF('02_Конкуренты'!$H$4:$H$11,"завершен") -> 8 | C6: Сколько профилей можно использовать для итоговых выводов | E6: =1 -> 1 | F6: =IFERROR(INDEX('09_Матрица'!$B$4:$B$11,MATCH(LARGE('09_Матрица'!$Q$4:$Q$11,ROW(A1)),'09_Матрица'!$Q$4:$Q$11,0)),"") -> Lucidchart | G6: =IFERROR(LARGE('09_Матрица'!$Q$4:$Q$11,ROW(A1)),"") -> 4.5175833
A7: Доля завершенных профилей | B7: =IFERROR($B$6/$B$5,0) -> 1 | C7: Контроль готовности исследования | E7: =2 -> 2 | F7: =IFERROR(INDEX('09_Матрица'!$B$4:$B$11,MATCH(LARGE('09_Матрица'!$Q$4:$Q$11,ROW(A2)),'09_Матрица'!$Q$4:$Q$11,0)),"") -> Storm (StormBPMN) | G7: =IFERROR(LARGE('09_Матрица'!$Q$4:$Q$11,ROW(A2)),"") -> 4.0482857
A8: Средняя полнота бизнес-модели | B8: =IFERROR(AVERAGE('04_Бизнес_модель'!$O$4:$O$203),0) -> 1 | C8: Насколько полно заполнены ключевые блоки бизнес-модели | E8: =3 -> 3 | F8: =IFERROR(INDEX('09_Матрица'!$B$4:$B$11,MATCH(LARGE('09_Матрица'!$Q$4:$Q$11,ROW(A3)),'09_Матрица'!$Q$4:$Q$11,0)),"") -> Eraser | G8: =IFERROR(LARGE('09_Матрица'!$Q$4:$Q$11,ROW(A3)),"") -> 4.006
A9: Средняя доказательность выводов | B9: =IFERROR(AVERAGE('04_Бизнес_модель'!$P$4:$P$203),0) -> 3.8616071 | C9: Насколько выводы подтверждены фактами с сайта | E9: =4 -> 4 | F9: =IFERROR(INDEX('09_Матрица'!$B$4:$B$11,MATCH(LARGE('09_Матрица'!$Q$4:$Q$11,ROW(A4)),'09_Матрица'!$Q$4:$Q$11,0)),"") -> draw.io (diagrams.net) | G9: =IFERROR(LARGE('09_Матрица'!$Q$4:$Q$11,ROW(A4)),"") -> 3.99025
A10: Средний индекс силы бизнес-модели | B10: =IFERROR(AVERAGE('09_Матрица'!$Q$4:$Q$11),0) -> 3.9841518 | C10: Сопоставимая оценка по матрице бизнес-модели | E10: =5 -> 5 | F10: =IFERROR(INDEX('09_Матрица'!$B$4:$B$11,MATCH(LARGE('09_Матрица'!$Q$4:$Q$11,ROW(A5)),'09_Матрица'!$Q$4:$Q$11,0)),"") -> Mermaid Chart | G10: =IFERROR(LARGE('09_Матрица'!$Q$4:$Q$11,ROW(A5)),"") -> 3.9760952
A11: Количество зафиксированных преимуществ | B11: =COUNTIF('11_Преимущества'!$A$4:$A$11,"<>") -> 8 | C11: Сколько гипотез преимуществ внесено на лист 11_Преимущества | E11: =6 -> 6 | F11: =IFERROR(INDEX('09_Матрица'!$B$4:$B$11,MATCH(LARGE('09_Матрица'!$Q$4:$Q$11,ROW(A6)),'09_Матрица'!$Q$4:$Q$11,0)),"") -> Whimsical | G11: =IFERROR(LARGE('09_Матрица'!$Q$4:$Q$11,ROW(A6)),"") -> 3.922
E12: =7 -> 7 | F12: =IFERROR(INDEX('09_Матрица'!$B$4:$B$11,MATCH(LARGE('09_Матрица'!$Q$4:$Q$11,ROW(A7)),'09_Матрица'!$Q$4:$Q$11,0)),"") -> Mermaid (библиотека) | G12: =IFERROR(LARGE('09_Матрица'!$Q$4:$Q$11,ROW(A7)),"") -> 3.8144286
E13: =8 -> 8 | F13: =IFERROR(INDEX('09_Матрица'!$B$4:$B$11,MATCH(LARGE('09_Матрица'!$Q$4:$Q$11,ROW(A8)),'09_Матрица'!$Q$4:$Q$11,0)),"") -> PlantUML | G13: =IFERROR(LARGE('09_Матрица'!$Q$4:$Q$11,ROW(A8)),"") -> 3.5985714
A14: Классификация практик бизнес-модели | E14: =9 -> 9 | F14: =IFERROR(INDEX('09_Матрица'!$B$4:$B$11,MATCH(LARGE('09_Матрица'!$Q$4:$Q$11,ROW(A9)),'09_Матрица'!$Q$4:$Q$11,0)),"") | G14: =IFERROR(LARGE('09_Матрица'!$Q$4:$Q$11,ROW(A9)),"")
A15: Статус | B15: Количество | C15: Что означает | E15: =10 -> 10 | F15: =IFERROR(INDEX('09_Матрица'!$B$4:$B$11,MATCH(LARGE('09_Матрица'!$Q$4:$Q$11,ROW(A10)),'09_Матрица'!$Q$4:$Q$11,0)),"") | G15: =IFERROR(LARGE('09_Матрица'!$Q$4:$Q$11,ROW(A10)),"")
A16: рыночный стандарт | B16: =COUNTIF('10_Стандарт'!$F$4:$F$22,"рыночный стандарт") -> 5 | C16: Минимальный уровень, без которого товар или модель воспринимаются слабее рынка
A17: формирующийся стандарт | B17: =COUNTIF('10_Стандарт'!$F$4:$F$22,"формирующийся стандарт") -> 11 | C17: Практика уже заметна, но еще не стала обязательной
A18: зона дифференциации | B18: =COUNTIF('10_Стандарт'!$F$4:$F$22,"зона дифференциации") -> 1 | C18: Поле, где можно отличаться от конкурентов
A19: слабый сигнал | B19: =COUNTIF('10_Стандарт'!$F$4:$F$22,"слабый сигнал") -> 2 | C19: Требует дополнительной проверки до управленческого вывода
A22: Шаблон итогового вывода
A23: 1. Рыночный стандарт бизнес-модели | B23: Рыночный стандарт (порог шаблона 70 %): бесплатный доступ и интеграции (8 из 8), независимые отзывы (7 из 8), раздел о безопасности и документация (по 6 из 8)
A24: 2. Доминирующая логика получения выручки | B24: Преобладает условно-бесплатная модель: Free плюс подписка за пользователя или редактора в месяц (Mermaid Chart, Storm, Lucidchart, Eraser, Whimsical - 5 из 8); три инструмента бесплатны с открытым кодом (PlantUML, Mermaid, draw.io)
A25: 3. Зоны конкурентной дифференциации | B25: Зона дифференциации по порогам шаблона: открытый код и сообщество (3 из 8). Формирующийся стандарт: подписка, открытая страница тарифов, ИИ, API, SSO, вход (по 5 из 8), корпоративный тариф, годовая оплата, гости, данные о числе клиентов (по 4 из 8). Слабые сигналы (по 1 из 8): пробный период (Lucidchart), тарифы в рублях (Storm); IDEF0, DFD и сети Петри на сайтах не найдены
A26: 4. Наиболее сильные конкуренты | B26: Сильнейшие по итогу матрицы с учётом надёжности: Lucidchart (4,52), Storm (StormBPMN) (4,05), Eraser (4,01); профили опираются на просмотренные страницы, доказательность 3,6-4,0
A27: 5. Риски копирования чужой модели | B27: Видимые элементы (тарифы, лимиты, отзывы) копировать можно; ресурсы (сообщество 90 489 звёзд Mermaid, 100M+ пользователей draw.io, Fortune 500 у Lucidchart) и партнёрства быстро не повторяются

Sheet 14_Журнал
A1: Журнал рабочей копии: исправления, источники, правила, ограничения
A3: Раздел | B3: Код | C3: Содержание
A4: Исправление шаблона | B4: Д-1 | C4: Лист 10_Стандарт, столбец E (Доля конкурентов): формула делила на ячейку 12_Сводка!B4 (заголовок «Значение»), поэтому доля везде была 0 и статус «слабый сигнал». Знаменатель заменён на 12_Сводка!B5 (число конкурентов в реестре); остальная логика сохранена
A5: Источники | B5: И-1 | C5: Страницы тарифов, главные страницы, документация конкурентов: автоматическое извлечение текста 01.10.2026 и чтение во встроенном браузере (Lucidchart, тарифы Mermaid Chart); Similarweb Pro, GitHub, отзывы - ЛР1-ЛР4 (30.09.2026)
A6: Выборка | B6: В-1 | C6: 8 конкурентов части B. Типы по справочнику 13_Справочники: PlantUML - прямой; Storm - смежная модель; Whimsical - заменитель; остальные - косвенные
A7: Правило | B7: П-1 | C7: Доказательность 1-5: 5 - данные GitHub API и страницы тарифов SaaS-конкурентов; 4 - явное описание на странице, главная страница; 3 - найдено по ключевым словам или данным Similarweb
A8: Правило | B8: П-2 | C8: Баллы 09_Матрица (1-5) - экспертная оценка силы подтверждения блока и положения на рынке; веса в строке 2 заданы шаблоном. Оценки 1-5 листов 06, 07, 08, 11 - экспертные
A9: Правило | B9: П-3 | C9: Статус «завершен»: все 12 блоков заполнены; блоки деятельности, партнёров, затрат и сетевых эффектов основаны на косвенных признаках и гипотезах и помечены в тексте
A10: Ограничения | B10: О-1 | C10: Страницы просмотрены с одного устройства и из одной страны; рекламные библиотеки и выдача поиска не проверялись (доступ закрыт). Планируется собрать: рекламные объявления, отзывы G2 и Capterra по Storm
A11: Дозаполнение | B11: Д-2 | C11: 05_Товар_ценность: заполнены столбцы 8 (Клиентская проблема), 9 (Клиентский результат), 13 (Вывод о роли товара) для C01–C08 (24 ячейки)
A12: Дозаполнение | B12: Д-3 | C12: 06_Монетизация: восстановлены формулы VLOOKUP в столбце «Название» (col2), поврежденные автозаменой при очистке текста
A13: Дозаполнение | B13: Д-4 | C13: 11_Преимущества: заполнен столбец 13 (Риск для нашей модели) для C01–C08 (8 ячеек)
