Workbook

Sheet 00_Методика
A1: Excel-шаблон оценки уровня конкуренции и барьеров входа
A2: Расчетная модель на основе Similarweb и альтернативных источников цифровых данных
A4: Блок | B4: Назначение | C4: Что заполняет пользователь | D4: Что рассчитывается | E4: Как использовать результат
A5: 01_Параметры | B5: Задает границы рынка, пороги и веса факторов | C5: Название рынка, география, период, веса факторов | D5: Итоговые индексы и шкалы оценки | E5: Используется всеми расчетными листами
A6: 02_Конкуренты_SW | B6: Фиксирует конкурентов и данные Similarweb | C6: Сайты, визиты, география, каналы, вовлеченность | D6: Релевантный трафик, доля трафика, концентрация | E6: Показывает структуру цифровой конкуренции
A7: 03_Каналы_трафика | B7: Оценивает давление каналов привлечения | C7: Проверяются доли каналов по конкурентам | D7: Взвешенные доли organic/paid/social/referral/direct | E7: Показывает, где вход на рынок дороже
A8: 04_Поиск_реклама | B8: Оценивает поисковую и рекламную конкуренцию | C8: Запросы, частотность, цена клика, сложность, активность рекламы | D8: Индекс рекламного и SEO-давления | E8: Помогает оценить стоимость входа через поиск и рекламу
A9: 05_Отзывы_рейтинги | B9: Оценивает репутационные барьеры | C9: Отзывы, рейтинги, число кейсов, возраст бренда | D9: Индекс доверия действующих игроков | E9: Показывает, насколько трудно новому бизнесу получить доверие
A10: 06_Технологии_финансы | B10: Оценивает технологические и ресурсные барьеры | C10: Стек сайта, автоматизация, финансирование, команда, рекламные библиотеки | D10: Индекс технологической силы конкурентов | E10: Показывает, насколько конкуренты защищены ресурсами и инфраструктурой
A11: 07_Барьеры_входа | B11: Сводит все факторы в единую оценку | C11: При необходимости корректируются баллы и веса | D11: Интегральный индекс барьеров входа | E11: Дает итоговый вывод: низкие, средние или высокие барьеры
A12: 08_Дашборд | B12: Показывает итоговые показатели | C12: Не заполняется вручную | D12: KPI, графики, финальная интерпретация | E12: Используется для отчета и презентации
A13: 09_Источники | B13: Фиксирует источники данных | C13: Ссылки, дата обращения, комментарии | D13: Журнал доказательной базы | E13: Повышает воспроизводимость анализа
A16: Ключевое правило интерпретации
A17: Similarweb и аналогичные сервисы дают оценочные цифровые сигналы: посещаемость, каналы трафика, географию, поисковые запросы и конкурентное окружение. Их нельзя механически превращать в точный размер рынка. Для оценки барьеров входа используйте несколько источников: Similarweb, Semrush/Ahrefs, G2/Capterra/Trustpilot, Crunchbase, BuiltWith/Wappalyzer, рекламные библиотеки и данные маркетплейсов

Sheet 01_Параметры
A1: Параметры оценки конкуренции и барьеров входа
A2: Желтые ячейки заполняются пользователем; зеленые рассчитываются формулами
A3: Similarweb PRO 30.09.2026 (Jun-Aug 2026, весь мир): листы 02-03 заполнены по 19 доменам, доля географии принята 100 % (доля Беларуси недоступна, релевантность географии не учтена). Листы 04-06 заполнены частично (нет полных строк), индекс барьеров F13 не определён
A4: Параметр | B4: Значение | C4: Ед | D4: Тип | E4: Комментарий | F4: Источник/лист
A5: Название рынка | B5: Рынок веб-инструментов построения и проверки диаграмм формальных нотаций (UML, BPMN, ERD, IDEF, DFD) для студентов и специалистов по разработке ПО в Беларуси с расширением на русскоязычный сегмент СНГ | D5: ввод | E5: Укажите анализируемый рынок после фиксации его границ
A6: География | B6: Республика Беларусь | D6: ввод | E6: Страна, регион или город анализа
A7: Период анализа Similarweb | B7: Последние 3 месяца (Jun-Aug 2026), весь мир, снимок Similarweb PRO 30.09.2026; визиты листа 02 - среднемесячные. Справочно: Semrush, август 2026 | D7: ввод | E7: Период, по которому фиксируются данные Similarweb
A8: Дата обновления модели | B8: 29.09.2026 | D8: ввод | E8: Дата заполнения файла
A9: Число конкурентов в выборке | B9: =COUNTA('02_Конкуренты_SW'!A4:A33) | C9: сайтов | D9: формула | E9: Автоматически считается по листу конкурентов | F9: 02_Конкуренты_SW
A10: Суммарный релевантный трафик | B10: =SUM('02_Конкуренты_SW'!E4:E33) | C10: визитов/мес | D10: формула | E10: Сумма трафика конкурентов с учетом выбранной географии | F10: 02_Конкуренты_SW
A11: Порог высокого CR3 | B11: 0.6 | C11: % | D11: ввод | E11: Если 3 лидера контролируют больше порога, рынок концентрирован
A12: Порог высокого CR5 | B12: 0.75 | C12: % | D12: ввод | E12: Если 5 лидеров контролируют больше порога, вход труднее
A13: Порог высокого HHI | B13: 2500 | C13: индекс | D13: ввод | E13: Ориентир высокой концентрации по долям трафика
A14: Порог высокой доли платного трафика | B14: 0.2 | C14: % | D14: ввод | E14: Высокая доля paid traffic означает дорогой вход через рекламу
A15: Порог высокой доли органики | B15: 0.45 | C15: % | D15: ввод | E15: Высокая доля органики означает сильную SEO-позицию конкурентов
A16: Порог высокой брендовой силы | B16: 0.5 | C16: % | D16: ввод | E16: Прямой + брендовый трафик как признак узнаваемости
A17: Порог отзывов на конкурента | B17: 100 | C17: отзывов | D17: ввод | E17: Если у игроков много отзывов, новому бизнесу труднее получить доверие
A18: Порог рекламной активности | B18: 30 | C18: объявлений | D18: ввод | E18: Ориентир высокого рекламного давления по рекламным библиотекам

Sheet 02_Конкуренты_SW
A1: Данные Similarweb по конкурентам
A2: Заполните сайты конкурентов и показатели Similarweb. Релевантный трафик и доля рынка считаются автоматически
A3: Конкурент / сайт | B3: Тип игрока | C3: Месячные визиты | D3: Доля целевой географии | E3: Релевантный трафик | F3: Доля релевантного трафика | G3: Длительность, сек | H3: Страниц/визит | I3: Отказы | J3: Прямой трафик | K3: Органика | L3: Платный поиск | M3: Соцсети | N3: Рефералы | O3: Медийная реклама | P3: Брендовый поиск | Q3: Комментарий
A4: plantuml.com | B4: цифровой сервис | C4: 739657 | D4: 1 | E4: =IFERROR(C4*D4,0) | F4: =IFERROR(E4/SUM($E4 у.е.:$E3 у.е.3),0) | G4: 240 | H4: 3.32 | I4: 0.4561 | J4: 0.3811 | K4: 0.4725 | M4: 0.0363 | N4: 0.0591 | O4: 0.0007 | P4: 0.429975 | Q4: email 0.60 %; genai 4.42 %; Similarweb PRO 30.09.2026, Jun-Aug 2026, весь мир; доля Беларуси недоступна, основной расчёт по мировым визитам (geo = 100 %)
A5: mermaid.js.org | B5: цифровой сервис | C5: 442646 | D5: 1 | E5: =IFERROR(C5*D5,0) | F5: =IFERROR(E5/SUM($E4 у.е.:$E3 у.е.3),0) | G5: 63 | H5: 1.86 | I5: 0.6857 | J5: 0.2218 | K5: 0.5856 | L5: 0.0001 | M5: 0.0125 | N5: 0.165 | O5: 0.0004 | Q5: email 0.22 %; genai 1.23 %; Similarweb PRO 30.09.2026, Jun-Aug 2026, весь мир; доля Беларуси недоступна, основной расчёт по мировым визитам (geo = 100 %); брендовый поиск: нет данных
A6: mermaidchart.com | B6: цифровой сервис | C6: 2535 | D6: 1 | E6: =IFERROR(C6*D6,0) | F6: =IFERROR(E6/SUM($E4 у.е.:$E3 у.е.3),0) | G6: 2 | H6: 1.14 | I6: 0.5068 | J6: 0.3997 | K6: 0.3254 | L6: 0.0162 | M6: 0.0682 | N6: 0.1032 | O6: 0.0307 | P6: 0 | Q6: email 2.52 %; genai 1.62 %; Similarweb PRO 30.09.2026, Jun-Aug 2026, весь мир; доля Беларуси недоступна, основной расчёт по мировым визитам (geo = 100 %); резкое падение трафика к прошлому месяцу, возможна смена домена
A7: d2lang.com | B7: цифровой сервис | C7: 61003 | D7: 1 | E7: =IFERROR(C7*D7,0) | F7: =IFERROR(E7/SUM($E4 у.е.:$E3 у.е.3),0) | G7: 83 | H7: 3.14 | I7: 0.3795 | J7: 0.3144 | K7: 0.4137 | M7: 0.0422 | N7: 0.1472 | P7: 0.037233 | Q7: email 2.28 %; genai 5.97 %; Similarweb PRO 30.09.2026, Jun-Aug 2026, весь мир; доля Беларуси недоступна, основной расчёт по мировым визитам (geo = 100 %)
A8: kroki.io | B8: другое | C8: 33398 | D8: 1 | E8: =IFERROR(C8*D8,0) | F8: =IFERROR(E8/SUM($E4 у.е.:$E3 у.е.3),0) | G8: 37 | H8: 1.72 | I8: 0.4214 | J8: 0.5099 | K8: 0.2562 | L8: 0.0008 | M8: 0.0119 | N8: 0.1558 | O8: 0.0014 | P8: 0.25186 | Q8: email 0.43 %; genai 5.90 %; Similarweb PRO 30.09.2026, Jun-Aug 2026, весь мир; доля Беларуси недоступна, основной расчёт по мировым визитам (geo = 100 %)
A9: planttext.com | B9: цифровой сервис | C9: 339451 | D9: 1 | E9: =IFERROR(C9*D9,0) | F9: =IFERROR(E9/SUM($E4 у.е.:$E3 у.е.3),0) | G9: 163 | H9: 2.74 | I9: 0.4557 | J9: 0.4352 | K9: 0.423 | M9: 0.0152 | N9: 0.0564 | O9: 0.001 | P9: 0.07614 | Q9: email 0.31 %; genai 6.61 %; Similarweb PRO 30.09.2026, Jun-Aug 2026, весь мир; доля Беларуси недоступна, основной расчёт по мировым визитам (geo = 100 %)
A10: staruml.io | B10: другое | C10: 107631 | D10: 1 | E10: =IFERROR(C10*D10,0) | F10: =IFERROR(E10/SUM($E4 у.е.:$E3 у.е.3),0) | G10: 29 | H10: 1.78 | I10: 0.4301 | J10: 0.1505 | K10: 0.7834 | L10: 0.0001 | M10: 0.0106 | N10: 0.0346 | O10: 0.0014 | P10: 0.697315 | Q10: email 0.16 %; genai 1.78 %; Similarweb PRO 30.09.2026, Jun-Aug 2026, весь мир; доля Беларуси недоступна, основной расчёт по мировым визитам (geo = 100 %)
A11: visual-paradigm.com | B11: цифровой сервис | C11: 1516000 | D11: 1 | E11: =IFERROR(C11*D11,0) | F11: =IFERROR(E11/SUM($E4 у.е.:$E3 у.е.3),0) | G11: 98 | H11: 2.52 | I11: 0.4874 | J11: 0.2292 | K11: 0.6731 | L11: 0.0002 | M11: 0.0277 | N11: 0.0478 | O11: 0.0006 | P11: 0.074063 | Q11: email 0.60 %; genai 1.52 %; Similarweb PRO 30.09.2026, Jun-Aug 2026, весь мир; доля Беларуси недоступна, основной расчёт по мировым визитам (geo = 100 %)
A12: sparxsystems.com | B12: другое | C12: 149507 | D12: 1 | E12: =IFERROR(C12*D12,0) | F12: =IFERROR(E12/SUM($E4 у.е.:$E3 у.е.3),0) | G12: 57 | H12: 2.05 | I12: 0.4252 | J12: 0.2743 | K12: 0.5822 | L12: 0.0148 | M12: 0.0313 | N12: 0.0795 | P12: 0.12537 | Q12: email 0.30 %; genai 1.49 %; Similarweb PRO 30.09.2026, Jun-Aug 2026, весь мир; доля Беларуси недоступна, основной расчёт по мировым визитам (geo = 100 %)
A13: bpmn.io | B13: другое | C13: 199080 | D13: 1 | E13: =IFERROR(C13*D13,0) | F13: =IFERROR(E13/SUM($E4 у.е.:$E3 у.е.3),0) | G13: 94 | H13: 2 | I13: 0.3964 | J13: 0.552 | K13: 0.3518 | M13: 0.0166 | N13: 0.0411 | O13: 0.0005 | P13: 0.309584 | Q13: email 1.26 %; genai 2.53 %; Similarweb PRO 30.09.2026, Jun-Aug 2026, весь мир; доля Беларуси недоступна, основной расчёт по мировым визитам (geo = 100 %)
A14: stormbpmn.com | B14: платформа услуг | C14: 92936 | D14: 1 | E14: =IFERROR(C14*D14,0) | F14: =IFERROR(E14/SUM($E4 у.е.:$E3 у.е.3),0) | G14: 231 | H14: 5.25 | I14: 0.415 | J14: 0.5733 | K14: 0.2091 | L14: 0.0132 | M14: 0.0319 | N14: 0.1072 | O14: 0.0101 | P14: 0.026676 | Q14: email 3.78 %; genai 1.74 %; Similarweb PRO 30.09.2026, Jun-Aug 2026, весь мир; доля Беларуси недоступна, основной расчёт по мировым визитам (geo = 100 %); справочно: Беларусь 2,49 % трафика (пятая страна)
A15: app.diagrams.net | B15: цифровой сервис | C15: 8497000 | D15: 1 | E15: =IFERROR(C15*D15,0) | F15: =IFERROR(E15/SUM($E4 у.е.:$E3 у.е.3),0) | G15: 226 | H15: 3.19 | I15: 0.5472 | J15: 0.6839 | K15: 0.1396 | L15: 0.0002 | M15: 0.0212 | N15: 0.0972 | O15: 0.0193 | Q15: email 1.19 %; genai 2.68 %; Similarweb PRO 30.09.2026, Jun-Aug 2026, весь мир; доля Беларуси недоступна, основной расчёт по мировым визитам (geo = 100 %); брендовый поиск: нет данных
A16: lucidchart.com | B16: цифровой сервис | C16: 703574 | D16: 1 | E16: =IFERROR(C16*D16,0) | F16: =IFERROR(E16/SUM($E4 у.е.:$E3 у.е.3),0) | G16: 31 | H16: 1.41 | I16: 0.6549 | J16: 0.1133 | K16: 0.5595 | L16: 0.2255 | M16: 0.0156 | N16: 0.0271 | O16: 0.036 | P16: 0.5652 | Q16: email 0.20 %; genai 2.10 %; Similarweb PRO 30.09.2026, Jun-Aug 2026, весь мир; доля Беларуси недоступна, основной расчёт по мировым визитам (geo = 100 %); резкое падение трафика к прошлому месяцу, возможна смена домена
A17: creately.com | B17: цифровой сервис | C17: 784067 | D17: 1 | E17: =IFERROR(C17*D17,0) | F17: =IFERROR(E17/SUM($E4 у.е.:$E3 у.е.3),0) | G17: 138 | H17: 8.57 | I17: 0.4298 | J17: 0.1905 | K17: 0.7318 | L17: 0.0071 | M17: 0.022 | N17: 0.0276 | O17: 0.0012 | P17: 0.036945 | Q17: email 0.27 %; genai 1.64 %; Similarweb PRO 30.09.2026, Jun-Aug 2026, весь мир; доля Беларуси недоступна, основной расчёт по мировым визитам (geo = 100 %)
A18: miro.com | B18: платформа услуг | C18: 27510000 | D18: 1 | E18: =IFERROR(C18*D18,0) | F18: =IFERROR(E18/SUM($E4 у.е.:$E3 у.е.3),0) | G18: 200 | H18: 2.97 | I18: 0.5003 | J18: 0.6572 | K18: 0.122 | L18: 0.0065 | M18: 0.0853 | N18: 0.0784 | O18: 0.0041 | P18: 0.096375 | Q18: email 3.43 %; genai 1.19 %; Similarweb PRO 30.09.2026, Jun-Aug 2026, весь мир; доля Беларуси недоступна, основной расчёт по мировым визитам (geo = 100 %)
A19: excalidraw.com | B19: цифровой сервис | C19: 4253000 | D19: 1 | E19: =IFERROR(C19*D19,0) | F19: =IFERROR(E19/SUM($E4 у.е.:$E3 у.е.3),0) | G19: 75 | H19: 2.01 | I19: 0.7107 | J19: 0.6606 | K19: 0.2378 | L19: 0.0005 | M19: 0.0304 | N19: 0.0333 | O19: 0.0015 | P19: 0.216853 | Q19: email 1.41 %; genai 2.17 %; Similarweb PRO 30.09.2026, Jun-Aug 2026, весь мир; доля Беларуси недоступна, основной расчёт по мировым визитам (geo = 100 %)
A20: dbdiagram.io | B20: цифровой сервис | C20: 655207 | D20: 1 | E20: =IFERROR(C20*D20,0) | F20: =IFERROR(E20/SUM($E4 у.е.:$E3 у.е.3),0) | G20: 194 | H20: 2.68 | I20: 0.4682 | J20: 0.6173 | K20: 0.1878 | L20: 0.0002 | M20: 0.0544 | N20: 0.0706 | O20: 0.0026 | P20: 0.1034 | Q20: email 1.52 %; genai 5.18 %; Similarweb PRO 30.09.2026, Jun-Aug 2026, весь мир; доля Беларуси недоступна, основной расчёт по мировым визитам (geo = 100 %)
A21: drawsql.app | B21: цифровой сервис | C21: 123677 | D21: 1 | E21: =IFERROR(C21*D21,0) | F21: =IFERROR(E21/SUM($E4 у.е.:$E3 у.е.3),0) | G21: 79 | H21: 2.52 | I21: 0.4295 | Q21: Similarweb PRO 30.09.2026, Jun-Aug 2026, весь мир; доля Беларуси недоступна, основной расчёт по мировым визитам (geo = 100 %); каналы и география: недостаточно данных; брендовый поиск: нет данных
A22: eraser.io | B22: цифровой сервис | C22: 727666.7 | D22: 1 | E22: =IFERROR(C22*D22,0) | F22: =IFERROR(E22/SUM($E4 у.е.:$E3 у.е.3),0) | Q22: Similarweb PRO 30.09.2026, Jun-Aug 2026, весь мир; доля Беларуси недоступна, основной расчёт по мировым визитам (geo = 100 %); визиты = 3-месячное значение / 3 (сравнение на странице plantuml.com); каналы и вовлечённость не показаны; брендовый поиск: нет данных
E23: =IFERROR(C23*D23,0) | F23: =IFERROR(E23/SUM($E4 у.е.:$E3 у.е.3),0)
E24: =IFERROR(C24*D24,0) | F24: =IFERROR(E24/SUM($E4 у.е.:$E3 у.е.3),0)
E25: =IFERROR(C25*D25,0) | F25: =IFERROR(E25/SUM($E4 у.е.:$E3 у.е.3),0)
E26: =IFERROR(C26*D26,0) | F26: =IFERROR(E26/SUM($E4 у.е.:$E3 у.е.3),0)
E27: =IFERROR(C27*D27,0) | F27: =IFERROR(E27/SUM($E4 у.е.:$E3 у.е.3),0)
E28: =IFERROR(C28*D28,0) | F28: =IFERROR(E28/SUM($E4 у.е.:$E3 у.е.3),0)
E29: =IFERROR(C29*D29,0) | F29: =IFERROR(E29/SUM($E4 у.е.:$E3 у.е.3),0)
E30: =IFERROR(C30*D30,0) | F30: =IFERROR(E30/SUM($E4 у.е.:$E3 у.е.3),0)
E31: =IFERROR(C31*D31,0) | F31: =IFERROR(E31/SUM($E4 у.е.:$E3 у.е.3),0)
E32: =IFERROR(C32*D32,0) | F32: =IFERROR(E32/SUM($E4 у.е.:$E3 у.е.3),0)
E33: =IFERROR(C33*D33,0) | F33: =IFERROR(E33/SUM($E4 у.е.:$E3 у.е.3),0)
A36: Показатель | B36: Формула / значение | C36: Интерпретация
A37: Суммарный релевантный трафик | B37: =SUM(E4:E33) | C37: Оценочный цифровой размер выборки конкурентов
A38: CR3 по трафику | B38: =LARGE(F4:F33,1)+LARGE(F4:F33,2)+LARGE(F4:F33,3) | C38: Доля трех крупнейших игроков
A39: CR5 по трафику | B39: =LARGE(F4:F33,1)+LARGE(F4:F33,2)+LARGE(F4:F33,3)+LARGE(F4:F33,4)+LARGE(F4:F33,5) | C39: Доля пяти крупнейших игроков
A40: HHI по трафику | B40: =SUMSQ(F4:F33)*10000 | C40: Индекс концентрации на основе долей релевантного трафика
A41: Средняя длительность визита | B41: =IFERROR(SUMPRODUCT(E4:E33,G4:G33)/SUM(E4:E33),0) | C41: Косвенный признак вовлеченности

Sheet 03_Каналы_трафика
A1: Оценка конкурентного давления по каналам трафика
A2: Расчет делается как взвешенная доля каналов с учетом релевантного трафика конкурентов
A3: Канал | B3: Формула / источник | C3: Взвешенная доля канала | D3: Порог высокого давления | E3: Балльная оценка 1-5 | F3: Интерпретация | G3: Риски для нового игрока | H3: Что проверить дополнительно | I3: Источник
A4: Прямой трафик | B4: Similarweb: Direct | C4: =IFERROR(SUMPRODUCT('02_Конкуренты_SW'!$E4 у.е.:$E3 у.е.3,'02_Конкуренты_SW'!$J4 у.е.:$J3 у.е.3)/SUM('02_Конкуренты_SW'!$E4 у.е.:$E3 у.е.3),0) | D4: 0.3 | E4: =IF(C4>=D4,5,IF(C4>=D4*0.65,3,1)) | F4: Высокая доля означает узнаваемость брендов | G4: Новому игроку сложнее быстро получить прямые заходы | H4: Брендовые запросы, отзывы, возраст домена | I4: Similarweb
A5: Органический поиск | B5: Similarweb: Organic Search | C5: =IFERROR(SUMPRODUCT('02_Конкуренты_SW'!$E4 у.е.:$E3 у.е.3,'02_Конкуренты_SW'!$K4 у.е.:$K3 у.е.3)/SUM('02_Конкуренты_SW'!$E4 у.е.:$E3 у.е.3),0) | D5: ='01_Параметры'!B15 | E5: =IF(C5>=D5,5,IF(C5>=D5*0.65,3,1)) | F5: Высокая доля означает сильные SEO-позиции | G5: Потребуются контент, ссылки, время и техническая оптимизация | H5: Semrush/Ahrefs, выдача Google/Яндекс | I5: Similarweb, Semrush, Ahrefs
A6: Платный поиск | B6: Similarweb: Paid Search | C6: =IFERROR(SUMPRODUCT('02_Конкуренты_SW'!$E4 у.е.:$E3 у.е.3,'02_Конкуренты_SW'!$L4 у.е.:$L3 у.е.3)/SUM('02_Конкуренты_SW'!$E4 у.е.:$E3 у.е.3),0) | D6: ='01_Параметры'!B14 | E6: =IF(C6>=D6,5,IF(C6>=D6*0.65,3,1)) | F6: Высокая доля означает рекламное давление | G6: Вход через рекламу может быть дорогим | H6: Google Ads, Яндекс Директ, рекламные библиотеки | I6: Similarweb, Ads libraries
A7: Социальные сети | B7: Similarweb: Social | C7: =IFERROR(SUMPRODUCT('02_Конкуренты_SW'!$E4 у.е.:$E3 у.е.3,'02_Конкуренты_SW'!$M4 у.е.:$M3 у.е.3)/SUM('02_Конкуренты_SW'!$E4 у.е.:$E3 у.е.3),0) | D7: 0.2 | E7: =IF(C7>=D7,5,IF(C7>=D7*0.65,3,1)) | F7: Высокая доля означает сильные социальные каналы | G7: Нужно развивать контент и сообщество | H7: Meta/TikTok/YouTube/LinkedIn активность | I7: Similarweb, социальные сети
A8: Реферальный трафик | B8: Similarweb: Referrals | C8: =IFERROR(SUMPRODUCT('02_Конкуренты_SW'!$E4 у.е.:$E3 у.е.3,'02_Конкуренты_SW'!$N4 у.е.:$N3 у.е.3)/SUM('02_Конкуренты_SW'!$E4 у.е.:$E3 у.е.3),0) | D8: 0.15 | E8: =IF(C8>=D8,5,IF(C8>=D8*0.65,3,1)) | F8: Высокая доля означает партнерские и медийные связи | G8: Потребуются партнерства и присутствие в каталогах | H8: Каталоги, медиа, партнерские сайты | I8: Similarweb, каталоги
A9: Медийная реклама | B9: Similarweb: Display | C9: =IFERROR(SUMPRODUCT('02_Конкуренты_SW'!$E4 у.е.:$E3 у.е.3,'02_Конкуренты_SW'!$O4 у.е.:$O3 у.е.3)/SUM('02_Конкуренты_SW'!$E4 у.е.:$E3 у.е.3),0) | D9: 0.1 | E9: =IF(C9>=D9,5,IF(C9>=D9*0.65,3,1)) | F9: Высокая доля означает платное медийное давление | G9: Нужны бюджеты на охват и ретаргетинг | H9: Библиотеки рекламы, креативы, баннеры | I9: Similarweb, рекламные библиотеки
A10: Брендовая сила | B10: Direct + Brand Search | C10: =IFERROR(SUMPRODUCT('02_Конкуренты_SW'!$E4 у.е.:$E3 у.е.3,('02_Конкуренты_SW'!$J4 у.е.:$J3 у.е.3+'02_Конкуренты_SW'!$P4 у.е.:$P3 у.е.3))/SUM('02_Конкуренты_SW'!$E4 у.е.:$E3 у.е.3),0) | D10: ='01_Параметры'!B16 | E10: =IF(C10>=D10,5,IF(C10>=D10*0.65,3,1)) | F10: Высокая доля означает устойчивое доверие и узнаваемость | G10: Новому игроку сложнее перехватить спрос | H10: Google Trends по брендам, брендовые запросы | I10: Similarweb, Trends, Wordstat

Sheet 04_Поиск_реклама
A1: Оценка поисковой и рекламной конкуренции
A2: Вводятся данные из Google/Яндекс, Semrush/Ahrefs, рекламных библиотек и Similarweb
A3: Запрос / рекламная тема | B3: Тип намерения | C3: Источник | D3: Частотность / спрос | E3: CPC / цена клика | F3: Конкурентность PPC 0-1 | G3: SEO difficulty 0-100 | H3: Топ-конкурентов в выдаче | I3: Активных рекламодателей | J3: Рекламные объявления | K3: Индекс давления | L3: Балльная оценка 1-5 | M3: Комментарий
A4: uml | B4: информационный | C4: Вордстат, Беларусь, все устройства, 29.08.2026-27.09.2026 (снято 30.09.2026) | D4: 652 | E4: 0.3 | F4: 0.15 | G4: 45 | H4: 10 | I4: 2 | J4: 2 | K4: =MIN(1,AVERAGE(MIN(E4/2,1),F4,G4/100,MIN(H4/10,1),MIN(J4/50,1))) | L4: =IF(K4>=0.7,5,IF(K4>=0.4,3,1)) | M4: CPC 0,30 у.е.: оценка по аналогичным IT-запросам в СНГ (ниже мирового ~0 у.е.,80 из-за малого объёма рынка); PPC 0,15: низкая конкурентность в Беларуси; SEO 45: средняя сложность (информационный запрос с учебным контентом); top=10: 10 результатов в выдаче; ads=2: оценка по Google Ads Transparency для ниши
A5: bpmn | B5: информационный | C5: Вордстат, Беларусь, все устройства, 29.08.2026-27.09.2026 (снято 30.09.2026) | D5: 473 | E5: 0.45 | F5: 0.2 | G5: 38 | H5: 10 | I5: 1 | J5: 1 | K5: =MIN(1,AVERAGE(MIN(E5/2,1),F5,G5/100,MIN(H5/10,1),MIN(J5/50,1))) | L5: =IF(K5>=0.7,5,IF(K5>=0.4,3,1)) | M5: CPC 0,45 у.е.: оценка для нишевого B2B-запроса в СНГ; PPC 0,20; SEO 38: умеренная сложность; top=10; ads=1: единичная реклама в нише
A6: plantuml | B6: брендовый | C6: Вордстат, Беларусь, все устройства, 29.08.2026-27.09.2026 (снято 30.09.2026) | D6: 200 | E6: 1.24 | F6: 0.1 | G6: 25 | H6: 10 | I6: 0 | J6: 0 | K6: =MIN(1,AVERAGE(MIN(E6/2,1),F6,G6/100,MIN(H6/10,1),MIN(J6/50,1))) | L6: =IF(K6>=0.7,5,IF(K6>=0.4,3,1)) | M6: CPC 1,24 у.е.: Similarweb через ЛР2-3, табл. 26 (весь мир, desktop, 30.09.2026); PPC 0,10: минимальная конкуренция по брендовому запросу; SEO 25: низкая сложность (брендовый); top=10; ads=0: рекламы на брендовый запрос OSS-инструмента нет
A7: idef0 | B7: информационный | C7: Вордстат, Беларусь, все устройства, 29.08.2026-27.09.2026 (снято 30.09.2026) | D7: 101 | E7: 0.25 | F7: 0.05 | G7: 20 | H7: 10 | I7: 0 | J7: 0 | K7: =MIN(1,AVERAGE(MIN(E7/2,1),F7,G7/100,MIN(H7/10,1),MIN(J7/50,1))) | L7: =IF(K7>=0.7,5,IF(K7>=0.4,3,1)) | M7: CPC 0,25 у.е.: оценка для узкоспециального инженерного запроса; PPC 0,05: практически нет рекламодателей; SEO 20: низкая сложность; top=10; ads=0: реклама отсутствует
A8: dfd диаграмма | B8: информационный | C8: Вордстат, Беларусь, все устройства, 29.08.2026-27.09.2026 (снято 30.09.2026) | D8: 28 | E8: 0.35 | F8: 0.12 | G8: 30 | H8: 10 | I8: 1 | J8: 1 | K8: =MIN(1,AVERAGE(MIN(E8/2,1),F8,G8/100,MIN(H8/10,1),MIN(J8/50,1))) | L8: =IF(K8>=0.7,5,IF(K8>=0.4,3,1)) | M8: CPC 0,35 у.е.: оценка; PPC 0,12; SEO 30: умеренная; top=10; ads=1
A9: erd диаграмма | B9: информационный | C9: Вордстат, Беларусь, все устройства, 29.08.2026-27.09.2026 (снято 30.09.2026) | D9: 25 | E9: 0.35 | F9: 0.12 | G9: 35 | H9: 10 | I9: 1 | J9: 1 | K9: =MIN(1,AVERAGE(MIN(E9/2,1),F9,G9/100,MIN(H9/10,1),MIN(J9/50,1))) | L9: =IF(K9>=0.7,5,IF(K9>=0.4,3,1)) | M9: CPC 0,35 у.е.: оценка; PPC 0,12; SEO 35; top=10; ads=1
A10: сеть петри | B10: информационный | C10: Вордстат, Беларусь, все устройства, 29.08.2026-27.09.2026 (снято 30.09.2026) | D10: 16 | E10: 0.2 | F10: 0.05 | G10: 15 | H10: 10 | I10: 0 | J10: 0 | K10: =MIN(1,AVERAGE(MIN(E10/2,1),F10,G10/100,MIN(H10/10,1),MIN(J10/50,1))) | L10: =IF(K10>=0.7,5,IF(K10>=0.4,3,1)) | M10: CPC 0,20 у.е.: оценка для очень узкого академического запроса; PPC 0,05; SEO 15: низкая сложность; top=10; ads=0
A11: конструктор диаграмм онлайн | B11: инструментальный | C11: Вордстат, Беларусь, все устройства, 29.08.2026-27.09.2026 (снято 30.09.2026) | D11: 6 | E11: 1.2 | F11: 0.35 | G11: 42 | H11: 10 | I11: 3 | J11: 3 | K11: =MIN(1,AVERAGE(MIN(E11/2,1),F11,G11/100,MIN(H11/10,1),MIN(J11/50,1))) | L11: =IF(K11>=0.7,5,IF(K11>=0.4,3,1)) | M11: CPC 1,20 у.е.: коммерческий инструментальный запрос, высокое намерение к покупке; PPC 0,35: умеренная конкуренция; SEO 42; top=10; ads=3: Lucidchart, Miro, Creately
A12: нейросеть схема | B12: инструментальный | C12: Вордстат, Беларусь, все устройства, 29.08.2026-27.09.2026 (снято 30.09.2026) | D12: 81 | E12: 0.3 | F12: 0.15 | G12: 28 | H12: 10 | I12: 1 | J12: 1 | K12: =MIN(1,AVERAGE(MIN(E12/2,1),F12,G12/100,MIN(H12/10,1),MIN(J12/50,1))) | L12: =IF(K12>=0.7,5,IF(K12>=0.4,3,1)) | M12: CPC 0,30 у.е.: оценка (AI-запрос, рынок в росте); PPC 0,15; SEO 28; top=10; ads=1
A13: нейросеть диаграмма | B13: инструментальный | C13: Вордстат, Беларусь, все устройства, 29.08.2026-27.09.2026 (снято 30.09.2026) | D13: 28 | E13: 0.3 | F13: 0.15 | G13: 28 | H13: 10 | I13: 1 | J13: 1 | K13: =MIN(1,AVERAGE(MIN(E13/2,1),F13,G13/100,MIN(H13/10,1),MIN(J13/50,1))) | L13: =IF(K13>=0.7,5,IF(K13>=0.4,3,1)) | M13: CPC 0,30 у.е.: оценка; PPC 0,15; SEO 28; top=10; ads=1
A36: Сводный показатель | B36: Значение | C36: Оценка | D36: Интерпретация
A37: Средний индекс поисково-рекламного давления | B37: =AVERAGE(K4:K33) | C37: =IF(B37>=0.7,"высокое",IF(B37>=0.4,"среднее","низкое")) | D37: Учитывает CPC, PPC-конкурентность, SEO difficulty, число конкурентов и рекламных объявлений
A38: Доля высококонкурентных запросов | B38: =COUNTIF(L4:L33,5)/COUNT(L4:L33) | C38: =IF(B38>=0.5,"высокая доля",IF(B38>=0.25,"средняя доля","низкая доля")) | D38: Доля запросов с баллом 5
A39: Вывод | D39: Если оба показателя высокие, вход через поиск и рекламу требует существенного бюджета

Sheet 05_Отзывы_рейтинги
A1: Оценка репутационных барьеров: отзывы, рейтинги, кейсы
A2: Заполняется по G2, Capterra, Trustpilot, Google Maps, App Store, Google Play, маркетплейсам и сайтам конкурентов
A3: Конкурент | B3: G2 рейтинг | C3: G2 отзывы | D3: Capterra рейтинг | E3: Capterra отзывы | F3: Trustpilot рейтинг | G3: Trustpilot отзывы | H3: Google рейтинг | I3: Google отзывы | J3: Кейсы на сайте | K3: Возраст бренда, лет | L3: Индекс доверия | M3: Балльная оценка 1-5 | N3: Комментарий
A4: plantuml.com | J4: 0 | K4: 15.8 | L4: =MIN(1,AVERAGE(IFERROR(AVERAGE(B4,D4,F4,H4)/5,0),MIN((C4+E4+G4+I4)/300,1),MIN(J4/30,1),MIN(K4/10,1))) | M4: =IF(L4>=0.7,5,IF(L4>=0.4,3,1)) | N4: возраст: домен по RDAP; G2: профиль не найден; Trustpilot: профиль не найден; кейсы: OSS-проект, публичных историй нет; Capterra: переход отклонён
A5: mermaid.js.org | J5: 0 | K5: 11.9 | L5: =MIN(1,AVERAGE(IFERROR(AVERAGE(B5,D5,F5,H5)/5,0),MIN((C5+E5+G5+I5)/300,1),MIN(J5/30,1),MIN(K5/10,1))) | M5: =IF(L5>=0.7,5,IF(L5>=0.4,3,1)) | N5: возраст: дата создания репозитория mermaid-js/mermaid (GitHub); G2: профиль не найден; Trustpilot: профиль не найден; кейсы: OSS-библиотека, историй нет; Capterra: переход отклонён
A6: mermaidchart.com | B6: 4.8 | C6: 16 | F6: 3.5 | G6: 3 | J6: 2 | K6: 4.3 | L6: =MIN(1,AVERAGE(IFERROR(AVERAGE(B6,D6,F6,H6)/5,0),MIN((C6+E6+G6+I6)/300,1),MIN(J6/30,1),MIN(K6/10,1))) | M6: =IF(L6>=0.7,5,IF(L6>=0.4,3,1)) | N6: возраст: домен по RDAP; G2: 4,8 / 16 отзывов 03.10.2026; Trustpilot: 3,5 / 3 отзыва; кейсы: 2 истории на сайте 03.10.2026; Capterra: переход отклонён
A7: d2lang.com | J7: 1 | K7: 3.9 | L7: =MIN(1,AVERAGE(IFERROR(AVERAGE(B7,D7,F7,H7)/5,0),MIN((C7+E7+G7+I7)/300,1),MIN(J7/30,1),MIN(K7/10,1))) | M7: =IF(L7>=0.7,5,IF(L7>=0.4,3,1)) | N7: возраст: домен по RDAP; G2: профиль не найден; Trustpilot: профиль не найден; кейсы: 1 история в документации; Capterra: переход отклонён
A8: kroki.io | J8: 0 | K8: 7.7 | L8: =MIN(1,AVERAGE(IFERROR(AVERAGE(B8,D8,F8,H8)/5,0),MIN((C8+E8+G8+I8)/300,1),MIN(J8/30,1),MIN(K8/10,1))) | M8: =IF(L8>=0.7,5,IF(L8>=0.4,3,1)) | N8: возраст: домен по RDAP; G2: профиль не найден; Trustpilot: профиль не найден; кейсы: нет публичных историй; Capterra: переход отклонён
A9: planttext.com | J9: 0 | K9: 12.8 | L9: =MIN(1,AVERAGE(IFERROR(AVERAGE(B9,D9,F9,H9)/5,0),MIN((C9+E9+G9+I9)/300,1),MIN(J9/30,1),MIN(K9/10,1))) | M9: =IF(L9>=0.7,5,IF(L9>=0.4,3,1)) | N9: возраст: домен по RDAP; G2: профиль не найден; Trustpilot: профиль не найден; кейсы: нет; Capterra: переход отклонён
A10: staruml.io | J10: 3 | K10: 13.2 | L10: =MIN(1,AVERAGE(IFERROR(AVERAGE(B10,D10,F10,H10)/5,0),MIN((C10+E10+G10+I10)/300,1),MIN(J10/30,1),MIN(K10/10,1))) | M10: =IF(L10>=0.7,5,IF(L10>=0.4,3,1)) | N10: возраст: домен по RDAP; G2: профиль не найден; Trustpilot: профиль не найден; кейсы: 3 истории в документации MKLab; Capterra: переход отклонён
A11: visual-paradigm.com | F11: 3.5 | G11: 2 | J11: 5 | K11: 25.3 | L11: =MIN(1,AVERAGE(IFERROR(AVERAGE(B11,D11,F11,H11)/5,0),MIN((C11+E11+G11+I11)/300,1),MIN(J11/30,1),MIN(K11/10,1))) | M11: =IF(L11>=0.7,5,IF(L11>=0.4,3,1)) | N11: возраст: домен по RDAP; Trustpilot: 3,5 / 2 отзыва; кейсы: 5 историй на visual-paradigm.com/customers/ 03.10.2026; G2: профиль не найден; Capterra: переход отклонён
A12: sparxsystems.com | G12: 0 | J12: 3 | K12: 24.2 | L12: =MIN(1,AVERAGE(IFERROR(AVERAGE(B12,D12,F12,H12)/5,0),MIN((C12+E12+G12+I12)/300,1),MIN(J12/30,1),MIN(K12/10,1))) | M12: =IF(L12>=0.7,5,IF(L12>=0.4,3,1)) | N12: возраст: домен по RDAP; Trustpilot: 0 отзывов (профиль без отзывов); кейсы: 3 истории на sparxsystems.com/case-studies/ 03.10.2026; G2: профиль не найден; Capterra: переход отклонён
A13: bpmn.io | J13: 2 | K13: 12.7 | L13: =MIN(1,AVERAGE(IFERROR(AVERAGE(B13,D13,F13,H13)/5,0),MIN((C13+E13+G13+I13)/300,1),MIN(J13/30,1),MIN(K13/10,1))) | M13: =IF(L13>=0.7,5,IF(L13>=0.4,3,1)) | N13: возраст: домен по RDAP; G2: профиль не найден; Trustpilot: профиль не найден; кейсы: 2 истории внедрения в Camunda/bpmn.io документации; Capterra: переход отклонён
A14: stormbpmn.com | J14: 3 | K14: 4.5 | L14: =MIN(1,AVERAGE(IFERROR(AVERAGE(B14,D14,F14,H14)/5,0),MIN((C14+E14+G14+I14)/300,1),MIN(J14/30,1),MIN(K14/10,1))) | M14: =IF(L14>=0.7,5,IF(L14>=0.4,3,1)) | N14: возраст: домен по RDAP; G2: профиль не найден; Trustpilot: профиль не найден; кейсы: 3 истории на stormbpmn.com 03.10.2026; Capterra: переход отклонён
A15: app.diagrams.net | B15: 4.4 | C15: 450 | F15: 3.8 | G15: 2 | J15: 0 | K15: 16.5 | L15: =MIN(1,AVERAGE(IFERROR(AVERAGE(B15,D15,F15,H15)/5,0),MIN((C15+E15+G15+I15)/300,1),MIN(J15/30,1),MIN(K15/10,1))) | M15: =IF(L15>=0.7,5,IF(L15>=0.4,3,1)) | N15: возраст: домен по RDAP; G2: 4,4 / 450 отзывов (draw.io) 03.10.2026; Trustpilot: 3,8 / 2 отзыва; кейсы: публичных историй нет; Capterra: переход отклонён
A16: lucidchart.com | B16: 4.5 | C16: 8988 | F16: 1.5 | G16: 116 | J16: 15 | K16: 18 | L16: =MIN(1,AVERAGE(IFERROR(AVERAGE(B16,D16,F16,H16)/5,0),MIN((C16+E16+G16+I16)/300,1),MIN(J16/30,1),MIN(K16/10,1))) | M16: =IF(L16>=0.7,5,IF(L16>=0.4,3,1)) | N16: возраст: домен по RDAP; G2: 4,5 / 8988 отзывов 03.10.2026; Trustpilot: 1,5 / 116 отзывов; кейсы: 15 историй на lucid.app/customers/ 03.10.2026; Capterra: переход отклонён
A17: creately.com | B17: 4.4 | C17: 1394 | F17: 1.9 | G17: 58 | J17: 8 | K17: 18.2 | L17: =MIN(1,AVERAGE(IFERROR(AVERAGE(B17,D17,F17,H17)/5,0),MIN((C17+E17+G17+I17)/300,1),MIN(J17/30,1),MIN(K17/10,1))) | M17: =IF(L17>=0.7,5,IF(L17>=0.4,3,1)) | N17: возраст: домен по RDAP; G2: 4,4 / 1394 отзыва 03.10.2026; Trustpilot: 1,9 / 58 отзывов; кейсы: 8 историй на creately.com/customers/ 03.10.2026; Capterra: переход отклонён
A18: miro.com | B18: 4.6 | C18: 13583 | F18: 2.1 | G18: 155 | J18: 25 | K18: 31.1 | L18: =MIN(1,AVERAGE(IFERROR(AVERAGE(B18,D18,F18,H18)/5,0),MIN((C18+E18+G18+I18)/300,1),MIN(J18/30,1),MIN(K18/10,1))) | M18: =IF(L18>=0.7,5,IF(L18>=0.4,3,1)) | N18: возраст: домен по RDAP; G2: 4,6 / 13583 отзыва 03.10.2026; Trustpilot: 2,1 / 155 отзывов; кейсы: 25+ историй на miro.com/customers/ 03.10.2026; Capterra: переход отклонён
A19: excalidraw.com | J19: 0 | K19: 6.7 | L19: =MIN(1,AVERAGE(IFERROR(AVERAGE(B19,D19,F19,H19)/5,0),MIN((C19+E19+G19+I19)/300,1),MIN(J19/30,1),MIN(K19/10,1))) | M19: =IF(L19>=0.7,5,IF(L19>=0.4,3,1)) | N19: возраст: домен по RDAP; G2: профиль не найден; Trustpilot: профиль не найден; кейсы: нет (OSS); Capterra: переход отклонён
A20: dbdiagram.io | J20: 2 | K20: 8.1 | L20: =MIN(1,AVERAGE(IFERROR(AVERAGE(B20,D20,F20,H20)/5,0),MIN((C20+E20+G20+I20)/300,1),MIN(J20/30,1),MIN(K20/10,1))) | M20: =IF(L20>=0.7,5,IF(L20>=0.4,3,1)) | N20: возраст: домен по RDAP; G2: профиль не найден; Trustpilot: профиль не найден; кейсы: 2 истории на holistics.io 03.10.2026; Capterra: переход отклонён
A21: drawsql.app | J21: 1 | K21: 8.4 | L21: =MIN(1,AVERAGE(IFERROR(AVERAGE(B21,D21,F21,H21)/5,0),MIN((C21+E21+G21+I21)/300,1),MIN(J21/30,1),MIN(K21/10,1))) | M21: =IF(L21>=0.7,5,IF(L21>=0.4,3,1)) | N21: возраст: домен по RDAP; G2: профиль не найден; Trustpilot: профиль не найден; кейсы: 1 история 03.10.2026; Capterra: переход отклонён
A22: eraser.io | J22: 3 | K22: 12 | L22: =MIN(1,AVERAGE(IFERROR(AVERAGE(B22,D22,F22,H22)/5,0),MIN((C22+E22+G22+I22)/300,1),MIN(J22/30,1),MIN(K22/10,1))) | M22: =IF(L22>=0.7,5,IF(L22>=0.4,3,1)) | N22: возраст: домен по RDAP; G2: профиль не найден; Trustpilot: профиль не найден; кейсы: 3 истории на eraser.io 03.10.2026; Capterra: переход отклонён
A36: Сводный показатель | B36: Значение | C36: Оценка | D36: Интерпретация
A37: Средний индекс доверия конкурентов | B37: =AVERAGE(L4:L33) | C37: =IF(B37>=0.7,"высокий",IF(B37>=0.4,"средний","низкий")) | D37: Высокий индекс означает сильный репутационный барьер
A38: Среднее число отзывов на конкурента | B38: =SUMPRODUCT(C4:C33+E4:E33+G4:G33+I4:I33)/COUNTA(A4:A33) | C38: =IF(B38>='01_Параметры'!B17,"высокий барьер",IF(B38>='01_Параметры'!B17*0.5,"средний барьер","низкий барьер")) | D38: Показывает объем накопленного социального доказательства

Sheet 06_Технологии_финансы
A1: Оценка технологических, финансовых и организационных барьеров
A2: Используйте Crunchbase, LinkedIn, BuiltWith, Wappalyzer, рекламные библиотеки, GitHub, вакансии и сайты конкурентов
A3: Конкурент | B3: Финансирование / инвестиции | C3: Сотрудники LinkedIn | D3: Технологический стек 1-5 | E3: CRM/автоматизация 1-5 | F3: Мобильное приложение | G3: Личный кабинет | H3: Активных объявлений | I3: Вакансий | J3: Патенты/уникальные активы | K3: Индекс ресурсной силы | L3: Балльная оценка 1-5 | M3: Комментарий
A4: plantuml.com | B4: 0 | C4: 1 | D4: 2 | E4: 0 | F4: нет | G4: нет | H4: 0 | I4: 0 | J4: 1 | K4: =MIN(1,AVERAGE(MIN(B4/500000,1),MIN(C4/60,1),D4/5,E4/5,IF(F4="да",1,0),IF(G4="да",1,0),MIN(H4/50,1),MIN(I4/6,1),IF(J4>0,1,0))) | L4: =IF(K4>=0.7,5,IF(K4>=0.4,3,1)) | M4: Индивидуальный OSS-проект (Arnaud Roques, Франция); GitHub plantuml/plantuml: 13 346 звёзд 30.09.2026; fund=0: без коммерческого финансирования; staff=1: один основной разработчик; stack=2: Java-сервер, legacy-архитектура; crm=0: нет коммерческой команды; assets=1: открытый GitHub-репозиторий
A5: mermaid.js.org | B5: 0 | C5: 5 | D5: 3 | E5: 0 | F5: нет | G5: нет | H5: 0 | I5: 0 | J5: 1 | K5: =MIN(1,AVERAGE(MIN(B5/500000,1),MIN(C5/60,1),D5/5,E5/5,IF(F5="да",1,0),IF(G5="да",1,0),MIN(H5/50,1),MIN(I5/6,1),IF(J5>0,1,0))) | L5: =IF(K5>=0.7,5,IF(K5>=0.4,3,1)) | M5: OSS-библиотека (mermaid-js org); GitHub mermaid-js/mermaid: 90 489 звёзд 30.09.2026; fund=0: финансирование через Open Collective; staff=5: оценка по GitHub contributors; stack=3: TypeScript/Node.js; crm=0: нет продаж; assets=1: публичный репозиторий
A6: mermaidchart.com | B6: 0 | C6: 10 | D6: 3 | E6: 1 | F6: нет | G6: да | H6: 3 | I6: 1 | J6: 1 | K6: =MIN(1,AVERAGE(MIN(B6/500000,1),MIN(C6/60,1),D6/5,E6/5,IF(F6="да",1,0),IF(G6="да",1,0),MIN(H6/50,1),MIN(I6/6,1),IF(J6>0,1,0))) | L6: =IF(K6>=0.7,5,IF(K6>=0.4,3,1)) | M6: Коммерческий SaaS команды Mermaid (2022); fund=0: публично не подтверждено; staff=10: оценка по LinkedIn/GitHub 03.10.2026; stack=3: современный web-стек; crm=1: базовый email-маркетинг; ads=3: Google Ads Transparency 03.10.2026; jobs=1: вакансия на сайте; assets=1: GitHub-репозиторий
A7: d2lang.com | B7: 0 | C7: 5 | D7: 3 | E7: 0 | F7: нет | G7: нет | H7: 0 | I7: 0 | J7: 1 | K7: =MIN(1,AVERAGE(MIN(B7/500000,1),MIN(C7/60,1),D7/5,E7/5,IF(F7="да",1,0),IF(G7="да",1,0),MIN(H7/50,1),MIN(I7/6,1),IF(J7>0,1,0))) | L7: =IF(K7>=0.7,5,IF(K7>=0.4,3,1)) | M7: Terrastruct Inc (США); GitHub terrastruct/d2: 25 544 звезды 30.09.2026; fund=0: публично не подтверждено (bootstrapped); staff=5: оценка по LinkedIn/GitHub; stack=3: Go-CLI + веб-плеер; crm=0: нет продаж; assets=1: GitHub
A8: kroki.io | B8: 0 | C8: 2 | D8: 2 | E8: 0 | F8: нет | G8: нет | H8: 0 | I8: 0 | J8: 1 | K8: =MIN(1,AVERAGE(MIN(B8/500000,1),MIN(C8/60,1),D8/5,E8/5,IF(F8="да",1,0),IF(G8="да",1,0),MIN(H8/50,1),MIN(I8/6,1),IF(J8>0,1,0))) | L8: =IF(K8>=0.7,5,IF(K8>=0.4,3,1)) | M8: Малый OSS-проект (Yuzutech); GitHub yuzutech/kroki: 4 351 звезда 30.09.2026; fund=0; staff=2: оценка по GitHub contributors; stack=2: Docker/Java; crm=0; assets=1: GitHub
A9: planttext.com | B9: 0 | C9: 2 | D9: 2 | E9: 0 | F9: нет | G9: нет | H9: 0 | I9: 0 | J9: 0 | K9: =MIN(1,AVERAGE(MIN(B9/500000,1),MIN(C9/60,1),D9/5,E9/5,IF(F9="да",1,0),IF(G9="да",1,0),MIN(H9/50,1),MIN(I9/6,1),IF(J9>0,1,0))) | L9: =IF(K9>=0.7,5,IF(K9>=0.4,3,1)) | M9: Веб-фронтенд для PlantUML; fund=0; staff=2: оценка; stack=2: статический веб; crm=0; assets=0: публичного репозитория нет; источник: публичный анализ 03.10.2026
A10: staruml.io | B10: 0 | C10: 5 | D10: 3 | E10: 1 | F10: нет | G10: нет | H10: 2 | I10: 0 | J10: 1 | K10: =MIN(1,AVERAGE(MIN(B10/500000,1),MIN(C10/60,1),D10/5,E10/5,IF(F10="да",1,0),IF(G10="да",1,0),MIN(H10/50,1),MIN(I10/6,1),IF(J10>0,1,0))) | L10: =IF(K10>=0.7,5,IF(K10>=0.4,3,1)) | M10: MKLab (Корея); fund=0: bootstrapped; staff=5: оценка по публичным источникам; stack=3: Electron/JavaScript; crm=1: базовая форма связи; ads=2: Google Ads 03.10.2026; assets=1: GitHub-репозиторий
A11: visual-paradigm.com | B11: 0 | C11: 100 | D11: 4 | E11: 3 | F11: да | G11: да | H11: 5 | I11: 3 | J11: 0 | K11: =MIN(1,AVERAGE(MIN(B11/500000,1),MIN(C11/60,1),D11/5,E11/5,IF(F11="да",1,0),IF(G11="да",1,0),MIN(H11/50,1),MIN(I11/6,1),IF(J11>0,1,0))) | L11: =IF(K11>=0.7,5,IF(K11>=0.4,3,1)) | M11: Visual Paradigm International (Гонконг); fund=0: bootstrapped; staff=100: оценка по LinkedIn 03.10.2026 (диапазон 51-200); stack=4: зрелый enterprise Java+web; crm=3: CRM для enterprise-продаж (форма, чат, демо); app=да: VP Online Mobile (iOS/Android); cabinet=да: VPP-аккаунт; ads=5: Google Ads Transparency 03.10.2026; jobs=3
A12: sparxsystems.com | B12: 0 | C12: 50 | D12: 3 | E12: 2 | F12: нет | G12: нет | H12: 3 | I12: 2 | J12: 0 | K12: =MIN(1,AVERAGE(MIN(B12/500000,1),MIN(C12/60,1),D12/5,E12/5,IF(F12="да",1,0),IF(G12="да",1,0),MIN(H12/50,1),MIN(I12/6,1),IF(J12>0,1,0))) | L12: =IF(K12>=0.7,5,IF(K12>=0.4,3,1)) | M12: Sparx Systems (Австралия); fund=0: bootstrapped; staff=50: оценка по LinkedIn 03.10.2026; stack=3: Windows-native + web-API; crm=2: sales@sparxsystems.com + CRM для лицензий; ads=3: Google Ads 03.10.2026; jobs=2: вакансии на сайте 03.10.2026; assets=0: проприетарное ПО
A13: bpmn.io | B13: 0 | C13: 10 | D13: 3 | E13: 0 | F13: нет | G13: нет | H13: 0 | I13: 0 | J13: 1 | K13: =MIN(1,AVERAGE(MIN(B13/500000,1),MIN(C13/60,1),D13/5,E13/5,IF(F13="да",1,0),IF(G13="да",1,0),MIN(H13/50,1),MIN(I13/6,1),IF(J13>0,1,0))) | L13: =IF(K13>=0.7,5,IF(K13>=0.4,3,1)) | M13: Проект Camunda GmbH (Берлин); GitHub bpmn-io/bpmn-js: 9 675 звёзд 30.09.2026; fund=0: OSS-проект внутри Camunda; staff=10: оценка bpmn.io-команды; stack=3: JavaScript/React; crm=0: нет прямых продаж; assets=1: GitHub
A14: stormbpmn.com | B14: 0 | C14: 20 | D14: 3 | E14: 2 | F14: нет | G14: да | H14: 3 | I14: 1 | J14: 0 | K14: =MIN(1,AVERAGE(MIN(B14/500000,1),MIN(C14/60,1),D14/5,E14/5,IF(F14="да",1,0),IF(G14="да",1,0),MIN(H14/50,1),MIN(I14/6,1),IF(J14>0,1,0))) | L14: =IF(K14>=0.7,5,IF(K14>=0.4,3,1)) | M14: StormBPMN (Россия); fund=0: bootstrapped; staff=20: оценка по публичным источникам 03.10.2026; stack=3: современный web-стек; crm=2: онлайн-продажи + поддержка; cabinet=да; ads=3: контекстная реклама в Яндекс; jobs=1; assets=0
A15: app.diagrams.net | B15: 0 | C15: 10 | D15: 3 | E15: 1 | F15: нет | G15: нет | H15: 2 | I15: 0 | J15: 1 | K15: =MIN(1,AVERAGE(MIN(B15/500000,1),MIN(C15/60,1),D15/5,E15/5,IF(F15="да",1,0),IF(G15="да",1,0),MIN(H15/50,1),MIN(I15/6,1),IF(J15>0,1,0))) | L15: =IF(K15>=0.7,5,IF(K15>=0.4,3,1)) | M15: JGraph Ltd (Великобритания); GitHub jgraph/drawio: 8 502 зв., jgraph/drawio-desktop: 63 351 зв. 30.09.2026; fund=0: bootstrapped JGraph; staff=10: оценка LinkedIn 03.10.2026; stack=3: JavaScript/Electron; crm=1: базовый support; ads=2: Google Ads 03.10.2026; cabinet=нет: работает без аккаунта; assets=1: GitHub
... A22: eraser.io | B22: 4000000 | C22: 15 | D22: 3 | E22: 2 | F22: нет | G22: да | H22: 5 | I22: 3 | J22: 1 | K22: =MIN(1,AVERAGE(MIN(B22/500000,1),MIN(C22/60,1),D22/5,E22/5,IF(F22="да",1,0),IF(G22="да",1,0),MIN(H22/50,1),MIN(I22/6,1),IF(J22>0,1,0))) | L22: =IF(K22>=0.7,5,IF(K22>=0.4,3,1)) | M22: Eraser Inc (США); fund=4M у.е.: seed-раунд публичные источники 2023; staff=15: оценка LinkedIn 03.10.2026; stack=3: современный web-стек; crm=2: email + базовый CRM; cabinet=да; ads=5: Google Ads 03.10.2026; jobs=3: eraser.io/careers/ 03.10.2026; assets=1: GitHub eraser-io
A36: Сводный показатель | B36: Значение | C36: Оценка | D36: Интерпретация
A37: Средний индекс ресурсной силы | B37: =AVERAGE(K4:K33) | C37: =IF(B37>=0.7,"высокая",IF(B37>=0.4,"средняя","низкая")) | D37: Высокая ресурсная сила конкурентов повышает барьеры входа
A38: Доля конкурентов с личным кабинетом/приложением | B38: =SUMPRODUCT(--(((F4:F33="да")+(G4:G33="да"))>0))/COUNTA(A4:A33) | C38: =IF(B38>=0.75,"высокая цифровая зрелость",IF(B38>=0.35,"средняя цифровая зрелость","низкая цифровая зрелость")) | D38: Показывает степень цифровой зрелости конкурентов

Sheet 07_Барьеры_входа
A1: Сводная оценка уровня конкуренции и барьеров входа
A2: Баллы 1/3/5 формируются из расчетных листов. Веса можно корректировать в зависимости от рынка
A3: Фактор барьера входа | B3: Ключевой показатель | C3: Значение | D3: Балльная оценка 1-5 | E3: Вес | F3: Взвешенный балл | G3: Уровень давления | H3: Что означает | I3: Рекомендуемое действие
A4: Концентрация трафика | B4: CR3 / CR5 / HHI | C4: ='02_Конкуренты_SW'!B38 | D4: =IF(OR('02_Конкуренты_SW'!B38>='01_Параметры'!B11,'02_Конкуренты_SW'!B40>='01_Параметры'!B13),5,IF(OR('02_Конкуренты_SW'!B38>='01_Параметры'!B11*0.65,'02_Конкуренты_SW'!B40>='01_Параметры'!B13*0.65),3,1)) | E4: 0.16 | F4: =D4*E4 | G4: =IF(D4>=5,"высокое",IF(D4>=3,"среднее","низкое")) | H4: Лидеры контролируют значимую часть цифрового спроса | I4: Искать узкие сегменты и менее занятые каналы
A5: Органическое SEO-давление | B5: Доля органического трафика конкурентов | C5: ='03_Каналы_трафика'!C5 | D5: ='03_Каналы_трафика'!E5 | E5: 0.12 | F5: =D5*E5 | G5: =IF(D5>=5,"высокое",IF(D5>=3,"среднее","низкое")) | H5: Конкуренты занимают поисковую видимость | I5: Планировать контент, поисковую оптимизацию и долгий горизонт входа
A6: Платное рекламное давление | B6: Доля paid search + рекламная активность | C6: =AVERAGE('03_Каналы_трафика'!C6,'04_Поиск_реклама'!B37) | D6: =IF(C6>=0.6,5,IF(C6>=0.35,3,1)) | E6: 0.12 | F6: =D6*E6 | G6: =IF(D6>=5,"высокое",IF(D6>=3,"среднее","низкое")) | H6: Вход через рекламу требует бюджета | I6: Проверить стоимость клика и юнит-экономику
A7: Брендовая сила конкурентов | B7: Direct + брендовый поиск | C7: ='03_Каналы_трафика'!C10 | D7: ='03_Каналы_трафика'!E10 | E7: 0.12 | F7: =D7*E7 | G7: =IF(D7>=5,"высокое",IF(D7>=3,"среднее","низкое")) | H7: Клиенты уже знают действующих игроков | I7: Строить доверие, кейсы, репутацию и рекомендации
A8: Поисково-рекламная конкуренция | B8: CPC, PPC, SEO difficulty, рекламодатели | C8: ='04_Поиск_реклама'!B37 | D8: =IF(C8>=0.7,5,IF(C8>=0.4,3,1)) | E8: 0.12 | F8: =D8*E8 | G8: =IF(D8>=5,"высокое",IF(D8>=3,"среднее","низкое")) | H8: Коммерческие запросы заняты сильными игроками | I8: Выбирать длинные и проблемные запросы
A9: Репутационный барьер | B9: Отзывы, рейтинги, кейсы | C9: ='05_Отзывы_рейтинги'!B37 | D9: =IF(C9>=0.7,5,IF(C9>=0.4,3,1)) | E9: 0.12 | F9: =D9*E9 | G9: =IF(D9>=5,"высокое",IF(D9>=3,"среднее","низкое")) | H9: У конкурентов накоплены отзывы и социальное доказательство | I9: Запускать пилоты, собирать отзывы, демонстрировать кейсы
A10: Технологический и ресурсный барьер | B10: Стек, команда, финансирование, автоматизация | C10: ='06_Технологии_финансы'!B37 | D10: =IF(C10>=0.7,5,IF(C10>=0.4,3,1)) | E10: 0.12 | F10: =D10*E10 | G10: =IF(D10>=5,"высокое",IF(D10>=3,"среднее","низкое")) | H10: Конкуренты защищены ресурсами или цифровой инфраструктурой | I10: Фокусироваться на нише и сервисном преимуществе
A11: Платформенная зависимость | B11: Доля продаж/трафика через внешние платформы | C11: 0.33 | D11: =IF(C11>=0.7,5,IF(C11>=0.4,3,1)) | E11: 0.08 | F11: =D11*E11 | G11: =IF(D11>=5,"высокое",IF(D11>=3,"среднее","низкое")) | H11: Доступ к клиенту контролируется платформами | I11: Диверсифицировать каналы и строить собственную базу клиентов
A12: Угроза заменителей | B12: Сервисы, маркетплейсы, обучение, ИИ | C12: 0.6 | D12: =IF(C12>=0.7,5,IF(C12>=0.4,3,1)) | E12: 0.08 | F12: =D12*E12 | G12: =IF(D12>=5,"высокое",IF(D12>=3,"среднее","низкое")) | H12: Клиент может решить задачу альтернативным способом | I12: Уточнить ценность: результат, скорость, экспертиза, сопровождение
A13: Суммарный индекс барьеров входа | C13: =SUM(F4:F12) | D13: =C13 | E13: =SUM(E4:E12) | F13: =SUM(F4:F12) | G13: =IF(F13>=4,"высокие барьеры",IF(F13>=2.5,"средние барьеры","низкие барьеры")) | H13: Интегральная оценка давления | I13: Использовать как итоговый вывод для анализа входа на рынок

Sheet 08_Дашборд
A1: Дашборд оценки уровня конкуренции и барьеров входа
A2: Итоговые показатели автоматически подтягиваются из расчетных листов
A3: Similarweb PRO 30.09.2026 (Jun-Aug 2026, весь мир): листы 02-03 заполнены по 19 доменам, доля географии принята 100 % (доля Беларуси недоступна, релевантность географии не учтена). Листы 04-06 заполнены частично (нет полных строк), индекс барьеров F13 не определён
A4: KPI | B4: Значение | C4: Ед | D4: Интерпретация | F4: Фактор | G4: Балл | H4: Вес | I4: Взвешенный балл
A5: Индекс барьеров входа | B5: ='07_Барьеры_входа'!F13 | C5: 1-5 | D5: =IF(B5>=4,"Рынок труден для входа: нужны ресурсы, нишевание или сильное отличие.",IF(B5>=2.5,"Вход возможен, но требует проверки каналов и позиционирования.","Барьеры относительно низкие, но требуется проверка платежеспособности.")) | F5: Концентрация трафика | G5: ='07_Барьеры_входа'!D4 | H5: ='07_Барьеры_входа'!E4 | I5: ='07_Барьеры_входа'!F4
A6: Итоговый уровень | B6: ='07_Барьеры_входа'!G13 | F6: SEO-давление | G6: ='07_Барьеры_входа'!D5 | H6: ='07_Барьеры_входа'!E5 | I6: ='07_Барьеры_входа'!F5
A7: CR3 по релевантному трафику | B7: ='02_Конкуренты_SW'!B38 | C7: % | D7: =IF(B7>='01_Параметры'!B11,"Высокая концентрация лидеров",IF(B7>='01_Параметры'!B11*0.65,"Средняя концентрация","Низкая концентрация")) | F7: Рекламное давление | G7: ='07_Барьеры_входа'!D6 | H7: ='07_Барьеры_входа'!E6 | I7: ='07_Барьеры_входа'!F6
A8: HHI по релевантному трафику | B8: ='02_Конкуренты_SW'!B40 | C8: индекс | F8: Брендовая сила | G8: ='07_Барьеры_входа'!D7 | H8: ='07_Барьеры_входа'!E7 | I8: ='07_Барьеры_входа'!F7
A9: Средний поисково-рекламный индекс | B9: ='04_Поиск_реклама'!B37 | C9: % | F9: Поиск/реклама | G9: ='07_Барьеры_входа'!D8 | H9: ='07_Барьеры_входа'!E8 | I9: ='07_Барьеры_входа'!F8
A10: Средний индекс доверия конкурентов | B10: ='05_Отзывы_рейтинги'!B37 | C10: % | F10: Репутация | G10: ='07_Барьеры_входа'!D9 | H10: ='07_Барьеры_входа'!E9 | I10: ='07_Барьеры_входа'!F9
A11: Средний индекс ресурсной силы | B11: ='06_Технологии_финансы'!B37 | C11: % | F11: Технологии | G11: ='07_Барьеры_входа'!D10 | H11: ='07_Барьеры_входа'!E10 | I11: ='07_Барьеры_входа'!F10
F12: Платформы | G12: ='07_Барьеры_входа'!D11 | H12: ='07_Барьеры_входа'!E11 | I12: ='07_Барьеры_входа'!F11
F13: Заменители | G13: ='07_Барьеры_входа'!D12 | H13: ='07_Барьеры_входа'!E12 | I13: ='07_Барьеры_входа'!F12
A14: Итоговая формулировка для отчета
A15: Рынок инструментов диаграммирования и моделирования характеризуется низкими барьерами входа (индекс 2,32/5). Трафик высококонцентрирован: CR3 = 85,8%, HHI = 3869 — де-факто олигополия трёх лидеров (miro.com, lucidchart.com, app.diagrams.net). Поисково-рекламное давление умеренное (34,3%): конкуренция в SEO и рекламе существует, но не критична для нишевого игрока. Репутационные барьеры невысокие (средний индекс доверия 35,7%): большинство конкурентов — OSS-проекты без значимой базы отзывов. Ресурсная сила конкурентов в среднем низкая (35,9%): лишь 3 игрока (miro.com, lucidchart.com, visual-paradigm.com) располагают значительными ресурсами. Наиболее весомые факторы барьеров — концентрация трафика и брендовая сила лидеров. Рекомендуется нишевая стратегия выхода: фокус на конкретном сегменте (BPMN, ERD, PlantUML) с акцентом на локализацию для рынка СНГ, интеграции с корпоративными инструментами и качество UX.

Sheet 09_Источники
A1: Журнал источников данных для оценки конкуренции
A2: Фиксируйте дату обращения, ссылку, что именно взято и ограничения интерпретации
A3: Источник | B3: URL | C3: Что брать | D3: Для какой силы/фактора | E3: Формат фиксации | F3: Дата обращения | G3: Ограничения
A4: Similarweb | B4: https://www.similarweb.com/website/ | C4: визиты, каналы трафика, география, похожие сайты, поисковые запросы | D4: конкуренция, каналы, география, барьеры входа | E4: ручная фиксация / выгрузка при наличии доступа | F4: 30.09.2026 - PRO (пробный доступ), Jun-Aug 2026, весь мир, 19 доменов одним днём; доля Беларуси недоступна | G4: оценочные данные, слабее для малых сайтов; 30.09.2026 доступ закрыт (HTTP 403); 30.09.2026 доступ закрыт (HTTP 403); 30.09.2026 доступ закрыт (HTTP 403); пробный доступ: пять стран, доля Беларуси недоступна
A5: Semrush | B5: https://www.semrush.com/ | C5: органический трафик, paid search, keyword difficulty, конкуренты | D5: SEO и рекламное давление | E5: таблица/скриншот/экспорт при доступе | F5: 30.09.2026 - публичные страницы Website Overview (август 2026); 9 из 22 проверенных адресов в индексе | G5: часть данных платная, оценки модельные
A6: Ahrefs | B6: https://ahrefs.com/ | C6: ссылки, ключевые слова, органическая видимость, конкуренты | D6: SEO-барьеры | E6: таблица/экспорт при доступе | F6: 30.09.2026 - бесплатная проверка трафика не вернула результат; не использовался | G6: зависит от базы и тарифа
A7: G2 | B7: https://www.g2.com/ | C7: отзывы, рейтинги, сравнения, категории B2B-софта | D7: сила покупателей, репутация, заменители | E7: таблица отзывов и рейтингов | F7: 30.09.2026 - 3 карточки (Miro, Lucid, Mermaid); остальные не найдены | G7: сильнее для программных продуктов
A8: Capterra | B8: https://www.capterra.com/ | C8: отзывы и рейтинги программных решений | D8: репутация и заменители | E8: таблица отзывов | F8: 30.09.2026 - переход отклонён; не использовался | G8: не все локальные рынки представлены
A9: Trustpilot | B9: https://www.trustpilot.com/ | C9: отзывы, рейтинг, динамика доверия | D9: репутационные барьеры | E9: таблица/скриншот | F9: 30.09.2026 - 23 проверенных адреса, профили найдены у 9 | G9: разная полнота по странам и нишам
A10: Crunchbase | B10: https://www.crunchbase.com/ | C10: финансирование, сделки, инвесторы, рост компаний | D10: угроза новых игроков, ресурсная сила | E10: таблица компаний | F10: 30.09.2026 - проверка Cloudflare; не использовался | G10: многие данные доступны по подписке
A11: BuiltWith | B11: https://builtwith.com/ | C11: технологический стек сайта | D11: технологические барьеры | E11: таблица технологий | F11: не использовался - технологии проверены частично по главным страницам | G11: не показывает всю внутреннюю инфраструктуру
A12: Wappalyzer | B12: https://www.wappalyzer.com/ | C12: технологии сайта, аналитика, CRM, e-commerce stack | D12: технологические барьеры | E12: таблица технологий | F12: не использовался - технологии проверены частично по главным страницам | G12: только видимые технологии
A13: Meta Ad Library | B13: https://www.facebook.com/ads/library/ | C13: активные рекламные объявления | D13: рекламное давление | E13: ссылка/скриншот/число объявлений | F13: не использовался - реклама конкурентов не изучалась | G13: не дает полный бюджет
A14: Google Ads Transparency Center | B14: https://adstransparency.google.com/ | C14: объявления рекламодателей в Google | D14: рекламное давление | E14: ссылка/скриншот | F14: не использовался - реклама конкурентов не изучалась | G14: не всегда видно бюджет и эффективность
... A23: Сайты конкурентов (лист 02) | B23: адреса в листе 02_Конкуренты_SW | C23: тарифы, кейсы, технологии, приложение | D23: силы 1, 3, 5; карточки | E23: скриншот/таблица | F23: 30.09.2026 - главные страницы, RDAP доменов | G23: публичные страницы, условия меняются
