Workbook

Sheet 11_Вариант_М2
A1: Вариант по М2 (табл. 9, 11, 21): охват 0,45 / 0,65 / 0,85; коммерчески релевантная доля 20 / 35 / 50 %; годовой объём = месячный × 12
A3: Показатель | B3: Осторожный | C3: Базовый | D3: Оптимистичный | E3: Комментарий
A4: V_sample: визиты выборки, мес. (Σ) | B4: =SUM('02_Конкуренты_SW'!E4:E23) | C4: =SUM('02_Конкуренты_SW'!E4:E23) | D4: =SUM('02_Конкуренты_SW'!E4:E23) | E4: М2 табл. 8
A5: Доля географии (РБ), Д-01 | B5: ='02_Конкуренты_SW'!F4 | C5: ='02_Конкуренты_SW'!F4 | D5: ='02_Конкуренты_SW'!F4
A6: V_geo = V_sample × доля географии | B6: =B4*B5 | C6: =C4*C5 | D6: =D4*D5
A7: Коэффициент охвата выборки | B7: 0.45 | C7: 0.65 | D7: 0.85 | E7: М2 табл. 21 (шкала табл. 9: 0,40–0,55 / 0,60–0,75 / 0,80–0,90)
A8: V_total = V_geo / охват | B8: =B6/B7 | C8: =C6/C7 | D8: =D6/D7 | E8: Осторожный сценарий даёт БОЛЬШЕ трафика (W-15)
A9: Коммерчески релевантная доля | B9: 0.2 | C9: 0.35 | D9: 0.5 | E9: М2 табл. 21
A10: Коммерчески релевантные визиты, мес | B10: =B8*B9 | C10: =C8*C9 | D10: =D8*D9
A11: CR1 (визит → заявка) | B11: 0.0035 | C11: 0.01 | D11: 0.0225 | E11: середины диапазонов М2 табл. 11
A12: CR2 (заявка → оплата Pro) | B12: 0.03 | C12: 0.04 | D12: 0.05 | E12: допущение проекта Free → Pro 3–5 % (шкала М2 5–40 % для freemium неприменима)
A13: Средний чек, BYN/год | B13: 121.14 | C13: 121.14 | D13: 290.74 | E13: 40 у.е./год (осторожный, базовый); медиана входных тарифов конкурентов
A14: Месячный объём, BYN | B14: =B10*B11*B12*B13 | C14: =C10*C11*C12*C13 | D14: =D10*D11*D12*D13
A15: Годовой объём, BYN (× 12, М2) | B15: =B14*12 | C15: =C14*12 | D15: =D14*12 | E15: М2: × 12 (в SW-X: × 12 × покупок)
A16: Достижимая доля (SOM) | B16: 0.005 | C16: 0.015 | D16: 0.035 | E16: как в листе 06
A17: SOM, BYN/год | B17: =B15*B16 | C17: =C15*C16 | D17: =D15*D16

Sheet 10_TAM_SAM_SOM_М1
A1: TAM / SAM / SOM цифрового внимания по М1 табл. 22 (базовый сценарий листа 06)
A3: TAM цифрового внимания: суммарный трафик релевантных сайтов категории, визиты/мес | B3: =SUM('02_Конкуренты_SW'!E4:E23)
A4: Доля страны (Беларусь), допущение Д-01 | B4: ='02_Конкуренты_SW'!F4
A5: SAM по географии, визиты/мес. = TAM × доля страны | B5: =B3*B4
A6: Доля релевантных каналов (Organic Search, plantuml.com) | B6: ='03_Каналы'!B5
A7: SAM по каналу, визиты/мес | B7: =B5*B6
A8: Достижимая доля (базовая, лист 06) | B8: ='06_Воронка_сценарии'!C13
A9: SOM по трафику, визиты/мес. = SAM × достижимая доля | B9: =B7*B8
A10: CR1 (лист 06, базовый) | B10: ='06_Воронка_сценарии'!D6
A11: CR2 (лист 06, базовый) | B11: ='06_Воронка_сценарии'!E6
A12: Средний чек, BYN (лист 06) | B12: ='06_Воронка_сценарии'!F6
A13: Число покупок в год | B13: ='06_Воронка_сценарии'!G6
A14: SOM по выручке, BYN/год = SOM по трафику × 12 × CR1 × CR2 × чек × число покупок | B14: =B9*12*B10*B11*B12*B13
A15: Проверка конкурентами: средняя выручка конкурента (при параметрах NotaCode), BYN/год | B15: =AVERAGE('02_Конкуренты_SW'!G4:G7)*12*B10*B11*B12*B13
A16: Число активных конкурентов в выборке | B16: ='01_Параметры'!B8
A17: Проверка конкурентами: сумма, BYN/год | B17: =B15*B16
A20: Канальный SAM рассчитан по доле Organic одного домена (plantuml.com) — остальные доли в бесплатном доступе не показаны. Проверка поиском — лист 05_Запросы

Sheet 09_Концентрация
A1: Концентрация цифрового трафика: CR3, CR5, HHI (дополнение к шаблону, Р-42; М1 §7.2, М2 §12)
A3: Домен | B3: Визиты/мес. (сырые) | C3: Доля по сырым визитам (М1 ф. 2, SWБ §7) | D3: Доля² × 10 000 (сырые) | E3: Релевантные визиты (РБ) | F3: Доля по релевантным визитам (М2 §7) | G3: Доля² × 10 000 (релевантные) | H3: Доля релевантного трафика (Д-02) | I3: Релевантные визиты с учётом Д-02 | J3: Доля по визитам с учётом Д-02 | K3: Доля² × 10 000 (с учётом Д-02)
A4: ='02_Конкуренты_SW'!A4 | B4: ='02_Конкуренты_SW'!E4 | C4: =B4/SUM($B\$4:$B\$7) | D4: =C4^2*10000 | E4: ='02_Конкуренты_SW'!G4 | F4: =E4/SUM($E\$4:$E\$7) | G4: =F4^2*10000 | H4: 0.75 | I4: =E4*H4 | J4: =I4/SUM($I\$4:$I\$7) | K4: =J4^2*10000
A5: ='02_Конкуренты_SW'!A5 | B5: ='02_Конкуренты_SW'!E5 | C5: =B5/SUM($B\$4:$B\$7) | D5: =C5^2*10000 | E5: ='02_Конкуренты_SW'!G5 | F5: =E5/SUM($E\$4:$E\$7) | G5: =F5^2*10000 | H5: 0.35 | I5: =E5*H5 | J5: =I5/SUM($I\$4:$I\$7) | K5: =J5^2*10000
A6: ='02_Конкуренты_SW'!A6 | B6: ='02_Конкуренты_SW'!E6 | C6: =B6/SUM($B\$4:$B\$7) | D6: =C6^2*10000 | E6: ='02_Конкуренты_SW'!G6 | F6: =E6/SUM($E\$4:$E\$7) | G6: =F6^2*10000 | H6: 0.5 | I6: =E6*H6 | J6: =I6/SUM($I\$4:$I\$7) | K6: =J6^2*10000
A7: ='02_Конкуренты_SW'!A7 | B7: ='02_Конкуренты_SW'!E7 | C7: =B7/SUM($B\$4:$B\$7) | D7: =C7^2*10000 | E7: ='02_Конкуренты_SW'!G7 | F7: =E7/SUM($E\$4:$E\$7) | G7: =F7^2*10000 | H7: 0.7 | I7: =E7*H7 | J7: =I7/SUM($I\$4:$I\$7) | K7: =J7^2*10000
A9: Сумма | B9: =SUM(B4:B7) | D9: =SUM(D4:D7) | E9: =SUM(E4:E7) | G9: =SUM(G4:G7) | I9: =SUM(I4:I7) | K9: =SUM(K4:K7)
A11: Показатель | B11: По сырым визитам | C11: По релевантным визитам | D11: С учётом доли релевантного (Д-02)
A12: CR3, % | B12: =(LARGE(C4:C7,1)+LARGE(C4:C7,2)+LARGE(C4:C7,3))*100 | C12: =(LARGE(F4:F7,1)+LARGE(F4:F7,2)+LARGE(F4:F7,3))*100 | D12: =(LARGE(J4:J7,1)+LARGE(J4:J7,2)+LARGE(J4:J7,3))*100
A13: CR5, % | B13: =SUM(C4:C7)*100 | C13: =SUM(F4:F7)*100 | D13: =SUM(J4:J7)*100
A14: HHI = Σ (доля в %)² | B14: =D9 | C14: =G9 | D14: =K9
A15: Уровень по шкале М2 табл. 16 | B15: =IF(B14<1500,"низкая концентрация",IF(B14<=2500,"умеренная","высокая")) | C15: =IF(C14<1500,"низкая концентрация",IF(C14<=2500,"умеренная","высокая")) | D15: =IF(D14<1500,"низкая концентрация",IF(D14<=2500,"умеренная","высокая"))
A16: Проверка: HHI ≥ CR3² / 3 | B16: =IF(B14>=B12^2/3,"выполняется","НЕ выполняется") | C16: =IF(C14>=C12^2/3,"выполняется","НЕ выполняется") | D16: =IF(D14>=D12^2/3,"выполняется","НЕ выполняется")
A18: Пояснения: шкала М2 табл. 16 — до 1 500 низкая, 1 500–2 500 умеренная, выше 2 500 высокая; М1 табл. 10 задаёт три качественных уровня без чисел. Значения — оценка концентрации ЦИФРОВОГО ТРАФИКА выборки из 4 доменов (не выручки и не рыночной власти); CR5 при 4 доменах равен 100 %. Выборка меньше минимума М2 (5 доменов) и состоит из доменов разных типов; доминирует универсальный редактор draw.io

Sheet 00_Методика
A1: Методика оценки объема рынка электронного бизнеса по данным Similarweb
A3: Блок | B3: Цель | C3: Действие | D3: Что фиксировать | E3: Расчетный результат | F3: Ограничения | G3: Лист Excel | H3: Выходной вывод
A4: 1. Границы рынка | B4: Уточнить, какой рынок оценивается | C4: Зафиксировать продукт, географию, аудиторию и цифровые каналы | D4: Название рынка, территория, период, сегменты | E4: Паспорт расчетной модели | F4: Без границ рынка трафик конкурентов нельзя трактовать как объем рынка | G4: 01_Параметры | H4: Что именно считается рынком
A5: 2. Конкуренты | B5: Определить ядро цифрового рынка | C5: Собрать сайты прямых и частичных конкурентов | D5: Домен, сегмент, тип конкурента | E5: Список цифровых игроков | F5: Малые сайты могут отображаться неполно | G5: 02_Конкуренты_SW | H5: Кто формирует цифровое предложение
A6: 3. Трафик | B6: Оценить цифровой масштаб сегмента | C6: Внести посещения, географическую долю и релевантность | D6: Monthly visits, доля выбранной географии, релевантная доля | E6: Релевантный месячный и годовой трафик | F6: Трафик не равен покупкам | G6: 02_Конкуренты_SW | H6: Насколько велик цифровой поток аудитории
A7: 4. Каналы | B7: Понять структуру привлечения аудитории | C7: Разложить трафик по Direct, Organic, Referral, Social, Paid, Mail, Display | D7: Доли каналов по конкурентам | E7: Канальная структура рынка | F7: Доли каналов оценочные | G7: 03_Каналы | H7: Какие каналы важны для входа на рынок
A8: 5. География | B8: Проверить территориальную концентрацию спроса | C8: Сопоставить страны/регионы по доле трафика | D8: Страна, доля, интерпретация | E8: Приоритетные географии | F8: Доля трафика не равна платежеспособности | G8: 04_География | H8: Где целесообразно анализировать рынок
A9: 6. Поиск | B9: Определить коммерческий спрос внутри трафика | C9: Зафиксировать ключевые запросы и намерение аудитории | D9: Запрос, доля или объем, тип намерения | E9: Индекс коммерческого интереса | F9: Запросы видны неполно в бесплатном доступе | G9: 05_Запросы | H9: Какие потребности приводят аудиторию
A10: 7. Воронка | B10: Перевести трафик в возможные заказы | C10: Задать конверсии и средний чек | D10: CR в заявку, CR в продажу, средний чек | E10: Оценка объема рынка в деньгах | F10: Конверсии задаются сценарно | G10: 06_Воронка_сценарии | H10: Диапазон рынка по сценариям
A11: 8. Проверка | B11: Снизить риск завышения оценки | C11: Сопоставить расчет с другими источниками | D11: Google Trends, Вордстат, статистика, рекламные кабинеты | E11: Уточненный диапазон оценки | F11: Источники измеряют разные показатели | G11: 08_Источники | H11: Насколько расчет устойчив
A13: Ключевая расчетная логика
A14: 1 | B14: Наблюдаемый цифровой сегмент | C14: Сумма релевантного трафика выбранных конкурентов | D14: = сумма посещений × доля географии × доля релевантности
A15: 2 | B15: Оценка всего цифрового рынка | C15: Наблюдаемый сегмент / коэффициент покрытия конкурентов | D15: Если список конкурентов покрывает 70% рынка, общий рынок = наблюдаемый трафик / 70%
A16: 3 | B16: Оценка заявок | C16: Рыночный трафик × конверсия в заявку | D16: Конверсия задается по сценариям
A17: 4 | B17: Оценка продаж | C17: Заявки × конверсия в продажу | D17: Отражает платежеспособный спрос
A18: 5 | B18: Денежный объем | C18: Продажи × средний чек × повторные покупки | D18: Итоговый объем рынка за год

Sheet 01_Параметры
A1: Параметры оценки рынка
A3: Параметр | B3: Значение | C3: Единица / формат | D3: Комментарий
A4: Название рынка | B4: Веб-инструменты построения и проверки диаграмм формальных нотаций (UML, BPMN, ERD, IDEF, DFD) для студентов и специалистов по ПО | C4: текст | D4: Замените на ваш рынок
A5: Географическая граница | B5: Республика Беларусь | C5: текст | D5: Страна, регион или город
A6: Период анализа | B6: последние 3 месяца (июнь–август 2026); требование М1 «не менее 12 мес.» при бесплатном доступе невыполнимо | C6: текст | D6: Период, показанный в Similarweb
A7: Дата фиксации данных | B7: 29.09.2026 | C7: дата | D7: Дата ручного сбора или выгрузки
A8: Количество конкурентов в выборке | B8: =COUNT('02_Конкуренты_SW'!E4:E23) | C8: формула | D8: Заполняется автоматически
A9: Наблюдаемый релевантный трафик, мес | B9: =SUM('02_Конкуренты_SW'!G4:G23) | C9: посещения | D9: Исправлено в рабочей копии (П-1): суммирование с 4-й строки; в шаблоне диапазон G5:G24 терял первого конкурента
A10: Наблюдаемый релевантный трафик, год | B10: =SUM('02_Конкуренты_SW'!H4:H23) | C10: посещения | D10: Исправлено (П-1): H4:H23
A11: Коэффициент покрытия конкурентов | B11: 0.7 | C11: % | D11: Значение шаблона (базовый сценарий листа 06 — 0,7); шкала М2 табл. 9 для типовой ситуации 0,60–0,75
A12: Оценка всего цифрового трафика рынка, мес | B12: =IFERROR(B9/B11,0) | C12: посещения | D12: Наблюдаемый трафик / покрытие
A13: Оценка всего цифрового трафика рынка, год | B13: =IFERROR(B10/B11,0) | C13: посещения | D13: Наблюдаемый трафик / покрытие
A15: Правила заполнения
A16: 1 | B16: Сначала зафиксируйте границы рынка | C16: Без этого нельзя решить, какие сайты считать конкурентами
A17: 2 | B17: В Similarweb соберите данные по 5–20 сайтам | C17: Чем шире выборка, тем устойчивее оценка
A18: 3 | B18: Вносите только сопоставимый период | C18: Например, последние 3 месяца для всех сайтов
A19: 4 | B19: Разделяйте весь трафик и релевантный трафик | C19: Не все посещения сайта относятся к анализируемому рынку
A20: 5 | B20: Итог давайте диапазоном | C20: Осторожный, базовый и оптимистичный сценарии

Sheet 02_Конкуренты_SW
A1: Ввод данных Similarweb по конкурентам
A3: Домен | B3: Название / конкурент | C3: Сегмент | D3: Тип | E3: Monthly visits | F3: Доля выбранной географии | G3: Релевантный трафик, мес | H3: Релевантный трафик, год | I3: Доля рынка по трафику | J3: Bounce rate | K3: Pages / visit | L3: Avg duration | M3: Direct | N3: Organic search | O3: Referral | P3: Social | Q3: Paid search | R3: Display | S3: Комментарий
A4: plantuml.com | B4: PlantUML | C4: диаграммы по тексту | D4: прямой | E4: 507000 | F4: 0.001958 | G4: =IFERROR(E4*F4,0) | H4: =G4*12 | I4: =IFERROR(G4/SUM($G\$4:$G\$23),0) | J4: 0.4552 | K4: 3.18 | L4: 00:03:16 | N4: 0.4847 | S4: ФАКТ (Similarweb, авг. 2026, скриншот). Доля РБ — допущение Д-01 (Similarweb не показывает). Каналы: бесплатная карточка показывает только Organic (plantuml.com); остальные — «нет данных в бесплатном доступе»
A5: app.diagrams.net | B5: draw.io (diagrams.net) | C5: визуальные редакторы | D5: заменитель | E5: 7800000 | F5: 0.001958 | G5: =IFERROR(E5*F5,0) | H5: =G5*12 | I5: =IFERROR(G5/SUM($G\$4:$G\$23),0) | S5: отчёт ЛР1, без скриншота. Доля РБ — допущение Д-01 (Similarweb не показывает). Каналы: бесплатная карточка показывает только Organic (plantuml.com); остальные — «нет данных в бесплатном доступе»
A6: eraser.io | B6: Eraser | C6: диаграммы по тексту | D6: прямой | E6: 678500 | F6: 0.001958 | G6: =IFERROR(E6*F6,0) | H6: =G6*12 | I6: =IFERROR(G6/SUM($G\$4:$G\$23),0) | S6: предварительный замер 17–23.09.2026, не подтверждён. Доля РБ — допущение Д-01 (Similarweb не показывает). Каналы: бесплатная карточка показывает только Organic (plantuml.com); остальные — «нет данных в бесплатном доступе»
A7: mermaidchart.com | B7: Mermaid Chart | C7: диаграммы по тексту | D7: прямой | E7: 20000 | F7: 0.001958 | G7: =IFERROR(E7*F7,0) | H7: =G7*12 | I7: =IFERROR(G7/SUM($G\$4:$G\$23),0) | S7: предварительный замер: «менее 20 тыс.» (верхняя граница), не подтверждён. Доля РБ — допущение Д-01 (Similarweb не показывает). Каналы: бесплатная карточка показывает только Organic (plantuml.com); остальные — «нет данных в бесплатном доступе»
G8: =IFERROR(E8*F8,0) | H8: =G8*12 | I8: =IFERROR(G8/SUM($G\$4:$G\$23),0)
G9: =IFERROR(E9*F9,0) | H9: =G9*12 | I9: =IFERROR(G9/SUM($G\$4:$G\$23),0)
G10: =IFERROR(E10*F10,0) | H10: =G10*12 | I10: =IFERROR(G10/SUM($G\$4:$G\$23),0)
G11: =IFERROR(E11*F11,0) | H11: =G11*12 | I11: =IFERROR(G11/SUM($G\$4:$G\$23),0)
G12: =IFERROR(E12*F12,0) | H12: =G12*12 | I12: =IFERROR(G12/SUM($G\$4:$G\$23),0)
G13: =IFERROR(E13*F13,0) | H13: =G13*12 | I13: =IFERROR(G13/SUM($G\$4:$G\$23),0)
G14: =IFERROR(E14*F14,0) | H14: =G14*12 | I14: =IFERROR(G14/SUM($G\$4:$G\$23),0)
G15: =IFERROR(E15*F15,0) | H15: =G15*12 | I15: =IFERROR(G15/SUM($G\$4:$G\$23),0)
G16: =IFERROR(E16*F16,0) | H16: =G16*12 | I16: =IFERROR(G16/SUM($G\$4:$G\$23),0)
G17: =IFERROR(E17*F17,0) | H17: =G17*12 | I17: =IFERROR(G17/SUM($G\$4:$G\$23),0)
G18: =IFERROR(E18*F18,0) | H18: =G18*12 | I18: =IFERROR(G18/SUM($G\$4:$G\$23),0)
G19: =IFERROR(E19*F19,0) | H19: =G19*12 | I19: =IFERROR(G19/SUM($G\$4:$G\$23),0)
... G23: =IFERROR(E23*F23,0) | H23: =G23*12 | I23: =IFERROR(G23/SUM($G\$4:$G\$23),0)
A25: ИТОГО / среднее | E25: =SUM(E4:E23) | G25: =SUM(G4:G23) | H25: =SUM(H4:H23) | I25: =SUM(I4:I23) | J25: =AVERAGE(J4:J23) | K25: =AVERAGE(K4:K23) | M25: =IFERROR(SUMPRODUCT($G\$4:$G\$23,M4:M23)/SUMIF(M4:M23,">0",$G\$4:$G\$23),0) | N25: =IFERROR(SUMPRODUCT($G\$4:$G\$23,N4:N23)/SUMIF(N4:N23,">0",$G\$4:$G\$23),0) | O25: =IFERROR(SUMPRODUCT($G\$4:$G\$23,O4:O23)/SUMIF(O4:O23,">0",$G\$4:$G\$23),0) | P25: =IFERROR(SUMPRODUCT($G\$4:$G\$23,P4:P23)/SUMIF(P4:P23,">0",$G\$4:$G\$23),0) | Q25: =IFERROR(SUMPRODUCT($G\$4:$G\$23,Q4:Q23)/SUMIF(Q4:Q23,">0",$G\$4:$G\$23),0) | R25: =IFERROR(SUMPRODUCT($G\$4:$G\$23,R4:R23)/SUMIF(R4:R23,">0",$G\$4:$G\$23),0)
A27: Каналы: у plantuml.com показана только доля Organic Search 48,47 %; Direct и Referrals названы 2-м и 3-м без долей, Social, Paid, Mail, Display бесплатная карточка не показывает. Средневзвешенные доли каналов (строка 25) в копии считаются только по строкам, где доля показана (П-18)

Sheet 03_Каналы
A1: Канальная структура рынка по данным Similarweb
A3: Канал | B3: Средневзвешенная доля | C3: Оценка рыночного трафика, мес | D3: Оценка рыночного трафика, год | E3: Коммерческая интерпретация | F3: Что проверить дополнительно | G3: Ограничение | H3: Приоритет
A4: Direct | B4: ='02_Конкуренты_SW'!M25 | C4: =B4*'01_Параметры'!$B\$12 | D4: =C4*12 | E4: Сила бренда и повторные посещения | F4: Узнаваемость конкурентов, прямые заходы | G4: Не всегда означает новый спрос | H4: нет данных
A5: Organic search | B5: ='02_Конкуренты_SW'!N25 | C5: =B5*'01_Параметры'!$B\$12 | D5: =C5*12 | E5: Поисковый спрос и эффективность содержания | F5: Семантическое ядро, видимость в поиске | G5: Запросы могут быть информационными | H5: =IF(B5>=0.3,"высокий",IF(B5>=0.15,"средний","низкий"))
A6: Referral | B6: ='02_Конкуренты_SW'!O25 | C6: =B6*'01_Параметры'!$B\$12 | D6: =C6*12 | E6: Партнерские и справочные источники | F6: Каталоги, публикации, партнеры | G6: Часть переходов может быть нерелевантна | H6: нет данных
A7: Social | B7: ='02_Конкуренты_SW'!P25 | C7: =B7*'01_Параметры'!$B\$12 | D7: =C7*12 | E7: Спрос через социальные сети | F7: Активность в соцсетях и сообществах | G7: Социальный трафик не всегда конверсионный | H7: нет данных
A8: Paid search | B8: ='02_Конкуренты_SW'!Q25 | C8: =B8*'01_Параметры'!$B\$12 | D8: =C8*12 | E8: Платный спрос и рекламная конкуренция | F8: Стоимость клика, рекламные объявления | G8: Высокая доля может отражать закупку трафика | H8: нет данных
A9: Display | B9: ='02_Конкуренты_SW'!R25 | C9: =B9*'01_Параметры'!$B\$12 | D9: =C9*12 | E9: Медийная реклама и охват | F9: Баннеры, ретаргетинг | G9: Слабее связан с намерением покупки | H9: нет данных
A11: Показан только Organic (plantuml.com); остальные доли — «нет данных в бесплатном доступе»; приоритет по каналам, кроме Organic, не определяется

Sheet 04_География
A1: Географическая структура цифрового рынка
A3: Страна / регион | B3: Доля трафика по Similarweb | C3: Оценка месячного трафика рынка | D3: Оценка годового трафика рынка | E3: Платежеспособность / доступность | F3: Конкурентная плотность | G3: Приоритет рынка | H3: Комментарий | I3: Корректно (П-10): трафик до географического сужения × доля, мес | J3: Корректно, год
A4: Республика Беларусь | B4: 0.001958 | C4: =B4*'01_Параметры'!$B\$12 | D4: =C4*12 | E4: средняя | F4: средняя | G4: =IF(B4>=0.35,"высокий",IF(B4>=0.15,"средний","низкий")) | H4: Основная география (В-6). Доля — допущение Д-01 | I4: =B4*SUM('02_Конкуренты_SW'!$E\$4:$E\$23)/'01_Параметры'!$B\$11 | J4: =I4*12
A5: Минск (город) | B5: 0.001428 | C5: =B5*'01_Параметры'!$B\$12 | D5: =C5*12 | E5: выше средней | F5: высокая | G5: =IF(B5>=0.35,"высокий",IF(B5>=0.15,"средний","низкий")) | H5: Вордстат, plantuml: Минск 124 из 170 запросов РБ (73 %), окно 29.08–27.09.2026 | I5: =B5*SUM('02_Конкуренты_SW'!$E\$4:$E\$23)/'01_Параметры'!$B\$11 | J5: =I5*12
A6: Остальная Беларусь (включая областные центры) | B6: 0.00053 | C6: =B6*'01_Параметры'!$B\$12 | D6: =C6*12 | E6: средняя | F6: средняя | G6: =IF(B6>=0.35,"высокий",IF(B6>=0.15,"средний","низкий")) | H6: Разница; данных по областным центрам нет | I6: =B6*SUM('02_Конкуренты_SW'!$E\$4:$E\$23)/'01_Параметры'!$B\$11 | J6: =I6*12
A7: Россия (другие русскоязычные рынки) | B7: 0.0907 | C7: =B7*'01_Параметры'!$B\$12 | D7: =C7*12 | E7: разная | F7: высокая | G7: =IF(B7>=0.35,"высокий",IF(B7>=0.15,"средний","низкий")) | H7: Similarweb, plantuml.com, август 2026: 9,07 % (факт); гипотеза расширения, вне итогового диапазона (В-6) | I7: =B7*SUM('02_Конкуренты_SW'!$E\$4:$E\$23)/'01_Параметры'!$B\$11 | J7: =I7*12
A9: В шаблоне (столбцы C, D) доля умножается на B12 — трафик, уже суженный до Беларуси (П-10); корректный вариант — столбцы I, J

Sheet 05_Запросы
A1: Поисковые запросы и коммерческий интерес
A3: Запрос / ключевая фраза | B3: Источник | C3: Доля поискового трафика | D3: Оценочный месячный трафик | E3: Тип намерения | F3: Коммерческий вес | G3: Индекс коммерческого интереса | H3: Сегмент | I3: Решение | J3: Комментарий | K3: Корректно (П-11): D × доля Organic
A4: uml купить | B4: Яндекс Вордстат (РБ, Топы, 30 дней) | C4: 0.0068 | D4: =C4*'01_Параметры'!$B\$12 | E4: коммерческий | F4: 1 | G4: =D4*F4 | H4: S-02/S-03 | I4: включить | J4: Частотность 5 запр./мес.; доля — среди перечисленных запросов (Similarweb долей запросов в бесплатном доступе не показывает) | K4: =D4*'03_Каналы'!$B\$5
A5: visio купить | B5: Яндекс Вордстат (РБ, Топы, 30 дней) | C5: 0.0096 | D5: =C5*'01_Параметры'!$B\$12 | E5: коммерческий | F5: 1 | G5: =D5*F5 | H5: S-02/S-03 | I5: включить (конкурент) | J5: Частотность 7 запр./мес.; доля — среди перечисленных запросов (Similarweb долей запросов в бесплатном доступе не показывает) | K5: =D5*'03_Каналы'!$B\$5
A6: нейросеть схема | B6: Яндекс Вордстат (РБ, Топы, 30 дней) | C6: 0.1038 | D6: =C6*'01_Параметры'!$B\$12 | E6: инструментальный | F6: 0.7 | G6: =D6*F6 | H6: все | I6: включить | J6: Частотность 76 запр./мес.; доля — среди перечисленных запросов (Similarweb долей запросов в бесплатном доступе не показывает) | K6: =D6*'03_Каналы'!$B\$5
A7: uml онлайн | B7: Яндекс Вордстат (РБ, Топы, 30 дней) | C7: 0.0383 | D7: =C7*'01_Параметры'!$B\$12 | E7: инструментальный | F7: 0.7 | G7: =D7*F7 | H7: S-01/S-03 | I7: включить | J7: Частотность 28 запр./мес.; доля — среди перечисленных запросов (Similarweb долей запросов в бесплатном доступе не показывает) | K7: =D7*'03_Каналы'!$B\$5
A8: plantuml online | B8: Яндекс Вордстат (РБ, Топы, 30 дней) | C8: 0.0191 | D8: =C8*'01_Параметры'!$B\$12 | E8: инструментальный | F8: 0.7 | G8: =D8*F8 | H8: S-03 | I8: включить | J8: Частотность 14 запр./мес.; доля — среди перечисленных запросов (Similarweb долей запросов в бесплатном доступе не показывает) | K8: =D8*'03_Каналы'!$B\$5
A9: idef0 как | B9: Яндекс Вордстат (РБ, Топы, 30 дней) | C9: 0.015 | D9: =C9*'01_Параметры'!$B\$12 | E9: проблемный | F9: 0.6 | G9: =D9*F9 | H9: S-01 | I9: включить | J9: Частотность 11 запр./мес.; доля — среди перечисленных запросов (Similarweb долей запросов в бесплатном доступе не показывает) | K9: =D9*'03_Каналы'!$B\$5
A10: uml | B10: Яндекс Вордстат (РБ, Топы, 30 дней) | C10: 0.8074 | D10: =C10*'01_Параметры'!$B\$12 | E10: информационный | F10: 0.1 | G10: =D10*F10 | H10: S-01 | I10: исключить (не подтверждает платёжеспособный спрос) | J10: Частотность 591 запр./мес.; доля — среди перечисленных запросов (Similarweb долей запросов в бесплатном доступе не показывает) | K10: =D10*'03_Каналы'!$B\$5
A12: Столбец D в шаблоне = доля × трафик всего рынка (П-11), что вероятно завышает поисковую часть; в столбце K — умножение на долю Organic (48,47 %, plantuml.com). Веса намерений SW-X (проблемный 0,6–0,8, информационный 0,1) отличаются от ПС табл. 9 (проблемный 0,30–0,60) — Р-44

Sheet 06_Воронка_сценарии
A1: Расчет объема рынка через цифровую воронку и сценарии
A3: Сценарные допущения
A4: Сценарий | B4: Коэффициент покрытия конкурентов | C4: Оценка рынка: посещения/мес | D4: Конверсия в заявку | E4: Конверсия заявки в продажу | F4: Средний чек | G4: Покупок/клиента в год | H4: Заказов/мес | I4: Выручка/мес | J4: Выручка/год
A5: Осторожный | B5: 0.8 | C5: =IFERROR('01_Параметры'!$B\$9/B5,0) | D5: 0.008 | E5: 0.03 | F5: 121.14 | G5: 1 | H5: =C5*D5*E5 | I5: =H5*F5 | J5: =I5*12*G5
A6: Базовый | B6: 0.7 | C6: =IFERROR('01_Параметры'!$B\$9/B6,0) | D6: 0.015 | E6: 0.04 | F6: 121.14 | G6: 1 | H6: =C6*D6*E6 | I6: =H6*F6 | J6: =I6*12*G6
A7: Оптимистичный | B7: 0.55 | C7: =IFERROR('01_Параметры'!$B\$9/B7,0) | D7: 0.025 | E7: 0.05 | F7: 290.74 | G7: 1 | H7: =C7*D7*E7 | I7: =H7*F7 | J7: =I7*12*G7
A10: Достижимая доля нового бизнеса (SOM)
A11: Сценарий | B11: Рыночная выручка/год | C11: Достижимая доля нового бизнеса | D11: Потенциальная выручка нового бизнеса/год | E11: Комментарий | F11: Ограничение
A12: Осторожный | B12: =J5 | C12: 0.005 | D12: =B12*C12 | E12: Первые клиенты, тестирование канала | F12: Не учитывать как гарантированный доход
A13: Базовый | B13: =J6 | C13: 0.015 | D13: =B13*C13 | E13: Устойчивый канал привлечения | F13: Требуется конкурентный анализ
A14: Оптимистичный | B14: =J7 | C14: 0.035 | D14: =B14*C14 | E14: Сильное позиционирование и повторные продажи | F14: Требуется подтверждение продажами
A17: Формула итогового вывода
A18: Оценочный цифровой объем рынка за год определяется как диапазон между осторожным и оптимистичным сценариями
A19: Минимум | C19: База | E19: Максимум | G19: Единица | H19: руб./год
A20: =A12 | B20: =D12 | C20: =A13 | D20: =D13 | E20: =A14 | F20: =D14
A21: Рыночная выручка минимум | B21: =J5 | C21: Рыночная выручка база | D21: =J6 | E21: Рыночная выручка максимум | F21: =J7
A22: Вывод | B22: ="При заданных допущениях годовой объем цифрового рынка оценивается в диапазоне от "&TEXT(J5,"# ##0")&" до "&TEXT(J7,"# ##0")&" руб., а достижимая выручка нового бизнеса — от "&TEXT(D12,"# ##0")&" до "&TEXT(D14,"# ##0")&" руб. в год."

Sheet 07_Дашборд
A1: Итоговая панель оценки объема рынка по Similarweb
A3: Ключевые показатели
A4: Рынок | B4: ='01_Параметры'!B4 | C4: География | D4: ='01_Параметры'!B5 | E4: Конкурентов | F4: ='01_Параметры'!B8 | G4: Наблюдаемый трафик/мес | H4: ='01_Параметры'!B9 | I4: Оценка трафика рынка/мес | J4: ='01_Параметры'!B12
A5: Осторожный рынок/год | B5: ='06_Воронка_сценарии'!J5 | C5: Базовый рынок/год | D5: ='06_Воронка_сценарии'!J6 | E5: Оптимистичный рынок/год | F5: ='06_Воронка_сценарии'!J7 | G5: SOM базовый/год | H5: ='06_Воронка_сценарии'!D13 | I5: Главный канал | J5: =INDEX('03_Каналы'!A4:A9,MATCH(MAX('03_Каналы'!B4:B9),'03_Каналы'!B4:B9,0))
A6: Главный конкурент | B6: =INDEX('02_Конкуренты_SW'!B4:B23,MATCH(MAX('02_Конкуренты_SW'!G4:G23),'02_Конкуренты_SW'!G4:G23,0)) | C6: Доля главного конкурента | D6: =MAX('02_Конкуренты_SW'!I4:I23) | E6: Главный поисковый запрос | F6: =INDEX('05_Запросы'!A4:A10,MATCH(MAX('05_Запросы'!G4:G10),'05_Запросы'!G4:G10,0)) | G6: Коммерческий индекс | H6: =MAX('05_Запросы'!G4:G10)
A7: Итоговый вывод | B7: ='06_Воронка_сценарии'!B22
A10: Сценарий | B10: Рынок, год | C10: SOM нового бизнеса, год
A11: Осторожный | B11: ='06_Воронка_сценарии'!J5 | C11: ='06_Воронка_сценарии'!D12
A12: Базовый | B12: ='06_Воронка_сценарии'!J6 | C12: ='06_Воронка_сценарии'!D13
A13: Оптимистичный | B13: ='06_Воронка_сценарии'!J7 | C13: ='06_Воронка_сценарии'!D14
A16: Канал | B16: Доля | C16: Трафик/мес
A17: Direct | B17: ='03_Каналы'!B4 | C17: ='03_Каналы'!C4
A18: Organic search | B18: ='03_Каналы'!B5 | C18: ='03_Каналы'!C5
A19: Referral | B19: ='03_Каналы'!B6 | C19: ='03_Каналы'!C6
A20: Social | B20: ='03_Каналы'!B7 | C20: ='03_Каналы'!C7
A21: Paid search | B21: ='03_Каналы'!B8 | C21: ='03_Каналы'!C8
A22: Display | B22: ='03_Каналы'!B9 | C22: ='03_Каналы'!C9

Sheet 08_Источники
A1: Источники данных и журнал фиксации
A3: Источник | B3: Что брать | C3: Как фиксировать | D3: Ссылка | E3: Дата обращения | F3: Ограничение
A4: Similarweb Website Analysis | B4: Посещаемость, каналы, география, похожие сайты, поисковые запросы | C4: Ручной ввод или экспорт при наличии доступа | D4: https://www.similarweb.com/website/ | E4: 29.09.2026 | F4: Данные оценочные, полнота зависит от доступа
A5: Similarweb Data Methodology | B5: Описание природы и ограничений данных | C5: Использовать для методологических оговорок | D5: https://support.similarweb.com/hc/en-us/articles/360001631538-Similarweb-Data-Methodology | E5: 29.09.2026 | F5: Методология может обновляться
A6: Similarweb Data Exporter | B6: Выгрузка настраиваемых наборов данных | C6: Использовать при наличии платного доступа или единиц извлечения | D6: https://support.similarweb.com/hc/en-us/articles/13252032019101-Data-Exporter | E6: 29.09.2026 | F6: Может быть недоступно в бесплатной версии
A7: Google Trends | B7: Динамика относительного поискового интереса | C7: CSV-выгрузка и фиксация параметров | D7: https://trends.google.com/ | E7: 29.09.2026 | F7: Индекс 0–100, не абсолютный объем спроса
A8: Яндекс Вордстат | B8: Частотность и динамика поисковых запросов | C8: CSV/XLSX или ручная фиксация | D8: https://wordstat.yandex.ru/ | E8: 29.09.2026 | F8: Отражает аудиторию Яндекса
A9: Белстат / официальная статистика | B9: Количество организаций, отрасли, население, доходы | C9: Использовать для проверки сегмента клиентов | D9: https://www.belstat.gov.by/ | E9: 29.09.2026 | F9: Официальные категории могут не совпадать с цифровым рынком
A12: Журнал ручного сбора данных
A13: Дата | B13: Сайт / домен | C13: Раздел Similarweb | D13: Показатель | E13: Значение | F13: Комментарий / снимок экрана
A14: 29.09.2026 | B14: plantuml.com | C14: Overview | D14: Total visits (август 2026) | E14: 507000 | F14: скриншот similarweb_traffic_plantuml.com_global_last3months_2026-09-30.png
A15: 29.09.2026 | B15: plantuml.com | C15: Overview | D15: Global Rank | E15: 93517 | F15: ранг; Country Rank #24 334 (Россия); Category Rank #692
A16: 29.09.2026 | B16: plantuml.com | C16: Geography | D16: Доля России в трафике | E16: 0.0907 | F16: Беларусь в топ-5 стран не показана: нет данных в бесплатном доступе
A17: 29.09.2026 | B17: plantuml.com | C17: Marketing Channels | D17: Organic Search | E17: 0.4847 | F17: Direct и Referrals — 2-е и 3-е места без долей
A18: 29.09.2026 | B18: plantuml.com | C18: Engagement | D18: Bounce rate | E18: 0.4552 | F18: Pages/visit 3,18; Avg duration 00:03:16
A19: 29.09.2026 | B19: app.diagrams.net | C19: Overview | D19: Total visits | E19: доступ закрыт | F19: лимит бесплатных просмотров (скриншот ...global_limit_2026-09-30.png); значение 7,8 млн — из выгрузки ЛР1
A20: 29.09.2026 | B20: mermaid.live | C20: Overview | D20: Total visits | E20: доступ закрыт | F20: лимит бесплатных просмотров
A21: 29.09.2026 | B21: lucidchart.com | C21: Overview | D21: Total visits | E21: доступ закрыт | F21: лимит бесплатных просмотров; 🔲 ДОСНЯТЬ: Similarweb, страница lucidchart.com, снимок экрана (вручную, по странице источника; табл. 91, п. 1)
A24: Значения eraser.io (678,5 тыс.), app.diagrams.net (7,8 млн), mermaidchart.com (< 20 тыс.) указаны без скриншота (app.diagrams.net — по отчёту ЛР1, остальные — предварительный замер 17–23.09.2026); повторный замер 30.09.2026 невозможен (лимит) 🔲 ДОСНЯТЬ минимум ещё 6 доменов.
