Workbook

Sheet 00_Методика
A1: Методика оценки объема рынка через количество потенциальных клиентов
A3: Назначение Excel-шаблона
A4: Цель | B4: Рассчитать оценочный объем рынка электронного бизнеса через количество потенциальных клиентов, коэффициенты сужения, средний чек, частоту покупки и достижимую долю рынка
A5: Логика | B5: 1) определить клиентские сегменты; 2) задать исходное число потенциальных клиентов; 3) сузить базу по границам рынка, потребности, цифровой готовности и платежеспособности; 4) рассчитать SAM; 5) задать достижимую долю и получить SOM
A6: Ключевая формула | B6: Объем рынка = количество клиентов × доля соответствия границам × доля потребности × доля цифровой готовности × доля платежеспособности × средний чек × частота покупки
A7: Применение | B7: Подходит для B2B-услуг, B2C-продуктов, электронных сервисов и платформ, если можно определить базу потенциальных клиентов
A8: Ограничение | B8: Расчет является оценочным. Все коэффициенты должны подтверждаться источниками: статистикой, Similarweb, Google Trends, Яндекс Вордстат, рекламными кабинетами, конкурентным анализом, опросами или экспертными допущениями
A10: Порядок работы с файлом
A11: Шаг | B11: Действие | C11: Лист | D11: Результат
A12: 1 | B12: Заполнить исходные параметры бизнес-идеи, географии, валюты и периода расчета | C12: 01_Параметры | D12: Зафиксированы границы расчета
A13: 2 | B13: Заполнить клиентские сегменты и коэффициенты сужения | C13: 02_Сегменты | D13: Получены TAM, SAM и SOM по сегментам
A14: 3 | B14: Проверить осторожный, базовый и оптимистичный сценарии | C14: 03_Сценарии | D14: Получен диапазон возможного объема рынка
A15: 4 | B15: Сопоставить расчет с цифровыми данными конкурентов из Similarweb | C15: 05_Similarweb | D15: Проверена реалистичность цифрового спроса
A16: 5 | B16: Посмотреть итоговую панель, выводы и контрольные индикаторы | C16: 06_Дашборд | D16: Получен итоговый результат для отчета
A17: 6 | B17: Зафиксировать источники и степень надежности данных | C17: 07_Источники | D17: Обеспечена воспроизводимость расчета
A20: Интерпретация итоговых показателей
A21: Показатель | B21: Как читать
A22: TAM | B22: Максимальный потенциальный объем спроса до сужения по реальным ограничениям выбранного рынка
A23: SAM | B23: Объем рынка в выбранных продуктовых и географических границах с учетом потребности, цифровой готовности и платежеспособности
A24: SOM | B24: Часть SAM, которую новый бизнес может реалистично привлечь в выбранном периоде
A25: Расчет через Similarweb | B25: Проверочный ориентир по цифровой активности конкурентов и объему трафика в выбранном сегменте
A26: Сценарии | B26: Диапазон неопределенности: осторожная, базовая и оптимистичная оценка

Sheet 01_Параметры
A1: Исходные параметры расчета
A3: Параметр | B3: Значение | C3: Комментарий | D3: Источник / обоснование
A4: Название бизнес-идеи | B4: NotaCode — веб-IDE для построения и проверки диаграмм формальных нотаций как текста (подписка Free / Pro) | C4: Можно заменить на свою бизнес-идею | D4: Паспорт бизнес-идеи
A5: Компетенция | B5: Аналитика и проектирование ПО (UML, BPMN, ERD, IDEF, DFD) | C5: Профессиональная основа бизнеса | D5: Исходная гипотеза
A6: Продуктовые границы | B6: Онлайн-редакторы и генераторы диаграмм формальных нотаций по текстовому описанию; UML/BPMN-редакторы; универсальные редакторы в части нотационных диаграмм. Исключены: универсальные доски, корпоративные CASE-платформы, курсы программирования | C6: Что входит в анализируемый рынок | D6: Методика фиксации границ рынка
A7: Географические границы | B7: Республика Беларусь (РФ/СНГ — гипотеза вне расчёта, решение В-6) | C7: Территория первичного расчета | D7: Выбранная территория анализа
A8: Тип рынка | B8: B2C-подписка (freemium Free / Pro); единица клиента — пользователь (физическое лицо) | C8: Основной клиент — организация или предприниматель | D8: Описание модели бизнеса
A9: Валюта | B9: BYN | C9: Валюта расчетов | D9: Допущение
A10: Период расчета | B10: 1 год | C10: Все итоговые показатели приводятся в годовом выражении | D10: Допущение
A11: Дата составления | B11: 29.09.2026 | C11: Дата версии расчета | D11: Автоматически / вручную
A12: Ответственный | B12: К. А. Хаджинова | C12: ФИО или группа
A15: Единицы интерпретации
A16: Единица | B16: Значение
A17: Количество клиентов | B17: Количество организаций, ИП, домохозяйств или пользователей в выбранном сегменте
A18: Коэффициент сужения | B18: Доля от 0 до 100 %, показывающая, какая часть базы реально относится к выбранному рынку
A19: Средний чек | B19: Средний платеж за одну покупку или договор
A20: Частота покупки | B20: Среднее число покупок или оплат в год
A21: SAM | B21: Доступный объем рынка в выбранных границах
A22: SOM | B22: Реалистично достижимый объем рынка для нового бизнеса

Sheet 02_Сегменты
A1: Расчет объема рынка через количество потенциальных клиентов по сегментам
A3: Сегмент клиентов | B3: Тип клиента | C3: Источник количества | D3: Потенциальных клиентов всего | E3: Доля соответствия границам рынка | F3: Клиентов в границах рынка | G3: Доля имеющих потребность | H3: Доля готовых покупать онлайн | I3: Доля платежеспособных | J3: Реально адресуемых клиентов | K3: Средний чек | L3: Покупок в год | M3: SAM: доступный объем рынка | N3: Достижимая доля нового бизнеса | O3: SOM: достижимый объем | P3: Надежность данных | Q3: Комментарий
A4: S-01 Студенты технических и экономических специальностей | B4: B2C | C4: Белстат, «Образование в Республике Беларусь, 2026», табл. 7.1 (229,0 тыс., 2025/26) | D4: 229000 | E4: 0.3 | F4: =D4*E4 | G4: 0.225 | H4: 0.55 | I4: 0.0875 | J4: =F4*G4*H4*I4 | K4: 121.14 | L4: 1 | M4: =J4*K4*L4 | N4: 0.01 | O4: =M4*N4 | P4: Средняя | Q4: Тариф Free (первичный). К1–К4 — допущения в диапазонах ПК табл. 7 (базовые значения), К5 — достижимая доля. Годовой чек 40 у.е. × 3,0285
A5: S-02/S-03 Аналитики, архитекторы ПО и разработчики | B5: B2C | C5: Белстат, работники организаций цифровой экономики, 2024 (130 549) | D5: 130549 | E5: 0.3 | F5: =D5*E5 | G5: 0.225 | H5: 0.55 | I5: 0.175 | J5: =F5*G5*H5*I5 | K5: 121.14 | L5: 1 | M5: =J5*K5*L5 | N5: 0.02 | O5: =M5*N5 | P5: Низкая | Q5: Тариф Pro. К1–К4 — допущения в диапазонах ПК табл. 7 (базовые значения), К5 — достижимая доля. Годовой чек 40 у.е. × 3,0285
A6: S-04 Преподаватели технических дисциплин | B6: B2C | C6: Белстат, ППС вузов (17,1 тыс., 2025/26); доля технических дисциплин неизвестна | D6: 17100 | E6: 0.2 | F6: =D6*E6 | G6: 0.225 | H6: 0.55 | I6: 0.1 | J6: =F6*G6*H6*I6 | K6: 121.14 | L6: 1 | M6: =J6*K6*L6 | N6: 0.01 | O6: =M6*N6 | P6: Низкая | Q6: Тариф Free / Pro. К1–К4 — допущения в диапазонах ПК табл. 7 (базовые значения), К5 — достижимая доля. Годовой чек 40 у.е. × 3,0285
F7: =D7*E7 | J7: =F7*G7*H7*I7 | M7: =J7*K7*L7 | O7: =M7*N7
F8: =D8*E8 | J8: =F8*G8*H8*I8 | M8: =J8*K8*L8 | O8: =M8*N8
F9: =D9*E9 | J9: =F9*G9*H9*I9 | M9: =J9*K9*L9 | O9: =M9*N9
F10: =D10*E10 | J10: =F10*G10*H10*I10 | M10: =J10*K10*L10 | O10: =M10*N10
A12: Итого | D12: =SUM(D4:D10) | F12: =SUM(F4:F10) | J12: =SUM(J4:J10) | M12: =SUM(M4:M10) | O12: =SUM(O4:O10)
A14: Строка-гипотеза вне расчёта (решение В-6) | C14: Расширение РФ/СНГ: Росстат и национальные статистики — в итоговый диапазон не включается

Sheet 03_Сценарии
A1: Сценарная оценка объема рынка
A3: Сценарий | B3: Множитель потребности | C3: Множитель онлайн-готовности | D3: Множитель платежеспособности | E3: Множитель среднего чека | F3: Множитель частоты покупки | G3: Достижимая доля | H3: TAM | I3: SAM | J3: SOM | K3: Комментарий
A4: Осторожный | B4: 0.75 | C4: 0.8 | D4: 0.75 | E4: 0.8 | F4: 0.8 | G4: 0.008 | H4: =SUMPRODUCT('02_Сегменты'!$D\$4:$D\$10,'02_Сегменты'!$K\$4:$K\$10,'02_Сегменты'!$L\$4:$L\$10)*E4*F4 | I4: =SUMPRODUCT('02_Сегменты'!$F\$4:$F\$10,'02_Сегменты'!$G\$4:$G\$10,'02_Сегменты'!$H\$4:$H\$10,'02_Сегменты'!$I\$4:$I\$10,'02_Сегменты'!$K\$4:$K\$10,'02_Сегменты'!$L\$4:$L\$10)*B4*C4*D4*E4*F4 | J4: =I4*G4 | K4: Низкие коэффициенты и ограниченный выход на рынок
A5: Базовый | B5: 1 | C5: 1 | D5: 1 | E5: 1 | F5: 1 | G5: 0.02 | H5: =SUMPRODUCT('02_Сегменты'!$D\$4:$D\$10,'02_Сегменты'!$K\$4:$K\$10,'02_Сегменты'!$L\$4:$L\$10)*E5*F5 | I5: =SUMPRODUCT('02_Сегменты'!$F\$4:$F\$10,'02_Сегменты'!$G\$4:$G\$10,'02_Сегменты'!$H\$4:$H\$10,'02_Сегменты'!$I\$4:$I\$10,'02_Сегменты'!$K\$4:$K\$10,'02_Сегменты'!$L\$4:$L\$10)*B5*C5*D5*E5*F5 | J5: =I5*G5 | K5: Основной расчет на базе листа сегментов
A6: Оптимистичный | B6: 1.2 | C6: 1.15 | D6: 1.2 | E6: 1.15 | F6: 1.1 | G6: 0.04 | H6: =SUMPRODUCT('02_Сегменты'!$D\$4:$D\$10,'02_Сегменты'!$K\$4:$K\$10,'02_Сегменты'!$L\$4:$L\$10)*E6*F6 | I6: =SUMPRODUCT('02_Сегменты'!$F\$4:$F\$10,'02_Сегменты'!$G\$4:$G\$10,'02_Сегменты'!$H\$4:$H\$10,'02_Сегменты'!$I\$4:$I\$10,'02_Сегменты'!$K\$4:$K\$10,'02_Сегменты'!$L\$4:$L\$10)*B6*C6*D6*E6*F6 | J6: =I6*G6 | K6: Усиленная конверсия, высокий чек и более заметная доля рынка

Sheet 04_Расчет
A1: Итоговые расчетные показатели по методу потенциальных клиентов
A3: Показатель | B3: Формула / источник | C3: Значение | D3: Интерпретация
A4: TAM по базовому подходу | B4: SUMPRODUCT(потенциальные клиенты × средний чек × частота) | C4: =SUMPRODUCT('02_Сегменты'!$D\$4:$D\$10,'02_Сегменты'!$K\$4:$K\$10,'02_Сегменты'!$L\$4:$L\$10) | D4: Максимальный ориентир до сужения рынка
A5: Клиенты в границах рынка | B5: Сумма клиентов после продуктово-географического сужения | C5: ='02_Сегменты'!F12 | D5: Потенциальная база в выбранных границах
A6: Реально адресуемые клиенты | B6: Сумма после учета потребности, онлайн-готовности и платежеспособности | C6: ='02_Сегменты'!J12 | D6: Практически доступная клиентская база
A7: SAM | B7: Реально адресуемые клиенты × средний чек × частота | C7: ='02_Сегменты'!M12 | D7: Доступный объем рынка
A8: SOM | B8: SAM × достижимая доля | C8: ='02_Сегменты'!O12 | D8: Реалистичный объем для нового бизнеса
A9: Доля SOM в SAM | B9: SOM / SAM | C9: =IFERROR(C8/C7,0) | D9: Оценка амбициозности выхода на рынок
A12: Коэффициенты качества расчета
A13: Проверка | B13: Расчет | C13: Значение | D13: Как интерпретировать
A14: Доля реально адресуемых клиентов | B14: реально адресуемые / клиенты в границах | C14: =IFERROR(C6/C5,0) | D14: Если значение слишком высокое, коэффициенты могли быть завышены
A15: Средний SAM на одного адресуемого клиента | B15: SAM / реально адресуемые клиенты | C15: =IFERROR(C7/C6,0) | D15: Показывает среднюю годовую выручку на клиента
A16: Сравнение SOM и Similarweb-ориентира | B16: SOM / оценочная годовая выручка конкурентов | C16: =IFERROR(C8/'05_Similarweb'!N12,0) | D16: Используется как проверка реалистичности

Sheet 05_Similarweb
A1: Проверочная оценка рынка через Similarweb и цифровые следы конкурентов
A3: Конкурент / сайт | B3: URL | C3: Роль на рынке | D3: Месячные визиты | E3: Доля выбранной географии | F3: Визиты из выбранной географии | G3: Доля релевантных каналов | H3: Коэффициент коммерческого намерения | I3: Релевантный рыночный трафик | J3: Конверсия в заявку | K3: Конверсия заявки в оплату | L3: Средний чек | M3: Заказов в месяц | N3: Выручка в месяц | O3: Выручка в год
A4: PlantUML | B4: https://www.similarweb.com/website/plantuml.com/ | C4: прямой (текстовый DSL) | D4: 507000 | E4: 0.001958 | F4: =D4*E4 | G4: 0.75 | H4: 0.35 | I4: =F4*G4*H4 | J4: 0.025 | K4: 0.04 | L4: 121.14 | M4: =I4*J4*K4 | N4: =M4*L4 | O4: =N4*12
A5: draw.io (diagrams.net) | B5: https://www.similarweb.com/website/app.diagrams.net/ | C5: заменитель (визуальный редактор) | D5: 7800000 | E5: 0.001958 | F5: =D5*E5 | G5: 0.35 | H5: 0.35 | I5: =F5*G5*H5 | J5: 0.025 | K5: 0.04 | L5: 121.14 | M5: =I5*J5*K5 | N5: =M5*L5 | O5: =N5*12
A6: Eraser | B6: https://www.similarweb.com/website/eraser.io/ | C6: прямой (AI + diagram as code) | D6: 678500 | E6: 0.001958 | F6: =D6*E6 | G6: 0.5 | H6: 0.35 | I6: =F6*G6*H6 | J6: 0.025 | K6: 0.04 | L6: 121.14 | M6: =I6*J6*K6 | N6: =M6*L6 | O6: =N6*12
A7: Mermaid Chart | B7: https://www.similarweb.com/website/mermaidchart.com/ | C7: прямой (текстовый DSL) | D7: 20000 | E7: 0.001958 | F7: =D7*E7 | G7: 0.7 | H7: 0.35 | I7: =F7*G7*H7 | J7: 0.025 | K7: 0.04 | L7: 121.14 | M7: =I7*J7*K7 | N7: =M7*L7 | O7: =N7*12
F8: =D8*E8 | I8: =F8*G8*H8 | M8: =I8*J8*K8 | N8: =M8*L8 | O8: =N8*12
A10: Итого / среднее | D10: =SUM(D4:D8) | F10: =SUM(F4:F8) | I10: =SUM(I4:I8) | M10: =SUM(M4:M8) | N10: =SUM(N4:N8) | O10: =SUM(O4:O8)
A12: Годовая оценка выручки конкурентов по Similarweb | N12: =O10
A14: Визиты: plantuml.com — Similarweb, авг. 2026 (скриншот); остальные — отчёт ЛР1 и предварительный замер 17–23.09.2026 без скриншота (mermaidchart.com — верхняя граница «менее 20 тыс.»). Доля РБ — допущение Д-01. Конверсии и чек — параметры NotaCode (CR1 — шаблон, CR2 = 4 % — проект, чек = цена Pro), поэтому результат — «выручка при параметрах NotaCode», а не фактическая выручка конкурентов. Выборка 4 домена < 5 —

Sheet 06_Дашборд
A1: Итоговая панель оценки объема рынка через потенциальных клиентов
A3: Показатель | B3: Значение | C3: Интерпретация | G3: Объем по сегментам: SAM и SOM
A4: TAM | B4: ='04_Расчет'!C4 | C4: Общий потенциальный рынок до сужения | G4: Сегмент | H4: SAM | I4: SOM
A5: SAM | B5: ='04_Расчет'!C7 | C5: Доступный рынок в зафиксированных границах | G5: ='02_Сегменты'!A4 | H5: ='02_Сегменты'!M4 | I5: ='02_Сегменты'!O4
A6: SOM | B6: ='04_Расчет'!C8 | C6: Реалистично достижимый объем для нового бизнеса | G6: ='02_Сегменты'!A5 | H6: ='02_Сегменты'!M5 | I6: ='02_Сегменты'!O5
A7: Адресуемые клиенты | B7: ='04_Расчет'!C6 | C7: Клиенты после учета потребности, онлайн-готовности и платежеспособности | G7: ='02_Сегменты'!A6 | H7: ='02_Сегменты'!M6 | I7: ='02_Сегменты'!O6
A8: Similarweb-ориентир | B8: ='05_Similarweb'!N12 | C8: Оценочная годовая выручка конкурентов по цифровому трафику | G8: ='02_Сегменты'!A7 | H8: ='02_Сегменты'!M7 | I8: ='02_Сегменты'!O7
A9: Доля SOM в SAM | B9: ='04_Расчет'!C9 | C9: Проверка амбициозности выхода на рынок | G9: ='02_Сегменты'!A8 | H9: ='02_Сегменты'!M8 | I9: ='02_Сегменты'!O8
G10: ='02_Сегменты'!A9 | H10: ='02_Сегменты'!M9 | I10: ='02_Сегменты'!O9
A12: Сценарный диапазон объема рынка
A13: Сценарий | B13: TAM | C13: SAM | D13: SOM | E13: Вывод
A14: Осторожный | B14: ='03_Сценарии'!H4 | C14: ='03_Сценарии'!I4 | D14: ='03_Сценарии'!J4 | E14: Минимальный ориентир при слабой конверсии и низкой достижимой доле
A15: Базовый | B15: ='03_Сценарии'!H5 | C15: ='03_Сценарии'!I5 | D15: ='03_Сценарии'!J5 | E15: Основной расчет
A16: Оптимистичный | B16: ='03_Сценарии'!H6 | C16: ='03_Сценарии'!I6 | D16: ='03_Сценарии'!J6 | E16: Верхняя граница при благоприятных условиях
A19: Шаблон итогового вывода
A20: По результатам оценки через количество потенциальных клиентов базовый доступный объем рынка составляет ориентировочно 197 988 BYN в год, а реалистично достижимый объем для нового бизнеса составляет 3 007 BYN в год (по долям сегментов; по единой доле 2 % — 3 960 BYN). Оценка является сценарной и требует проверки через фактические данные о клиентах, конкурентах, рекламных каналах, Similarweb, поисковом спросе и платежеспособности целевых сегментов

Sheet 07_Источники
A1: Журнал источников данных и допущений
A3: Блок расчета | B3: Показатель | C3: Источник | D3: Ссылка / файл | E3: Дата обращения | F3: Статус данных | G3: Надежность | H3: Комментарий
A4: Количество клиентов | B4: Студенты УВО РБ: 229,0 тыс | C4: Белстат, «Образование в Республике Беларусь, 2026», табл. 7.1 | D4: belstat.gov.by/upload/iblock/6af/m93v33ohm51kl00b333cmrhjbhj42ouo.pdf | E4: 29.09.2026 | F4: факт | G4: Высокая | H4: Заполнить фактический источник при выполнении расчета
A5: Количество клиентов | B5: Работники организаций цифровой экономики: 130 549 (2024) | C5: Белстат, digital_economy-2024.xls | D5: belstat.gov.by/upload-belstat/upload-belstat-excel/Oficial_statistika/2024/digital_economy-2024.xls | E5: 29.09.2026 | F5: факт | G5: Средняя | H5: Желательно подтвердить через опрос или коммерческие запросы
A6: Количество клиентов | B6: ППС вузов: 17,1 тыс | C6: Белстат, «Образование в Республике Беларусь, 2026» | D6: там же | E6: 29.09.2026 | F6: факт | G6: Средняя | H6: Проверяет, насколько рынок доступен через цифровые каналы
A7: К1 релевантность сегмента | B7: 30 % / 30 % / 20 % | C7: Допущение в диапазоне ПК табл. 7 (20–40 %) | D7: 🔲 разбивка студентов по профилям (Белстат / Минобразования) | E7: 29.09.2026 | F7: экспертное допущение | G7: Низкая | H7: Не следует путать интерес с готовностью платить
A8: К2 потребность | B8: 22,5 % | C8: Допущение, середина диапазона ПК табл. 7 (15–30 %) | D8: 🔲 опрос ≥20–30 респондентов; Вордстат | E8: 29.09.2026 | F8: экспертное допущение | G8: Низкая | H8: Использовать диапазон и сценарии
A9: К3 цифровая доступность | B9: 55 % | C9: Допущение, середина диапазона ПК табл. 7 (40–70 %); потолок — 94,3 % населения в интернете (Белстат 2024) | D9: belstat.gov.by | E9: 29.09.2026 | F9: экспертное допущение | G9: Низкая | H9: Данные являются оценочными и требуют проверки
A10: К4 готовность платить | B10: 8,75 % / 17,5 % / 10 % | C10: Допущение в диапазонах ПК табл. 7 (5–10 % и 10–25 %); проектное Free → Pro 3–5 % | D10: 🔲 опрос | E10: 29.09.2026 | F10: экспертное допущение | G10: Низкая
A11: Средний чек | B11: 121,14 BYN/год | C11: Концепция NotaCode (годовой тариф 40 у.е.) × курс НБРБ 3,0285 (30.09.2026); альтернатива 48 у.е. (4 у.е. × 12) = 145,37 BYN | D11: api.nbrb.by/exrates/rates/431 | E11: 29.09.2026 | F11: проектное допущение | G11: Средняя
A12: Similarweb | B12: Трафик домена-образца | C12: Similarweb, бесплатная карточка, август 2026 (plantuml.com) | D12: similarweb.com/website/plantuml.com/ | E12: 29.09.2026 | F12: факт / оценка | G12: Средняя
A13: Доля географии | B13: 0,1958 % | C13: Расчёт: 9,07 % (Россия, Similarweb) × 170/7874 (РБ/РФ, Вордстат, окно 29.08–27.09.2026) | D13: wordstat.yandex.ru; similarweb.com | E13: 29.09.2026 | F13: экспертное допущение | G13: Низкая

Sheet 08_Справочник
A1: Справочные списки для выпадающих полей
A3: Тип клиента | B3: Статус данных | C3: Надежность | D3: Сценарий
A4: B2B | B4: Факт | C4: Высокая | D4: Осторожный
A5: B2C | B5: Оценка | C5: Средняя | D5: Базовый
A6: Платформа | B6: Экспертное допущение | C6: Низкая | D6: Оптимистичный
A7: Смешанный | B7: Нет данных
