Workbook

Sheet 00_Методика
A1: Методика проверки рынка через платежеспособность
A2: Excel-шаблон для оценки, способен ли выявленный интерес аудитории перейти в платежеспособный спрос
A4: Этап | B4: Что выполняется | C4: Какие данные нужны | D4: Результат
A5: 1. Сегментация | B5: Разделить потенциальных клиентов на группы по типу, размеру, потребности и цифровой доступности | C5: Сегменты клиентов, численность, доля потребности, доля готовности покупать онлайн | D5: Расчет платежеспособной клиентской базы
A6: 2. Ценовой коридор | B6: Собрать минимальные, медианные и максимальные цены конкурентов или аналогичных предложений | C6: Сайты конкурентов, прайс-листы, коммерческие предложения, маркетплейсы услуг | D6: Диапазон допустимой цены и ориентир среднего чека
A7: 3. Экономическая оправданность | B7: Проверить, окупается ли покупка для клиента через дополнительную выручку, экономию или снижение потерь | C7: Выручка клиента, маржинальность, ожидаемый эффект, стоимость услуги | D7: Показатель окупаемости и экономический аргумент покупки
A8: 4. Платежеспособность | B8: Сопоставить бюджет клиента с ежемесячной стоимостью предложения | C8: Доступный бюджет, цена услуги, регулярность оплаты | D8: Индекс платежеспособности и статус покупки
A9: 5. Сценарии | B9: Рассчитать осторожный, базовый и оптимистичный варианты рынка | C9: Коэффициенты потребности, платежеспособности, частоты покупки и среднего чека | D9: Диапазон платежеспособного объема рынка
A10: 6. Проверка цифровыми данными | B10: Использовать Similarweb и другие цифровые источники как косвенную проверку активности рынка | C10: Посещаемость конкурентов, каналы, география, поисковый трафик | D10: Проверка того, есть ли цифровая активность вокруг сегмента

Sheet 01_Параметры
A1: Исходные параметры модели
A2: Заполните базовые сведения о бизнес-идее и единых допущениях расчета
A4: Параметр | B4: Значение | C4: Комментарий
A5: Бизнес-идея | B5: NotaCode — веб-IDE для построения и проверки диаграмм формальных нотаций как текста (подписка Free / Pro) | C5: Можно заменить на собственную идею
A6: Географические границы | B6: Республика Беларусь | C6: Территория первичной проверки рынка
A7: Валюта расчета | B7: BYN | C7: Можно заменить на RUB, у.е., EUR
A8: Период расчета | B8: год | C8: Расчет годового платежеспособного объема рынка
A9: Базовая конверсия интереса в покупку | B9: 0.04 | C9: Доля регистраций, оплативших Pro: допущение проекта Free → Pro 3–5 % (базовое 4 %); формулами не используется (П-13)
A10: Минимальный индекс платежеспособности | B10: 1 | C10: Бюджет / цена ≥ 1 — покупка возможна; ниже 1 — затруднена (формулами не используется)
A11: Целевая маржинальность поставщика | B11: □ | C11: Себестоимость обслуживания пользователя в концепции не определена — (формулами не используется)
A12: Дата заполнения | B12: 29.09.2026 | C12: Дата версии расчета

Sheet 02_Сегменты
A1: Расчет рынка через количество платежеспособных клиентов
A2: Заполните клиентские сегменты, коэффициенты потребности и доступности покупки
A4: Сегмент | B4: Всего потенциальных клиентов | C4: Доля с потребностью | D4: Доля готовых покупать онлайн | E4: Доля платежеспособных | F4: Покупок/контрактов в год | G4: Средний чек | H4: Платежеспособные клиенты | I4: Годовое число покупок | J4: Потенциальный объем рынка | K4: Комментарий | L4: Источник
A5: S-01 Студенты технических и экономических специальностей | B5: 68700 | C5: 0.225 | D5: 0.55 | E5: 0.0875 | F5: 1 | G5: 121.14 | H5: =IF(A5="","",B5*C5*D5*E5) | I5: =IF(A5="","",H5*F5) | J5: =IF(A5="","",I5*G5) | K5: Тариф: Free (первичный). Клиенты в границах = численность 229 000 × К1 0.3 | L5: Белстат, «Образование в Республике Беларусь, 2026», табл. 7.1 (229,0 тыс., 2025/26)
A6: S-02/S-03 Аналитики, архитекторы ПО и разработчики | B6: 39165 | C6: 0.225 | D6: 0.55 | E6: 0.175 | F6: 1 | G6: 121.14 | H6: =IF(A6="","",B6*C6*D6*E6) | I6: =IF(A6="","",H6*F6) | J6: =IF(A6="","",I6*G6) | K6: Тариф: Pro. Клиенты в границах = численность 130 549 × К1 0.3 | L6: Белстат, работники организаций цифровой экономики, 2024 (130 549)
A7: S-04 Преподаватели технических дисциплин | B7: 3420 | C7: 0.225 | D7: 0.55 | E7: 0.1 | F7: 1 | G7: 121.14 | H7: =IF(A7="","",B7*C7*D7*E7) | I7: =IF(A7="","",H7*F7) | J7: =IF(A7="","",I7*G7) | K7: Тариф: Free / Pro. Клиенты в границах = численность 17 100 × К1 0.2 | L7: Белстат, ППС вузов (17,1 тыс., 2025/26); доля технических дисциплин неизвестна
H8: =IF(A8="","",B8*C8*D8*E8) | I8: =IF(A8="","",H8*F8) | J8: =IF(A8="","",I8*G8)
H9: =IF(A9="","",B9*C9*D9*E9) | I9: =IF(A9="","",H9*F9) | J9: =IF(A9="","",I9*G9)
H10: =IF(A10="","",B10*C10*D10*E10) | I10: =IF(A10="","",H10*F10) | J10: =IF(A10="","",I10*G10)
H11: =IF(A11="","",B11*C11*D11*E11) | I11: =IF(A11="","",H11*F11) | J11: =IF(A11="","",I11*G11)
H12: =IF(A12="","",B12*C12*D12*E12) | I12: =IF(A12="","",H12*F12) | J12: =IF(A12="","",I12*G12)
H13: =IF(A13="","",B13*C13*D13*E13) | I13: =IF(A13="","",H13*F13) | J13: =IF(A13="","",I13*G13)
H14: =IF(A14="","",B14*C14*D14*E14) | I14: =IF(A14="","",H14*F14) | J14: =IF(A14="","",I14*G14)
A16: Итого | H16: =SUM(H5:H14) | I16: =SUM(I5:I14) | J16: =SUM(J5:J14)
A18: Примечание | B18: Годовой чек 40 у.е. (решение В-5; альтернатива 48 у.е. = 4 у.е. × 12), в BYN по курсу НБРБ 3,0285 (30.09.2026); число оплат в год = 1 (годовой тариф). Доля платёжеспособных (E) совмещает финансовую возможность и готовность платить (К4 по ПК табл. 7). Строки ниже S-04 не используются (П-5)

Sheet 03_Ценовой_коридор
A1: Ценовой коридор и конкурентная цена
A2: Сравните цены аналогичных предложений и оцените допустимый средний чек
A4: Услуга / продукт | B4: Минимальная цена | C4: Медианная цена | D4: Максимальная цена | E4: Себестоимость | F4: Валовая маржа | G4: Цена в модели | H4: Индекс доступности цены | I4: Комментарий | J4: Источник
A5: Miro (платные тарифы, BYN/мес.) | B5: 24.23 | C5: 42.4 | D5: 60.57 | F5: =IF(OR(A5="",E5=""),"нет данных",(G5-E5)/G5) | G5: =IF(A5="","",C5) | H5: =IF(A5="","",G5/C5) | I5: Тарифы: Starter (за участника), Business (за участника); оплата за год, у.е. × 3,0285 | J5: Страница тарифов продукта, 30.09.2026
A6: Lucidchart (платные тарифы, BYN/мес.) | B6: 27.26 | C6: 28.77 | D6: 30.29 | F6: =IF(OR(A6="",E6=""),"нет данных",(G6-E6)/G6) | G6: =IF(A6="","",C6) | H6: =IF(A6="","",G6/C6) | I6: Тарифы: Individual, Team (за пользователя); оплата за год, у.е. × 3,0285 | J6: Страница тарифов продукта, 30.09.2026
A7: Mermaid Chart (платные тарифы, BYN/мес.) | B7: 30.29 | C7: 45.43 | D7: 60.57 | F7: =IF(OR(A7="",E7=""),"нет данных",(G7-E7)/G7) | G7: =IF(A7="","",C7) | H7: =IF(A7="","",G7/C7) | I7: Тарифы: Plus (за пользователя), Premium (за пользователя); оплата за год, у.е. × 3,0285 | J7: Страница тарифов продукта, 30.09.2026
A8: Visual Paradigm Online (платные тарифы, BYN/мес.) | B8: 12.11 | C8: 36.34 | D8: 90.86 | F8: =IF(OR(A8="",E8=""),"нет данных",(G8-E8)/G8) | G8: =IF(A8="","",C8) | H8: =IF(A8="","",G8/C8) | I8: Тарифы: Starter, Advance, Combo, Deluxe; оплата за год, у.е. × 3,0285 | J8: Страница тарифов продукта, 30.09.2026
A9: Creately (платные тарифы, BYN/мес.) | B9: 15.14 | C9: 15.14 | D9: 269.54 | F9: =IF(OR(A9="",E9=""),"нет данных",(G9-E9)/G9) | G9: =IF(A9="","",C9) | H9: =IF(A9="","",G9/C9) | I9: Тарифы: Starter, Team, Business; оплата за год, у.е. × 3,0285 | J9: Страница тарифов продукта, 30.09.2026
A10: Eraser (платные тарифы, BYN/мес.) | B10: 45.43 | C10: 90.86 | D10: 136.28 | F10: =IF(OR(A10="",E10=""),"нет данных",(G10-E10)/G10) | G10: =IF(A10="","",C10) | H10: =IF(A10="","",G10/C10) | I10: Тарифы: Starter, Business; оплата за год, у.е. × 3,0285 | J10: Страница тарифов продукта, 30.09.2026
A11: Whimsical (платные тарифы, BYN/мес.) | B11: 30.29 | C11: 45.43 | D11: 60.57 | F11: =IF(OR(A11="",E11=""),"нет данных",(G11-E11)/G11) | G11: =IF(A11="","",C11) | H11: =IF(A11="","",G11/C11) | I11: Тарифы: Pro, Business; оплата за год, у.е. × 3,0285 | J11: Страница тарифов продукта, 30.09.2026
A12: dbdiagram.io (платные тарифы, BYN/мес.) | B12: 24.23 | C12: 24.23 | D12: 24.23 | F12: =IF(OR(A12="",E12=""),"нет данных",(G12-E12)/G12) | G12: =IF(A12="","",C12) | H12: =IF(A12="","",G12/C12) | I12: Тарифы: Personal Pro; оплата за год, у.е. × 3,0285 | J12: Страница тарифов продукта, 30.09.2026
A14: Среднее / ориентир | B14: =AVERAGE(B5:B12) | C14: =AVERAGE(C5:C12) | D14: =AVERAGE(D5:D12) | E14: =IFERROR(AVERAGE(E5:E12),"нет данных") | F14: =IFERROR(AVERAGE(F5:F12),"нет данных") | G14: =AVERAGE(G5:G12) | H14: =AVERAGE(H5:H12)
A16: Справочно (в среднее не входят)
A17: NotaCode Pro | C17: 10.1 | I17: годовой тариф 40 у.е. = 10,10 BYN/мес.; помесячно 4 у.е. = 12,11 BYN
A18: Microsoft Visio Plan 1 / Plan 2 | C18: 15.14 / 45.43 | I18: 5 и 15 у.е./мес. за пользователя
A19: draw.io, PlantUML | C19: 0 | I19: бесплатные заменители (цена заменителя = 0)
A21: Себестоимость (столбец E) у конкурентов не публикуется — нет данных; формула валовой маржи в копии возвращает «нет данных» (в шаблоне при пустой ячейке давала 100 %). Индекс доступности цены H всегда равен 1 (особенность шаблона П-3) и в выводах не используется

Sheet 04_Экономика_покупки
A1: Экономическая оправданность покупки для клиента
A2: Проверяется, возвращает ли клиент вложения в продукт или услугу
A4: Сегмент | B4: Средняя месячная выручка клиента | C4: Маржинальность клиента | D4: Ожидаемый рост выручки | E4: Дополнительная валовая прибыль/мес | F4: Цена услуги/мес | G4: Окупаемость, мес | H4: ROI за год | I4: Экономический статус | J4: Комментарий | K4: Источник
A5: S-01 Студенты технических и экономических специальностей | B5: 298.68 | C5: 1 | D5: 0 | E5: =IF(A5="","",B5*C5*D5) | F5: 10.095 | G5: =IF(A5="","",IF(E5=0,"",F5/E5)) | H5: =IF(A5="","",((E5-F5)*12)/(F5*12)) | I5: =IF(A5="","",IF(H5>=0.5,"экономически оправдано",IF(H5>=0,"требует проверки","экономически слабо"))) | J5: Денежного эффекта у студента нет (продукт Free); показано для случая покупки Pro | K5: стипендия БГУИР (ИКТ), середина диапазона 229,75–367,60 BYN (таблица БГУИР с 01.08.2026)
A6: S-02/S-03 Аналитики, архитекторы ПО и разработчики | B6: 6413 | C6: 1 | D6: 0.017857 | E6: =IF(A6="","",B6*C6*D6) | F6: 10.095 | G6: =IF(A6="","",IF(E6=0,"",F6/E6)) | H6: =IF(A6="","",((E6-F6)*12)/(F6*12)) | I6: =IF(A6="","",IF(H6>=0.5,"экономически оправдано",IF(H6>=0,"требует проверки","экономически слабо"))) | J6: Эффект = доход × доля сэкономленного времени (3 ч из 168 ч в месяц; допущение Д-07, опрос) | K6: средняя з/п «информация и связь», июль 2026 (6 413 BYN, Белстат)
A7: S-04 Преподаватели технических дисциплин | B7: 3172 | C7: 1 | D7: 0.017857 | E7: =IF(A7="","",B7*C7*D7) | F7: 10.095 | G7: =IF(A7="","",IF(E7=0,"",F7/E7)) | H7: =IF(A7="","",((E7-F7)*12)/(F7*12)) | I7: =IF(A7="","",IF(H7>=0.5,"экономически оправдано",IF(H7>=0,"требует проверки","экономически слабо"))) | J7: Эффект = доход × доля сэкономленного времени (3 ч из 168 ч в месяц; допущение Д-07, опрос) | K7: средняя з/п по РБ, июль 2026 (3 172,0 BYN; данных по преподавателям нет)
E8: =IF(A8="","",B8*C8*D8) | G8: =IF(A8="","",IF(E8=0,"",F8/E8)) | H8: =IF(A8="","",((E8-F8)*12)/(F8*12)) | I8: =IF(A8="","",IF(H8>=0.5,"экономически оправдано",IF(H8>=0,"требует проверки","экономически слабо")))
E9: =IF(A9="","",B9*C9*D9) | G9: =IF(A9="","",IF(E9=0,"",F9/E9)) | H9: =IF(A9="","",((E9-F9)*12)/(F9*12)) | I9: =IF(A9="","",IF(H9>=0.5,"экономически оправдано",IF(H9>=0,"требует проверки","экономически слабо")))
E10: =IF(A10="","",B10*C10*D10) | G10: =IF(A10="","",IF(E10=0,"",F10/E10)) | H10: =IF(A10="","",((E10-F10)*12)/(F10*12)) | I10: =IF(A10="","",IF(H10>=0.5,"экономически оправдано",IF(H10>=0,"требует проверки","экономически слабо")))
E11: =IF(A11="","",B11*C11*D11) | G11: =IF(A11="","",IF(E11=0,"",F11/E11)) | H11: =IF(A11="","",((E11-F11)*12)/(F11*12)) | I11: =IF(A11="","",IF(H11>=0.5,"экономически оправдано",IF(H11>=0,"требует проверки","экономически слабо")))
E12: =IF(A12="","",B12*C12*D12) | G12: =IF(A12="","",IF(E12=0,"",F12/E12)) | H12: =IF(A12="","",((E12-F12)*12)/(F12*12)) | I12: =IF(A12="","",IF(H12>=0.5,"экономически оправдано",IF(H12>=0,"требует проверки","экономически слабо")))
A14: Среднее / сводный показатель | B14: =AVERAGE(B5:B12) | C14: =AVERAGE(C5:C12) | D14: =AVERAGE(D5:D12) | E14: =AVERAGE(E5:E12) | F14: =AVERAGE(F5:F12) | G14: =AVERAGE(G5:G12) | H14: =AVERAGE(H5:H12)
A16: Доход клиента — средняя месячная зарплата/стипендия; маржинальность принята 1,0 (трудовой доход, не выручка компании)

Sheet 05_Платежеспособность
A1: Проверка платежеспособности клиентских сегментов
A2: Индекс платежеспособности = доступный месячный бюджет клиента / месячная цена предложения
A4: Сегмент | B4: Средний доступный бюджет/мес | C4: Цена предложения/мес | D4: Индекс платежеспособности | E4: Статус | F4: Доля клиентов с бюджетом | G4: Платежеспособные клиенты | H4: Годовой чек | I4: Платежеспособный объем | J4: Комментарий
A5: S-01 Студенты технических и экономических специальностей | B5: 14.93 | C5: 10.095 | D5: =IF(A5="","",B5/C5) | E5: =IF(A5="","",IF(D5>=1.5,"высокая",IF(D5>=1,"достаточная",IF(D5>=0.7,"пограничная","низкая")))) | F5: 0.0875 | G5: =IF(A5="","",'02_Сегменты'!B5*F5) | H5: 121.14 | I5: =IF(A5="","",G5*H5) | J5: Бюджет = доход × 5% (Д-08); доля F = доле платёжеспособных листа 02 (решение В-11)
A6: S-02/S-03 Аналитики, архитекторы ПО и разработчики | B6: 320.65 | C6: 10.095 | D6: =IF(A6="","",B6/C6) | E6: =IF(A6="","",IF(D6>=1.5,"высокая",IF(D6>=1,"достаточная",IF(D6>=0.7,"пограничная","низкая")))) | F6: 0.175 | G6: =IF(A6="","",'02_Сегменты'!B6*F6) | H6: 121.14 | I6: =IF(A6="","",G6*H6) | J6: Бюджет = доход × 5% (Д-08); доля F = доле платёжеспособных листа 02 (решение В-11)
A7: S-04 Преподаватели технических дисциплин | B7: 158.6 | C7: 10.095 | D7: =IF(A7="","",B7/C7) | E7: =IF(A7="","",IF(D7>=1.5,"высокая",IF(D7>=1,"достаточная",IF(D7>=0.7,"пограничная","низкая")))) | F7: 0.1 | G7: =IF(A7="","",'02_Сегменты'!B7*F7) | H7: 121.14 | I7: =IF(A7="","",G7*H7) | J7: Бюджет = доход × 5% (Д-08); доля F = доле платёжеспособных листа 02 (решение В-11)
D8: =IF(A8="","",B8/C8) | E8: =IF(A8="","",IF(D8>=1.5,"высокая",IF(D8>=1,"достаточная",IF(D8>=0.7,"пограничная","низкая")))) | G8: =IF(A8="","",'02_Сегменты'!B8*F8) | I8: =IF(A8="","",G8*H8)
D9: =IF(A9="","",B9/C9) | E9: =IF(A9="","",IF(D9>=1.5,"высокая",IF(D9>=1,"достаточная",IF(D9>=0.7,"пограничная","низкая")))) | G9: =IF(A9="","",'02_Сегменты'!B9*F9) | I9: =IF(A9="","",G9*H9)
D10: =IF(A10="","",B10/C10) | E10: =IF(A10="","",IF(D10>=1.5,"высокая",IF(D10>=1,"достаточная",IF(D10>=0.7,"пограничная","низкая")))) | G10: =IF(A10="","",'02_Сегменты'!B10*F10) | I10: =IF(A10="","",G10*H10)
D11: =IF(A11="","",B11/C11) | E11: =IF(A11="","",IF(D11>=1.5,"высокая",IF(D11>=1,"достаточная",IF(D11>=0.7,"пограничная","низкая")))) | G11: =IF(A11="","",'02_Сегменты'!B11*F11) | I11: =IF(A11="","",G11*H11)
D12: =IF(A12="","",B12/C12) | E12: =IF(A12="","",IF(D12>=1.5,"высокая",IF(D12>=1,"достаточная",IF(D12>=0.7,"пограничная","низкая")))) | G12: =IF(A12="","",'02_Сегменты'!B12*F12) | I12: =IF(A12="","",G12*H12)
A14: Итого / среднее | B14: =AVERAGE(B5:B12) | C14: =AVERAGE(C5:C12) | D14: =AVERAGE(D5:D12) | F14: =AVERAGE(F5:F12) | G14: =SUM(G5:G12) | H14: =AVERAGE(H5:H12) | I14: =SUM(I5:I12)

Sheet 06_Сценарии
A1: Сценарная проверка платежеспособного объема рынка
A2: Сценарии позволяют не завышать вывод и показывать диапазон оценки
A4: Параметр | B4: Осторожный | C4: Базовый | D4: Оптимистичный | E4: Комментарий
A5: Коэффициент потребности | B5: 0.7 | C5: 1 | D5: 1.2 | E5: Корректировка доли клиентов с потребностью
A6: Коэффициент платежеспособности | B6: 0.6 | C6: 1 | D6: 1.25 | E6: Корректировка доли платежеспособных клиентов
A7: Коэффициент частоты покупки | B7: 0.75 | C7: 1 | D7: 1.15 | E7: Корректировка числа покупок/контрактов
A8: Коэффициент среднего чека | B8: 0.8 | C8: 1 | D8: 1.2 | E8: Корректировка цены
A9: Достижимая доля нового бизнеса | B9: 0.005 | C9: 0.015 | D9: 0.035 | E9: Реалистичная доля рынка для нового игрока
A12: Сегмент | B12: Базовый объем | C12: Осторожный рынок | D12: Базовый рынок | E12: Оптимистичный рынок | F12: Осторожная достижимая выручка | G12: Базовая достижимая выручка | H12: Оптимистичная достижимая выручка
A13: =IF('02_Сегменты'!A5="","",'02_Сегменты'!A5) | B13: ='02_Сегменты'!J5 | C13: =IF(A13="","",B13*$B\$5*$B\$6*$B\$7*$B\$8) | D13: =IF(A13="","",B13*$C\$5*$C\$6*$C\$7*$C\$8) | E13: =IF(A13="","",B13*$D\$5*$D\$6*$D\$7*$D\$8) | F13: =IF(A13="","",C13*$B\$9) | G13: =IF(A13="","",D13*$C\$9) | H13: =IF(A13="","",E13*$D\$9)
A14: =IF('02_Сегменты'!A6="","",'02_Сегменты'!A6) | B14: ='02_Сегменты'!J6 | C14: =IF(A14="","",B14*$B\$5*$B\$6*$B\$7*$B\$8) | D14: =IF(A14="","",B14*$C\$5*$C\$6*$C\$7*$C\$8) | E14: =IF(A14="","",B14*$D\$5*$D\$6*$D\$7*$D\$8) | F14: =IF(A14="","",C14*$B\$9) | G14: =IF(A14="","",D14*$C\$9) | H14: =IF(A14="","",E14*$D\$9)
A15: =IF('02_Сегменты'!A7="","",'02_Сегменты'!A7) | B15: ='02_Сегменты'!J7 | C15: =IF(A15="","",B15*$B\$5*$B\$6*$B\$7*$B\$8) | D15: =IF(A15="","",B15*$C\$5*$C\$6*$C\$7*$C\$8) | E15: =IF(A15="","",B15*$D\$5*$D\$6*$D\$7*$D\$8) | F15: =IF(A15="","",C15*$B\$9) | G15: =IF(A15="","",D15*$C\$9) | H15: =IF(A15="","",E15*$D\$9)
A16: =IF('02_Сегменты'!A8="","",'02_Сегменты'!A8) | B16: ='02_Сегменты'!J8 | C16: =IF(A16="","",B16*$B\$5*$B\$6*$B\$7*$B\$8) | D16: =IF(A16="","",B16*$C\$5*$C\$6*$C\$7*$C\$8) | E16: =IF(A16="","",B16*$D\$5*$D\$6*$D\$7*$D\$8) | F16: =IF(A16="","",C16*$B\$9) | G16: =IF(A16="","",D16*$C\$9) | H16: =IF(A16="","",E16*$D\$9)
A17: =IF('02_Сегменты'!A9="","",'02_Сегменты'!A9) | B17: ='02_Сегменты'!J9 | C17: =IF(A17="","",B17*$B\$5*$B\$6*$B\$7*$B\$8) | D17: =IF(A17="","",B17*$C\$5*$C\$6*$C\$7*$C\$8) | E17: =IF(A17="","",B17*$D\$5*$D\$6*$D\$7*$D\$8) | F17: =IF(A17="","",C17*$B\$9) | G17: =IF(A17="","",D17*$C\$9) | H17: =IF(A17="","",E17*$D\$9)
A18: =IF('02_Сегменты'!A10="","",'02_Сегменты'!A10) | B18: ='02_Сегменты'!J10 | C18: =IF(A18="","",B18*$B\$5*$B\$6*$B\$7*$B\$8) | D18: =IF(A18="","",B18*$C\$5*$C\$6*$C\$7*$C\$8) | E18: =IF(A18="","",B18*$D\$5*$D\$6*$D\$7*$D\$8) | F18: =IF(A18="","",C18*$B\$9) | G18: =IF(A18="","",D18*$C\$9) | H18: =IF(A18="","",E18*$D\$9)
A19: =IF('02_Сегменты'!A11="","",'02_Сегменты'!A11) | B19: ='02_Сегменты'!J11 | C19: =IF(A19="","",B19*$B\$5*$B\$6*$B\$7*$B\$8) | D19: =IF(A19="","",B19*$C\$5*$C\$6*$C\$7*$C\$8) | E19: =IF(A19="","",B19*$D\$5*$D\$6*$D\$7*$D\$8) | F19: =IF(A19="","",C19*$B\$9) | G19: =IF(A19="","",D19*$C\$9) | H19: =IF(A19="","",E19*$D\$9)
A20: =IF('02_Сегменты'!A12="","",'02_Сегменты'!A12) | B20: ='02_Сегменты'!J12 | C20: =IF(A20="","",B20*$B\$5*$B\$6*$B\$7*$B\$8) | D20: =IF(A20="","",B20*$C\$5*$C\$6*$C\$7*$C\$8) | E20: =IF(A20="","",B20*$D\$5*$D\$6*$D\$7*$D\$8) | F20: =IF(A20="","",C20*$B\$9) | G20: =IF(A20="","",D20*$C\$9) | H20: =IF(A20="","",E20*$D\$9)
A22: Итого | B22: =SUM(B13:B20) | C22: =SUM(C13:C20) | D22: =SUM(D13:D20) | E22: =SUM(E13:E20) | F22: =SUM(F13:F20) | G22: =SUM(G13:G20) | H22: =SUM(H13:H20)

Sheet 07_Similarweb
A1: Проверка цифровой активности через Similarweb
A2: Используется как косвенная проверка рынка: трафик конкурентов, география, каналы и поисковые запросы
A4: Сайт / конкурент | B4: Месячные посещения | C4: Доля целевой географии | D4: Релевантный трафик | E4: Доля поискового трафика | F4: Доля прямого трафика | G4: Доля соцсетей | H4: Оценка конверсии в заявку | I4: Оценка заявок/мес | J4: Средний чек | K4: Оценка выручки/мес | L4: Источник / дата
A5: plantuml.com | B5: 507000 | C5: 0.001958 | D5: =IF(A5="","",B5*C5) | E5: 0.4847 | F5: 0.22 | G5: 0.15 | H5: 0.001 | I5: =IF(A5="","",D5*H5) | J5: 121.14 | K5: =IF(A5="","",I5*J5) | L5: ФАКТ (Similarweb, авг. 2026, скриншот); 30.09.2026. Доля РБ — допущение Д-01. H = CR1 × CR2 (в шаблоне отдельной конверсии в оплату нет)
A6: app.diagrams.net | B6: 7800000 | C6: 0.001958 | D6: =IF(A6="","",B6*C6) | E6: 0.42 | F6: 0.18 | G6: 0.2 | H6: 0.001 | I6: =IF(A6="","",D6*H6) | J6: 121.14 | K6: =IF(A6="","",I6*J6) | L6: отчёт ЛР1, без скриншота; 30.09.2026. Доля РБ — допущение Д-01. H = CR1 × CR2 (в шаблоне отдельной конверсии в оплату нет)
A7: eraser.io | B7: 678500 | C7: 0.001958 | D7: =IF(A7="","",B7*C7) | E7: 0.35 | F7: 0.25 | G7: 0.18 | H7: 0.001 | I7: =IF(A7="","",D7*H7) | J7: 121.14 | K7: =IF(A7="","",I7*J7) | L7: предварительный замер 17–23.09.2026, не подтверждён; 30.09.2026. Доля РБ — допущение Д-01. H = CR1 × CR2 (в шаблоне отдельной конверсии в оплату нет)
A8: mermaidchart.com | B8: 20000 | C8: 0.001958 | D8: =IF(A8="","",B8*C8) | H8: 0.001 | I8: =IF(A8="","",D8*H8) | J8: 121.14 | K8: =IF(A8="","",I8*J8) | L8: предварительный замер: «менее 20 тыс.» (верхняя граница), не подтверждён; 30.09.2026. Доля РБ — допущение Д-01. H = CR1 × CR2 (в шаблоне отдельной конверсии в оплату нет)
D9: =IF(A9="","",B9*C9) | I9: =IF(A9="","",D9*H9) | K9: =IF(A9="","",I9*J9)
D10: =IF(A10="","",B10*C10) | I10: =IF(A10="","",D10*H10) | K10: =IF(A10="","",I10*J10)
D11: =IF(A11="","",B11*C11) | I11: =IF(A11="","",D11*H11) | K11: =IF(A11="","",I11*J11)
D12: =IF(A12="","",B12*C12) | I12: =IF(A12="","",D12*H12) | K12: =IF(A12="","",I12*J12)
A14: Итого / среднее | B14: =SUM(B5:B12) | C14: =AVERAGE(C5:C12) | D14: =SUM(D5:D12) | E14: =AVERAGE(E5:E12) | F14: =AVERAGE(F5:F12) | G14: =AVERAGE(G5:G12) | H14: =AVERAGE(H5:H12) | I14: =SUM(I5:I12) | J14: =AVERAGE(J5:J12) | K14: =SUM(K5:K12)
A16: Доля поискового трафика (E) показана бесплатной карточкой только у plantuml.com (Organic 48,47 %); прямой трафик и соцсети не показаны («нет данных в бесплатном доступе»)

Sheet 08_Итоговая_панель
A1: Итоговая панель проверки платежеспособности
A2: Ключевые показатели, сценарии и вывод для принятия решения
A4: Показатель | B4: Значение | C4: Интерпретация | E4: Сценарий | F4: Рынок | G4: Достижимая выручка | H4: Комментарий
A5: Потенциальный объем по сегментам | B5: ='02_Сегменты'!J16 | C5: Сумма по всем сегментам с учетом потребности, цифровой доступности и платежеспособности | E5: Осторожный | F5: ='06_Сценарии'!C22 | G5: ='06_Сценарии'!F22 | H5: Нижняя граница
A6: Платежеспособные клиенты | B6: ='02_Сегменты'!H16 | C6: Расчетная база клиентов, способных купить предложение | E6: Базовый | F6: ='06_Сценарии'!D22 | G6: ='06_Сценарии'!G22 | H6: Плановый ориентир
A7: Средний индекс платежеспособности | B7: ='05_Платежеспособность'!D14 | C7: Бюджет клиента / цена предложения | E7: Оптимистичный | F7: ='06_Сценарии'!E22 | G7: ='06_Сценарии'!H22 | H7: Верхняя граница
A8: Средний ROI клиента за год | B8: ='04_Экономика_покупки'!H14 | C8: Экономическая оправданность покупки с позиции клиента
A9: Осторожная достижимая выручка | B9: ='06_Сценарии'!F22 | C9: Реалистичный нижний сценарий для нового игрока
A10: Базовая достижимая выручка | B10: ='06_Сценарии'!G22 | C10: Основной сценарий для планирования
A11: Оптимистичная достижимая выручка | B11: ='06_Сценарии'!H22 | C11: Верхний сценарий при высокой реализации
A12: Оценка выручки конкурентов по Similarweb/мес | B12: ='07_Similarweb'!K14 | C12: Косвенный ориентир цифровой активности рынка
A15: Автоматизированный предварительный вывод
A16: =IF(B7>=1,"Платежеспособность сегментов в среднем достаточная: бюджет клиентов сопоставим с ценой предложения. Рекомендуется переходить к проверке конкурентов, каналов продаж и пилотному запуску.","Платежеспособность сегментов требует дополнительной проверки: цена предложения выше доступного бюджета. Нужно уточнить сегменты, снизить стоимость входного продукта или изменить состав предложения.")

Sheet 09_Источники
A1: Журнал источников данных и допущений
A2: Заполняется для воспроизводимости расчета и проверки ограничений
A4: Источник | B4: Какие данные брать | C4: Как использовать | D4: Ссылка / путь | E4: Дата обращения | F4: Ограничение
A5: Белстат / государственная статистика | B5: Количество компаний, отрасли, доходы, социально-экономические показатели | C5: Оценка потенциальной клиентской базы и платежеспособности | D5: https://www.belstat.gov.by/ | E5: 29.09.2026 | F5: Официальные данные могут быть укрупненными
A6: Similarweb | B6: Посещаемость конкурентов, каналы, география, поисковый трафик | C6: Проверка цифровой активности и конкурентной среды | D6: https://www.similarweb.com/website/ | E6: 29.09.2026 | F6: Оценочные данные, точность ниже для малых сайтов
A7: Google Trends | B7: Динамика относительного интереса | C7: Проверка устойчивости интереса к теме | D7: https://trends.google.com/ | E7: 29.09.2026 | F7: Индекс 0–100 не равен абсолютному спросу
A8: Яндекс Вордстат | B8: Частотность запросов, регионы, динамика | C8: Проверка поискового спроса и коммерческих формулировок | D8: https://wordstat.yandex.ru/ | E8: 29.09.2026 | F8: Отражает аудиторию Яндекса
A9: Сайты конкурентов | B9: Цены, пакеты услуг, позиционирование, офферы | C9: Определение ценового коридора и коммерческих условий | D9: Страницы тарифов Miro, Lucidchart, Mermaid Chart, Visual Paradigm, Creately, Eraser, Whimsical, dbdiagram.io (30.09.2026) | E9: 29.09.2026 | F9: Неполная видимость фактических продаж
A10: Опросы / интервью клиентов | B10: Бюджет, готовность платить, барьеры покупки | C10: Проверка платежеспособности и экономической оправданности | D10: Планируемый первичный опрос ≥20–30 респондентов (готовность платить, допустимая цена) | F10: Может быть смещенность выборки
A12: Белстат, стипендия и зарплата | B12: Доход сегментов | C12: Доля цены в доходе, бюджет | D12: стипендия БГУИР (вторичный источник teenage.by); з/п: Белстат, экспресс-информация янв.–авг. 2026; «информация и связь» — Белстат, таблица по видам деятельности, июль 2026 (nach_sr_zarplata-2607.xlsx) | E12: 29.09.2026
A13: НБРБ | B13: Курс у.е./BYN 3,0285 | C13: Перевод цен | D13: https://api.nbrb.by/exrates/rates/431 | E13: 29.09.2026
