Workbook

Sheet 00_Методика
A1: Методика оценки объема рынка электронного бизнеса
A2: Excel-шаблон для подходов «сверху вниз» и «снизу вверх» с использованием Similarweb
A4: Назначение | B4: Расчетный шаблон для оценки объема рынка: макро-ориентир «сверху вниз», расчет через клиентские сегменты «снизу вверх», проверка через цифровые признаки Similarweb
A5: Принцип | B5: Желтые ячейки заполняются пользователем. Зеленые ячейки рассчитываются автоматически
A6: Similarweb | B6: Используется как источник оценочных данных о посещаемости сайтов конкурентов, каналах трафика, географии аудитории и конкурентном окружении
A7: Ограничение | B7: Данные Similarweb не являются прямым измерением выручки. Итог должен оформляться как оценочный диапазон
A8: Итог | B8: После заполнения файла формируется диапазон объема рынка: нижняя, базовая и верхняя оценка
A11: Шаг | B11: Действие | C11: Результат
A12: 1 | B12: Зафиксировать продуктовые и географические границы рынка | C12: Понятно, какой рынок измеряется
A13: 2 | B13: Ввести исходные параметры и допущения | C13: Задана база расчетов
A14: 3 | B14: Рассчитать объем рынка методом «сверху вниз» | C14: Получен общий ориентир масштаба
A15: 4 | B15: Рассчитать объем рынка методом «снизу вверх» | C15: Получен расчет через клиентские сегменты
A16: 5 | B16: Внести доступные данные Similarweb | C16: Проверена цифровая активность конкурентов
A17: 6 | B17: Построить воронку Similarweb | C17: Получена оценка денежного объема через трафик
A18: 7 | B18: Сравнить методы | C18: Сформирован итоговый диапазон
A19: 8 | B19: Описать ограничения | C19: Подготовлен корректный управленческий вывод

Sheet 01_Параметры
A1: Исходные параметры
A2: Параметры используются во всех расчетах. Демонстрационные значения заменяются на фактические
A4: Параметр | B4: Значение | C4: Единица | D4: Назначение | E4: Комментарий | F4: Тип
A5: Название рынка | B5: Веб-инструменты построения и проверки диаграмм формальных нотаций (UML, BPMN, ERD, IDEF, DFD) для студентов и специалистов по ПО в Республике Беларусь | D5: Описание рынка | E5: Заменить на свою идею | F5: Ввод
A6: География | B6: Республика Беларусь | D6: Территория анализа | E6: Заменить при необходимости | F6: Ввод
A7: Валюта | B7: BYN | D7: Валюта расчетов | E7: Можно заменить | F7: Ввод
A8: Средний годовой чек | B8: 121.14 | C8: BYN/клиент/год | D8: Денежный расчет рынка услуг | E8: Pro: 40 у.е. × 3,0285 (НБРБ, 30.09.2026); альтернатива 48 у.е./год = 145,37 BYN | F8: Ввод
A9: Среднее число покупок в год | B9: 1 | C9: раз | D9: Для товарных и сервисных моделей | E9: Годовой тариф — одна оплата в год (в формулах не используется) | F9: Ввод
A10: Конверсия визита в заявку | B10: 0.025 | C10: доля | D10: Воронка Similarweb | E10: Посетитель → регистрация; значение шаблона (Word СВ табл. 22 — 2–6 %) | F10: Ввод
A11: Конверсия заявки в продажу | B11: 0.04 | C11: доля | D11: Воронка Similarweb | E11: Регистрация → оплата Pro: допущение проекта (Free → Pro 3–5 %); шкалы методик для услуг неприменимы | F11: Ввод
A12: Коэффициент повторных продаж | B12: 1.2 | C12: раз | D12: Уточнение годовой выручки | E12: Шкала шаблона; срок удержания — допущение | F12: Ввод
A13: Корректировка на неполную выборку конкурентов | B13: 1.15 | C13: коэффициент | D13: Учитывает конкурентов вне выборки | E13: Значение шаблона; в варианте Word — явное покрытие 0,5 / 0,7 / 0,9 | F13: Ввод
A14: Осторожный сценарий | B14: 0.6 | C14: коэффициент | D14: Понижающий коэффициент | E14: Риски низкой конверсии | F14: Сценарий
A15: Базовый сценарий | B15: 1 | C15: коэффициент | D15: Базовый расчет | E15: Основной сценарий | F15: Сценарий
A16: Оптимистичный сценарий | B16: 1.4 | C16: коэффициент | D16: Повышающий коэффициент | E16: Высокий спрос/лучшие конверсии | F16: Сценарий

Sheet 02_Сверху_вниз
A1: Методика «сверху вниз»
A2: От общего показателя рынка к доступному цифровому сегменту
A4: Показатель | B4: Осторожный | C4: Базовый | D4: Оптимистичный | E4: Единица | F4: Источник / комментарий | G4: Тип
A5: Общий ориентир: число потенциальных организаций/клиентов | B5: 376649 | C5: 376649 | D5: 376649 | E5: ед | F5: Численность целевых групп по статистике РБ: студенты 229,0 тыс. + работники цифровой экономики 130,5 тыс. + ППС 17,1 тыс. (ИНСТР §7.1: число пользователей) | G5: Ввод
A6: Доля клиентов в продуктовых границах рынка | B6: 0.15 | C6: 0.3 | D6: 0.5 | E6: доля | F6: К1 по ПК табл. 7: 15 / 30 / 50 % (середины диапазонов сценариев) | G6: Ввод
A7: Доля клиентов в выбранной географии | B7: 1 | C7: 1 | D7: 1 | E7: доля | F7: Исходные данные уже по Республике Беларусь — 1,0 | G7: Ввод
A8: Доля клиентов, доступных через цифровые каналы | B8: 0.3 | C8: 0.55 | D8: 0.8 | E8: доля | F8: К3 по ПК табл. 7: 30 / 55 / 80 % | G8: Ввод
A9: Доля клиентов с вероятной потребностью | B9: 0.0075 | C9: 0.039375 | D9: 0.13 | E9: доля | F9: К2 × К4 (потребность × готовность платить) по ПК табл. 7: 10×7,5 % / 22,5×17,5 % / 40×32,5 % | G9: Ввод
A10: Средний годовой чек | B10: ='01_Параметры'!B8 | C10: ='01_Параметры'!B8 | D10: ='01_Параметры'!B8 | E10: BYN | F10: Подтягивается из параметров | G10: Формула
A11: Расчетное число клиентов рынка | B11: =B5*B6*B7*B8*B9 | C11: =C5*C6*C7*C8*C9 | D11: =D5*D6*D7*D8*D9 | E11: клиенты | F11: Сужение общего рынка до достижимой базы | G11: Формула
A12: Оценка годового объема рынка | B12: =B11*B10 | C12: =C11*C10 | D12: =D11*D10 | E12: BYN/год | F12: Клиенты × средний годовой чек | G12: Формула

Sheet 03_Снизу_вверх
A1: Методика «снизу вверх»
A2: Расчет через клиентские сегменты, средний чек и частоту покупки
A4: Сегмент клиентов | B4: Потенциальные клиенты | C4: Доля с потребностью | D4: Цифровая доступность | E4: Покупок/год | F4: Средний чек | G4: Годовой объем | H4: Доля сегмента | I4: Источник/комментарий | J4: Статус
A5: S-01 Студенты технических и экономических специальностей | B5: 68700 | C5: 0.019688 | D5: 0.55 | E5: 1 | F5: 121.14 | G5: =B5*C5*D5*E5*F5 | H5: =G5/SUM($G\$5:$G\$10) | I5: Белстат, «Образование в Республике Беларусь, 2026», табл. 7.1 (229,0 тыс., 2025/26); C = К2 × К4 (потребность и готовность платить) | J5: Допущение
A6: S-02/S-03 Аналитики, архитекторы ПО и разработчики | B6: 39165 | C6: 0.039375 | D6: 0.55 | E6: 1 | F6: 121.14 | G6: =B6*C6*D6*E6*F6 | H6: =G6/SUM($G\$5:$G\$10) | I6: Белстат, работники организаций цифровой экономики, 2024 (130 549); C = К2 × К4 (потребность и готовность платить) | J6: Допущение
A7: S-04 Преподаватели технических дисциплин | B7: 3420 | C7: 0.0225 | D7: 0.55 | E7: 1 | F7: 121.14 | G7: =B7*C7*D7*E7*F7 | H7: =G7/SUM($G\$5:$G\$10) | I7: Белстат, ППС вузов (17,1 тыс., 2025/26); доля технических дисциплин неизвестна; C = К2 × К4 (потребность и готовность платить) | J7: Допущение
G8: =B8*C8*D8*E8*F8 | H8: =G8/SUM($G\$5:$G\$10)
G9: =B9*C9*D9*E9*F9 | H9: =G9/SUM($G\$5:$G\$10)
G10: =B10*C10*D10*E10*F10 | H10: =G10/SUM($G\$5:$G\$10)
A11: ИТОГО | B11: =SUM(B5:B10) | G11: =SUM(G5:G10) | H11: =SUM(H5:H10)

Sheet 04_Similarweb
A1: Данные Similarweb по конкурентам
A2: Вводятся доступные оценочные данные: посещаемость, география, каналы, релевантность
A4: Домен / сайт | B4: Тип конкурента | C4: Месячные визиты | D4: Доля целевой географии | E4: Доля релевантных каналов | F4: Коммерческая релевантность | G4: Коэффициент вовлеченности | H4: Релевантные визиты/мес | I4: Релевантные визиты/год | J4: Доля трафика | K4: Источник данных | L4: Дата фиксации | M4: Комментарий
A5: plantuml.com | B5: Прямой | C5: 507000 | D5: 0.001958 | E5: 0.75 | F5: 0.35 | G5: 1 | H5: =C5*D5*E5*F5*G5 | I5: =H5*12 | J5: =I5/SUM($I\$5:$I\$14) | K5: https://www.similarweb.com/website/plantuml.com/ | L5: 29.09.2026 | M5: ФАКТ (Similarweb, авг. 2026, скриншот); доля РБ — допущение Д-01; коммерческая релевантность 35 % (М2 табл. 21, базовый); вовлечённость 1,0
A6: app.diagrams.net | B6: Заменитель | C6: 7800000 | D6: 0.001958 | E6: 0.35 | F6: 0.35 | G6: 1 | H6: =C6*D6*E6*F6*G6 | I6: =H6*12 | J6: =I6/SUM($I\$5:$I\$14) | K6: https://www.similarweb.com/website/app.diagrams.net/ | L6: 29.09.2026 | M6: отчёт ЛР1, без скриншота; доля РБ — допущение Д-01; коммерческая релевантность 35 % (М2 табл. 21, базовый); вовлечённость 1,0
A7: eraser.io | B7: Прямой | C7: 678500 | D7: 0.001958 | E7: 0.5 | F7: 0.35 | G7: 1 | H7: =C7*D7*E7*F7*G7 | I7: =H7*12 | J7: =I7/SUM($I\$5:$I\$14) | K7: https://www.similarweb.com/website/eraser.io/ | L7: 29.09.2026 | M7: предварительный замер 17–23.09.2026, не подтверждён; доля РБ — допущение Д-01; коммерческая релевантность 35 % (М2 табл. 21, базовый); вовлечённость 1,0
A8: mermaidchart.com | B8: Прямой | C8: 20000 | D8: 0.001958 | E8: 0.7 | F8: 0.35 | G8: 1 | H8: =C8*D8*E8*F8*G8 | I8: =H8*12 | J8: =I8/SUM($I\$5:$I\$14) | K8: https://www.similarweb.com/website/mermaidchart.com/ | L8: 29.09.2026 | M8: предварительный замер: «менее 20 тыс.» (верхняя граница), не подтверждён; доля РБ — допущение Д-01; коммерческая релевантность 35 % (М2 табл. 21, базовый); вовлечённость 1,0
H9: =C9*D9*E9*F9*G9 | I9: =H9*12 | J9: =I9/SUM($I\$5:$I\$14)
H10: =C10*D10*E10*F10*G10 | I10: =H10*12 | J10: =IFERROR(I10/SUM($I\$5:$I\$14),0)
H11: =C11*D11*E11*F11*G11 | I11: =H11*12 | J11: =IFERROR(I11/SUM($I\$5:$I\$14),0)
H12: =C12*D12*E12*F12*G12 | I12: =H12*12 | J12: =IFERROR(I12/SUM($I\$5:$I\$14),0)
H13: =C13*D13*E13*F13*G13 | I13: =H13*12 | J13: =IFERROR(I13/SUM($I\$5:$I\$14),0)
H14: =C14*D14*E14*F14*G14 | I14: =H14*12 | J14: =IFERROR(I14/SUM($I\$5:$I\$14),0)
A15: ИТОГО | C15: =SUM(C5:C14) | H15: =SUM(H5:H14) | I15: =SUM(I5:I14) | J15: =SUM(J5:J14)

Sheet 05_Воронка_SW
A1: Цифровая воронка на основе Similarweb
A2: Релевантный трафик конкурентов переводится в оценку заявок, продаж и объема рынка
A4: Показатель | B4: Осторожный | C4: Базовый | D4: Оптимистичный | E4: Единица | F4: Формула / источник | G4: Комментарий
A5: Годовые релевантные визиты конкурентов | B5: ='04_Similarweb'!I15*'01_Параметры'!B14 | C5: ='04_Similarweb'!I15*'01_Параметры'!B15 | D5: ='04_Similarweb'!I15*'01_Параметры'!B16 | E5: визиты/год | F5: Сумма Similarweb × сценарный коэффициент | G5: Цифровой объем внимания
A6: Корректировка на неполную выборку | B6: ='01_Параметры'!B13 | C6: ='01_Параметры'!B13 | D6: ='01_Параметры'!B13 | E6: коэф | F6: Параметры | G6: Если внесены не все конкуренты
A7: Скорректированные релевантные визиты | B7: =B5*B6 | C7: =C5*C6 | D7: =D5*D6 | E7: визиты/год | F7: Визиты × корректировка | G7: Оценочный цифровой спрос
A8: Конверсия визита в заявку | B8: ='01_Параметры'!B10*0.7 | C8: ='01_Параметры'!B10 | D8: ='01_Параметры'!B10*1.3 | E8: доля | F8: Параметры и сценарий | G8: Заменить реальными данными
A9: Оценочное число заявок | B9: =B7*B8 | C9: =C7*C8 | D9: =D7*D8 | E9: заявки/год | F9: Визиты × конверсия в заявку
A10: Конверсия заявки в продажу | B10: ='01_Параметры'!B11*0.8 | C10: ='01_Параметры'!B11 | D10: ='01_Параметры'!B11*1.2 | E10: доля | F10: Параметры и сценарий
A11: Оценочное число продаж | B11: =B9*B10 | C11: =C9*C10 | D11: =D9*D10 | E11: продажи/год | F11: Заявки × конверсия в продажу
A12: Средний годовой чек | B12: ='01_Параметры'!B8*0.8 | C12: ='01_Параметры'!B8 | D12: ='01_Параметры'!B8*1.2 | E12: BYN | F12: Параметры и сценарий
A13: Коэффициент повторных продаж | B13: ='01_Параметры'!B12*0.9 | C13: ='01_Параметры'!B12 | D13: ='01_Параметры'!B12*1.1 | E13: коэф | F13: Параметры
A14: Оценка годового объема рынка по Similarweb | B14: =B11*B12*B13 | C14: =C11*C12*C13 | D14: =D11*D12*D13 | E14: BYN/год | F14: Продажи × чек × повторность | G14: Оценочный диапазон

Sheet 06_Сверка
A1: Сверка расчетных подходов
A2: Итоговый диапазон оценки объема рынка на основе трех подходов
A4: Метод оценки | B4: Осторожный | C4: Базовый | D4: Оптимистичный | E4: Комментарий | F4: Надежность | G4: Что проверяет | H4: Ограничение
A5: Сверху вниз | B5: ='02_Сверху_вниз'!B12 | C5: ='02_Сверху_вниз'!C12 | D5: ='02_Сверху_вниз'!D12 | E5: Макро-ориентир через общий рынок и коэффициенты сужения | F5: Средняя | G5: Масштаб рынка | H5: Риск завышения
A6: Снизу вверх | B6: ='03_Снизу_вверх'!G11*'01_Параметры'!B14 | C6: ='03_Снизу_вверх'!G11*'01_Параметры'!B15 | D6: ='03_Снизу_вверх'!G11*'01_Параметры'!B16 | E6: Расчет через клиентские сегменты | F6: Высокая при хороших данных | G6: Реалистичность сегментов | H6: Зависит от качества допущений
A7: Similarweb + воронка | B7: ='05_Воронка_SW'!B14 | C7: ='05_Воронка_SW'!C14 | D7: ='05_Воронка_SW'!D14 | E7: Проверка через цифровой трафик конкурентов | F7: Средняя | G7: Цифровой спрос | H7: Трафик не равен выручке
A8: Минимум по методам | B8: =MIN(B5:B7) | C8: =MIN(C5:C7) | D8: =MIN(D5:D7) | E8: Нижняя граница оценки
A9: Среднее по методам | B9: =AVERAGE(B5:B7) | C9: =AVERAGE(C5:C7) | D9: =AVERAGE(D5:D7) | E9: Центральный ориентир
A10: Максимум по методам | B10: =MAX(B5:B7) | C10: =MAX(C5:C7) | D10: =MAX(D5:D7) | E10: Верхняя граница оценки

Sheet 07_Дашборд
A1: Панель итоговой оценки
A2: Ключевые показатели после заполнения шаблона
A4: Показатель | B4: Значение | C4: Комментарий | E4: Метод | F4: Осторожный | G4: Базовый | H4: Оптимистичный
A5: Итоговая нижняя оценка рынка | B5: ='06_Сверка'!B8 | C5: Минимум по трем подходам, осторожный сценарий | E5: Сверху вниз | F5: ='06_Сверка'!B5 | G5: ='06_Сверка'!C5 | H5: ='06_Сверка'!D5
A6: Итоговая базовая оценка рынка | B6: ='06_Сверка'!C9 | C6: Среднее по трем подходам, базовый сценарий | E6: Снизу вверх | F6: ='06_Сверка'!B6 | G6: ='06_Сверка'!C6 | H6: ='06_Сверка'!D6
A7: Итоговая верхняя оценка рынка | B7: ='06_Сверка'!D10 | C7: Максимум по трем подходам, оптимистичный сценарий | E7: Similarweb | F7: ='06_Сверка'!B7 | G7: ='06_Сверка'!C7 | H7: ='06_Сверка'!D7
A8: Годовой релевантный трафик конкурентов | B8: ='04_Similarweb'!I15 | C8: Сумма релевантных визитов в год
A9: Суммарный объем по методу снизу вверх | B9: ='03_Снизу_вверх'!G11 | C9: Расчет по клиентским сегментам
A10: Объем по Similarweb-воронке, базовый | B10: ='05_Воронка_SW'!C14 | C10: Цифровая проверка через трафик и конверсии | E10: Конкурент | F10: Доля релевантного трафика
E11: ='04_Similarweb'!A5 | F11: ='04_Similarweb'!J5
E12: ='04_Similarweb'!A6 | F12: ='04_Similarweb'!J6
E13: ='04_Similarweb'!A7 | F13: ='04_Similarweb'!J7
E14: ='04_Similarweb'!A8 | F14: ='04_Similarweb'!J8
E15: ='04_Similarweb'!A9 | F15: ='04_Similarweb'!J9

Sheet 08_Источники
A1: Источники данных и журнал фиксации
A2: Заполняется для воспроизводимости расчета
A4: Группа данных | B4: Показатель | C4: Источник | D4: URL | E4: Дата обращения | F4: Что переносится в Excel | G4: Ограничение | H4: Статус
A5: Similarweb | B5: Similarweb (plantuml.com, авг. 2026; остальные домены — отчёт ЛР1 и предварительный замер 17–23.09.2026) | C5: Similarweb Website Analysis | D5: https://www.similarweb.com/website/ | E5: 2026-05-02 | F5: Месячные визиты, каналы, география, похожие сайты | G5: Оценочные данные; для малых сайтов надежность ниже | H5: Заменить URL конкурентов
A6: Similarweb | B6: Методология данных | C6: Similarweb Data Methodology | D6: https://support.similarweb.com/hc/en-us/articles/360001631538-Similarweb-Data-Methodology | E6: 2026-05-02 | F6: Обоснование природы оценочных данных | G6: Не является прямым измерением выручки | H6: Справочно
A7: Similarweb | B7: Data Exporter | C7: Similarweb Help Center | D7: https://support.similarweb.com/hc/en-us/articles/13252032019101-Data-Exporter | E7: 2026-05-02 | F7: Возможности экспорта при соответствующем доступе | G7: Зависит от подписки и единиц извлечения данных | H7: Справочно
A8: Официальная статистика | B8: Количество организаций/клиентов | C8: Национальная статистика / реестры / отраслевые отчеты | F8: Общий ориентир для расчета сверху вниз | G8: Нужно подбирать под страну и отрасль | H8: Заполнить
A9: Конкуренты | B9: Средний чек, тарифы, предложения | C9: Сайты конкурентов | F9: Средний чек и сегменты | G9: Цены могут быть скрыты или неполны | H9: Заполнить
A10: Реклама | B10: Охват и стоимость привлечения | C10: Рекламные кабинеты | F10: Допущения по цифровой воронке | G10: Требует тестовых кампаний | H10: Опционально
