Workbook

Sheet 00_Методика
A1: Методика сценарной оценки рынка с учетом данных Similarweb: расчетный Excel-шаблон
A3: Назначение файла | B3: Позволяет рассчитать оценочный объем рынка электронного бизнеса по трем сценариям на основе данных Similarweb, цифровой воронки и платформенной модели
A4: Ключевая логика | B4: Similarweb используется как источник цифровых признаков рынка: посещаемость конкурентов, география, каналы трафика, поисковые запросы и конкурентное окружение. Денежный объем рассчитывается через допущения по релевантности трафика, конверсиям и среднему чеку
A5: Главный результат | B5: Диапазон оценки рынка: осторожный, базовый и оптимистичный сценарии; отдельно рассчитываются выручка через воронку и модель GMV для платформ
A6: Важное ограничение | B6: Данные Similarweb являются оценочными. Итоговые значения следует рассматривать как расчетный диапазон, а не как точное измерение фактической емкости рынка
A8: Шаг | B8: Лист | C8: Что заполнить | D8: Что рассчитывается | E8: Какие данные Similarweb используются | F8: Ключевой результат | G8: Проверка качества | H8: Комментарий
A9: 1 | B9: 01_Параметры | C9: Бизнес-идея, география, валюта, период, средний чек | D9: Базовые вводные для всех расчетов | E9: Нет, только параметры проекта | F9: Единая исследовательская постановка | G9: Параметры не должны противоречить границам рынка | H9: Заполняется первым
A10: 2 | B10: 02_Similarweb | C10: Сайты конкурентов, посещаемость, доля географии, релевантность трафика | D10: Релевантный месячный и годовой трафик рынка | E10: Visits, geography, traffic channels, engagement | F10: База для сценариев | G10: Не менее 3–5 конкурентов | H10: При бесплатном доступе значения можно фиксировать вручную
A11: 3 | B11: 03_Сценарии | C11: Коэффициенты покрытия рынка, надежности и корректировки | D11: Сценарный объем релевантного трафика | E11: Суммарный релевантный трафик конкурентов | F11: Трафиковая оценка рынка | G11: Осторожный < базовый < оптимистичный | H11: Коэффициенты должны быть обоснованы
A12: 4 | B12: 04_Воронка | C12: Конверсии, средний чек, повторные покупки, достижимая доля | D12: Продажи, выручка рынка, достижимая выручка | E12: Релевантный рыночный трафик | F12: Денежная оценка рынка | G12: Проверить адекватность конверсий | H12: Главный лист для сервисного электронного бизнеса
A13: 5 | B13: 05_Платформа | C13: Регистрации, активность, сделки, средняя сумма сделки, комиссия | D13: GMV и выручка платформы | E13: Рыночный трафик как вход в платформу | F13: Отдельная модель для платформ | G13: Не смешивать GMV и выручку | H13: Используется при платформенной бизнес-модели
A14: 6 | B14: 06_Сверка | C14: При необходимости добавить оценки других методов | D14: Диапазон итоговой оценки | E14: Данные Similarweb как один из методов | F14: Итоговый рыночный диапазон | G14: Расхождения методов должны быть объяснены | H14: Завершающий аналитический лист
A15: 7 | B15: 07_Дашборд | C15: Не заполнять вручную | D15: Ключевые показатели и графики | E15: Автоматически из расчетных листов | F15: Итоговая панель вывода | G15: Проверить, что значения обновились | H15: Лист для отчета
A16: 8 | B16: 08_Источники | C16: Ссылки, дата обращения, комментарии | D16: Журнал воспроизводимости | E16: URL, дата, ограничения Similarweb | F16: Доказательная база расчета | G16: Источник должен быть указан для каждого блока данных | H16: Заполняется по мере анализа

Sheet 01_Параметры
A1: Исходные параметры сценарной оценки рынка
A3: Параметр | B3: Значение | C3: Единица | D3: Тип | E3: Источник / основание | F3: Комментарий
A4: Название бизнес-идеи | B4: NotaCode — веб-IDE для построения и проверки диаграмм формальных нотаций как текста (подписка Free / Pro) | C4: текст | D4: ввод | E4: Границы рынка / бизнес-гипотеза | F4: Можно заменить на свою бизнес-идею
A5: Географические границы | B5: Республика Беларусь | C5: текст | D5: ввод | E5: Паспорт границ рынка | F5: Указать страну, город или регион
A6: Валюта расчета | B6: BYN | C6: текст | D6: ввод | E6: Выбор исследователя | F6: Используется в денежных расчетах
A7: Период оценки | B7: 12 | C7: месяцев | D7: ввод | E7: Период Similarweb / анализа | F7: Обычно 12 месяцев
A8: Средний чек базовый | B8: 121.14 | C8: BYN | D8: ввод | E8: Прайсы конкурентов / экспертная оценка | F8: Pro: 40 у.е. × 3,0285 (НБРБ 30.09.2026)
A9: Покупок в год на клиента | B9: 1 | C9: раз | D9: ввод | E9: Модель повторных покупок | F9: Годовой тариф — одна оплата в год; для помесячного Pro — 12 оплат по 10,10 BYN (эквивалент годового тарифа; тот же результат)
A10: Доля целевой географии | B10: 0.001958 | C10: % | D10: ввод | E10: Similarweb geography | F10: Допущение Д-01 (доля РФ по Similarweb × отношение запросов РБ/РФ в Вордстате); не используется формулами (П-13), доля вводится по доменам на листе 02
A11: Доля релевантного трафика | B11: 0.3846 | C11: % | D11: ввод | E11: Similarweb channels / keywords | F11: Средневзвешенная по визитам; не используется формулами (П-13)
A12: Коэффициент качества трафика | B12: 0.9053 | C12: доля | D12: ввод | E12: Engagement / экспертная оценка | F12: Средневзвешенная; не используется формулами (П-13)
A13: Дата заполнения | B13: 29.09.2026 | C13: дата | D13: ввод | E13: Исследователь | F13: Обновлять при пересчете
A15: Параметр сценария | B15: Осторожный | C15: Базовый | D15: Оптимистичный | E15: Смысл параметра | F15: Комментарий
A16: Охват неучтенных конкурентов | B16: 1.1 | C16: 1.35 | D16: 1.8 | E16: Во сколько раз рынок шире набора найденных конкурентов | F16: Больше 1, если Similarweb охватывает не всех игроков
A17: Коэффициент надежности данных | B17: 0.75 | C17: 0.9 | D17: 1 | E17: Поправка на оценочный характер данных Similarweb | F17: Для малых сайтов лучше снижать
A18: Корректировка на недоступный спрос | B18: 0.8 | C18: 1 | D18: 1.15 | E18: Поправка на спрос вне сайтов конкурентов | F18: Может учитывать социальные сети, рекомендации, мессенджеры
A19: Конверсия визит → заявка | B19: 0.005 | C19: 0.015 | D19: 0.03 | E19: Доля релевантных посещений, превращающихся в заявку | F19: Для услуг обычно ниже, чем для простых товаров
A20: Конверсия заявка → продажа | B20: 0.03 | C20: 0.04 | D20: 0.05 | E20: Доля заявок, превращающихся в оплату | F20: Регистрация → оплата Pro: допущение проекта 3–5 % (вне шкалы Word СЦ 10–60 % и шкалы шаблона)
A21: Множитель среднего чека | B21: 0.8 | C21: 1 | D21: 1.25 | E21: Корректирует базовый средний чек | F21: Используется для сценарного расчета
A22: Покупок в год | B22: 1 | C22: 1 | D22: 1 | E22: Частота покупок / продлений в год | F22: Для подписки может быть 12
A23: Достижимая доля рынка | B23: 0.005 | C23: 0.015 | D23: 0.04 | E23: Реально достижимая доля рынка новым бизнесом | F23: Используется для SOM

Sheet 02_Similarweb
A1: Ввод и расчет данных Similarweb по конкурентам
A2: Заполните строки по сайтам прямых и косвенных конкурентов. При бесплатном доступе данные фиксируются вручную из интерфейса Similarweb с указанием даты и ссылки на источник | B2: Заполните строки по сайтам прямых и косвенных конкурентов. При бесплатном доступе данные фиксируются вручную из интерфейса Similarweb с указанием даты и ссылки на источник | C2: Заполните строки по сайтам прямых и косвенных конкурентов. При бесплатном доступе данные фиксируются вручную из интерфейса Similarweb с указанием даты и ссылки на источник | D2: Заполните строки по сайтам прямых и косвенных конкурентов. При бесплатном доступе данные фиксируются вручную из интерфейса Similarweb с указанием даты и ссылки на источник | E2: Заполните строки по сайтам прямых и косвенных конкурентов. При бесплатном доступе данные фиксируются вручную из интерфейса Similarweb с указанием даты и ссылки на источник | F2: Заполните строки по сайтам прямых и косвенных конкурентов. При бесплатном доступе данные фиксируются вручную из интерфейса Similarweb с указанием даты и ссылки на источник | G2: Заполните строки по сайтам прямых и косвенных конкурентов. При бесплатном доступе данные фиксируются вручную из интерфейса Similarweb с указанием даты и ссылки на источник | H2: Заполните строки по сайтам прямых и косвенных конкурентов. При бесплатном доступе данные фиксируются вручную из интерфейса Similarweb с указанием даты и ссылки на источник | I2: Заполните строки по сайтам прямых и косвенных конкурентов. При бесплатном доступе данные фиксируются вручную из интерфейса Similarweb с указанием даты и ссылки на источник | J2: Заполните строки по сайтам прямых и косвенных конкурентов. При бесплатном доступе данные фиксируются вручную из интерфейса Similarweb с указанием даты и ссылки на источник | K2: Заполните строки по сайтам прямых и косвенных конкурентов. При бесплатном доступе данные фиксируются вручную из интерфейса Similarweb с указанием даты и ссылки на источник | L2: Заполните строки по сайтам прямых и косвенных конкурентов. При бесплатном доступе данные фиксируются вручную из интерфейса Similarweb с указанием даты и ссылки на источник | M2: Заполните строки по сайтам прямых и косвенных конкурентов. При бесплатном доступе данные фиксируются вручную из интерфейса Similarweb с указанием даты и ссылки на источник
A4: № | B4: Конкурент | C4: Домен | D4: Тип игрока | E4: Месячные посещения | F4: Доля целевой географии | G4: Доля релевантного трафика | H4: Коэффициент качества | I4: Релевантные посещения/мес | J4: Релевантные посещения/год | K4: Доля среди учтенных конкурентов | L4: Источник данных | M4: Комментарий
A5: 1 | B5: PlantUML | C5: plantuml.com | D5: прямой (текстовый DSL) | E5: 507000 | F5: 0.001958 | G5: 0.75 | H5: 1 | I5: =IFERROR(E5*F5*G5*H5,0) | J5: =I5*12 | K5: =IFERROR(I5/SUM($I\$5:$I\$19),0) | L5: https://www.similarweb.com/website/plantuml.com/ | M5: ФАКТ (Similarweb, авг. 2026, скриншот); период «последние 3 месяца» (августовское значение). Доля РБ — допущение Д-01, доля релевантного — Д-02
A6: 2 | B6: draw.io (diagrams.net) | C6: app.diagrams.net | D6: заменитель (визуальный редактор) | E6: 7800000 | F6: 0.001958 | G6: 0.35 | H6: 0.9 | I6: =IFERROR(E6*F6*G6*H6,0) | J6: =I6*12 | K6: =IFERROR(I6/SUM($I\$5:$I\$19),0) | L6: https://www.similarweb.com/website/app.diagrams.net/ | M6: отчёт ЛР1, без скриншота; период «последние 3 месяца» (августовское значение). Доля РБ — допущение Д-01, доля релевантного — Д-02
A7: 3 | B7: Eraser | C7: eraser.io | D7: прямой (AI + diagram as code) | E7: 678500 | F7: 0.001958 | G7: 0.5 | H7: 0.9 | I7: =IFERROR(E7*F7*G7*H7,0) | J7: =I7*12 | K7: =IFERROR(I7/SUM($I\$5:$I\$19),0) | L7: https://www.similarweb.com/website/eraser.io/ | M7: предварительный замер 17–23.09.2026, не подтверждён; период «последние 3 месяца» (августовское значение). Доля РБ — допущение Д-01, доля релевантного — Д-02
A8: 4 | B8: Mermaid Chart | C8: mermaidchart.com | D8: прямой (текстовый DSL) | E8: 20000 | F8: 0.001958 | G8: 0.7 | H8: 0.75 | I8: =IFERROR(E8*F8*G8*H8,0) | J8: =I8*12 | K8: =IFERROR(I8/SUM($I\$5:$I\$19),0) | L8: https://www.similarweb.com/website/mermaidchart.com/ | M8: предварительный замер: «менее 20 тыс.» (верхняя граница), не подтверждён; период «последние 3 месяца» (августовское значение). Доля РБ — допущение Д-01, доля релевантного — Д-02
I9: =IFERROR(E9*F9*G9*H9,0) | J9: =I9*12 | K9: =IFERROR(I9/SUM($I\$5:$I\$19),0)
I10: =IFERROR(E10*F10*G10*H10,0) | J10: =I10*12 | K10: =IFERROR(I10/SUM($I\$5:$I\$19),0)
I11: =IFERROR(E11*F11*G11*H11,0) | J11: =I11*12 | K11: =IFERROR(I11/SUM($I\$5:$I\$19),0)
I12: =IFERROR(E12*F12*G12*H12,0) | J12: =I12*12 | K12: =IFERROR(I12/SUM($I\$5:$I\$19),0)
I13: =IFERROR(E13*F13*G13*H13,0) | J13: =I13*12 | K13: =IFERROR(I13/SUM($I\$5:$I\$19),0)
I14: =IFERROR(E14*F14*G14*H14,0) | J14: =I14*12 | K14: =IFERROR(I14/SUM($I\$5:$I\$19),0)
I15: =IFERROR(E15*F15*G15*H15,0) | J15: =I15*12 | K15: =IFERROR(I15/SUM($I\$5:$I\$19),0)
I16: =IFERROR(E16*F16*G16*H16,0) | J16: =I16*12 | K16: =IFERROR(I16/SUM($I\$5:$I\$19),0)
I17: =IFERROR(E17*F17*G17*H17,0) | J17: =I17*12 | K17: =IFERROR(I17/SUM($I\$5:$I\$19),0)
I18: =IFERROR(E18*F18*G18*H18,0) | J18: =I18*12 | K18: =IFERROR(I18/SUM($I\$5:$I\$19),0)
I19: =IFERROR(E19*F19*G19*H19,0) | J19: =I19*12 | K19: =IFERROR(I19/SUM($I\$5:$I\$19),0)
A21: Итого учтенные конкуренты | I21: =SUM(I5:I19) | J21: =SUM(J5:J19)
B22: Выборка — 4 домена (< 5, Word СЦ: 5–15);com подтверждён скриншотом, остальные — выгрузка ЛР1)

Sheet 03_Сценарии
A1: Сценарный расчет рыночного трафика на основе Similarweb
A2: Лист переводит суммарный релевантный трафик найденных конкурентов в оценку общего рыночного трафика по трем сценариям. Коэффициенты берутся из листа 01_Параметры | B2: Лист переводит суммарный релевантный трафик найденных конкурентов в оценку общего рыночного трафика по трем сценариям. Коэффициенты берутся из листа 01_Параметры | C2: Лист переводит суммарный релевантный трафик найденных конкурентов в оценку общего рыночного трафика по трем сценариям. Коэффициенты берутся из листа 01_Параметры | D2: Лист переводит суммарный релевантный трафик найденных конкурентов в оценку общего рыночного трафика по трем сценариям. Коэффициенты берутся из листа 01_Параметры | E2: Лист переводит суммарный релевантный трафик найденных конкурентов в оценку общего рыночного трафика по трем сценариям. Коэффициенты берутся из листа 01_Параметры | F2: Лист переводит суммарный релевантный трафик найденных конкурентов в оценку общего рыночного трафика по трем сценариям. Коэффициенты берутся из листа 01_Параметры | G2: Лист переводит суммарный релевантный трафик найденных конкурентов в оценку общего рыночного трафика по трем сценариям. Коэффициенты берутся из листа 01_Параметры | H2: Лист переводит суммарный релевантный трафик найденных конкурентов в оценку общего рыночного трафика по трем сценариям. Коэффициенты берутся из листа 01_Параметры | I2: Лист переводит суммарный релевантный трафик найденных конкурентов в оценку общего рыночного трафика по трем сценариям. Коэффициенты берутся из листа 01_Параметры | J2: Лист переводит суммарный релевантный трафик найденных конкурентов в оценку общего рыночного трафика по трем сценариям. Коэффициенты берутся из листа 01_Параметры | K2: Лист переводит суммарный релевантный трафик найденных конкурентов в оценку общего рыночного трафика по трем сценариям. Коэффициенты берутся из листа 01_Параметры
A4: Сценарий | B4: Охват неучтенных конкурентов | C4: Коэффициент надежности данных | D4: Корректировка на недоступный спрос | E4: Релевантный трафик конкурентов/мес | F4: Оценка рыночного трафика/мес | G4: Оценка рыночного трафика/год | H4: Нижняя граница/год | I4: Верхняя граница/год | J4: Интерпретация | K4: Комментарий
A5: Осторожный | B5: ='01_Параметры'!B16 | C5: ='01_Параметры'!B17 | D5: ='01_Параметры'!B18 | E5: ='02_Similarweb'!I21 | F5: =E5*B5*C5*D5 | G5: =F5*12 | H5: =G5*0.85 | I5: =G5*1.15 | J5: Минимальная оценка при неполном охвате и пониженной надежности данных
A6: Базовый | B6: ='01_Параметры'!C16 | C6: ='01_Параметры'!C17 | D6: ='01_Параметры'!C18 | E6: ='02_Similarweb'!I21 | F6: =E6*B6*C6*D6 | G6: =F6*12 | H6: =G6*0.85 | I6: =G6*1.15 | J6: Рабочая оценка при умеренных допущениях
A7: Оптимистичный | B7: ='01_Параметры'!D16 | C7: ='01_Параметры'!D17 | D7: ='01_Параметры'!D18 | E7: ='02_Similarweb'!I21 | F7: =E7*B7*C7*D7 | G7: =F7*12 | H7: =G7*0.85 | I7: =G7*1.15 | J7: Верхняя оценка при широком рынке и благоприятных условиях

Sheet 04_Воронка
A1: Оценка объема рынка через цифровую воронку
A2: Расчет переводит рыночный трафик Similarweb в заявки, продажи, годовую выручку рынка и достижимую выручку нового бизнеса | B2: Расчет переводит рыночный трафик Similarweb в заявки, продажи, годовую выручку рынка и достижимую выручку нового бизнеса | C2: Расчет переводит рыночный трафик Similarweb в заявки, продажи, годовую выручку рынка и достижимую выручку нового бизнеса | D2: Расчет переводит рыночный трафик Similarweb в заявки, продажи, годовую выручку рынка и достижимую выручку нового бизнеса | E2: Расчет переводит рыночный трафик Similarweb в заявки, продажи, годовую выручку рынка и достижимую выручку нового бизнеса | F2: Расчет переводит рыночный трафик Similarweb в заявки, продажи, годовую выручку рынка и достижимую выручку нового бизнеса | G2: Расчет переводит рыночный трафик Similarweb в заявки, продажи, годовую выручку рынка и достижимую выручку нового бизнеса | H2: Расчет переводит рыночный трафик Similarweb в заявки, продажи, годовую выручку рынка и достижимую выручку нового бизнеса | I2: Расчет переводит рыночный трафик Similarweb в заявки, продажи, годовую выручку рынка и достижимую выручку нового бизнеса | J2: Расчет переводит рыночный трафик Similarweb в заявки, продажи, годовую выручку рынка и достижимую выручку нового бизнеса | K2: Расчет переводит рыночный трафик Similarweb в заявки, продажи, годовую выручку рынка и достижимую выручку нового бизнеса | L2: Расчет переводит рыночный трафик Similarweb в заявки, продажи, годовую выручку рынка и достижимую выручку нового бизнеса
A4: Сценарий | B4: Рыночные визиты/год | C4: Конверсия визит → заявка | D4: Конверсия заявка → продажа | E4: Продаж/год | F4: Средний чек | G4: Покупок в год | H4: Выручка рынка/год | I4: Достижимая доля | J4: Достижимая выручка/год | K4: TAM/SAM/SOM логика | L4: Комментарий
A5: Осторожный | B5: ='03_Сценарии'!G5 | C5: ='01_Параметры'!B19 | D5: ='01_Параметры'!B20 | E5: =B5*C5*D5 | F5: ='01_Параметры'!$B\$8*'01_Параметры'!B21 | G5: ='01_Параметры'!B22 | H5: =E5*F5*G5 | I5: ='01_Параметры'!B23 | J5: =H5*I5 | K5: SAM → SOM
A6: Базовый | B6: ='03_Сценарии'!G6 | C6: ='01_Параметры'!C19 | D6: ='01_Параметры'!C20 | E6: =B6*C6*D6 | F6: ='01_Параметры'!$B\$8*'01_Параметры'!C21 | G6: ='01_Параметры'!C22 | H6: =E6*F6*G6 | I6: ='01_Параметры'!C23 | J6: =H6*I6 | K6: SAM → SOM
A7: Оптимистичный | B7: ='03_Сценарии'!G7 | C7: ='01_Параметры'!D19 | D7: ='01_Параметры'!D20 | E7: =B7*C7*D7 | F7: ='01_Параметры'!$B\$8*'01_Параметры'!D21 | G7: ='01_Параметры'!D22 | H7: =E7*F7*G7 | I7: ='01_Параметры'!D23 | J7: =H7*I7 | K7: SAM → SOM
A10: Итог по воронке | B10: Осторожный | C10: Базовый | D10: Оптимистичный
A11: Выручка рынка/год | B11: =H5 | C11: =H6 | D11: =H7
A12: Достижимая выручка/год | B12: =J5 | C12: =J6 | D12: =J7
A13: Продаж/год | B13: =E5 | C13: =E6 | D13: =E7

Sheet 05_Платформа
A1: Платформенная модель: оценка GMV и выручки платформы
A2: Используйте этот лист, если электронный бизнес является платформой, агрегатором или маркетплейсом. GMV — это объем сделок через платформу, а не собственная выручка платформы | B2: Используйте этот лист, если электронный бизнес является платформой, агрегатором или маркетплейсом. GMV — это объем сделок через платформу, а не собственная выручка платформы | C2: Используйте этот лист, если электронный бизнес является платформой, агрегатором или маркетплейсом. GMV — это объем сделок через платформу, а не собственная выручка платформы | D2: Используйте этот лист, если электронный бизнес является платформой, агрегатором или маркетплейсом. GMV — это объем сделок через платформу, а не собственная выручка платформы | E2: Используйте этот лист, если электронный бизнес является платформой, агрегатором или маркетплейсом. GMV — это объем сделок через платформу, а не собственная выручка платформы | F2: Используйте этот лист, если электронный бизнес является платформой, агрегатором или маркетплейсом. GMV — это объем сделок через платформу, а не собственная выручка платформы | G2: Используйте этот лист, если электронный бизнес является платформой, агрегатором или маркетплейсом. GMV — это объем сделок через платформу, а не собственная выручка платформы | H2: Используйте этот лист, если электронный бизнес является платформой, агрегатором или маркетплейсом. GMV — это объем сделок через платформу, а не собственная выручка платформы | I2: Используйте этот лист, если электронный бизнес является платформой, агрегатором или маркетплейсом. GMV — это объем сделок через платформу, а не собственная выручка платформы | J2: Используйте этот лист, если электронный бизнес является платформой, агрегатором или маркетплейсом. GMV — это объем сделок через платформу, а не собственная выручка платформы | K2: Используйте этот лист, если электронный бизнес является платформой, агрегатором или маркетплейсом. GMV — это объем сделок через платформу, а не собственная выручка платформы
A4: Сценарий | B4: Рыночные визиты/год | C4: Регистрация/лид | D4: Активные участники | E4: Сделок на участника/год | F4: Средняя сумма сделки | G4: GMV/год | H4: Комиссия платформы | I4: Выручка платформы/год | J4: Достижимая доля | K4: Достижимая выручка платформы
A5: Осторожный | B5: ='03_Сценарии'!G5 | C5: 0.01 | D5: =B5*C5*0.3 | E5: 1 | F5: 600 | G5: =D5*E5*F5 | H5: 0.08 | I5: =G5*H5 | J5: 0.005 | K5: =I5*J5
A6: Базовый | B6: ='03_Сценарии'!G6 | C6: 0.03 | D6: =B6*C6*0.45 | E6: 2 | F6: 1000 | G6: =D6*E6*F6 | H6: 0.1 | I6: =G6*H6 | J6: 0.015 | K6: =I6*J6
A7: Оптимистичный | B7: ='03_Сценарии'!G7 | C7: 0.06 | D7: =B7*C7*0.6 | E7: 4 | F7: 1500 | G7: =D7*E7*F7 | H7: 0.15 | I7: =G7*H7 | J7: 0.04 | K7: =I7*J7

Sheet 06_Сверка
A1: Сверка сценарной оценки рынка по нескольким подходам
A2: Лист объединяет результаты Similarweb-воронки, платформенной модели и дополнительных методов. Значения дополнительных методов можно заменить собственными расчетами | B2: Лист объединяет результаты Similarweb-воронки, платформенной модели и дополнительных методов. Значения дополнительных методов можно заменить собственными расчетами | C2: Лист объединяет результаты Similarweb-воронки, платформенной модели и дополнительных методов. Значения дополнительных методов можно заменить собственными расчетами | D2: Лист объединяет результаты Similarweb-воронки, платформенной модели и дополнительных методов. Значения дополнительных методов можно заменить собственными расчетами | E2: Лист объединяет результаты Similarweb-воронки, платформенной модели и дополнительных методов. Значения дополнительных методов можно заменить собственными расчетами | F2: Лист объединяет результаты Similarweb-воронки, платформенной модели и дополнительных методов. Значения дополнительных методов можно заменить собственными расчетами | G2: Лист объединяет результаты Similarweb-воронки, платформенной модели и дополнительных методов. Значения дополнительных методов можно заменить собственными расчетами | H2: Лист объединяет результаты Similarweb-воронки, платформенной модели и дополнительных методов. Значения дополнительных методов можно заменить собственными расчетами
A4: Метод оценки | B4: Осторожный | C4: Базовый | D4: Оптимистичный | E4: Комментарий
A5: Similarweb → цифровая воронка | B5: ='04_Воронка'!J5 | C5: ='04_Воронка'!J6 | D5: ='04_Воронка'!J7 | E5: Основная оценка для сервисного электронного бизнеса
A6: Similarweb → платформенная GMV-модель | E6: Не применяется: NotaCode не является платформой (решение В-3); строка в MIN / AVERAGE / MAX не включается (П-9)
A7: Поисковый спрос | B7: 11.434792 | C7: 73.18267 | D7: 720.40182 | E7: Результат ПС-X (достижимая выручка через поисковый канал, BYN/год) — уровень SOM
A8: Количество потенциальных клиентов | B8: 456.16485 | C8: 3959.7643 | D8: 16590.145 | E8: Результат ПК-X (SOM по сценариям, BYN/год)
A9: Сверху вниз / снизу вверх | E9: Уровень «рынок» (СВ-X, ПК-X SAM) сопоставляется отдельно; здесь только SOM (П-9)
A11: Итоговый диапазон | B11: Осторожный | C11: Базовый | D11: Оптимистичный | E11: Интерпретация
A12: Минимум по методам | B12: =MIN(B5:B9) | C12: =MIN(C5:C9) | D12: =MIN(D5:D9) | E12: Нижняя граница с учетом всех подходов
A13: Среднее по методам | B13: =AVERAGE(B5:B9) | C13: =AVERAGE(C5:C9) | D13: =AVERAGE(D5:D9) | E13: Ориентир при сбалансированных допущениях
A14: Максимум по методам | B14: =MAX(B5:B9) | C14: =MAX(C5:C9) | D14: =MAX(D5:D9) | E14: Верхняя граница с учетом всех подходов
A15: Рекомендуемый диапазон | B15: =TEXT(B12,"# ##0")&" – "&TEXT(B14,"# ##0") | C15: =TEXT(C12,"# ##0")&" – "&TEXT(C14,"# ##0") | D15: =TEXT(D12,"# ##0")&" – "&TEXT(D14,"# ##0") | E15: Диапазон для управленческого вывода

Sheet 07_Дашборд
A1: Итоговая панель сценарной оценки рынка
A3: Показатель | B3: Значение | D3: Сценарная сводка
A4: Бизнес-идея | B4: ='01_Параметры'!B4 | D4: Показатель | E4: Осторожный | F4: Базовый | G4: Оптимистичный | H4: Комментарий
A5: География | B5: ='01_Параметры'!B5 | D5: Рыночный трафик/год | E5: ='03_Сценарии'!G5 | F5: ='03_Сценарии'!G6 | G5: ='03_Сценарии'!G7 | H5: Visits, Similarweb-based
A6: Базовый рыночный трафик/год | B6: ='03_Сценарии'!G6 | D6: Выручка рынка/год | E6: ='04_Воронка'!H5 | F6: ='04_Воронка'!H6 | G6: ='04_Воронка'!H7 | H6: Market revenue through funnel
A7: Базовая выручка рынка/год | B7: ='04_Воронка'!H6 | D7: Достижимая выручка/год | E7: ='04_Воронка'!J5 | F7: ='04_Воронка'!J6 | G7: ='04_Воронка'!J7 | H7: SOM
A8: Базовая достижимая выручка/год | B8: ='04_Воронка'!J6 | D8: GMV платформы/год | E8: ='05_Платформа'!G5 | F8: ='05_Платформа'!G6 | G8: ='05_Платформа'!G7 | H8: Only for platform model
A9: Базовая выручка платформы/год | B9: ='05_Платформа'!I6 | D9: Выручка платформы/год | E9: ='05_Платформа'!I5 | F9: ='05_Платформа'!I6 | G9: ='05_Платформа'!I7 | H9: Commission revenue
A10: Итоговый средний ориентир | B10: ='06_Сверка'!C13
A13: Шаблон итогового вывода
A14: По результатам сценарной оценки рынок в выбранных границах следует описывать диапазоном, а не одним числом. Базовый расчет формируется на основе данных Similarweb о релевантном трафике конкурентов, дополненных допущениями по конверсиям, среднему чеку и достижимой доле рынка. Осторожный сценарий отражает минимальную оценку при неполном охвате и низких конверсиях, оптимистичный — верхнюю границу при благоприятных условиях. Итоговый вывод должен сопровождаться указанием источников данных и ограничений Similarweb

Sheet 08_Источники
A1: Журнал источников данных и ограничений
A3: № | B3: Источник | C3: URL | D3: Какие данные используются | E3: Дата обращения | F3: Уровень надежности | G3: Комментарий / ограничение
A4: 1 | B4: Similarweb Website Traffic Checker | C4: https://www.similarweb.com/website/ | D4: Посещаемость сайта, каналы трафика, география, похожие сайты | E4: 03.05.2026 | F4: оценочные данные | G4: При бесплатном доступе доступен ограниченный набор показателей
A5: 2 | B5: Similarweb Data Methodology | C5: https://support.similarweb.com/hc/en-us/articles/360001631538-Similarweb-Data-Methodology | D5: Методологическое описание природы данных Similarweb | E5: 03.05.2026 | F5: методологический источник | G5: Данные основаны на цифровых сигналах, синтезе и моделировании
A6: 3 | B6: Similarweb Data Exporter | C6: https://support.similarweb.com/hc/en-us/articles/13252032019101-Data-Exporter | D6: Выгрузки, если доступна соответствующая подписка | E6: 03.05.2026 | F6: официальная справка | G6: Полные выгрузки зависят от тарифа и прав доступа
A7: 4 | B7: Сайты конкурентов | C7: [вставить URL] | D7: Прайсы, услуги, средний чек, позиционирование | E7: 03.05.2026 | F7: проверяемый источник | G7: Требуется ручная фиксация даты и условий
A8: 5 | B8: Google Trends / Яндекс Вордстат | C8: [вставить URL] | D8: Проверка интереса аудитории и сезонности | E8: 03.05.2026 | F8: дополнительный источник | G8: Используется для сопоставления с Similarweb
A9: 6
A10: 7
A11: 8
A12: 9
A13: 10
A14: 11
A15: 12
A16: 13
A17: 14
A18: 15
