Workbook

Sheet Справочники
A1: Справочники для выпадающих списков и шкал
A2: Используются на расчетных листах для унификации классификации, оценок и статусов
A3: Шкала_1_5 | B3: Сегменты | C3: Тип_проблемы | D3: Тип_ценности | E3: Тип_ЦП | F3: Тип_цифрового_товара | G3: Единица_монетизации | H3: Периодичность | I3: Статус | J3: Да_нет | K3: Элемент_БМ | L3: Решение_проверки | M3: Приоритет
A4: 1 | B4: B2B | C4: Функциональная | D4: Экономия времени | E4: Устранение боли | F4: Веб-сервис | G4: Пользователь | H4: Разово | I4: Черновик | J4: Да | K4: Клиентские сегменты | L4: Проходят проверку | M4: Критический
A5: 2 | B5: B2C | C5: Экономическая | D5: Снижение затрат | E5: Усиление результата | F5: Мобильное приложение | G5: Рабочее место | H5: Ежемесячно | I5: Нужно дополнить | J5: Нет | K5: Ценностное предложение | L5: Требуется доработка | M5: Высокий
A6: 3 | B6: B2B2C | C6: Организационная | D6: Снижение риска | E6: Повышение удобства | F6: Личный кабинет | G6: Транзакция | H6: Ежеквартально | I6: Готово | K6: Каналы | L6: Недостаточно данных | M6: Средний
A7: 4 | B7: Государственный сектор | C7: Информационная | D7: Повышение точности | E7: Автоматизация процесса | F7: Платформа | G7: Проект | H7: Ежегодно | I7: Отклонить | K7: Отношения с клиентами | M7: Низкий
A8: 5 | B8: Смешанный сегмент | C8: Эмоциональная | D8: Рост дохода | E8: Новая возможность | F8: Расширение/модуль | G8: Объем данных | H8: По использованию | K8: Потоки доходов
C9: Техническая | D9: Контроль и прозрачность | E9: Дифференциация | F9: Прикладной программный интерфейс | G9: Операция | H9: Подписка | K9: Ключевые ресурсы
C10: Правовая/регуляторная | D10: Доступность | E10: Снижение барьера входа | F10: Цифровой контент | G10: Пакет функций | H10: Комиссия | K10: Ключевые виды деятельности
D11: Персонализация | F11: Аналитический сервис | G11: Результат/отчет | H11: Смешанная модель | K11: Ключевые партнеры
F12: Маркетплейс | G12: Доступ к аудитории | K12: Структура затрат

Sheet Инструкция
A1: Excel-шаблон к методике формулирования ценностного предложения и цифрового товара
A2: Книга предназначена для перехода от анализа проблем и конкурентов к проверяемому ценностному предложению, цифровому товару и единице монетизации
A4: Раздел | B4: Что заполняется | C4: Результат
A5: 1. Исходные данные | B5: Фиксируются источники: отзывы, сайты конкурентов, страницы тарифов, описания функций, кейсы, часто задаваемые вопросы | C5: Контролируемая база доказательств
A6: 2. Проблемы клиентов | B6: Каждая проблема оценивается по частоте, интенсивности, срочности, незакрытости конкурентами, готовности платить и доказательности | C6: Рейтинг проблем для выбора опорной проблемы
A7: 3. Конкурентные решения | B7: По каждому конкуренту фиксируется, как он закрывает проблему и насколько убедительно оформляет свое решение | C7: Понимание рыночного стандарта и пробелов
A8: 4. Ценностные предложения | B8: Для выбранных проблем формулируется обещаемый результат, разрыв рынка и итоговая формулировка ценностного предложения | C8: Готовая формула ценности для клиента
A9: 5. Цифровой товар | B9: Ценностное предложение переводится в состав цифрового товара: функции, данные, сценарии использования и условия доступа | C9: Проверяемое описание товара как носителя ценности
A10: 6. Единица монетизации | B10: Определяется, за что именно платит клиент: пользователь, доступ, транзакция, операция, объем данных, результат, пакет функций | C10: Экономическая единица бизнес-модели
A11: 7. Связь с бизнес-моделью | B11: Проверяется, как товар и ценность связаны с клиентами, каналами, отношениями, ресурсами, доходами и затратами | C11: Согласованная бизнес-модель
A12: 8. Проверка связности | B12: Оценивается, не разорвана ли цепочка: проблема → ценность → товар → монетизация → бизнес-модель | C12: Итоговое решение о готовности концепции

Sheet Исходные данные
A1: Исходные данные анализа
A2: Единый реестр источников, на основании которых выделяются проблемы, конкурентные решения и признаки ценности
A4: ID источника | B4: Дата сбора | C4: Тип источника | D4: Площадка/сайт | E4: Компания/товар | F4: Ссылка | G4: Фрагмент факта | H4: Какая проблема/решение подтверждается | I4: Достоверность 1–5 | J4: Комментарий
A5: SRC-001 | B5: 30.09.2026 | C5: Поисковый спрос | D5: Яндекс Вордстат | E5: Запросы по нотациям, Беларусь | F5: https://wordstat.yandex.ru | G5: Частотность запросов uml, bpmn, plantuml, idef0, erd и др. за 29.08-27.09.2026 (ЛР1, ЛР4) | H5: Спрос на диаграммы формальных нотаций | I5: 4 | J5: Данные ЛР1-ЛР5; дата - день получения
A6: SRC-002 | B6: 30.09.2026 | C6: Трафик | D6: Similarweb Pro | E6: plantuml.com, mermaid.js.org и др. | F6: https://pro.similarweb.com | G6: PlantUML 739 657 визитов в месяц, 47,25 % органический поиск (июнь - август 2026) | H6: Текстовые инструменты востребованы | I6: 4 | J6: Данные ЛР1-ЛР5; дата - день получения
A7: SRC-003 | B7: 30.09.2026 | C7: Опрос | D7: Опрос студентов (ЛР4) | E7: 27 студентов | F7: ЛР4_Пять_сил_Портера/Python/data/survey_students.csv | G7: Коллаборация важна 26 из 27, экспорт PNG 27 из 27, SVG 18 из 27; средняя сложность Mermaid 2,6 из 5 | H7: Требования к функциям и порог сложности текстовых языков | I7: 3 | J7: Данные ЛР1-ЛР5; дата - день получения
A8: SRC-004 | B8: 30.09.2026 | C8: Опрос | D8: Опрос студентов (ЛР4) | E8: Готовность платить | F8: ЛР4_Пять_сил_Портера/Python/data/survey_students.csv | G8: 18 из 27 готовы платить; средняя максимальная цена 728 руб. (период в данных не указан) | H8: Готовность платить | I8: 3 | J8: Данные ЛР1-ЛР5; дата - день получения
A9: SRC-005 | B9: 30.09.2026 | C9: Оценки | D9: Trustpilot | E9: Miro, Lucidchart, Creately | F9: https://www.trustpilot.com | G9: Lucidchart 1,5 (116 отзывов), Miro 2,1 (155), Creately 1,9 (58) (ЛР4) | H9: Неудовлетворенность платными универсальными редакторами | I9: 3 | J9: Данные ЛР1-ЛР5; дата - день получения
A10: SRC-006 | B10: 30.09.2026 | C10: Оценки | D10: G2, Capterra | E10: Lucidchart, draw.io, Eraser | F10: https://www.g2.com | G10: Lucidchart G2 4,5 (8 988); draw.io Capterra 4,6 (773) (ЛР2-3, ЛР4) | H10: Рынок высоко оценивает универсальные редакторы | I10: 3 | J10: Данные ЛР1-ЛР5; дата - день получения
A11: SRC-007 | B11: 01.10.2026 | C11: Страница тарифов | D11: mermaid.ai | E11: Mermaid Chart | F11: https://mermaid.ai/pricing/ | G11: Basic Free (до 6 диаграмм, 15 ИИ-кредитов), Plus 10 у.е., Premium 20 у.е., Enterprise | H11: Тарифная логика за пользователя | I11: 5 | J11: Данные ЛР1-ЛР5; дата - день получения
A12: SRC-008 | B12: 01.10.2026 | C12: Страница тарифов | D12: lucid.app | E12: Lucidchart | F12: https://lucid.app/pricing/lucidchart | G12: Free (3 документа, 75 фигур), Individual 9 у.е., Team 10 у.е., Enterprise; пробный период 7 дней | H12: Тарифная логика, ограничения Free | I12: 5 | J12: Данные ЛР1-ЛР5; дата - день получения
A13: SRC-009 | B13: 01.10.2026 | C13: Страница тарифов | D13: eraser.io | E13: Eraser | F13: https://www.eraser.io/pricing | G13: Free 0 у.е. (3 файла, 3 ИИ-диаграммы), Starter 15 у.е., Business 45 у.е., Enterprise | H13: Лимиты ИИ как единица тарифа | I13: 5 | J13: Данные ЛР1-ЛР5; дата - день получения
A14: SRC-010 | B14: 01.10.2026 | C14: Страница тарифов | D14: whimsical.com | E14: Whimsical | F14: https://whimsical.com/pricing | G14: Free (50 объектов в месяц), Pro 10 у.е., Business 20 у.е. за редактора | H14: Тарифная логика | I14: 5 | J14: Данные ЛР1-ЛР5; дата - день получения
A15: SRC-011 | B15: 01.10.2026 | C15: Страница тарифов | D15: stormbpmn.com | E15: Storm | F15: https://stormbpmn.com/pricing | G15: Персональный бесплатно, Команда 1 200 руб., Бизнес 4 720 руб. за пользователя в месяц, Enterprise on-prem от 990 тыс. руб. в год | H15: Русскоязычный рынок, тарифы в рублях | I15: 5 | J15: Данные ЛР1-ЛР5; дата - день получения
A16: SRC-012 | B16: 01.10.2026 | C16: Сайт продукта | D16: drawio.com | E16: draw.io | F16: https://www.drawio.com/ | G16: Бесплатное приложение с открытым кодом, без enterprise-тарифа, 100M+ пользователей | H16: Бесплатный стандарт рынка | I16: 4 | J16: Данные ЛР1-ЛР5; дата - день получения
... A23: SRC-019 | B23: 23.09.2026 | C23: Документация проекта | D23: NotaCode/docs | E23: План MVP | F23: NotaCode/docs/planning/agile-plan.md | G23: Must: нотации волны 1 (UML, ERD, IDEF0, IDEF1X, IDEF3, DFD), редактор, холст, валидация, экспорт SVG и PNG, сохранение, ИИ-заглушка; BPMN - волна 2, сети Петри - волна 3; MVP до 06.12.2026 | H23: Состав первого релиза и сроки | I23: 4 | J23: Данные ЛР1-ЛР5; дата - день получения

Sheet Проблемы клиентов
A1: Анализ проблем клиентов
A2: Приоритет проблемы рассчитывается по частоте, интенсивности, срочности, незакрытости конкурентами, готовности платить и доказательности
A4: ID проблемы | B4: Сегмент | C4: Тип проблемы | D4: Формулировка проблемы клиента | E4: Частота 1–5 | F4: Интенсивность 1–5 | G4: Срочность 1–5 | H4: Незакрытость конкурентами 1–5 | I4: Готовность платить 1–5 | J4: Доказательность 1–5 | K4: Индекс проблемы | L4: Приоритет | M4: Комментарий
A5: P-001 | B5: B2C | C5: Информационная | D5: Студент или аналитик, которому нужна диаграмма UML, BPMN или ERD к проекту, тратит время на освоение синтаксиса текстовых языков (PlantUML, Mermaid) и теряет результат при ошибке; сложность Mermaid в опросе в среднем 2,6 из 5 | E5: 4 | F5: 3 | G5: 4 | H5: 3 | I5: 3 | J5: 3 | K5: =IF(COUNTA(E5:J5)=0,"",ROUND(((E5*0.18)+(F5*0.22)+(G5*0.18)+(H5*0.2)+(I5*0.14)+(J5*0.08))*20,0)) -> 67 | L5: =IF(K5="","",IF(K5>=80,"Критический",IF(K5>=65,"Высокий",IF(K5>=45,"Средний","Низкий")))) -> Высокий | M5: Оценка экспертная. Источники SRC-003, SRC-013, SRC-014
A6: P-002 | B6: Смешанный сегмент | C6: Функциональная | D6: Нотации IDEF0, DFD и сети Петри не поддерживаются ни одним из 8 просмотренных конкурентов; полный набор UML, BPMN и ERD есть только у платного Lucidchart | E6: 3 | F6: 4 | G6: 3 | H6: 5 | I6: 3 | J6: 4 | K6: =IF(COUNTA(E6:J6)=0,"",ROUND(((E6*0.18)+(F6*0.22)+(G6*0.18)+(H6*0.2)+(I6*0.14)+(J6*0.08))*20,0)) -> 74 | L6: =IF(K6="","",IF(K6>=80,"Критический",IF(K6>=65,"Высокий",IF(K6>=45,"Средний","Низкий")))) -> Высокий | M6: Оценка экспертная. Источники SRC-015, SRC-008; ЛР5
A7: P-003 | B7: B2C | C7: Экономическая | D7: Платные редакторы тарифицируются за пользователя от 9 до 20 у.е. в месяц (Mermaid Chart, Lucidchart, Eraser, Whimsical); бесплатные тарифы ограничены 3-6 документами или диаграммами | E7: 4 | F7: 4 | G7: 3 | H7: 3 | I7: 4 | J7: 4 | K7: =IF(COUNTA(E7:J7)=0,"",ROUND(((E7*0.18)+(F7*0.22)+(G7*0.18)+(H7*0.2)+(I7*0.14)+(J7*0.08))*20,0)) -> 72 | L7: =IF(K7="","",IF(K7>=80,"Критический",IF(K7>=65,"Высокий",IF(K7>=45,"Средний","Низкий")))) -> Высокий | M7: Оценка экспертная. Источники SRC-004, SRC-007 - SRC-010
A8: P-004 | B8: B2C | C8: Функциональная | D8: Совместная работа и экспорт - ожидаемый минимум: коллаборация важна 26 из 27 опрошенных, экспорт PNG 27 из 27, SVG 18 из 27; эти функции уже есть у большинства конкурентов | E8: 5 | F8: 3 | G8: 3 | H8: 2 | I8: 2 | J8: 4 | K8: =IF(COUNTA(E8:J8)=0,"",ROUND(((E8*0.18)+(F8*0.22)+(G8*0.18)+(H8*0.2)+(I8*0.14)+(J8*0.08))*20,0)) -> 62 | L8: =IF(K8="","",IF(K8>=80,"Критический",IF(K8>=65,"Высокий",IF(K8>=45,"Средний","Низкий")))) -> Средний | M8: Оценка экспертная. Источник SRC-003; ЛР5 (экспорт 8 из 8, коллаборация 6 из 8)
A9: P-005 | B9: B2C | C9: Техническая | D9: Редактор не подсказывает ошибки правил нотации при вводе; данных о реализации у конкурентов нет (не собрано: проверка продуктов) | E9: 3 | F9: 4 | G9: 3 | H9: 3 | I9: 3 | J9: 1 | K9: =IF(COUNTA(E9:J9)=0,"",ROUND(((E9*0.18)+(F9*0.22)+(G9*0.18)+(H9*0.2)+(I9*0.14)+(J9*0.08))*20,0)) -> 61 | L9: =IF(K9="","",IF(K9>=80,"Критический",IF(K9>=65,"Высокий",IF(K9>=45,"Средний","Низкий")))) -> Средний | M9: Оценка экспертная. Гипотеза; доказательность низкая
A10: P-006 | B10: Смешанный сегмент | C10: Информационная | D10: Русскоязычная среда и оплата в рублях: на русском языке с тарифами в рублях найден только Storm (платформа процессов BPMN) | E10: 3 | F10: 3 | G10: 2 | H10: 4 | I10: 3 | J10: 3 | K10: =IF(COUNTA(E10:J10)=0,"",ROUND(((E10*0.18)+(F10*0.22)+(G10*0.18)+(H10*0.2)+(I10*0.14)+(J10*0.08))*20,0)) -> 60 | L10: =IF(K10="","",IF(K10>=80,"Критический",IF(K10>=65,"Высокий",IF(K10>=45,"Средний","Низкий")))) -> Средний | M10: Оценка экспертная. Источник SRC-011

Sheet Конкурентные решения
A1: Анализ конкурентных решений
A2: Лист показывает, какие проблемы конкуренты уже закрывают, где находится рыночный стандарт и где сохраняется пространство для дифференциации
A4: Компания | B4: Сайт | C4: ID проблемы | D4: Как конкурент решает проблему | E4: Покрытие проблемы 1–5 | F4: Ясность обещания 1–5 | G4: Полнота товара 1–5 | H4: Удобство доступа 1–5 | I4: Доказательность 1–5 | J4: Индекс силы решения | K4: Уровень решения | L4: Комментарий
A5: Lucidchart | B5: https://lucid.co/lucidchart | C5: P-002 | D5: UML-, BPMN-шаблоны и ERD markup, но платный полный набор; IDEF0 и DFD не найдены | E5: 3 | F5: 4 | G5: 5 | H5: 3 | I5: 5 | J5: =IF(COUNTA(E5:I5)=0,"",ROUND(((E5*0.25)+(F5*0.2)+(G5*0.2)+(H5*0.15)+(I5*0.2))*20,0)) -> 80 | K5: =IF(J5="","",IF(J5>=80,"Сильное решение",IF(J5>=60,"Рыночный стандарт",IF(J5>=40,"Частичное решение","Слабое решение")))) -> Сильное решение | L5: Страницы просмотрены 01.10.2026 (ЛР5)
A6: draw.io | B6: https://www.drawio.com/ | C6: P-002 | D6: UML, ER и блок-схемы в бесплатном редакторе; IDEF0 и DFD на главной странице не найдены | E6: 3 | F6: 4 | G6: 4 | H6: 5 | I6: 4 | J6: =IF(COUNTA(E6:I6)=0,"",ROUND(((E6*0.25)+(F6*0.2)+(G6*0.2)+(H6*0.15)+(I6*0.2))*20,0)) -> 78 | K6: =IF(J6="","",IF(J6>=80,"Сильное решение",IF(J6>=60,"Рыночный стандарт",IF(J6>=40,"Частичное решение","Слабое решение")))) -> Рыночный стандарт | L6: Страницы просмотрены 01.10.2026 (ЛР5)
A7: PlantUML | B7: https://plantuml.com/ | C7: P-002 | D7: Классовые, ER и другие диаграммы из текста; IDEF0, DFD, BPMN-редактора нет в просмотренных разделах | E7: 3 | F7: 4 | G7: 4 | H7: 5 | I7: 4 | J7: =IF(COUNTA(E7:I7)=0,"",ROUND(((E7*0.25)+(F7*0.2)+(G7*0.2)+(H7*0.15)+(I7*0.2))*20,0)) -> 78 | K7: =IF(J7="","",IF(J7>=80,"Сильное решение",IF(J7>=60,"Рыночный стандарт",IF(J7>=40,"Частичное решение","Слабое решение")))) -> Рыночный стандарт | L7: Страницы просмотрены 01.10.2026 (ЛР5)
A8: PlantUML | B8: https://plantuml.com/ | C8: P-001 | D8: Язык описания с подробным справочником; требует изучения синтаксиса | E8: 3 | F8: 3 | G8: 4 | H8: 5 | I8: 4 | J8: =IF(COUNTA(E8:I8)=0,"",ROUND(((E8*0.25)+(F8*0.2)+(G8*0.2)+(H8*0.15)+(I8*0.2))*20,0)) -> 74 | K8: =IF(J8="","",IF(J8>=80,"Сильное решение",IF(J8>=60,"Рыночный стандарт",IF(J8>=40,"Частичное решение","Слабое решение")))) -> Рыночный стандарт | L8: Страницы просмотрены 01.10.2026 (ЛР5)
A9: Mermaid Chart | B9: https://www.mermaidchart.com/ | C9: P-001 | D9: Облачный редактор Mermaid с ИИ-кредитами (15 в Free) | E9: 4 | F9: 5 | G9: 4 | H9: 4 | I9: 5 | J9: =IF(COUNTA(E9:I9)=0,"",ROUND(((E9*0.25)+(F9*0.2)+(G9*0.2)+(H9*0.15)+(I9*0.2))*20,0)) -> 88 | K9: =IF(J9="","",IF(J9>=80,"Сильное решение",IF(J9>=60,"Рыночный стандарт",IF(J9>=40,"Частичное решение","Слабое решение")))) -> Сильное решение | L9: Страницы просмотрены 01.10.2026 (ЛР5)
A10: Eraser | B10: https://www.eraser.io/ | C10: P-001 | D10: ИИ-генерация диаграмм и diagram-as-code; Free: 3 ИИ-диаграммы | E10: 4 | F10: 5 | G10: 4 | H10: 4 | I10: 5 | J10: =IF(COUNTA(E10:I10)=0,"",ROUND(((E10*0.25)+(F10*0.2)+(G10*0.2)+(H10*0.15)+(I10*0.2))*20,0)) -> 88 | K10: =IF(J10="","",IF(J10>=80,"Сильное решение",IF(J10>=60,"Рыночный стандарт",IF(J10>=40,"Частичное решение","Слабое решение")))) -> Сильное решение | L10: Страницы просмотрены 01.10.2026 (ЛР5)
A11: Lucidchart | B11: https://lucid.app/pricing/lucidchart | C11: P-003 | D11: Free: 3 документа, 75 фигур; Individual 9 у.е., Team 10 у.е.. | E11: 2 | F11: 5 | G11: 5 | H11: 3 | I11: 5 | J11: =IF(COUNTA(E11:I11)=0,"",ROUND(((E11*0.25)+(F11*0.2)+(G11*0.2)+(H11*0.15)+(I11*0.2))*20,0)) -> 79 | K11: =IF(J11="","",IF(J11>=80,"Сильное решение",IF(J11>=60,"Рыночный стандарт",IF(J11>=40,"Частичное решение","Слабое решение")))) -> Рыночный стандарт | L11: Страницы просмотрены 01.10.2026 (ЛР5)
A12: Mermaid Chart | B12: https://mermaid.ai/pricing/ | C12: P-003 | D12: Free: до 6 диаграмм; Plus 10 у.е., Premium 20 у.е.. | E12: 3 | F12: 5 | G12: 4 | H12: 4 | I12: 5 | J12: =IF(COUNTA(E12:I12)=0,"",ROUND(((E12*0.25)+(F12*0.2)+(G12*0.2)+(H12*0.15)+(I12*0.2))*20,0)) -> 83 | K12: =IF(J12="","",IF(J12>=80,"Сильное решение",IF(J12>=60,"Рыночный стандарт",IF(J12>=40,"Частичное решение","Слабое решение")))) -> Сильное решение | L12: Страницы просмотрены 01.10.2026 (ЛР5)
A13: Whimsical | B13: https://whimsical.com/pricing | C13: P-003 | D13: Free: 50 объектов в месяц, водяной знак; Pro 10 у.е., Business 20 у.е.. | E13: 2 | F13: 4 | G13: 3 | H13: 4 | I13: 5 | J13: =IF(COUNTA(E13:I13)=0,"",ROUND(((E13*0.25)+(F13*0.2)+(G13*0.2)+(H13*0.15)+(I13*0.2))*20,0)) -> 70 | K13: =IF(J13="","",IF(J13>=80,"Сильное решение",IF(J13>=60,"Рыночный стандарт",IF(J13>=40,"Частичное решение","Слабое решение")))) -> Рыночный стандарт | L13: Страницы просмотрены 01.10.2026 (ЛР5)
A14: draw.io | B14: https://www.drawio.com/ | C14: P-003 | D14: Полностью бесплатное приложение с открытым кодом | E14: 5 | F14: 4 | G14: 4 | H14: 5 | I14: 4 | J14: =IF(COUNTA(E14:I14)=0,"",ROUND(((E14*0.25)+(F14*0.2)+(G14*0.2)+(H14*0.15)+(I14*0.2))*20,0)) -> 88 | K14: =IF(J14="","",IF(J14>=80,"Сильное решение",IF(J14>=60,"Рыночный стандарт",IF(J14>=40,"Частичное решение","Слабое решение")))) -> Сильное решение | L14: Страницы просмотрены 01.10.2026 (ЛР5)
A15: draw.io | B15: https://www.drawio.com/ | C15: P-004 | D15: Совместная работа в реальном времени, экспорт SVG, PNG, PDF | E15: 5 | F15: 4 | G15: 4 | H15: 5 | I15: 4 | J15: =IF(COUNTA(E15:I15)=0,"",ROUND(((E15*0.25)+(F15*0.2)+(G15*0.2)+(H15*0.15)+(I15*0.2))*20,0)) -> 88 | K15: =IF(J15="","",IF(J15>=80,"Сильное решение",IF(J15>=60,"Рыночный стандарт",IF(J15>=40,"Частичное решение","Слабое решение")))) -> Сильное решение | L15: Страницы просмотрены 01.10.2026 (ЛР5)
A16: Storm | B16: https://stormbpmn.com/pricing | C16: P-006 | D16: Русскоязычная платформа BPMN с тарифами в рублях; только процессная нотация | E16: 3 | F16: 5 | G16: 5 | H16: 3 | I16: 4 | J16: =IF(COUNTA(E16:I16)=0,"",ROUND(((E16*0.25)+(F16*0.2)+(G16*0.2)+(H16*0.15)+(I16*0.2))*20,0)) -> 80 | K16: =IF(J16="","",IF(J16>=80,"Сильное решение",IF(J16>=60,"Рыночный стандарт",IF(J16>=40,"Частичное решение","Слабое решение")))) -> Сильное решение | L16: Страницы просмотрены 01.10.2026 (ЛР5)

Sheet Ценностные предложения
A1: Формулирование ценностного предложения
A2: Ценностное предложение связывает опорную проблему клиента, конкурентный пробел и обещаемый измеримый результат
A4: ID ЦП | B4: ID проблемы | C4: Сегмент | D4: Опорная проблема | E4: Конкурентный пробел | F4: Обещаемый результат | G4: Механизм создания ценности | H4: Формулировка ценностного предложения | I4: Тип ЦП | J4: Тип ценности | K4: Индекс проблемы | L4: Статус | M4: Комментарий
A5: VP-001 | B5: P-002 | C5: Смешанный сегмент | D5: Нет единого инструмента для всех нотаций проекта: IDEF0, DFD и сети Петри не найдены у 8 конкурентов, полный набор UML, BPMN, ERD - только у платного Lucidchart | E5: Конкуренты закрывают UML, ERD и BPMN по отдельности; Lucidchart - платно (9-10 у.е. в месяц), draw.io и PlantUML - без IDEF0 и DFD | F5: Получить диаграмму в любой нотации проекта из текстового описания в одном бесплатном веб-инструменте | G5: Текстовый ввод, визуальный редактор, набор нотаций UML, BPMN 2.0, ERD, IDEF0, DFD, сети Петри, ИИ-ассистент, экспорт | H5: Для студентов технических специальностей и аналитиков ПО, которым нужны диаграммы UML, BPMN, ERD, IDEF0 и DFD к проектам и учебным работам, NotaCode - веб-IDE «диаграммы как код» - позволяет получить диаграмму в выбранной нотации по текстовому описанию в одном инструменте без установки, в отличие от текстовых языков без визуального редактора и платных редакторов с оплатой за пользователя, потому что поддерживает весь набор нотаций проекта (в том числе IDEF0, DFD и сети Петри, не найденные у 8 конкурентов) и имеет бесплатный уровень Free | I5: Дифференциация | J5: Доступность | K5: =IF(B5="","",IFERROR(INDEX('Проблемы клиентов'!$K$5:$K$10,MATCH(B5,'Проблемы клиентов'!$A$5:$A$10,0)),0)) -> 74 | L5: =IF(A5="","",IF(AND(B5<>"",F5<>"",G5<>"",H5<>"",I5<>"",J5<>""),"Готово","Нужно дополнить")) -> Готово | M5: Опорная проблема: наибольший индекс проблемы (74 по шаблону); ЦП нужно проверить на реальных клиентах

Sheet Цифровой товар
A1: Описание цифрового товара как носителя ценности
A2: На листе ценностное предложение переводится в состав цифрового товара, функции, пользовательский сценарий и условия доступа
A4: ID товара | B4: ID ЦП | C4: Название цифрового товара | D4: Тип цифрового товара | E4: Клиентская задача | F4: Базовая функция | G4: Расширенные функции | H4: Данные/алгоритмы как часть ценности | I4: Условия доступа и использования | J4: Носитель ценности | K4: Индекс товарной оформленности | L4: Статус | M4: Комментарий
A5: PR-001 | B5: VP-001 | C5: NotaCode | D5: Веб-сервис | E5: Построить диаграмму в нужной нотации из текстового описания без установки программ | F5: Редактор диаграмм «как код» (текст и визуализация) для UML, BPMN 2.0, ERD, IDEF0/IDEF1X/IDEF3, DFD, сетей Петри | G5: ИИ-ассистент (в MVP - заглушка с четырьмя режимами); экспорт SVG, PNG, XML и расширения нотации, кода и проекта (Pro: BPMN XML, XMI, PNML, draw.io, PlantUML, Mermaid, D2, DOT); работа в браузере (PWA) | H5: Описание диаграммы на текстовом языке; библиотека нотаций (данные и алгоритм разбора) | I5: Free - бесплатный доступ (все нотации, до 5 проектов, до 20 файлов, 20 последних версий); Pro - подписка 40 у.е. в год (48 у.е. при цене 4 у.е. в месяц, 4 x 12); вход через личный кабинет | J5: Да | K5: =IF(A5="","",ROUND((COUNTA(E5:I5)/5)*100,0)) -> 100 | L5: =IF(A5="","",IF(K5>=80,"Готово",IF(K5>=50,"Нужно дополнить","Черновик"))) -> Готово | M5: Продукт до выпуска MVP; состав подтверждается разработкой

Sheet Единица монетизации
A1: Определение единицы монетизации
A2: Единица монетизации показывает, за что именно платит клиент и как цифровой товар становится источником выручки
A4: ID монетизации | B4: ID товара | C4: Единица монетизации | D4: Что покупает клиент | E4: Периодичность | F4: Базовая цена | G4: Кол-во единиц в месяц | H4: Расчетная выручка | I4: Обоснование готовности платить | J4: Связь с ценностью 1–5 | K4: Простота тарификации 1–5 | L4: Повторяемость 1–5 | M4: Монетизационный потенциал | N4: Статус
A5: M-001 | B5: PR-001 | C5: Пользователь | D5: Подписка Pro: расширенные возможности и снятие ограничений Free | E5: Ежегодно | F5: 40 | G5: 1634 | H5: =IF(OR(F5="",G5=""),"",F5*G5) -> 65360 | I5: Базовая оценка ЛР2-3, ЛР4: около 1 634 платящих пользователей (SAM 197 988 BYN, около 65 375 у.е.); в опросе 18 из 27 готовы платить; у конкурентов 9-20 у.е. за пользователя в месяц | J5: 4 | K5: 5 | L5: 4 | M5: =IF(COUNTA(J5:L5)=0,"",ROUND(((J5*0.4)+(K5*0.3)+(L5*0.3))*20,0)) -> 86 | N5: =IF(A5="","",IF(M5>=80,"Готово",IF(M5>=60,"Нужно дополнить",IF(M5>=40,"Черновик","Отклонить")))) -> Готово
A6: M-002 | B6: PR-001 | C6: Пользователь | D6: Бесплатный доступ с ограничениями для студентов | E6: Разово | F6: 0 | G6: 0 | H6: =IF(OR(F6="",G6=""),"",F6*G6) -> 0 | I6: Free привлекает аудиторию и совпадает с практикой 8 из 8 конкурентов (бесплатный доступ или Free-тариф) | J6: 4 | K6: 5 | L6: 2 | M6: =IF(COUNTA(J6:L6)=0,"",ROUND(((J6*0.4)+(K6*0.3)+(L6*0.3))*20,0)) -> 74 | N6: =IF(A6="","",IF(M6>=80,"Готово",IF(M6>=60,"Нужно дополнить",IF(M6>=40,"Черновик","Отклонить")))) -> Нужно дополнить

Sheet Бизнес-модель
A1: Связь цифрового товара с бизнес-моделью
A2: Лист фиксирует, как ценностное предложение, цифровой товар и монетизация превращаются в элементы бизнес-модели
A4: ID модели | B4: ID товара | C4: Клиентские сегменты | D4: Ценностное предложение | E4: Каналы | F4: Отношения с клиентами | G4: Потоки доходов | H4: Ключевые ресурсы | I4: Ключевые виды деятельности | J4: Ключевые партнеры | K4: Структура затрат | L4: Индекс полноты бизнес-модели | M4: Комментарий
A5: BM-001 | B5: PR-001 | C5: Студенты технических специальностей (Free), аналитики и разработчики ПО (Pro); Беларусь, затем Россия и СНГ | D5: Диаграмма любой нотации проекта из текста в одном бесплатном веб-инструменте | E5: Сайт и PWA, поиск (Google, Яндекс), вузовские каналы, сообщества разработчиков | F5: Самообслуживание, документация, бесплатный уровень Free | G5: Подписка Pro 40 у.е. в год (48 у.е. при 4 x 12); Free без оплаты | H5: Платформа (PWA), движок нотаций, ИИ-ассистент, домен и репозиторий | I5: Разработка и поддержка движка нотаций, документация, продвижение | J5: Вузы (канал), платежный провайдер, ИИ-провайдер, облачная инфраструктура (не собрано: договоры) | K5: Разработка, облачная инфраструктура, ИИ-вызовы, поддержка | L5: =IF(A5="","",ROUND((COUNTA(C5:K5)/9)*100,0)) -> 100 | M5: Блоки 8-10 - гипотезы без подтверждения договорами

Sheet Проверка связности
A1: Проверка связности: проблема → ценность → товар → монетизация → бизнес-модель
A2: Итоговая проверка нужна для выявления разрывов между выбранной проблемой, обещанной ценностью, цифровым товаром и экономикой бизнес-модели
A4: ID проверки | B4: ID проблемы | C4: ID ЦП | D4: ID товара | E4: ID монетизации | F4: ID модели | G4: Индекс связности | H4: Решение | I4: Главный разрыв | J4: Что доработать
A5: CHK-001 | B5: P-002 | C5: VP-001 | D5: PR-001 | E5: M-001 | F5: BM-001 | G5: =IF(A5="","",ROUND((IFERROR(INDEX('Проблемы клиентов'!$K$5:$K$10,MATCH(B5,'Проблемы клиентов'!$A$5:$A$10,0)),0)*0.3+IFERROR(INDEX('Ценностные предложения'!$K$5:$K$5,MATCH(C5,'Ценностные предложения'!$A$5:$A$5,0)),0)*0.15+IFERROR(INDEX('Цифровой товар'!$K$5:$K$5,MATCH(D5,'Цифровой товар'!$A$5:$A$5,0)),0)*0.2+IFERROR(INDEX('Единица монетизации'!$M$5:$M$6,MATCH(E5,'Единица монетизации'!$A$5:$A$6,0)),0)*0.2+IFERROR(INDEX('Бизнес-модель'!$L$5:$L$5,MATCH(F5,'Бизнес-модель'!$A$5:$A$5,0)),0)*0.15),0)) -> 86 | H5: =IF(G5="","",IF(G5>=75,"Проходят проверку",IF(G5>=55,"Требуется доработка","Недостаточно данных"))) -> Проходят проверку | I5: Спрос не проверен на реальных клиентах; продукт до MVP | J5: Проверить цену Pro и состав Free опросом потребителей
A6: CHK-002 | B6: P-002 | C6: VP-001 | D6: PR-001 | E6: M-002 | F6: BM-001 | G6: =IF(A6="","",ROUND((IFERROR(INDEX('Проблемы клиентов'!$K$5:$K$10,MATCH(B6,'Проблемы клиентов'!$A$5:$A$10,0)),0)*0.3+IFERROR(INDEX('Ценностные предложения'!$K$5:$K$5,MATCH(C6,'Ценностные предложения'!$A$5:$A$5,0)),0)*0.15+IFERROR(INDEX('Цифровой товар'!$K$5:$K$5,MATCH(D6,'Цифровой товар'!$A$5:$A$5,0)),0)*0.2+IFERROR(INDEX('Единица монетизации'!$M$5:$M$6,MATCH(E6,'Единица монетизации'!$A$5:$A$6,0)),0)*0.2+IFERROR(INDEX('Бизнес-модель'!$L$5:$L$5,MATCH(F6,'Бизнес-модель'!$A$5:$A$5,0)),0)*0.15),0)) -> 83 | H6: =IF(G6="","",IF(G6>=75,"Проходят проверку",IF(G6>=55,"Требуется доработка","Недостаточно данных"))) -> Проходят проверку | I6: Free не дает выручки: нужна доля перехода в Pro | J6: Определить границу Free и Pro

Sheet Дашборд
A1: Сводный дашборд разработки ценностного предложения и цифрового товара
A2: Расчетные показатели обновляются после заполнения рабочих листов
A4: Показатель | B4: Значение | C4: Интерпретация | E4: Приоритет проблемы | F4: Количество | G4: Доля
A5: Количество выявленных проблем | B5: =COUNTIF('Проблемы клиентов'!$A$5:$A$10,"<>") -> 6 | C5: Объем базы проблем для выбора опорной проблемы | E5: Критический | F5: =COUNTIF('Проблемы клиентов'!$L$5:$L$10,E5) -> 0 | G5: =IFERROR(F5/SUM($F$5:$F$8),0) -> 0
A6: Максимальный индекс проблемы | B6: =IFERROR(MAX('Проблемы клиентов'!$K$5:$K$10),0) -> 74 | C6: Наиболее значимая проблема по текущей оценке | E6: Высокий | F6: =COUNTIF('Проблемы клиентов'!$L$5:$L$10,E6) -> 3 | G6: =IFERROR(F6/SUM($F$5:$F$8),0) -> 0.5
A7: Готовых ценностных предложений | B7: =COUNTIF('Ценностные предложения'!$L$5:$L$5,"Готово") -> 1 | C7: Количество формулировок, прошедших минимальную проверку полноты | E7: Средний | F7: =COUNTIF('Проблемы клиентов'!$L$5:$L$10,E7) -> 3 | G7: =IFERROR(F7/SUM($F$5:$F$8),0) -> 0.5
A8: Готовых цифровых товаров | B8: =COUNTIF('Цифровой товар'!$L$5:$L$5,"Готово") -> 1 | C8: Количество описаний товара с достаточной оформленностью | E8: Низкий | F8: =COUNTIF('Проблемы клиентов'!$L$5:$L$10,E8) -> 0 | G8: =IFERROR(F8/SUM($F$5:$F$8),0) -> 0
A9: Средний индекс связности | B9: =IFERROR(ROUND(AVERAGE('Проверка связности'!$G$5:$G$6),0),0) -> 85 | C9: Согласованность цепочки проблема → ценность → товар → монетизация → бизнес-модель
A10: Расчетная выручка по заполненным единицам | B10: =IFERROR(SUM('Единица монетизации'!$H$5:$H$6),0) -> 65360 | C10: Сумма расчетной месячной выручки по листу монетизации
E11: Решение проверки | F11: Количество | G11: Доля
E12: Проходят проверку | F12: =COUNTIF('Проверка связности'!$H$5:$H$6,E12) -> 2 | G12: =IFERROR(F12/SUM($F$12:$F$14),0) -> 1
E13: Требуется доработка | F13: =COUNTIF('Проверка связности'!$H$5:$H$6,E13) -> 0 | G13: =IFERROR(F13/SUM($F$12:$F$14),0) -> 0
E14: Недостаточно данных | F14: =COUNTIF('Проверка связности'!$H$5:$H$6,E14) -> 0 | G14: =IFERROR(F14/SUM($F$12:$F$14),0) -> 0

Sheet Журнал_6_1
A1: Журнал рабочей копии: источники, формулы, ограничения
A3: Раздел | B3: Код | C3: Содержание
A4: Источники | B4: И-1 | C4: Данные ЛР1-ЛР5 (Вордстат, Similarweb Pro, опрос 27 студентов, Trustpilot, G2, Capterra, страницы 8 конкурентов 01.10.2026); 19 источников; страниц сайтов 8 в реестре и 40 в ЛР5 (норма 10+); конкурентов 8 (норма 3+)
A5: Индекс проблемы | B5: Ф-1 | C5: Применена формула шаблона (веса 0,18/0,22/0,18/0,20/0,14/0,08, шкала 0-100). По формуле docx ИПП (0,20/0,25/0,20/0,15/0,10/0,10, шкала 1-5) для P-002: частота 3, последствие 4, неудовлетворенность 5, платежеспособность 3, реализуемость 5, связь с ростом 4 = 3,95 («использовать после уточнения сегмента»)
A6: ИКЦП | B6: Ф-2 | C6: Ясность 4, значимость 4, отличимость 4, доказуемость 3, ограниченность 4, монетизационная связность 4: ИКЦП = 3,83 - нужно уточнение (порог 4,0)
A7: ИКСТ | B7: Ф-3 | C7: Стандарт 3 (продукт до MVP), отличие 4, доказательность 3, монетизация 4, снижение риска 3, защищенность 2: ИКСТ = 3,30 - уточнить состав и обещание
A8: Монетизация | B8: Ф-4 | C8: Единица - пользователь (подписка Pro, год). Число единиц 1 634 - годовая оценка платящих по ЛР2-3; шаблон считает выручку как цена на число единиц (65 360 у.е. в год), а в дашборде называет ее месячной - в отчете читать как годовую
A9: Ограничения | B9: О-1 | C9: Опрос студентов пробный, по условным профилям (ЛР4) и подтверждает требования, но не спрос. Оценки шкал экспертные. Планируется собрать: не менее 30 текстов отзывов (G2, Capterra) и проверка спроса и цены на реальных клиентах
