Workbook

Sheet Инструкция
A1: Шаблон перехода от бизнес-логики и пользовательских сценариев к страницам и экранам
A2: Рабочая книга предназначена для проектирования состава сайта или мобильного приложения на основе результатов анализа проблем, конкурентов, ценностного предложения, цифрового товара, бизнес-модели и пользовательских сценариев
A4: Шаг | B4: Действие | C4: Что сделать
A5: 1 | B5: Собрать исходные выводы | C5: Перенесите ключевые выводы из анализа проблем, конкурентов, отзывов, бизнес-модели и пользовательских сценариев в лист «Банк_выводов»
A6: 2 | B6: Зафиксировать роли | C6: Опишите пользовательские роли и сегменты на листе «Роли_и_сегменты». Эти роли используются дальше для сценариев, страниц и экранов
A7: 3 | B7: Описать сценарии | C7: На листе «Пользовательские_сценарии» заполните пользовательские цели, потоки, данные, критичность, частоту и сложность
A8: 4 | B8: Вывести страницы и экраны | C8: На листе «Страницы_и_экраны» каждая интерфейсная единица должна иметь связанный сценарий, задачу пользователя, действие и источник требования
A9: 5 | B9: Проверить покрытие | C9: Лист «Матрица_сценарий_интерфейс» связывает сценарии со страницами и экранами. По нему рассчитывается покрытие сценариев
A10: 6 | B10: Описать навигацию и состояния | C10: Заполните переходы, состояния, ошибки, пустые состояния и сообщения пользователю. Это снижает риск разрывов сценария
A11: 7 | B11: Сформировать паспорта | C11: На листе «Паспорт_экрана» оформите итоговое описание каждой страницы или экрана для передачи в проектирование прототипа и техническое задание
A12: 8 | B12: Приоритизировать | C12: Используйте лист «Приоритизация» для выбора первой версии, следующих выпусков и отложенных интерфейсных единиц
A13: 9 | B13: Проверить готовность | C13: Листы «Проверка_связности» и «Дашборд» показывают полноту и согласованность проектной логики

Sheet Банк_выводов
A1: Банк исходных выводов из всех видов анализа
A2: Каждая строка – доказанный вывод, который может повлиять на состав страниц, экранов, навигации, контента или состояний
A4: ID вывода | B4: Вид анализа | C4: Объект анализа | D4: Вывод / факт | E4: Доказательство / ссылка | F4: Надежность 1–5 | G4: Значимость 1–5 | H4: Влияние на интерфейс | I4: Связанные роли | J4: Связанные сценарии | K4: Решение для страниц/экранов
A5: F-001 | B5: Анализ конкурентов по сайтам | C5: Тарифы 5 конкурентов | D5: Страница тарифов с ценой за пользователя есть у 5 из 8 конкурентов | E5: ЛР5: лист 10_Стандарт | F5: 5 | G5: 5 | H5: Нужна страница тарифов Free и Pro | I5: ROLE-001, ROLE-002 | J5: SC-002, SC-008 | K5: Включить страницу тарифов в первую версию
A6: F-002 | B6: Анализ цифрового товара и стандарта | C6: Рыночный стандарт | D6: Экспорт у 8 из 8, документация у 6 из 8, вход у 5 из 8, совместная работа у 6 из 8 | E6: ЛР5: лист 07_Стандарт_рынка | F6: 5 | G6: 5 | H6: Нужны экспорт, документация, вход | I6: ROLE-002, ROLE-003 | J6: SC-003, SC-006, SC-010 | K6: Включить в первую версию экран экспорта и вход; документацию - важная страница
A7: F-003 | B7: Анализ цифрового товара и стандарта | C7: Конкурентный пробел | D7: IDEF0, DFD, сети Петри не найдены у 8 конкурентов | E7: ЛР5: лист 04_Кано | F7: 4 | G7: 5 | H7: Нужен выбор нотации и страница возможностей с нотациями | I7: ROLE-003 | J7: SC-005 | K7: Показать нотации на странице возможностей и в выборе нотации
A8: F-004 | B8: Анализ бизнес-моделей конкурентов | C8: Каналы | D8: Органический поиск 47-59 % трафика у текстовых инструментов | E8: Similarweb Pro (ЛР4) | F8: 4 | G8: 4 | H8: Главная и страница возможностей должны отвечать на поисковые запросы по нотациям | I8: ROLE-001 | J8: SC-001 | K8: Главная и страницы нотаций для поиска
A9: F-005 | B9: Анализ проблем клиентов | C9: Проблема P-001 | D9: Сложность синтаксиса текстовых языков | E9: 6.1; опрос 27 студентов (данные пробного опроса) | F9: 3 | G9: 4 | H9: Нужны примеры, подсказки об ошибках и ИИ-ассистент | I9: ROLE-002 | J9: SC-004, SC-009 | K9: Включить примеры в редактор; подсказки - во вторую версию
A10: F-006 | B10: Анализ монетизации | C10: Единица монетизации | D10: Подписка Pro 40 у.е. в год за пользователя; Free без оплаты | E10: 6.1: M-001; 6.2 | F10: 3 | G10: 5 | H10: Нужны экран подписки и оплата | I10: ROLE-004 | J10: SC-008 | K10: Оплата Pro в первой версии, если выбран платежный провайдер
A11: F-007 | B11: Пользовательские сценарии | C11: 6.3: сценарии | D11: Критический сценарий: оформление подписки; высокие - первая диаграмма и экспорт | E11: 6.3: Excel/6_3_... | F11: 4 | G11: 5 | H11: Каждому сценарию нужна страница или экран | I11: ROLE-001 - ROLE-005 | J11: SC-001 - SC-010 | K11: Составить реестр единиц по сценариям
A12: F-008 | B12: Отзывы и опрос | C12: Опрос студентов | D12: Коллаборация важна 26 из 27, экспорт PNG 27 из 27 | E12: ЛР4: survey_students.csv | F12: 2 | G12: 4 | H12: Экспорт - обязательный экран; коллаборация - позже | I12: ROLE-002 | J12: SC-006 | K12: Экспорт в первую версию, коллаборация - во вторую

Sheet Роли_и_сегменты
A1: Роли и пользовательские сегменты
A2: Роли используются как связующее звено между бизнес-логикой, сценариями, страницами и экранами
A4: Роль_ID | B4: Роль / сегмент | C4: Цель роли | D4: Основная проблема | E4: Ожидаемая ценность | F4: Цифровая зрелость | G4: Частота использования | H4: Критичность задачи 1–5 | I4: Канал входа | J4: Примечание
A5: ROLE-001 | B5: Посетитель | C5: Найти инструмент для диаграммы нотации | D5: Не ясно, какой инструмент поддерживает нужную нотацию | E5: Быстро убедиться в наборе нотаций и цене | F5: 4 | G5: 4 | H5: 4 | I5: Поиск Google и Яндекс | J5: Студент или аналитик до регистрации
A6: ROLE-002 | B6: Новый пользователь | C6: Получить первую диаграмму | D6: Сложность синтаксиса текстовых языков | E6: Корректная диаграмма из текста | F6: 3 | G6: 4 | H6: 5 | I6: Сайт, регистрация | J6: Основной сегмент Free
A7: ROLE-003 | B7: Активный пользователь | C7: Регулярно строить диаграммы разных нотаций | D7: Нужны несколько инструментов | E7: Все нотации в одном месте | F7: 4 | G7: 5 | H7: 4 | I7: Личный кабинет | J7: Студенты старших курсов и аналитики
A8: ROLE-004 | B8: Платящий клиент | C8: Снять ограничения Free | D8: Ограничения бесплатного уровня | E8: Профессиональный результат | F8: 4 | G8: 3 | H8: 5 | I8: Прямой заход, кабинет | J8: Подписка Pro
A9: ROLE-005 | B9: Внутренний администратор | C9: Обрабатывать обращения и ошибки | D9: Обращения по нотациям и оплате | E9: Качество сервиса | F9: 5 | G9: 3 | H9: 3 | I9: Поддержка | J9: Роль команды проекта

Sheet Пользовательские_сценарии
A1: Пользовательские сценарии
A2: Сценарий должен иметь пользовательскую цель, поток действий, бизнес-результат и связку с интерфейсными единицами
A4: Сценарий_ID | B4: Роль_ID | C4: Этап пути | D4: Пользовательская цель | E4: Начальный триггер | F4: Основной поток | G4: Альтернативный поток | H4: Данные / контент | I4: Бизнес-результат | J4: Критичность 1–5 | K4: Частота 1–5 | L4: Сложность 1–5 | M4: Кол-во страниц/экранов | N4: Статус покрытия | O4: Приоритет сценария
A5: SC-001 | B5: ROLE-001 | C5: Вход в сценарий | D5: Найти инструмент для диаграммы нотации | E5: Задание по проектированию, поиск | F5: Запрос в поиске, переход на главную, страница возможностей | G5: Выбор другого инструмента | H5: Названия нотаций, примеры | I5: Рост трафика | J5: 4 | K5: 4 | L5: 2 | M5: =IF(A5="","",COUNTIF(Страницы_и_экраны!$E$5:$E$17,A5)) -> 1 | N5: =IF(A5="","",IF(M5>0,"Покрыт","Нет страницы/экрана")) -> Покрыт | O5: =IF(A5="","",MAX(0,MIN(100,ROUND(((J5*0.45)+(K5*0.35)-(L5*0.2))*20,0)))) -> 56
A6: SC-002 | B6: ROLE-001 | C6: Проверка соответствия | D6: Сравнить NotaCode с другими инструментами и увидеть цену | E6: Сомнение в выборе | F6: Страница возможностей, тарифы, документация | G6: Уход к draw.io или PlantUML | H6: Тарифы, сравнение | I6: Конверсия в регистрацию | J6: 4 | K6: 4 | L6: 2 | M6: =IF(A6="","",COUNTIF(Страницы_и_экраны!$E$5:$E$17,A6)) -> 2 | N6: =IF(A6="","",IF(M6>0,"Покрыт","Нет страницы/экрана")) -> Покрыт | O6: =IF(A6="","",MAX(0,MIN(100,ROUND(((J6*0.45)+(K6*0.35)-(L6*0.2))*20,0)))) -> 56
A7: SC-003 | B7: ROLE-002 | C7: Принятие решения | D7: Зарегистрироваться в бесплатном уровне | E7: Решение попробовать | F7: Кнопка входа, форма, подтверждение, переход в редактор | G7: Отказ от регистрации | H7: Почта, пароль | I7: Активация | J7: 4 | K7: 4 | L7: 2 | M7: =IF(A7="","",COUNTIF(Страницы_и_экраны!$E$5:$E$17,A7)) -> 1 | N7: =IF(A7="","",IF(M7>0,"Покрыт","Нет страницы/экрана")) -> Покрыт | O7: =IF(A7="","",MAX(0,MIN(100,ROUND(((J7*0.45)+(K7*0.35)-(L7*0.2))*20,0)))) -> 56
A8: SC-004 | B8: ROLE-002 | C8: Первое получение ценности | D8: Построить первую диаграмму из текста | E8: Задание на диаграмму | F8: Выбор нотации, ввод текста, предпросмотр, правка | G8: Ошибка синтаксиса, подсказка | H8: Текст диаграммы | I8: Первое значимое действие | J8: 5 | K8: 5 | L8: 4 | M8: =IF(A8="","",COUNTIF(Страницы_и_экраны!$E$5:$E$17,A8)) -> 2 | N8: =IF(A8="","",IF(M8>0,"Покрыт","Нет страницы/экрана")) -> Покрыт | O8: =IF(A8="","",MAX(0,MIN(100,ROUND(((J8*0.45)+(K8*0.35)-(L8*0.2))*20,0)))) -> 64
A9: SC-005 | B9: ROLE-003 | C9: Первое получение ценности | D9: Построить диаграмму IDEF0 или DFD | E9: Задание по стандарту моделирования | F9: Выбор нотации, ввод текста, предпросмотр | G9: Достигнут лимит проектов Free | H9: Текст диаграммы | I9: Отличие от конкурентов | J9: 5 | K9: 3 | L9: 4 | M9: =IF(A9="","",COUNTIF(Страницы_и_экраны!$E$5:$E$17,A9)) -> 1 | N9: =IF(A9="","",IF(M9>0,"Покрыт","Нет страницы/экрана")) -> Покрыт | O9: =IF(A9="","",MAX(0,MIN(100,ROUND(((J9*0.45)+(K9*0.35)-(L9*0.2))*20,0)))) -> 50
A10: SC-006 | B10: ROLE-002 | C10: Первое получение ценности | D10: Экспортировать диаграмму в PNG или SVG | E10: Оформление работы | F10: Кнопка экспорта, выбор формата, скачивание | G10: Формат недоступен | H10: Диаграмма, формат | I10: Удовлетворенность | J10: 5 | K10: 5 | L10: 2 | M10: =IF(A10="","",COUNTIF(Страницы_и_экраны!$E$5:$E$17,A10)) -> 1 | N10: =IF(A10="","",IF(M10>0,"Покрыт","Нет страницы/экрана")) -> Покрыт | O10: =IF(A10="","",MAX(0,MIN(100,ROUND(((J10*0.45)+(K10*0.35)-(L10*0.2))*20,0)))) -> 72
A11: SC-007 | B11: ROLE-003 | C11: Регулярное использование | D11: Сохранить диаграмму и вернуться к ней | E11: Возврат к заданию | F11: Вход, список диаграмм, открытие | G11: Потеря версии | H11: Сохраненные диаграммы | I11: Удержание | J11: 4 | K11: 4 | L11: 3 | M11: =IF(A11="","",COUNTIF(Страницы_и_экраны!$E$5:$E$17,A11)) -> 1 | N11: =IF(A11="","",IF(M11>0,"Покрыт","Нет страницы/экрана")) -> Покрыт | O11: =IF(A11="","",MAX(0,MIN(100,ROUND(((J11*0.45)+(K11*0.35)-(L11*0.2))*20,0)))) -> 52
A12: SC-008 | B12: ROLE-004 | C12: Продление и развитие | D12: Оформить подписку Pro | E12: Достигнут лимит Free | F12: Тарифы, выбор Pro, оплата 40 у.е. в год | G12: Ошибка оплаты | H12: Платежные данные | I12: Выручка Pro | J12: 5 | K12: 3 | L12: 3 | M12: =IF(A12="","",COUNTIF(Страницы_и_экраны!$E$5:$E$17,A12)) -> 2 | N12: =IF(A12="","",IF(M12>0,"Покрыт","Нет страницы/экрана")) -> Покрыт | O12: =IF(A12="","",MAX(0,MIN(100,ROUND(((J12*0.45)+(K12*0.35)-(L12*0.2))*20,0)))) -> 54
A13: SC-009 | B13: ROLE-002 | C13: Поддержка и ошибки | D13: Исправить ошибку в описании диаграммы | E13: Сообщение об ошибке | F13: Сообщение, подсказка, пример, правка | G13: Обращение в поддержку | H13: Текст диаграммы, сообщение | I13: Снижение оттока | J13: 4 | K13: 4 | L13: 3 | M13: =IF(A13="","",COUNTIF(Страницы_и_экраны!$E$5:$E$17,A13)) -> 1 | N13: =IF(A13="","",IF(M13>0,"Покрыт","Нет страницы/экрана")) -> Покрыт | O13: =IF(A13="","",MAX(0,MIN(100,ROUND(((J13*0.45)+(K13*0.35)-(L13*0.2))*20,0)))) -> 52
A14: SC-010 | B14: ROLE-003 | C14: Поддержка и ошибки | D14: Найти ответ в документации | E14: Вопрос по нотации | F14: Поиск, раздел документации, пример | G14: Обращение в поддержку | H14: Статьи документации | I14: Снижение нагрузки на поддержку | J14: 3 | K14: 3 | L14: 2 | M14: =IF(A14="","",COUNTIF(Страницы_и_экраны!$E$5:$E$17,A14)) -> 1 | N14: =IF(A14="","",IF(M14>0,"Покрыт","Нет страницы/экрана")) -> Покрыт | O14: =IF(A14="","",MAX(0,MIN(100,ROUND(((J14*0.45)+(K14*0.35)-(L14*0.2))*20,0)))) -> 40

Sheet Страницы_и_экраны
A1: Страницы сайта и экраны приложения
A2: Каждая интерфейсная единица должна выводиться из сценария, проблемы, ценностного предложения или требования бизнес-модели
A4: Unit_ID | B4: Тип | C4: Название | D4: Назначение | E4: Связанный сценарий_ID | F4: Роль_ID | G4: Этап пути | H4: Главная задача пользователя | I4: Ключевое действие | J4: Источник требования | K4: Данные / контент | L4: Компоненты | M4: Состояния | N4: Ошибки / исключения | O4: Нужна авторизация | P4: Монетизационная роль | Q4: Оценка приоритета | R4: Статус | S4: Доказательность 1–5 | T4: Полнота описания | U4: Решение
A5: U-001 | B5: Страница сайта | C5: Главная страница | D5: Объяснить, что делает NotaCode, и привести к возможностям и регистрации | E5: SC-001 | F5: ROLE-001 | G5: Вход в сценарий | H5: Понять, подходит ли инструмент | I5: Перейти к возможностям или регистрации | J5: A-007; ЛР5 | K5: Обещание, нотации, примеры | L5: Заголовок, список нотаций, призыв «Попробовать бесплатно» | M5: Обычное, загрузка | N5: Нет ответа сервера | O5: Нет | P5: Косвенная | Q5: =IF(A5="","",IFERROR(INDEX(Пользовательские_сценарии!$O$5:$O$14,MATCH(E5,Пользовательские_сценарии!$A$5:$A$14,0)),0)) -> 56 | R5: Принято | S5: 4 | T5: =IF(A5="","",ROUND(COUNTA(D5:P5)/13,2)) -> 1 | U5: Оставить
A6: U-002 | B6: Страница сайта | C6: Возможности и нотации | D6: Показать нотации UML, BPMN, ERD, IDEF0, DFD, сети Петри и отличие | E6: SC-002 | F6: ROLE-001 | G6: Понимание ценности | H6: Убедиться в наборе нотаций | I6: Перейти к тарифам или регистрации | J6: ЛР5: конкурентный пробел | K6: Список нотаций, примеры диаграмм | L6: Блоки нотаций, примеры, сравнение | M6: Обычное | N6: Нет ответа сервера | O6: Нет | P6: Косвенная | Q6: =IF(A6="","",IFERROR(INDEX(Пользовательские_сценарии!$O$5:$O$14,MATCH(E6,Пользовательские_сценарии!$A$5:$A$14,0)),0)) -> 56 | R6: Принято | S6: 4 | T6: =IF(A6="","",ROUND(COUNTA(D6:P6)/13,2)) -> 1 | U6: Оставить
A7: U-003 | B7: Страница сайта | C7: Тарифы Free и Pro | D7: Прозрачный выбор между Free и Pro | E7: SC-002 | F7: ROLE-001 | G7: Принятие решения | H7: Понять цену и ограничения | I7: Выбрать Pro и перейти к оплате | J7: ЛР5: тарифы у 5 из 8; M-001 | K7: Free 0 у.е., Pro 40 у.е. в год (48 у.е. при 4 x 12) | L7: Таблица тарифов, ограничения, вопросы | M7: Новый пользователь, тариф выбран, активная подписка | N7: Ошибка загрузки цен | O7: Нет | P7: Подведение к оплате | Q7: =IF(A7="","",IFERROR(INDEX(Пользовательские_сценарии!$O$5:$O$14,MATCH(E7,Пользовательские_сценарии!$A$5:$A$14,0)),0)) -> 56 | R7: Принято | S7: 4 | T7: =IF(A7="","",ROUND(COUNTA(D7:P7)/13,2)) -> 1 | U7: Оставить
A8: U-004 | B8: Страница сайта | C8: Документация и примеры | D8: Научиться пользоваться нотациями без поддержки | E8: SC-010 | F8: ROLE-003 | G8: Поддержка и ошибки | H8: Найти пример нотации | I8: Открыть пример и скопировать в редактор | J8: ЛР5: документация у 6 из 8 | K8: Статьи, примеры | L8: Поиск, список статей, пример | M8: Обычное, пустой поиск | N8: Статья не найдена | O8: Нет | P8: Косвенная | Q8: =IF(A8="","",IFERROR(INDEX(Пользовательские_сценарии!$O$5:$O$14,MATCH(E8,Пользовательские_сценарии!$A$5:$A$14,0)),0)) -> 40 | R8: Принято | S8: 3 | T8: =IF(A8="","",ROUND(COUNTA(D8:P8)/13,2)) -> 1 | U8: Оставить
A9: U-005 | B9: Страница сайта | C9: Регистрация и вход | D9: Получить доступ к редактору Free | E9: SC-003 | F9: ROLE-002 | G9: Принятие решения | H9: Зарегистрироваться | I9: Отправить форму регистрации | J9: ЛР5: вход у 5 из 8 | K9: Почта, пароль | L9: Форма, согласие с условиями | M9: Начальное, ошибка валидации, успех | N9: Почта занята, ошибка сети | O9: Нет | P9: Косвенная | Q9: =IF(A9="","",IFERROR(INDEX(Пользовательские_сценарии!$O$5:$O$14,MATCH(E9,Пользовательские_сценарии!$A$5:$A$14,0)),0)) -> 56 | R9: Принято | S9: 4 | T9: =IF(A9="","",ROUND(COUNTA(D9:P9)/13,2)) -> 1 | U9: Оставить
A10: U-006 | B10: Страница сайта | C10: Оплата Pro | D10: Оформить годовую подписку Pro | E10: SC-008 | F10: ROLE-004 | G10: Продление и развитие | H10: Оплатить подписку | I10: Подтвердить оплату | J10: M-001; 6.2 | K10: Платежные данные (у провайдера) | L10: Состав заказа, платежная форма, подтверждение | M10: Выбран тариф, оплата, успех, ошибка оплаты | N10: Отказ платежа, повтор | O10: Да | P10: Прямая | Q10: =IF(A10="","",IFERROR(INDEX(Пользовательские_сценарии!$O$5:$O$14,MATCH(E10,Пользовательские_сценарии!$A$5:$A$14,0)),0)) -> 54 | R10: Требует уточнения | S10: 3 | T10: =IF(A10="","",ROUND(COUNTA(D10:P10)/13,2)) -> 1 | U10: Уточнить
A11: U-007 | B11: Экран приложения | C11: Выбор нотации и шаблона | D11: Выбрать нотацию и начать с примера | E11: SC-005 | F11: ROLE-002 | G11: Первое получение ценности | H11: Выбрать нотацию | I11: Выбрать нотацию или пример | J11: ЛР5: стандарт; 6.3: F-001 | K11: Список нотаций, примеры | L11: Карточки нотаций, шаблоны | M11: Начальное, пустое | N11: Ошибка загрузки списка | O11: Да | P11: Косвенная | Q11: =IF(A11="","",IFERROR(INDEX(Пользовательские_сценарии!$O$5:$O$14,MATCH(E11,Пользовательские_сценарии!$A$5:$A$14,0)),0)) -> 50 | R11: Принято | S11: 4 | T11: =IF(A11="","",ROUND(COUNTA(D11:P11)/13,2)) -> 1 | U11: Оставить
A12: U-008 | B12: Экран приложения | C12: Рабочая область редактора | D12: Ввести текст диаграммы и увидеть результат | E12: SC-004 | F12: ROLE-002 | G12: Первое получение ценности | H12: Построить диаграмму | I12: Ввести текст и увидеть предпросмотр | J12: 6.3: F-001; ЛР5 | K12: Текст диаграммы | L12: Поле ввода, предпросмотр, панель ошибок | M12: Нормальное, пустое, загрузка, ошибка, успех | N12: Ошибка синтаксиса, ошибка сети | O12: Да | P12: Прямая (ограничения Free) | Q12: =IF(A12="","",IFERROR(INDEX(Пользовательские_сценарии!$O$5:$O$14,MATCH(E12,Пользовательские_сценарии!$A$5:$A$14,0)),0)) -> 64 | R12: Принято | S12: 4 | T12: =IF(A12="","",ROUND(COUNTA(D12:P12)/13,2)) -> 1 | U12: Оставить
A13: U-009 | B13: Экран приложения | C13: Результат и экспорт | D13: Получить файл диаграммы | E13: SC-006 | F13: ROLE-002 | G13: Первое получение ценности | H13: Скачать диаграмму | I13: Выбрать формат и скачать | J13: ЛР5: экспорт у 8 из 8 | K13: Диаграмма, формат | L13: Выбор формата PNG, SVG, кнопка скачивания | M13: Нормальное, успех, формат недоступен | N13: Ошибка экспорта | O13: Да | P13: Прямая (форматы Pro) | Q13: =IF(A13="","",IFERROR(INDEX(Пользовательские_сценарии!$O$5:$O$14,MATCH(E13,Пользовательские_сценарии!$A$5:$A$14,0)),0)) -> 72 | R13: Принято | S13: 5 | T13: =IF(A13="","",ROUND(COUNTA(D13:P13)/13,2)) -> 1 | U13: Оставить
A14: U-010 | B14: Экран приложения | C14: Мои диаграммы | D14: Вернуться к сохраненным диаграммам | E14: SC-007 | F14: ROLE-003 | G14: Регулярное использование | H14: Открыть сохраненную диаграмму | I14: Открыть диаграмму из списка | J14: ЛР5: история версий у 5 из 8 | K14: Список диаграмм | L14: Список, поиск, действия | M14: Список, пустой список, загрузка | N14: Диаграмма не найдена | O14: Да | P14: Косвенная | Q14: =IF(A14="","",IFERROR(INDEX(Пользовательские_сценарии!$O$5:$O$14,MATCH(E14,Пользовательские_сценарии!$A$5:$A$14,0)),0)) -> 52 | R14: Принято | S14: 3 | T14: =IF(A14="","",ROUND(COUNTA(D14:P14)/13,2)) -> 1 | U14: Оставить
A15: U-011 | B15: Экран приложения | C15: Подсказка об ошибке синтаксиса | D15: Объяснить ошибку и предложить исправление | E15: SC-009 | F15: ROLE-002 | G15: Поддержка и ошибки | H15: Исправить ошибку | I15: Принять подсказку или исправить вручную | J15: Проблема P-001 (6.1); данные о реализации - гипотеза | K15: Текст диаграммы, сообщение | L15: Сообщение, пример исправления | M15: Ошибка, исправлено | N15: Подсказка недоступна | O15: Да | P15: Косвенная | Q15: =IF(A15="","",IFERROR(INDEX(Пользовательские_сценарии!$O$5:$O$14,MATCH(E15,Пользовательские_сценарии!$A$5:$A$14,0)),0)) -> 52 | R15: Гипотеза | S15: 2 | T15: =IF(A15="","",ROUND(COUNTA(D15:P15)/13,2)) -> 1 | U15: Перенести в следующий выпуск
A16: U-012 | B16: Экран приложения | C16: Профиль и подписка | D16: Управлять подпиской и настройками | E16: SC-008 | F16: ROLE-004 | G16: Продление и развитие | H16: Проверить и продлить подписку | I16: Продлить или отменить подписку | J16: M-001 | K16: Статус подписки, дата продления | L16: Профиль, подписка, настройки | M16: Free, активная подписка, истекший доступ | N16: Ошибка продления | O16: Да | P16: Прямая | Q16: =IF(A16="","",IFERROR(INDEX(Пользовательские_сценарии!$O$5:$O$14,MATCH(E16,Пользовательские_сценарии!$A$5:$A$14,0)),0)) -> 54 | R16: Принято | S16: 3 | T16: =IF(A16="","",ROUND(COUNTA(D16:P16)/13,2)) -> 1 | U16: Оставить
A17: U-013 | B17: Экран приложения | C17: ИИ-ассистент | D17: Описать диаграмму словами и получить текст диаграммы | E17: SC-004 | F17: ROLE-002 | G17: Первое получение ценности | H17: Сформулировать диаграмму словами | I17: Отправить запрос ассистенту | J17: 6.3: F-011; Eraser, Mermaid Chart | K17: Запрос, ответ | L17: Поле запроса, ответ, применение к редактору | M17: Начальное, загрузка, ответ, лимит исчерпан | N17: Лимит ИИ, ошибка сервиса | O17: Да | P17: Прямая (лимиты ИИ) | Q17: =IF(A17="","",IFERROR(INDEX(Пользовательские_сценарии!$O$5:$O$14,MATCH(E17,Пользовательские_сценарии!$A$5:$A$14,0)),0)) -> 64 | R17: Гипотеза | S17: 3 | T17: =IF(A17="","",ROUND(COUNTA(D17:P17)/13,2)) -> 1 | U17: Перенести в следующий выпуск

Sheet Матрица_сценарий_интерфейс
A1: Матрица связи сценариев со страницами и экранами
A2: Используется для проверки покрытия сценариев и исключения интерфейсных единиц без понятной задачи
A4: Связь_ID | B4: Сценарий_ID | C4: Unit_ID | D4: Тип связи | E4: Обязательность | F4: Порядок в сценарии | G4: Предыдущее Unit_ID | H4: Следующее Unit_ID | I4: Комментарий
A5: M-001 | B5: SC-001 | C5: U-001 | D5: Основной | E5: Обязательная | F5: 1 | H5: U-002 | I5: Главная страница ведет к регистрации или демонстрации
A6: M-002 | B6: SC-001 | C6: U-002 | D6: Вспомогательный | E6: Обязательная | F6: 2 | G6: U-001 | I6: Экран регистрации запускает пользовательскую работу с товаром
A7: M-003 | B7: SC-002 | C7: U-002 | D7: Основной | E7: Обязательная | F7: 1 | H7: U-003 | I7: Шаг 1 сценария SC-002: Возможности и нотации; основной шаг, обязательная
A8: M-004 | B8: SC-002 | C8: U-003 | D8: Вспомогательный | E8: Обязательная | F8: 2 | G8: U-002 | I8: Шаг 2 сценария SC-002: Тарифы Free и Pro; вспомогательный шаг, обязательная
A9: M-005 | B9: SC-003 | C9: U-005 | D9: Основной | E9: Обязательная | F9: 1 | H9: U-007 | I9: Шаг 1 сценария SC-003: Регистрация и вход; основной шаг, обязательная
A10: M-006 | B10: SC-003 | C10: U-007 | D10: Вспомогательный | E10: Обязательная | F10: 2 | G10: U-005 | I10: Шаг 2 сценария SC-003: Выбор нотации и шаблона; вспомогательный шаг, обязательная
A11: M-007 | B11: SC-004 | C11: U-007 | D11: Основной | E11: Обязательная | F11: 1 | H11: U-008 | I11: Шаг 1 сценария SC-004: Выбор нотации и шаблона; основной шаг, обязательная
A12: M-008 | B12: SC-004 | C12: U-008 | D12: Вспомогательный | E12: Обязательная | F12: 2 | G12: U-007 | H12: U-013 | I12: Шаг 2 сценария SC-004: Рабочая область редактора; вспомогательный шаг, обязательная
A13: M-009 | B13: SC-004 | C13: U-013 | D13: Вспомогательный | E13: Желательная | F13: 3 | G13: U-008 | I13: Шаг 3 сценария SC-004: ИИ-ассистент; вспомогательный шаг, желательная
A14: M-010 | B14: SC-005 | C14: U-007 | D14: Основной | E14: Обязательная | F14: 1 | H14: U-008 | I14: Шаг 1 сценария SC-005: Выбор нотации и шаблона; основной шаг, обязательная
A15: M-011 | B15: SC-005 | C15: U-008 | D15: Вспомогательный | E15: Обязательная | F15: 2 | G15: U-007 | I15: Шаг 2 сценария SC-005: Рабочая область редактора; вспомогательный шаг, обязательная
A16: M-012 | B16: SC-006 | C16: U-009 | D16: Основной | E16: Обязательная | F16: 1 | I16: Шаг 1 сценария SC-006: Результат и экспорт; основной шаг, обязательная
A17: M-013 | B17: SC-007 | C17: U-010 | D17: Основной | E17: Обязательная | F17: 1 | I17: Шаг 1 сценария SC-007: Мои диаграммы; основной шаг, обязательная
A18: M-014 | B18: SC-008 | C18: U-003 | D18: Основной | E18: Обязательная | F18: 1 | H18: U-006 | I18: Шаг 1 сценария SC-008: Тарифы Free и Pro; основной шаг, обязательная
A19: M-015 | B19: SC-008 | C19: U-006 | D19: Вспомогательный | E19: Обязательная | F19: 2 | G19: U-003 | H19: U-012 | I19: Шаг 2 сценария SC-008: Оплата Pro; вспомогательный шаг, обязательная
A20: M-016 | B20: SC-008 | C20: U-012 | D20: Вспомогательный | E20: Желательная | F20: 3 | G20: U-006 | I20: Шаг 3 сценария SC-008: Профиль и подписка; вспомогательный шаг, желательная
A21: M-017 | B21: SC-009 | C21: U-011 | D21: Основной | E21: Обязательная | F21: 1 | I21: Шаг 1 сценария SC-009: Подсказка об ошибке синтаксиса; основной шаг, обязательная
A22: M-018 | B22: SC-010 | C22: U-004 | D22: Основной | E22: Обязательная | F22: 1 | I22: Шаг 1 сценария SC-010: Документация и примеры; основной шаг, обязательная

Sheet Навигация_и_карта
A1: Навигация и карта переходов
A2: Каждый переход описывает действие, условие, направление и риск разрыва пользовательского сценария
A4: Переход_ID | B4: Откуда Unit_ID | C4: Куда Unit_ID | D4: Событие / действие | E4: Условие | F4: Роль_ID | G4: Этап пути | H4: Тип перехода | I4: Риск разрыва 1–5 | J4: Комментарий
A5: N-001 | B5: U-001 | C5: U-002 | D5: Открыть возможности | E5: Нет | F5: ROLE-001 | G5: Понимание ценности | H5: Сценарный | I5: 2 | J5: Главная ведет к нотациям
A6: N-002 | B6: U-001 | C6: U-005 | D6: Нажать «Попробовать бесплатно» | E6: Нет | F6: ROLE-001 | G6: Принятие решения | H6: Коммерческий | I6: 2 | J6: Прямой путь в Free
A7: N-003 | B7: U-002 | C7: U-003 | D7: Открыть тарифы | E7: Нет | F7: ROLE-001 | G7: Проверка соответствия | H7: Сценарный | I7: 2 | J7: Сравнение перед регистрацией
A8: N-004 | B8: U-002 | C8: U-005 | D8: Нажать «Попробовать бесплатно» | E8: Нет | F8: ROLE-001 | G8: Принятие решения | H8: Коммерческий | I8: 2 | J8: Регистрация
A9: N-005 | B9: U-003 | C9: U-006 | D9: Выбрать Pro | E9: Пользователь вошел | F9: ROLE-004 | G9: Продление и развитие | H9: Коммерческий | I9: 3 | J9: Переход к оплате
A10: N-006 | B10: U-003 | C10: U-005 | D10: Выбрать Free | E10: Нет аккаунта | F10: ROLE-001 | G10: Принятие решения | H10: Коммерческий | I10: 2 | J10: Регистрация
A11: N-007 | B11: U-005 | C11: U-007 | D11: Подтвердить регистрацию | E11: Успех | F11: ROLE-002 | G11: Первое получение ценности | H11: По состоянию | I11: 2 | J11: Переход к выбору нотации
A12: N-008 | B12: U-007 | C12: U-008 | D12: Выбрать нотацию | E12: Нотация доступна | F12: ROLE-002 | G12: Первое получение ценности | H12: Сценарный | I12: 2 | J12: Открыть редактор
A13: N-009 | B13: U-008 | C13: U-009 | D13: Нажать «Экспорт» | E13: Диаграмма построена | F13: ROLE-002 | G13: Первое получение ценности | H13: Сценарный | I13: 2 | J13: Получить файл
A14: N-010 | B14: U-008 | C14: U-011 | D14: Показать ошибку | E14: Ошибка синтаксиса | F14: ROLE-002 | G14: Поддержка и ошибки | H14: По состоянию | I14: 3 | J14: Подсказка
A15: N-011 | B15: U-008 | C15: U-013 | D15: Открыть ИИ-ассистента | E15: Лимит не исчерпан | F15: ROLE-002 | G15: Первое получение ценности | H15: Сценарный | I15: 3 | J15: Гипотеза
A16: N-012 | B16: U-009 | C16: U-010 | D16: Сохранить | E16: Пользователь вошел | F16: ROLE-003 | G16: Регулярное использование | H16: Возвратный | I16: 2 | J16: Возврат к работе
... A19: N-015 | B19: U-004 | C19: U-008 | D19: Открыть пример в редакторе | E19: Пример выбран | F19: ROLE-003 | G19: Поддержка и ошибки | H19: Сервисный | I19: 2 | J19: Из документации

Sheet Состояния_и_ошибки
A1: Состояния, ошибки и исключения
A2: Для каждой ключевой страницы или экрана фиксируются нормальные, пустые, загрузочные, ошибочные и успешные состояния
A4: State_ID | B4: Unit_ID | C4: Нормальное состояние | D4: Пустое состояние | E4: Загрузка | F4: Ошибка валидации | G4: Ошибка сети/сервера | H4: Нет прав | I4: Успешное завершение | J4: Сообщение пользователю | K4: Полнота состояний
A5: S-001 | B5: U-003 | C5: Таблица тарифов Free и Pro | D5: Тарифы недоступны | E5: Индикатор загрузки цен | F5: Не применимо | G5: Не удалось загрузить цены; повторить | H5: Не требуется | I5: Тариф выбран, переход к оплате | J5: Выберите тариф, чтобы продолжить | K5: =IF(A5="","",ROUND(COUNTA(C5:J5)/8,2)) -> 1
A6: S-002 | B6: U-005 | C6: Форма регистрации | D6: Пустая форма | E6: Отправка формы | F6: Почта указана неверно | G6: Сервер недоступен; повторить позже | H6: Не требуется | I6: Аккаунт создан, переход в редактор | J6: Проверьте почту и пароль | K6: =IF(A6="","",ROUND(COUNTA(C6:J6)/8,2)) -> 1
A7: S-003 | B7: U-006 | C7: Состав заказа и форма оплаты | D7: Тариф не выбран | E7: Обработка платежа | F7: Неверные данные платежа | G7: Платеж не прошел; повторить | H7: Нужен вход | I7: Подписка Pro активна | J7: Платеж не выполнен; деньги не списаны | K7: =IF(A7="","",ROUND(COUNTA(C7:J7)/8,2)) -> 1
A8: S-004 | B8: U-008 | C8: Редактор с предпросмотром | D8: Пустое поле: пример нотации | E8: Построение диаграммы | F8: Ошибка синтаксиса: строка и причина | G8: Нет соединения; черновик сохранен локально | H8: Нотация доступна в Pro | I8: Диаграмма построена | J8: Найдена ошибка в строке; посмотрите пример | K8: =IF(A8="","",ROUND(COUNTA(C8:J8)/8,2)) -> 1
A9: S-005 | B9: U-009 | C9: Выбор формата и скачивание | D9: Нет диаграммы для экспорта | E9: Подготовка файла | F9: Формат не поддерживается | G9: Ошибка экспорта; повторить | H9: Формат доступен в Pro | I9: Файл скачан | J9: Экспорт выполнен | K9: =IF(A9="","",ROUND(COUNTA(C9:J9)/8,2)) -> 1
A10: S-006 | B10: U-010 | C10: Список сохраненных диаграмм | D10: Нет сохраненных диаграмм | E10: Загрузка списка | F10: Не применимо | G10: Не удалось загрузить список | H10: Нужен вход | I10: Диаграмма открыта | J10: Создайте первую диаграмму | K10: =IF(A10="","",ROUND(COUNTA(C10:J10)/8,2)) -> 1

Sheet Контент_и_данные
A1: Контент и данные для страниц и экранов
A2: Лист нужен для перевода сценариев в состав данных, текстов, полей, правил отображения и источников информации
A4: Unit_ID | B4: Элемент контента / данных | C4: Источник данных | D4: Обязательность | E4: Частота обновления | F4: Персонализация | G4: Правило отображения | H4: Формат | I4: Ответственный
A5: U-001 | B5: Обещание и список нотаций | C5: ЦП VP-001 (6.1) | D5: Обязательно | E5: По релизам | F5: Нет | G5: Всегда | H5: Текст | I5: Руководитель проекта
A6: U-002 | B6: Примеры диаграмм нотаций | C6: Движок нотаций | D6: Обязательно | E6: По релизам | F6: Нет | G6: Всегда | H6: Изображения и текст | I6: Разработчик
A7: U-003 | B7: Таблица тарифов Free и Pro | C7: Единица монетизации M-001 | D7: Обязательно | E7: При смене цен | F7: Нет | G7: Цена в у.е. | H7: Таблица | I7: Руководитель проекта
A8: U-004 | B8: Статьи по нотациям и примеры | C8: Документация | D8: Желательно | E8: По релизам | F8: Нет | G8: По поиску | H8: Текст | I8: Разработчик
A9: U-006 | B9: Состав заказа и условия оплаты | C9: Платежный провайдер | D9: Обязательно | E9: При смене тарифов | F9: Да | G9: После выбора Pro | H9: Форма | I9: Руководитель проекта
A10: U-008 | B10: Текст диаграммы и результат | C10: Пользователь | D10: Обязательно | E10: В реальном времени | F10: Да | G10: Всегда | H10: Текст и изображение | I10: Пользователь
A11: U-009 | B11: Форматы экспорта PNG и SVG | C11: Требования F-005 (6.3) | D11: Обязательно | E11: По релизам | F11: Нет | G11: Pro: расширенные форматы | H11: Файл | I11: Разработчик
A12: U-011 | B12: Сообщения об ошибках и примеры исправления | C12: Движок нотаций | D12: Желательно | E12: По релизам | F12: Да | G12: При ошибке | H12: Текст | I12: Разработчик

Sheet Паспорт_экрана
A1: Паспорт страницы или экрана
A2: Итоговая форма описания интерфейсной единицы для прототипирования, постановки задачи и проверки связности
A4: Unit_ID | B4: Название | C4: Тип | D4: Сценарий_ID | E4: Роль_ID | F4: Назначение | G4: Главная задача | H4: Основное действие | I4: Состав блоков | J4: Состояния | K4: Навигация | L4: Метрики успеха | M4: Риски | N4: Полнота паспорта | O4: Вердикт
A5: U-003 | B5: Тарифы Free и Pro | C5: Страница сайта | D5: SC-002 | E5: ROLE-001 | F5: Прозрачный выбор между Free и Pro | G5: Понять цену и ограничения | H5: Выбрать тариф | I5: Таблица тарифов, ограничения, вопросы | J5: Новый пользователь, тариф выбран, активная подписка, ошибка загрузки | K5: Из главной и возможностей; в регистрацию и оплату | L5: Доля переходов в регистрацию и оплату | M5: Непонятные ограничения Free | N5: =IF(A5="","",ROUND(COUNTA(B5:M5)/12,2)) -> 1 | O5: =IF(A5="","",IF(N5>=0.85,"Готов к прототипу",IF(N5>=0.6,"Требует доработки","Недостаточно данных"))) -> Готов к прототипу
A6: U-005 | B6: Регистрация и вход | C6: Страница сайта | D6: SC-003 | E6: ROLE-002 | F6: Получить доступ к Free | G6: Зарегистрироваться | H6: Отправить форму | I6: Форма, согласие, ошибки | J6: Начальное, ошибка валидации, успех, ошибка сети | K6: Из тарифов и главной; в выбор нотации | L6: Доля завершенных регистраций | M6: Отказ от регистрации | N6: =IF(A6="","",ROUND(COUNTA(B6:M6)/12,2)) -> 1 | O6: =IF(A6="","",IF(N6>=0.85,"Готов к прототипу",IF(N6>=0.6,"Требует доработки","Недостаточно данных"))) -> Готов к прототипу
A7: U-006 | B7: Оплата Pro | C7: Страница сайта | D7: SC-008 | E7: ROLE-004 | F7: Оформить подписку | G7: Оплатить 40 у.е. в год | H7: Подтвердить оплату | I7: Состав заказа, форма оплаты, подтверждение | J7: Выбран тариф, оплата, успех, ошибка оплаты | K7: Из тарифов; в профиль | L7: Доля оплат от входа на страницу | M7: Отказ платежа, отсутствие провайдера | N7: =IF(A7="","",ROUND(COUNTA(B7:M7)/12,2)) -> 1 | O7: =IF(A7="","",IF(N7>=0.85,"Готов к прототипу",IF(N7>=0.6,"Требует доработки","Недостаточно данных"))) -> Готов к прототипу
A8: U-008 | B8: Рабочая область редактора | C8: Экран приложения | D8: SC-004 | E8: ROLE-002 | F8: Построить диаграмму из текста | G8: Ввести текст и получить диаграмму | H8: Ввести текст | I8: Поле ввода, предпросмотр, панель ошибок | J8: Нормальное, пустое, загрузка, ошибка, успех | K8: Из выбора нотации; в экспорт и сохранение | L8: Доля пользователей, построивших первую диаграмму | M8: Сложность синтаксиса | N8: =IF(A8="","",ROUND(COUNTA(B8:M8)/12,2)) -> 1 | O8: =IF(A8="","",IF(N8>=0.85,"Готов к прототипу",IF(N8>=0.6,"Требует доработки","Недостаточно данных"))) -> Готов к прототипу
A9: U-009 | B9: Результат и экспорт | C9: Экран приложения | D9: SC-006 | E9: ROLE-002 | F9: Получить файл диаграммы | G9: Скачать PNG или SVG | H9: Выбрать формат | I9: Выбор формата, скачивание | J9: Нормальное, успех, формат недоступен, ошибка экспорта | K9: Из редактора | L9: Доля экспортов от построенных диаграмм | M9: Ограничения форматов Free | N9: =IF(A9="","",ROUND(COUNTA(B9:M9)/12,2)) -> 1 | O9: =IF(A9="","",IF(N9>=0.85,"Готов к прототипу",IF(N9>=0.6,"Требует доработки","Недостаточно данных"))) -> Готов к прототипу
A10: U-012 | B10: Профиль и подписка | C10: Экран приложения | D10: SC-008 | E10: ROLE-004 | F10: Управлять подпиской | G10: Проверить и продлить подписку | H10: Продлить | I10: Профиль, подписка, настройки | J10: Free, активная подписка, истекший доступ | K10: Из тарифов и кабинета | L10: Доля продлений | M10: Потеря доступа при просрочке | N10: =IF(A10="","",ROUND(COUNTA(B10:M10)/12,2)) -> 1 | O10: =IF(A10="","",IF(N10>=0.85,"Готов к прототипу",IF(N10>=0.6,"Требует доработки","Недостаточно данных"))) -> Готов к прототипу

Sheet Приоритизация
A1: Приоритизация страниц, экранов и интерфейсных инициатив
A2: Итоговый балл помогает определить состав первой версии и очередность следующих выпусков
A4: Unit_ID | B4: Название | C4: Связанный сценарий_ID | D4: Ценность для пользователя 1–5 | E4: Влияние на бизнес 1–5 | F4: Частота использования 1–5 | G4: Риск без реализации 1–5 | H4: Сложность 1–5 | I4: Итоговый балл | J4: Класс приоритета | K4: Основание | L4: Решение
A5: U-001 | B5: Главная страница | C5: SC-001 | D5: 4 | E5: 3 | F5: 5 | G5: 3 | H5: 2 | I5: =IF(A5="","",MAX(0,MIN(100,ROUND(((D5*0.3)+(E5*0.3)+(F5*0.15)+(G5*0.15)-(H5*0.1))*20,0)))) -> 62 | J5: =IF(A5="","",IF(I5>=80,"P1 – первая версия",IF(I5>=60,"P2 – следующий выпуск",IF(I5>=40,"P3 – можно отложить","Не включать")))) -> P2 – следующий выпуск | K5: Вход в воронку | L5: Включить
A6: U-002 | B6: Возможности и нотации | C6: SC-002 | D6: 5 | E6: 4 | F6: 4 | G6: 4 | H6: 2 | I6: =IF(A6="","",MAX(0,MIN(100,ROUND(((D6*0.3)+(E6*0.3)+(F6*0.15)+(G6*0.15)-(H6*0.1))*20,0)))) -> 74 | J6: =IF(A6="","",IF(I6>=80,"P1 – первая версия",IF(I6>=60,"P2 – следующий выпуск",IF(I6>=40,"P3 – можно отложить","Не включать")))) -> P2 – следующий выпуск | K6: Конкурентное отличие и поиск | L6: Включить
A7: U-003 | B7: Тарифы Free и Pro | C7: SC-002 | D7: 5 | E7: 5 | F7: 4 | G7: 4 | H7: 2 | I7: =IF(A7="","",MAX(0,MIN(100,ROUND(((D7*0.3)+(E7*0.3)+(F7*0.15)+(G7*0.15)-(H7*0.1))*20,0)))) -> 80 | J7: =IF(A7="","",IF(I7>=80,"P1 – первая версия",IF(I7>=60,"P2 – следующий выпуск",IF(I7>=40,"P3 – можно отложить","Не включать")))) -> P1 – первая версия | K7: Монетизация и доверие | L7: Включить
A8: U-004 | B8: Документация и примеры | C8: SC-010 | D8: 4 | E8: 3 | F8: 3 | G8: 3 | H8: 2 | I8: =IF(A8="","",MAX(0,MIN(100,ROUND(((D8*0.3)+(E8*0.3)+(F8*0.15)+(G8*0.15)-(H8*0.1))*20,0)))) -> 56 | J8: =IF(A8="","",IF(I8>=80,"P1 – первая версия",IF(I8>=60,"P2 – следующий выпуск",IF(I8>=40,"P3 – можно отложить","Не включать")))) -> P3 – можно отложить | K8: Снижает нагрузку поддержки | L8: Включить после проверки
A9: U-005 | B9: Регистрация и вход | C9: SC-003 | D9: 4 | E9: 4 | F9: 4 | G9: 5 | H9: 2 | I9: =IF(A9="","",MAX(0,MIN(100,ROUND(((D9*0.3)+(E9*0.3)+(F9*0.15)+(G9*0.15)-(H9*0.1))*20,0)))) -> 71 | J9: =IF(A9="","",IF(I9>=80,"P1 – первая версия",IF(I9>=60,"P2 – следующий выпуск",IF(I9>=40,"P3 – можно отложить","Не включать")))) -> P2 – следующий выпуск | K9: Активация | L9: Включить
A10: U-006 | B10: Оплата Pro | C10: SC-008 | D10: 4 | E10: 5 | F10: 2 | G10: 5 | H10: 3 | I10: =IF(A10="","",MAX(0,MIN(100,ROUND(((D10*0.3)+(E10*0.3)+(F10*0.15)+(G10*0.15)-(H10*0.1))*20,0)))) -> 69 | J10: =IF(A10="","",IF(I10>=80,"P1 – первая версия",IF(I10>=60,"P2 – следующий выпуск",IF(I10>=40,"P3 – можно отложить","Не включать")))) -> P2 – следующий выпуск | K10: Выручка Pro | L10: Включить после выбора провайдера
A11: U-007 | B11: Выбор нотации и шаблона | C11: SC-005 | D11: 4 | E11: 3 | F11: 4 | G11: 3 | H11: 2 | I11: =IF(A11="","",MAX(0,MIN(100,ROUND(((D11*0.3)+(E11*0.3)+(F11*0.15)+(G11*0.15)-(H11*0.1))*20,0)))) -> 59 | J11: =IF(A11="","",IF(I11>=80,"P1 – первая версия",IF(I11>=60,"P2 – следующий выпуск",IF(I11>=40,"P3 – можно отложить","Не включать")))) -> P3 – можно отложить | K11: Старт работы | L11: Включить
A12: U-008 | B12: Рабочая область редактора | C12: SC-004 | D12: 5 | E12: 5 | F12: 5 | G12: 5 | H12: 4 | I12: =IF(A12="","",MAX(0,MIN(100,ROUND(((D12*0.3)+(E12*0.3)+(F12*0.15)+(G12*0.15)-(H12*0.1))*20,0)))) -> 82 | J12: =IF(A12="","",IF(I12>=80,"P1 – первая версия",IF(I12>=60,"P2 – следующий выпуск",IF(I12>=40,"P3 – можно отложить","Не включать")))) -> P1 – первая версия | K12: Ядро ценности | L12: Включить
A13: U-009 | B13: Результат и экспорт | C13: SC-006 | D13: 5 | E13: 4 | F13: 5 | G13: 5 | H13: 2 | I13: =IF(A13="","",MAX(0,MIN(100,ROUND(((D13*0.3)+(E13*0.3)+(F13*0.15)+(G13*0.15)-(H13*0.1))*20,0)))) -> 80 | J13: =IF(A13="","",IF(I13>=80,"P1 – первая версия",IF(I13>=60,"P2 – следующий выпуск",IF(I13>=40,"P3 – можно отложить","Не включать")))) -> P1 – первая версия | K13: Обязательный минимум | L13: Включить
A14: U-010 | B14: Мои диаграммы | C14: SC-007 | D14: 4 | E14: 3 | F14: 4 | G14: 3 | H14: 3 | I14: =IF(A14="","",MAX(0,MIN(100,ROUND(((D14*0.3)+(E14*0.3)+(F14*0.15)+(G14*0.15)-(H14*0.1))*20,0)))) -> 57 | J14: =IF(A14="","",IF(I14>=80,"P1 – первая версия",IF(I14>=60,"P2 – следующий выпуск",IF(I14>=40,"P3 – можно отложить","Не включать")))) -> P3 – можно отложить | K14: Удержание | L14: Вторая версия
A15: U-011 | B15: Подсказка об ошибке синтаксиса | C15: SC-009 | D15: 4 | E15: 3 | F15: 4 | G15: 3 | H15: 4 | I15: =IF(A15="","",MAX(0,MIN(100,ROUND(((D15*0.3)+(E15*0.3)+(F15*0.15)+(G15*0.15)-(H15*0.1))*20,0)))) -> 55 | J15: =IF(A15="","",IF(I15>=80,"P1 – первая версия",IF(I15>=60,"P2 – следующий выпуск",IF(I15>=40,"P3 – можно отложить","Не включать")))) -> P3 – можно отложить | K15: Снижает отказы, данные слабые | L15: Вторая версия
A16: U-012 | B16: Профиль и подписка | C16: SC-008 | D16: 3 | E16: 4 | F16: 3 | G16: 3 | H16: 2 | I16: =IF(A16="","",MAX(0,MIN(100,ROUND(((D16*0.3)+(E16*0.3)+(F16*0.15)+(G16*0.15)-(H16*0.1))*20,0)))) -> 56 | J16: =IF(A16="","",IF(I16>=80,"P1 – первая версия",IF(I16>=60,"P2 – следующий выпуск",IF(I16>=40,"P3 – можно отложить","Не включать")))) -> P3 – можно отложить | K16: Продление | L16: Вторая версия
A17: U-013 | B17: ИИ-ассистент | C17: SC-004 | D17: 4 | E17: 4 | F17: 4 | G17: 2 | H17: 4 | I17: =IF(A17="","",MAX(0,MIN(100,ROUND(((D17*0.3)+(E17*0.3)+(F17*0.15)+(G17*0.15)-(H17*0.1))*20,0)))) -> 58 | J17: =IF(A17="","",IF(I17>=80,"P1 – первая версия",IF(I17>=60,"P2 – следующий выпуск",IF(I17>=40,"P3 – можно отложить","Не включать")))) -> P3 – можно отложить | K17: Гипотеза | L17: Вторая версия

Sheet Проверка_связности
A1: Проверка связности проектной логики
A2: Лист показывает, насколько интерфейсные единицы выведены из анализа и связаны со сценариями, навигацией, состояниями и бизнес-моделью
A4: Проверка | B4: Описание | C4: Расчет / критерий | D4: Результат | E4: Статус | F4: Что исправить
A5: Покрытие сценариев | B5: У каждого значимого сценария есть хотя бы одна страница или экран | C5: Сценарии с покрытием / всего сценариев | D5: =IFERROR(COUNTIF(Пользовательские_сценарии!$N$5:$N$14,"Покрыт")/SUMPRODUCT(--(Пользовательские_сценарии!$A$5:$A$14<>"")),0) -> 1 | E5: =IF(D5>=0.9,"Норма",IF(D5>=0.7,"Требует проверки","Проблема")) -> Норма | F5: Для сценариев без покрытия добавить интерфейсную единицу или исключить сценарий
A6: Интерфейсные единицы без сценария | B6: Не должно быть страниц и экранов без связанного сценария | C6: Количество строк с пустым сценарием | D6: =SUMPRODUCT(--(Страницы_и_экраны!$A$5:$A$17<>""),--(Страницы_и_экраны!$E$5:$E$17="")) -> 0 | E6: =IF(D6=0,"Норма","Проблема") -> Норма | F6: Указать сценарий или удалить лишнюю единицу
A7: Полнота паспортов | B7: Паспорта ключевых страниц и экранов должны быть заполнены не менее чем на 85% | C7: Средняя полнота паспортов | D7: =IFERROR(AVERAGE(Паспорт_экрана!$N$5:$N$10),0) -> 1 | E7: =IF(D7>=0.85,"Норма",IF(D7>=0.6,"Требует проверки","Проблема")) -> Норма | F7: Заполнить назначение, задачи, действия, состояния, навигацию, метрики
A8: Навигация | B8: Ключевые страницы и экраны должны иметь переходы | C8: Количество описанных переходов | D8: =SUMPRODUCT(--(Навигация_и_карта!$A$5:$A$19<>"")) -> 15 | E8: =IF(D8>=SUMPRODUCT(--(Страницы_и_экраны!$A$5:$A$17<>""))-1,"Норма",IF(D8>0,"Требует проверки","Проблема")) -> Норма | F8: Добавить переходы между интерфейсными единицами
A9: Состояния и ошибки | B9: Для ключевых страниц и экранов описаны состояния и исключения | C9: Средняя полнота состояний | D9: =IFERROR(AVERAGE(Состояния_и_ошибки!$K$5:$K$10),0) -> 1 | E9: =IF(D9>=0.85,"Норма",IF(D9>=0.6,"Требует проверки","Проблема")) -> Норма | F9: Заполнить пустые, загрузочные, ошибочные и успешные состояния
A10: Монетизационная связность | B10: Хотя бы одна интерфейсная единица должна вести к монетизации или поддерживать ее | C10: Количество единиц с монетизационной ролью | D10: =SUMPRODUCT(--(Страницы_и_экраны!$A$5:$A$17<>""),--(Страницы_и_экраны!$P$5:$P$17<>""),--(Страницы_и_экраны!$P$5:$P$17<>"Не связана напрямую")) -> 13 | E10: =IF(D10>=1,"Норма","Требует проверки") -> Норма | F10: Уточнить роль экранов в оплате, тарифах, удержании или снижении затрат
A11: Доказательность | B11: У интерфейсных единиц есть источник требования | C11: Доля строк с источником требования | D11: =IFERROR(SUMPRODUCT(--(Страницы_и_экраны!$A$5:$A$17<>""),--(Страницы_и_экраны!$J$5:$J$17<>""))/SUMPRODUCT(--(Страницы_и_экраны!$A$5:$A$17<>"")),0) -> 1 | E11: =IF(D11>=0.8,"Норма",IF(D11>=0.6,"Требует проверки","Проблема")) -> Норма | F11: Добавить ссылки на выводы, сценарии, отзывы, конкурентов или бизнес-модель

Sheet Дашборд
A1: Дашборд готовности перехода к страницам и экранам
A2: Показывает готовность проектной логики: покрытие сценариев, полноту паспортов, состояние навигации, наличие состояний и приоритизацию
A4: Показатель | B4: Значение | C4: Интерпретация
A5: Всего сценариев | B5: =SUMPRODUCT(--(Пользовательские_сценарии!$A$5:$A$14<>"")) -> 10 | C5: Количество описанных пользовательских сценариев
A6: Покрытие сценариев страницами/экранами | B6: =IFERROR(COUNTIF(Пользовательские_сценарии!$N$5:$N$14,"Покрыт")/SUMPRODUCT(--(Пользовательские_сценарии!$A$5:$A$14<>"")),0) -> 1 | C6: Доля сценариев, для которых определена интерфейсная единица
A7: Всего страниц и экранов | B7: =SUMPRODUCT(--(Страницы_и_экраны!$A$5:$A$17<>"")) -> 13 | C7: Общее количество интерфейсных единиц
A8: Средняя полнота описания страниц/экранов | B8: =IFERROR(AVERAGE(Страницы_и_экраны!$T$5:$T$17),0) -> 1 | C8: Насколько заполнены назначения, данные, действия, состояния и требования
A9: Средняя полнота паспортов | B9: =IFERROR(AVERAGE(Паспорт_экрана!$N$5:$N$10),0) -> 1 | C9: Готовность к прототипированию и постановке задачи
A10: Средняя полнота состояний | B10: =IFERROR(AVERAGE(Состояния_и_ошибки!$K$5:$K$10),0) -> 1 | C10: Наличие нормальных, пустых, загрузочных и ошибочных состояний
A11: Интерфейсные единицы P1 | B11: =COUNTIF(Приоритизация!$J$5:$J$17,"P1 – первая версия") -> 3 | C11: Кандидаты в первую версию
A12: Интегральная готовность | B12: =ROUND(AVERAGE(B6,B8,B9,B10),2) -> 1 | C12: Средняя готовность к переходу в прототипирование
A14: Блок проверки | B14: Готовность
A15: Покрытие сценариев | B15: =B6 -> 1
A16: Описание страниц/экранов | B16: =B8 -> 1
A17: Паспорта | B17: =B9 -> 1
A18: Состояния | B18: =B10 -> 1

Sheet Справочники
A1: Справочники для выпадающих списков
A3: Вид анализа | B3: Этап пути | C3: Тип интерфейсной единицы | D3: Тип связи | E3: Обязательность | F3: Статус | G3: ДаНет | H3: Решение | I3: Канал входа | J3: Роль в монетизации | K3: Тип перехода | L3: Приоритет
A4: Анализ проблем | B4: Осведомление | C4: Страница сайта | D4: Основная | E4: Обязательно для первой версии | F4: Не начато | G4: Да | H4: Оставить | I4: Поиск | J4: Прямое получение оплаты | K4: Основной | L4: P1 – первая версия
A5: Анализ отзывов | B5: Первичный интерес | C5: Экран приложения | D5: Поддерживающая | E5: Желательно для первой версии | F5: Требует уточнения | G5: Нет | H5: Объединить | I5: Реклама | J5: Подведение к оплате | K5: Возврат | L5: P2 – следующий выпуск
A6: Анализ конкурентов | B6: Оценка решения | C6: Общий модуль | D6: Альтернативная | E6: Следующий выпуск | F6: В проектировании | G6: Частично | H6: Разделить | I6: Социальные сети | J6: Удержание | K6: Ветвление | L6: P3 – можно отложить
A7: Анализ цифрового товара | B7: Регистрация | C7: Системное состояние | D7: Сервисная | E7: Отложить | F7: В прототипе | H7: Уточнить | I7: Рекомендация | J7: Повышение ценности тарифа | K7: Переход после ошибки | L7: Не включать
A8: Ценностное предложение | B8: Настройка | C8: Форма | D8: Монетизационная | E8: Исключить | F8: Готово к ТЗ | H8: Исключить | I8: Партнерский канал | J8: Снижение затрат | K8: Переход после оплаты
A9: Бизнес-модель Канвас | B9: Основное использование | C9: Личный кабинет | D9: Контрольная | F9: Исключено | H9: Перенести в следующий выпуск | I9: Прямой вход | J9: Не связана напрямую | K9: Внешний переход
A10: Бизнес-логика | B10: Оплата | C10: Платежный экран | I10: Уведомление | K10: Системный переход
A11: Пользовательский сценарий | B11: Поддержка | I11: Внутренний переход
B12: Повторное использование
B13: Отток/возврат

Sheet Журнал_6_4
A1: Журнал рабочей копии: источники, единицы, ограничения
A3: Раздел | B3: Код | C3: Содержание
A4: Источники | B4: И-1 | C4: Банк выводов из ЛР5 (стандарт страниц, тарифы), методик 6.1-6.3 и ЛР4 (опрос, Similarweb)
A5: Единицы | B5: Е-1 | C5: 13 единиц: 6 страниц сайта и 7 экранов приложения (PWA). Страница правовых документов и поддержки не вынесена: правовые документы и контакты размещаются в подвале и должны быть в первой версии (не собрано: перечень документов)
A6: Паспорта | B6: П-1 | C6: Паспорта заполнены для 6 ключевых единиц (тарифы, регистрация, оплата, редактор, экспорт, профиль); для остальных - не собрано в проектировании
A7: Состояния | B7: С-1 | C7: Карта состояний заполнена для 6 единиц; прочерк означает, что состояние неприменимо
A8: Правило | B8: Р-2 | C8: По формуле шаблона P1 получают 3 единицы (выбор нотации, редактор, экспорт); тарифы, регистрация и оплата - P2 или P3, но цепочка «обнаружение ценности - выбор - оплата - первый результат» требует их включения в первый выпуск: решение принимается в методике 6.5
A9: Правило | B9: Р-1 | C9: Приоритет единицы - формула шаблона; оценки 1-5 экспертные. Страницы без доказательства из анализа (подсказка об ошибке, ИИ-ассистент) имеют статус «Гипотеза»
A10: Ограничения | B10: О-1 | C10: Опрос студентов пробный, по условным профилям (ЛР4); UX-тестирование и прототипы не проводились. Планируется собрать: прототип и проверка с пользователями
