Workbook

Sheet 00_Инструкция
A1: Excel-шаблон анализа конкурентов по сайтам
A2: Назначение: определить рыночный стандарт цифрового товара, выделить конкурентные преимущества по товару и сформулировать сам цифровой товар через модель Левитта и модель Кано
A4: Раздел | B4: Что делать | C4: Результат
A5: 1. Реестр конкурентов | B5: Заполнить лист «01_Конкуренты»: прямые конкуренты, косвенные конкуренты, эталонные сайты для наблюдения за лучшей практикой | C5: Сформирован сопоставимый контур анализа
A6: 2. Карта сайта | B6: Зафиксировать проверенные страницы: главная, лендинг товара, тарифы, функциональные страницы, личный кабинет, поддержка, вопросы и ответы, блог, документация | C6: Появляется проверяемая база доказательств, а не субъективное впечатление
A7: 3. Модель Левитта | B7: Разложить цифровой товар на уровни: базовая выгода, родовой товар, ожидаемый товар, расширенный товар, потенциальный товар | C7: Понятно, что именно продает конкурент и за счет каких уровней формируется ценность
A8: 4. Модель Кано | B8: Классифицировать функции и признаки товара: обязательные, линейные, привлекательные, безразличные, обратные, неясные | C8: Понятно, какие признаки должны быть обязательно, какие повышают удовлетворенность, а какие создают отличие
A9: 5. Сравнение | B9: Оценить конкурентов по критериям товара, сайта и цифрового сервиса по шкале 0–5 | C9: Получается количественная карта сильных и слабых сторон
A10: 6. Рыночный стандарт | B10: Определить признаки, встречающиеся у большинства конкурентов, особенно если они относятся к обязательным или линейным требованиям Кано | C10: Сформулирован минимально приемлемый состав цифрового товара на рынке
A11: 7. Преимущества | B11: Выделить признаки, которые редки, хорошо реализованы, заметны пользователю и повышают воспринимаемую ценность | C11: Сформирован список конкурентных преимуществ и гипотез дифференциации
A12: 8. Итоговая формулировка товара | B12: На листе «05_Матрица_товара» собрать описание целевого цифрового товара: для кого, какую задачу решает, какие функции включает, где границы продукта | C12: Получено предметное определение цифрового товара и требований к его составу
A14: Шкалы оценки
A15: Шкала | B15: 0 | C15: 1 | D15: 2 | E15: 3 | F15: 4 | G15: 5 | H15: Когда применять | I15: Интерпретация
A16: Наличие признака | B16: Нет | C16: Есть частично | D16: Есть явно | E16: Есть полно | H16: Для бинарных и полуколичественных признаков | I16: 0 — отсутствует; 1–3 — степень проявления
A17: Сила реализации | B17: Нет | C17: Слабая | D17: Средняя | E17: Сильная | H17: Для уровня Левитта и качества функции | I17: 3 означает, что признак хорошо заметен и функционально раскрыт
A18: Пользовательская ценность | B18: Нет | C18: Низкая | D18: Умеренная | E18: Высокая | F18: Очень высокая | G18: Критическая | H18: Для оценки влияния на решение о покупке/регистрации/использовании | I18: 4–5 — признак способен влиять на выбор товара
A19: Сравнение конкурентов | B19: Нет | C19: Очень слабо | D19: Слабо | E19: Средне | F19: Сильно | G19: Лучший уровень | H19: Для листа «06_Сравнение» | I19: Оценки сопоставимы только при одинаковой логике анализа

Sheet 01_Конкуренты
A1: 01. Реестр конкурентов и сайтов
A2: Заполните список конкурентов и базовые параметры. ID конкурента используется в остальных листах для связки данных
A6: ID | B6: Наименование конкурента | C6: Сайт | D6: Страна/рынок | E6: Тип конкурента | F6: Сегмент аудитории | G6: Модель монетизации | H6: Цифровой товар по сайту | I6: Приоритет анализа | J6: Статус | K6: Комментарий
A7: C01 | B7: PlantUML | C7: plantuml.com | D7: Весь мир (английский язык) | E7: Прямой конкурент | F7: Разработчики, студенты, архитекторы ПО | G7: Бесплатно, открытый код | H7: Построение UML-диаграмм из текстового описания, экспорт PNG, LaTeX, EPS, SVG. Главная страница: «Open-source tool that uses simple textual descriptions to draw beautiful UML diagrams» | I7: Высокий | J7: Завершён | K7: Выборка из части A (поле «Переходит в части B и C»); страницы просмотрены 01.10.2026
A8: C02 | B8: Mermaid (библиотека) | C8: mermaid.js.org | D8: Весь мир (английский язык) | E8: Близкий альтернативный конкурент | F8: Разработчики, авторы технической документации | G8: Бесплатно, открытый код (MIT); платные планы у Mermaid Chart | H8: Диаграммы и визуализации из текста и кода (JavaScript-библиотека). Главная страница: «Create diagrams and visualizations using text and code» | I8: Высокий | J8: Завершён | K8: Выборка из части A (поле «Переходит в части B и C»); страницы просмотрены 01.10.2026
A9: C03 | B9: Mermaid Chart | C9: mermaidchart.com | D9: Весь мир (США, Великобритания, Япония в топ-странах) | E9: Близкий альтернативный конкурент | F9: Команды разработки и документации | G9: Условно-бесплатная: Free, Plus 10 у.е., Premium 20 у.е., Enterprise | H9: Облачный редактор диаграмм Mermaid с тарифами Free, Plus, Premium. Главная страница: «Create diagrams, flowcharts, and documentation with Mermaid»; «You already think in systems» | I9: Высокий | J9: Завершён | K9: Выборка из части A (поле «Переходит в части B и C»); страницы просмотрены 01.10.2026
A10: C04 | B10: Storm (StormBPMN) | C10: stormbpmn.com | D10: Россия и СНГ (Россия 62,99 %, Беларусь 2,49 %) | E10: Смежная или потенциальная конкуренция | F10: Процессные аналитики, русскоязычный рынок | G10: Условно-бесплатная: Персональный бесплатно, Команда, Бизнес, Enterprise on-prem (руб.) | H10: Платформа из семи модулей: редактор, реестр, архитектура, оргструктура, опросы, ИИ, симуляция. Главная страница: «Соберите все процессы компании»; «Одна платформа - девять модулей процессного управления» | I10: Средний | J10: Завершён | K10: Выборка из части A (поле «Переходит в части B и C»); страницы просмотрены 01.10.2026
A11: C05 | B11: draw.io (diagrams.net) | C11: app.diagrams.net | D11: Весь мир (США, Индонезия, Индия, Китай, Россия) | E11: Косвенный конкурент / заменитель | F11: Студенты, разработчики, команды | G11: Бесплатно, открытый код (Apache 2.0) | H11: Бесплатный онлайн-редактор блок-схем, UML, ER и других диаграмм. Главная страница: «Security-first diagramming for teams»; «Free, open source diagramming application with 100M+ users» | I11: Высокий | J11: Завершён | K11: Выборка из части A (поле «Переходит в части B и C»); страницы просмотрены 01.10.2026
A12: C06 | B12: Lucidchart | C12: lucidchart.com | D12: Весь мир (США, Мексика, Бразилия в топ-странах) | E12: Косвенный конкурент / заменитель | F12: Команды, бизнес-пользователи | G12: Условно-бесплатная: Free, Individual 9 у.е., Team 10 у.е., Enterprise | H12: Облачный редактор диаграмм с тарифами Free, Individual, Team, Enterprise. Главная страница: «Diagramming powered by intelligence»: диаграммы с ИИ, данными и автоматизацией | I12: Средний | J12: Завершён | K12: Выборка из части A (поле «Переходит в части B и C»); страницы просмотрены 01.10.2026
A13: C07 | B13: Eraser | C13: eraser.io | D13: Весь мир | E13: Косвенный конкурент / заменитель | F13: Инженерные команды, разработчики | G13: Условно-бесплатная: Free, Starter 15 у.е., Business 45 у.е., Enterprise | H13: Создание технических диаграмм с помощью ИИ. Главная страница: «AI for diagrams that matter»; «Create technical diagrams using AI» | I13: Высокий | J13: Завершён | K13: Выборка из части A (поле «Переходит в части B и C»); страницы просмотрены 01.10.2026
A14: C08 | B14: Whimsical | C14: whimsical.com | D14: Весь мир | E14: Смежная или потенциальная конкуренция | F14: Команды продуктов | G14: Условно-бесплатная: Free, Pro 10 у.е., Business 20 у.е | H14: Редактор диаграмм, схем интерфейсов и документов; тарифы Free, Pro, Business (страница тарифов, 01.10.2026). Главная страница: «The whiteboard for product builders»: диаграммы, схемы интерфейсов, документы | I14: Низкий | J14: Завершён | K14: Выборка из части A (поле «Переходит в части B и C»); страницы просмотрены 01.10.2026
A15: C09 | J15: Не начато
A16: C10 | J16: Не начато
A17: C11 | J17: Не начато
A18: C12 | J18: Не начато
A19: C13 | J19: Не начато
A20: C14 | J20: Не начато
A21: C15 | J21: Не начато
A22: C16 | J22: Не начато
A23: C17 | J23: Не начато
A24: C18 | J24: Не начато
A25: C19 | J25: Не начато
A26: C20 | J26: Не начато
... A36: C30 | J36: Не начато

Sheet 02_Карта_сайтов
A1: 02. Карта страниц сайта конкурента
A2: Фиксируйте каждую страницу, которая стала источником вывода. Это повышает воспроизводимость анализа и качество итоговых решений
A6: ID конкурента | B6: Раздел/страница | C6: URL | D6: Тип страницы | E6: Цель анализа | F6: Что извлекаем | G6: Дата просмотра | H6: Скриншот/архив | I6: Достоверность 1–5 | J6: Краткий вывод
A7: C01 | B7: Главная | C7: https://plantuml.com/ | D7: Главная | E7: Определить обещание и состав товара | F7: Заголовок, разделы, тарифы, ключевые признаки | G7: 46296 | H7: Текст страницы, запрос 01.10.2026 | I7: 4 | J7: Заголовок: Open-source tool that uses simple textual descriptions to draw beautif. Признаки в тексте: integr, export, uml, erd
A8: C01 | B8: Документация | C8: https://plantuml.com/faq | D8: Документация | E8: Глубина документации, поддержка нотаций | F8: Заголовок, разделы, тарифы, ключевые признаки | G8: 46296 | H8: Текст страницы, запрос 01.10.2026 | I8: 4 | J8: Заголовок: Frequently Asked Questions. Признаки в тексте: free, integr, export, uml
A9: C01 | B9: Документация | C9: https://plantuml.com/running | D9: Документация | E9: Глубина документации, поддержка нотаций | F9: Заголовок, разделы, тарифы, ключевые признаки | G9: 46296 | H9: Текст страницы, запрос 01.10.2026 | I9: 4 | J9: Заголовок отсутствует. Признаки в тексте: integr, api, export, uml
A10: C01 | B10: Документация | C10: https://plantuml.com/download | D10: Документация | E10: Глубина документации, поддержка нотаций | F10: Заголовок, разделы, тарифы, ключевые признаки | G10: 46296 | H10: Текст страницы, запрос 01.10.2026 | I10: 4 | J10: Заголовок отсутствует. Признаки в тексте: integr, uml
A11: C01 | B11: Документация | C11: https://plantuml.com/class-diagram | D11: Документация | E11: Глубина документации, поддержка нотаций | F11: Заголовок, разделы, тарифы, ключевые признаки | G11: 46296 | H11: Текст страницы, запрос 01.10.2026 | I11: 4 | J11: Заголовок: Class Diagram syntax and features. Признаки в тексте: integr, security, uml
A12: C01 | B12: Документация | C12: https://plantuml.com/ie-diagram | D12: Документация | E12: Глубина документации, поддержка нотаций | F12: Заголовок, разделы, тарифы, ключевые признаки | G12: 46296 | H12: Текст страницы, запрос 01.10.2026 | I12: 4 | J12: Заголовок: Information Engineering diagram syntax and features. Признаки в тексте: integr, erd
A13: C01 | B13: Документация | C13: https://plantuml.com/activity-diagram-beta | D13: Документация | E13: Глубина документации, поддержка нотаций | F13: Заголовок, разделы, тарифы, ключевые признаки | G13: 46296 | H13: Текст страницы, запрос 01.10.2026 | I13: 4 | J13: Заголовок: New Activity Diagram Beta syntax and features. Признаки в тексте: integr, templates, security, uml
A14: C01 | B14: Репозиторий GitHub | C14: https://github.com/plantuml/plantuml | D14: Сообщество | E14: Открытый код, лицензия, активность | F14: Звёзды, форки, дата обновления | G14: 46295 | H14: GitHub API, ЛР4 | I14: 5 | J14: 13 346 звёзд, лицензия LGPL-3.0, обновление 2026-09-30
A15: C02 | B15: Главная | C15: https://mermaid.js.org/ | D15: Главная | E15: Определить обещание и состав товара | F15: Заголовок, разделы, тарифы, ключевые признаки | G15: 46296 | H15: Текст страницы, запрос 01.10.2026 | I15: 4 | J15: Заголовок: Mermaid | Diagramming and charting tool. Признаки в тексте: ai, integr
A16: C02 | B16: Документация | C16: https://mermaid.js.org/intro/ | D16: Документация | E16: Глубина документации, поддержка нотаций | F16: Заголовок, разделы, тарифы, ключевые признаки | G16: 46296 | H16: Текст страницы, запрос 01.10.2026 | I16: 4 | J16: Заголовок: About Mermaid | Mermaid. Признаки в тексте: ai, collab, integr, api, security, erd
A17: C02 | B17: Документация | C17: https://mermaid.js.org/intro/getting-started.html | D17: Документация | E17: Глубина документации, поддержка нотаций | F17: Заголовок, разделы, тарифы, ключевые признаки | G17: 46296 | H17: Текст страницы, запрос 01.10.2026 | I17: 4 | J17: Заголовок: Mermaid User Guide | Mermaid. Признаки в тексте: free, ai, collab, integr, api, export
A18: C02 | B18: Интеграции | C18: https://mermaid.js.org/ecosystem/integrations-community.html | D18: Интеграции | E18: Интеграции и экосистема | F18: Заголовок, разделы, тарифы, ключевые признаки | G18: 46296 | H18: Текст страницы, запрос 01.10.2026 | I18: 4 | J18: Заголовок: Integrations | Mermaid. Признаки в тексте: ai, integr, api, export, security, uml
... A46: C08 | B46: Документация | C46: https://whimsical.com/diagrams | D46: Документация | E46: Глубина документации, поддержка нотаций | F46: Заголовок, разделы, тарифы, ключевые признаки | G46: 46296 | H46: Текст страницы, запрос 01.10.2026 | I46: 4 | J46: Заголовок: Whimsical Diagrams, Flowcharts, and Mind Maps. Признаки в тексте: free, pricing, ai, collab, integr, templates

Sheet 03_Левитт
A1: 03. Анализ цифрового товара по модели Левитта
A2: Разложите товар конкурента на уровни: от базовой выгоды до потенциального развития. Оценка признака рассчитывается автоматически
A6: ID конкурента | B6: Товар/предложение | C6: URL/страница | D6: Уровень товара по Левитту | E6: Элемент товара / признак | F6: Как проявлен на сайте | G6: Доказательство | H6: Наличие 0/1 | I6: Сила реализации 0–3 | J6: Понятность 0–3 | K6: Влияние на ценность 1–5 | L6: Оценка признака | M6: Роль признака | N6: Примечание
A7: C01 | B7: PlantUML | C7: https://plantuml.com/ | D7: 1. Базовая выгода | E7: Основное обещание главной страницы | F7: «Open-source tool that uses simple textual descriptions to draw beautiful UML diagrams» | G7: Главная страница, просмотр 01.10.2026 | H7: 1 | I7: 3 | J7: 3 | K7: 5 | L7: =IF(OR(H7="",I7="",J7="",K7=""),"",ROUND(H7*((I7+J7)/6)*K7,2)) | M7: =IF(L7="","",IF(AND(L7>=3.5,H7=1),"Сильный признак",IF(AND(L7>=2,H7=1),"Рабочий признак",IF(H7=1,"Слабый признак","Отсутствует")))) | N7: Конкурентная норма с высоким влиянием; включить в минимальный состав NotaCode
A8: C01 | B8: PlantUML | C8: https://plantuml.com/ | D8: 2. Родовой товар | E8: Форма поставки товара | F8: Текстовый DSL, открытый код: Построение UML-диаграмм из текстового описания, экспорт PNG, LaTeX, EPS, SVG | G8: Страницы сайта, ЛР1 табл. 42, ЛР4 | H8: 1 | I8: 3 | J8: 3 | K8: 4 | L8: =IF(OR(H8="",I8="",J8="",K8=""),"",ROUND(H8*((I8+J8)/6)*K8,2)) | M8: =IF(L8="","",IF(AND(L8>=3.5,H8=1),"Сильный признак",IF(AND(L8>=2,H8=1),"Рабочий признак",IF(H8=1,"Слабый признак","Отсутствует")))) | N8: Конкурентная норма с высоким влиянием; включить в минимальный состав NotaCode
A9: C01 | B9: PlantUML | C9: https://plantuml.com/ | D9: 2. Родовой товар | E9: Описание диаграммы текстом (DSL) | F9: Признак найден на просмотренных страницах: описание диаграммы текстом (dsl) | G9: Страницы сайта, просмотр 01.10.2026 | H9: 1 | I9: 3 | J9: 2 | K9: 5 | L9: =IF(OR(H9="",I9="",J9="",K9=""),"",ROUND(H9*((I9+J9)/6)*K9,2)) | M9: =IF(L9="","",IF(AND(L9>=3.5,H9=1),"Сильный признак",IF(AND(L9>=2,H9=1),"Рабочий признак",IF(H9=1,"Слабый признак","Отсутствует")))) | N9: Конкурентная норма с высоким влиянием; включить в минимальный состав NotaCode
A10: C01 | B10: PlantUML | C10: https://plantuml.com/ | D10: 3. Ожидаемый товар | E10: Бесплатный доступ или Free-тариф | F10: Открытый код; раздел лицензирования на странице загрузки | G10: Страницы сайта, просмотр 01.10.2026 | H10: 1 | I10: 3 | J10: 2 | K10: 5 | L10: =IF(OR(H10="",I10="",J10="",K10=""),"",ROUND(H10*((I10+J10)/6)*K10,2)) | M10: =IF(L10="","",IF(AND(L10>=3.5,H10=1),"Сильный признак",IF(AND(L10>=2,H10=1),"Рабочий признак",IF(H10=1,"Слабый признак","Отсутствует")))) | N10: Конкурентная норма с высоким влиянием; включить в минимальный состав NotaCode
A11: C01 | B11: PlantUML | C11: https://plantuml.com/ | D11: 3. Ожидаемый товар | E11: Интеграции с другими сервисами | F11: Признак найден на просмотренных страницах: интеграции с другими сервисами | G11: Страницы сайта, просмотр 01.10.2026 | H11: 1 | I11: 2 | J11: 2 | K11: 4 | L11: =IF(OR(H11="",I11="",J11="",K11=""),"",ROUND(H11*((I11+J11)/6)*K11,2)) | M11: =IF(L11="","",IF(AND(L11>=3.5,H11=1),"Сильный признак",IF(AND(L11>=2,H11=1),"Рабочий признак",IF(H11=1,"Слабый признак","Отсутствует")))) | N11: Конкурентная норма с высоким влиянием; включить в минимальный состав NotaCode
A12: C01 | B12: PlantUML | C12: https://plantuml.com/ | D12: 4. Расширенный товар | E12: Открытый код и сообщество | F12: Признак найден на просмотренных страницах: открытый код и сообщество | G12: Страницы сайта, просмотр 01.10.2026 | H12: 1 | I12: 2 | J12: 2 | K12: 4 | L12: =IF(OR(H12="",I12="",J12="",K12=""),"",ROUND(H12*((I12+J12)/6)*K12,2)) | M12: =IF(L12="","",IF(AND(L12>=3.5,H12=1),"Сильный признак",IF(AND(L12>=2,H12=1),"Рабочий признак",IF(H12=1,"Слабый признак","Отсутствует")))) | N12: Конкурентная норма с высоким влиянием; включить в минимальный состав NotaCode
A13: C01 | B13: PlantUML | C13: https://plantuml.com/ | D13: 4. Расширенный товар | E13: Независимые отзывы и оценки | F13: Признак найден на просмотренных страницах: независимые отзывы и оценки | G13: Страницы сайта, просмотр 01.10.2026 | H13: 1 | I13: 2 | J13: 2 | K13: 3 | L13: =IF(OR(H13="",I13="",J13="",K13=""),"",ROUND(H13*((I13+J13)/6)*K13,2)) | M13: =IF(L13="","",IF(AND(L13>=3.5,H13=1),"Сильный признак",IF(AND(L13>=2,H13=1),"Рабочий признак",IF(H13=1,"Слабый признак","Отсутствует")))) | N13: Конкурентная норма с высоким влиянием; включить в минимальный состав NotaCode
A14: C01 | B14: PlantUML | C14: https://plantuml.com/ | D14: 3. Ожидаемый товар | E14: Экспорт диаграмм (PNG, SVG, PDF и др.) | F14: Признак найден на просмотренных страницах: экспорт диаграмм (png, svg, pdf и др.) | G14: Страницы сайта, просмотр 01.10.2026 | H14: 1 | I14: 3 | J14: 2 | K14: 5 | L14: =IF(OR(H14="",I14="",J14="",K14=""),"",ROUND(H14*((I14+J14)/6)*K14,2)) | M14: =IF(L14="","",IF(AND(L14>=3.5,H14=1),"Сильный признак",IF(AND(L14>=2,H14=1),"Рабочий признак",IF(H14=1,"Слабый признак","Отсутствует")))) | N14: Конкурентная норма с высоким влиянием; включить в минимальный состав NotaCode
A15: C01 | B15: PlantUML | C15: https://plantuml.com/ | D15: 3. Ожидаемый товар | E15: Документация и руководства | F15: Признак найден на просмотренных страницах: документация и руководства | G15: Страницы сайта, просмотр 01.10.2026 | H15: 1 | I15: 3 | J15: 2 | K15: 4 | L15: =IF(OR(H15="",I15="",J15="",K15=""),"",ROUND(H15*((I15+J15)/6)*K15,2)) | M15: =IF(L15="","",IF(AND(L15>=3.5,H15=1),"Сильный признак",IF(AND(L15>=2,H15=1),"Рабочий признак",IF(H15=1,"Слабый признак","Отсутствует")))) | N15: Конкурентная норма с высоким влиянием; включить в минимальный состав NotaCode
A16: C01 | B16: PlantUML | C16: https://plantuml.com/ | D16: 3. Ожидаемый товар | E16: Диаграммы UML | F16: Признак найден на просмотренных страницах: диаграммы uml | G16: Страницы сайта, просмотр 01.10.2026 | H16: 1 | I16: 3 | J16: 2 | K16: 5 | L16: =IF(OR(H16="",I16="",J16="",K16=""),"",ROUND(H16*((I16+J16)/6)*K16,2)) | M16: =IF(L16="","",IF(AND(L16>=3.5,H16=1),"Сильный признак",IF(AND(L16>=2,H16=1),"Рабочий признак",IF(H16=1,"Слабый признак","Отсутствует")))) | N16: Конкурентная норма с высоким влиянием; включить в минимальный состав NotaCode
A17: C01 | B17: PlantUML | C17: https://plantuml.com/ | D17: 4. Расширенный товар | E17: Диаграммы ERD | F17: Признак найден на просмотренных страницах: диаграммы erd | G17: Страницы сайта, просмотр 01.10.2026 | H17: 1 | I17: 3 | J17: 2 | K17: 4 | L17: =IF(OR(H17="",I17="",J17="",K17=""),"",ROUND(H17*((I17+J17)/6)*K17,2)) | M17: =IF(L17="","",IF(AND(L17>=3.5,H17=1),"Сильный признак",IF(AND(L17>=2,H17=1),"Рабочий признак",IF(H17=1,"Слабый признак","Отсутствует")))) | N17: Конкурентная норма с высоким влиянием; включить в минимальный состав NotaCode
A18: C01 | B18: PlantUML | C18: https://plantuml.com/ | D18: 4. Расширенный товар | E18: Развёртывание на своём сервере | F18: Признак найден на просмотренных страницах: развёртывание на своём сервере | G18: Страницы сайта, просмотр 01.10.2026 | H18: 1 | I18: 2 | J18: 2 | K18: 3 | L18: =IF(OR(H18="",I18="",J18="",K18=""),"",ROUND(H18*((I18+J18)/6)*K18,2)) | M18: =IF(L18="","",IF(AND(L18>=3.5,H18=1),"Сильный признак",IF(AND(L18>=2,H18=1),"Рабочий признак",IF(H18=1,"Слабый признак","Отсутствует")))) | N18: Конкурентная норма с высоким влиянием; включить в минимальный состав NotaCode
... A159: C08 | B159: Whimsical | C159: https://whimsical.com/ | D159: 4. Расширенный товар | E159: Настольное приложение | F159: Признак найден на просмотренных страницах: настольное приложение | G159: Страницы сайта, просмотр 01.10.2026 | H159: 1 | I159: 2 | J159: 3 | K159: 2 | L159: =IF(OR(H159="",I159="",J159="",K159=""),"",ROUND(H159*((I159+J159)/6)*K159,2)) | M159: =IF(L159="","",IF(AND(L159>=3.5,H159=1),"Сильный признак",IF(AND(L159>=2,H159=1),"Рабочий признак",IF(H159=1,"Слабый признак","Отсутствует")))) | N159: Конкурентная норма с высоким влиянием; включить в минимальный состав NotaCode
L160: =IF(OR(H160="",I160="",J160="",K160=""),"",ROUND(H160*((I160+J160)/6)*K160,2)) | M160: =IF(L160="","",IF(AND(L160>=3.5,H160=1),"Сильный признак",IF(AND(L160>=2,H160=1),"Рабочий признак",IF(H160=1,"Слабый признак","Отсутствует")))) | N160: Конкурентная норма с высоким влиянием; включить в минимальный состав NotaCode
L161: =IF(OR(H161="",I161="",J161="",K161=""),"",ROUND(H161*((I161+J161)/6)*K161,2)) | M161: =IF(L161="","",IF(AND(L161>=3.5,H161=1),"Сильный признак",IF(AND(L161>=2,H161=1),"Рабочий признак",IF(H161=1,"Слабый признак","Отсутствует")))) | N161: Конкурентная норма с высоким влиянием; включить в минимальный состав NotaCode
L162: =IF(OR(H162="",I162="",J162="",K162=""),"",ROUND(H162*((I162+J162)/6)*K162,2)) | M162: =IF(L162="","",IF(AND(L162>=3.5,H162=1),"Сильный признак",IF(AND(L162>=2,H162=1),"Рабочий признак",IF(H162=1,"Слабый признак","Отсутствует")))) | N162: Конкурентная норма с высоким влиянием; включить в минимальный состав NotaCode
L163: =IF(OR(H163="",I163="",J163="",K163=""),"",ROUND(H163*((I163+J163)/6)*K163,2)) | M163: =IF(L163="","",IF(AND(L163>=3.5,H163=1),"Сильный признак",IF(AND(L163>=2,H163=1),"Рабочий признак",IF(H163=1,"Слабый признак","Отсутствует")))) | N163: Конкурентная норма с высоким влиянием; включить в минимальный состав NotaCode
L164: =IF(OR(H164="",I164="",J164="",K164=""),"",ROUND(H164*((I164+J164)/6)*K164,2)) | M164: =IF(L164="","",IF(AND(L164>=3.5,H164=1),"Сильный признак",IF(AND(L164>=2,H164=1),"Рабочий признак",IF(H164=1,"Слабый признак","Отсутствует")))) | N164: Конкурентная норма с высоким влиянием; включить в минимальный состав NotaCode
L165: =IF(OR(H165="",I165="",J165="",K165=""),"",ROUND(H165*((I165+J165)/6)*K165,2)) | M165: =IF(L165="","",IF(AND(L165>=3.5,H165=1),"Сильный признак",IF(AND(L165>=2,H165=1),"Рабочий признак",IF(H165=1,"Слабый признак","Отсутствует")))) | N165: Конкурентная норма с высоким влиянием; включить в минимальный состав NotaCode
L166: =IF(OR(H166="",I166="",J166="",K166=""),"",ROUND(H166*((I166+J166)/6)*K166,2)) | M166: =IF(L166="","",IF(AND(L166>=3.5,H166=1),"Сильный признак",IF(AND(L166>=2,H166=1),"Рабочий признак",IF(H166=1,"Слабый признак","Отсутствует")))) | N166: Конкурентная норма с высоким влиянием; включить в минимальный состав NotaCode
L167: =IF(OR(H167="",I167="",J167="",K167=""),"",ROUND(H167*((I167+J167)/6)*K167,2)) | M167: =IF(L167="","",IF(AND(L167>=3.5,H167=1),"Сильный признак",IF(AND(L167>=2,H167=1),"Рабочий признак",IF(H167=1,"Слабый признак","Отсутствует")))) | N167: Конкурентная норма с высоким влиянием; включить в минимальный состав NotaCode
L168: =IF(OR(H168="",I168="",J168="",K168=""),"",ROUND(H168*((I168+J168)/6)*K168,2)) | M168: =IF(L168="","",IF(AND(L168>=3.5,H168=1),"Сильный признак",IF(AND(L168>=2,H168=1),"Рабочий признак",IF(H168=1,"Слабый признак","Отсутствует")))) | N168: Конкурентная норма с высоким влиянием; включить в минимальный состав NotaCode
L169: =IF(OR(H169="",I169="",J169="",K169=""),"",ROUND(H169*((I169+J169)/6)*K169,2)) | M169: =IF(L169="","",IF(AND(L169>=3.5,H169=1),"Сильный признак",IF(AND(L169>=2,H169=1),"Рабочий признак",IF(H169=1,"Слабый признак","Отсутствует")))) | N169: Конкурентная норма с высоким влиянием; включить в минимальный состав NotaCode
L170: =IF(OR(H170="",I170="",J170="",K170=""),"",ROUND(H170*((I170+J170)/6)*K170,2)) | M170: =IF(L170="","",IF(AND(L170>=3.5,H170=1),"Сильный признак",IF(AND(L170>=2,H170=1),"Рабочий признак",IF(H170=1,"Слабый признак","Отсутствует")))) | N170: Конкурентная норма с высоким влиянием; включить в минимальный состав NotaCode
L171: =IF(OR(H171="",I171="",J171="",K171=""),"",ROUND(H171*((I171+J171)/6)*K171,2)) | M171: =IF(L171="","",IF(AND(L171>=3.5,H171=1),"Сильный признак",IF(AND(L171>=2,H171=1),"Рабочий признак",IF(H171=1,"Слабый признак","Отсутствует")))) | N171: Конкурентная норма с высоким влиянием; включить в минимальный состав NotaCode
... L306: =IF(OR(H306="",I306="",J306="",K306=""),"",ROUND(H306*((I306+J306)/6)*K306,2)) | M306: =IF(L306="","",IF(AND(L306>=3.5,H306=1),"Сильный признак",IF(AND(L306>=2,H306=1),"Рабочий признак",IF(H306=1,"Слабый признак","Отсутствует")))) | N306: Конкурентная норма с высоким влиянием; включить в минимальный состав NotaCode

Sheet 04_Кано
A1: 04. Классификация признаков по модели Кано
A2: Классифицируйте требования к цифровому товару: что обязательно, что прямо повышает удовлетворенность, а что создает эффект привлекательности
A6: ID требования | B6: Функция / признак товара | C6: Пользовательская задача | D6: Доказательства с сайтов | E6: Категория Кано | F6: Вес 1–5 | G6: Кол-во конкурентов с признаком | H6: Доля конкурентов | I6: Средняя сила реализации 0–5 | J6: Интерпретация | K6: Решение для своего товара | L6: Ответственный | M6: Примечание
A7: R001 | B7: Описание диаграммы текстом (DSL) | C7: Быстро создавать и версионировать диаграммы как код | D7: Главные страницы PlantUML, Mermaid, Mermaid Chart; «Diagram-as-code» в тарифе Free Eraser; «Diagram as code» на lucid.co/lucidchart. Категория Кано - экспертная классификация по распространённости и роли признака (опрос не проводился) | E7: Обязательное | F7: 5 | G7: 5 | H7: =IF(G7="","",IFERROR(G7/MAX(1,COUNTIF('01_Конкуренты'!$B\$7:$B\$36,"?*")),"")) | I7: 5 | J7: =IF(B7="","",IF(E7="Обязательное",IF(H7>=0.6,"Минимальный рыночный стандарт","Потенциальный обязательный разрыв"),IF(E7="Линейное",IF(H7>=0.5,"Конкурентная норма с влиянием на выбор","Зона усиления ценности"),IF(E7="Привлекательное",IF(H7<0.5,"Зона дифференциации","Переходит в ожидаемую норму"),IF(E7="Безразличное","Не делать при дефиците ресурсов",IF(E7="Обратное","Исключить или проверить риск отторжения","Требует проверки")))))) | K7: Включить в минимальный состав NotaCode | L7: К. А. Хаджинова | M7: Отсутствие снижает удовлетворённость; обязательно включить в MVP NotaCode
A8: R002 | B8: Бесплатный доступ или Free-тариф | C8: Начать работу без оплаты | D8: Открытый код или тариф Free на страницах 8 из 8 конкурентов. Категория Кано - экспертная классификация по распространённости и роли признака (опрос не проводился) | E8: Обязательное | F8: 5 | G8: 8 | H8: =IF(G8="","",IFERROR(G8/MAX(1,COUNTIF('01_Конкуренты'!$B\$7:$B\$36,"?*")),"")) | I8: 5 | J8: =IF(B8="","",IF(E8="Обязательное",IF(H8>=0.6,"Минимальный рыночный стандарт","Потенциальный обязательный разрыв"),IF(E8="Линейное",IF(H8>=0.5,"Конкурентная норма с влиянием на выбор","Зона усиления ценности"),IF(E8="Привлекательное",IF(H8<0.5,"Зона дифференциации","Переходит в ожидаемую норму"),IF(E8="Безразличное","Не делать при дефиците ресурсов",IF(E8="Обратное","Исключить или проверить риск отторжения","Требует проверки")))))) | K8: Включить в минимальный состав NotaCode | L8: К. А. Хаджинова | M8: Отсутствие снижает удовлетворённость; обязательно включить в MVP NotaCode
A9: R003 | B9: Платная подписка по тарифным уровням | C9: Получить расширенные возможности за оплату | D9: Страницы тарифов Mermaid Chart, Storm, Lucidchart, Eraser, Whimsical. Категория Кано - экспертная классификация по распространённости и роли признака (опрос не проводился) | E9: Линейное | F9: 4 | G9: 5 | H9: =IF(G9="","",IFERROR(G9/MAX(1,COUNTIF('01_Конкуренты'!$B\$7:$B\$36,"?*")),"")) | I9: 5 | J9: =IF(B9="","",IF(E9="Обязательное",IF(H9>=0.6,"Минимальный рыночный стандарт","Потенциальный обязательный разрыв"),IF(E9="Линейное",IF(H9>=0.5,"Конкурентная норма с влиянием на выбор","Зона усиления ценности"),IF(E9="Привлекательное",IF(H9<0.5,"Зона дифференциации","Переходит в ожидаемую норму"),IF(E9="Безразличное","Не делать при дефиците ресурсов",IF(E9="Обратное","Исключить или проверить риск отторжения","Требует проверки")))))) | K9: Реализовать на уровне рынка | L9: К. А. Хаджинова | M9: Линейное влияние: чем лучше реализовано, тем выше оценка NotaCode
A10: R004 | B10: Открытая страница тарифов | C10: Понять цену и состав тарифа до регистрации | D10: Страницы тарифов (01.10.2026). Категория Кано - экспертная классификация по распространённости и роли признака (опрос не проводился) | E10: Обязательное | F10: 5 | G10: 5 | H10: =IF(G10="","",IFERROR(G10/MAX(1,COUNTIF('01_Конкуренты'!$B\$7:$B\$36,"?*")),"")) | I10: 5 | J10: =IF(B10="","",IF(E10="Обязательное",IF(H10>=0.6,"Минимальный рыночный стандарт","Потенциальный обязательный разрыв"),IF(E10="Линейное",IF(H10>=0.5,"Конкурентная норма с влиянием на выбор","Зона усиления ценности"),IF(E10="Привлекательное",IF(H10<0.5,"Зона дифференциации","Переходит в ожидаемую норму"),IF(E10="Безразличное","Не делать при дефиците ресурсов",IF(E10="Обратное","Исключить или проверить риск отторжения","Требует проверки")))))) | K10: Включить в минимальный состав NotaCode | L10: К. А. Хаджинова | M10: Отсутствие снижает удовлетворённость; обязательно включить в MVP NotaCode
A11: R005 | B11: Корпоративный тариф (Enterprise или on-prem) | C11: Подключить организацию целиком | D11: Enterprise по запросу на страницах тарифов; Storm: on-prem от 990 тыс. руб. в год. Категория Кано - экспертная классификация по распространённости и роли признака (опрос не проводился) | E11: Безразличное | F11: 2 | G11: 4 | H11: =IF(G11="","",IFERROR(G11/MAX(1,COUNTIF('01_Конкуренты'!$B\$7:$B\$36,"?*")),"")) | I11: 5 | J11: =IF(B11="","",IF(E11="Обязательное",IF(H11>=0.6,"Минимальный рыночный стандарт","Потенциальный обязательный разрыв"),IF(E11="Линейное",IF(H11>=0.5,"Конкурентная норма с влиянием на выбор","Зона усиления ценности"),IF(E11="Привлекательное",IF(H11<0.5,"Зона дифференциации","Переходит в ожидаемую норму"),IF(E11="Безразличное","Не делать при дефиците ресурсов",IF(E11="Обратное","Исключить или проверить риск отторжения","Требует проверки")))))) | K11: Не приоритет для сегмента студентов и аналитиков | L11: К. А. Хаджинова | M11: Слабое влияние на выбор; исключить из приоритетного плана
A12: R006 | B12: Скидка или цена при годовой оплате | C12: Снизить стоимость при долгом использовании | D12: Цены «billed annually» (Mermaid Chart, Lucidchart, Eraser), скидка 20 % (Storm). Категория Кано - экспертная классификация по распространённости и роли признака (опрос не проводился) | E12: Линейное | F12: 3 | G12: 4 | H12: =IF(G12="","",IFERROR(G12/MAX(1,COUNTIF('01_Конкуренты'!$B\$7:$B\$36,"?*")),"")) | I12: 5 | J12: =IF(B12="","",IF(E12="Обязательное",IF(H12>=0.6,"Минимальный рыночный стандарт","Потенциальный обязательный разрыв"),IF(E12="Линейное",IF(H12>=0.5,"Конкурентная норма с влиянием на выбор","Зона усиления ценности"),IF(E12="Привлекательное",IF(H12<0.5,"Зона дифференциации","Переходит в ожидаемую норму"),IF(E12="Безразличное","Не делать при дефиците ресурсов",IF(E12="Обратное","Исключить или проверить риск отторжения","Требует проверки")))))) | K12: Реализовать на уровне рынка | L12: К. А. Хаджинова | M12: Линейное влияние: чем лучше реализовано, тем выше оценка NotaCode
A13: R007 | B13: Пробный период платного тарифа | C13: Проверить платные функции до оплаты | D13: FAQ Lucidchart: пробный период 7 дней. Категория Кано - экспертная классификация по распространённости и роли признака (опрос не проводился) | E13: Безразличное | F13: 2 | G13: 1 | H13: =IF(G13="","",IFERROR(G13/MAX(1,COUNTIF('01_Конкуренты'!$B\$7:$B\$36,"?*")),"")) | I13: 5 | J13: =IF(B13="","",IF(E13="Обязательное",IF(H13>=0.6,"Минимальный рыночный стандарт","Потенциальный обязательный разрыв"),IF(E13="Линейное",IF(H13>=0.5,"Конкурентная норма с влиянием на выбор","Зона усиления ценности"),IF(E13="Привлекательное",IF(H13<0.5,"Зона дифференциации","Переходит в ожидаемую норму"),IF(E13="Безразличное","Не делать при дефиците ресурсов",IF(E13="Обратное","Исключить или проверить риск отторжения","Требует проверки")))))) | K13: Не приоритет для сегмента студентов и аналитиков | L13: К. А. Хаджинова | M13: Слабое влияние на выбор; исключить из приоритетного плана
A14: R008 | B14: Бесплатные гости или зрители | C14: Показать диаграмму без оплаты за каждого читателя | D14: Unlimited viewer seats (Mermaid Chart Premium); 100 гостей на участника (Storm); unlimited guests (Eraser, Whimsical). Категория Кано - экспертная классификация по распространённости и роли признака (опрос не проводился) | E14: Привлекательное | F14: 3 | G14: 4 | H14: =IF(G14="","",IFERROR(G14/MAX(1,COUNTIF('01_Конкуренты'!$B\$7:$B\$36,"?*")),"")) | I14: 5 | J14: =IF(B14="","",IF(E14="Обязательное",IF(H14>=0.6,"Минимальный рыночный стандарт","Потенциальный обязательный разрыв"),IF(E14="Линейное",IF(H14>=0.5,"Конкурентная норма с влиянием на выбор","Зона усиления ценности"),IF(E14="Привлекательное",IF(H14<0.5,"Зона дифференциации","Переходит в ожидаемую норму"),IF(E14="Безразличное","Не делать при дефиците ресурсов",IF(E14="Обратное","Исключить или проверить риск отторжения","Требует проверки")))))) | K14: Рассмотреть как дифференциатор Pro | L14: К. А. Хаджинова | M14: Дифференциатор; добавляет ценность при реализации; кандидат для Pro
A15: R009 | B15: ИИ-генерация или ИИ-помощник | C15: Ускорить создание диаграммы по описанию | D15: ИИ-кредиты (Mermaid Chart); ИИ-ассистент (Storm); Lucid AI; Eraser AI; ИИ в Whimsical. Категория Кано - экспертная классификация по распространённости и роли признака (опрос не проводился) | E15: Привлекательное | F15: 4 | G15: 5 | H15: =IF(G15="","",IFERROR(G15/MAX(1,COUNTIF('01_Конкуренты'!$B\$7:$B\$36,"?*")),"")) | I15: 5 | J15: =IF(B15="","",IF(E15="Обязательное",IF(H15>=0.6,"Минимальный рыночный стандарт","Потенциальный обязательный разрыв"),IF(E15="Линейное",IF(H15>=0.5,"Конкурентная норма с влиянием на выбор","Зона усиления ценности"),IF(E15="Привлекательное",IF(H15<0.5,"Зона дифференциации","Переходит в ожидаемую норму"),IF(E15="Безразличное","Не делать при дефиците ресурсов",IF(E15="Обратное","Исключить или проверить риск отторжения","Требует проверки")))))) | K15: Рассмотреть как дифференциатор Pro | L15: К. А. Хаджинова | M15: Дифференциатор; добавляет ценность при реализации; кандидат для Pro
A16: R010 | B16: Интеграции с другими сервисами | C16: Встроить инструмент в рабочие процессы | D16: Разделы и упоминания интеграций на страницах 8 из 8 конкурентов. Категория Кано - экспертная классификация по распространённости и роли признака (опрос не проводился) | E16: Линейное | F16: 4 | G16: 8 | H16: =IF(G16="","",IFERROR(G16/MAX(1,COUNTIF('01_Конкуренты'!$B\$7:$B\$36,"?*")),"")) | I16: 3.33 | J16: =IF(B16="","",IF(E16="Обязательное",IF(H16>=0.6,"Минимальный рыночный стандарт","Потенциальный обязательный разрыв"),IF(E16="Линейное",IF(H16>=0.5,"Конкурентная норма с влиянием на выбор","Зона усиления ценности"),IF(E16="Привлекательное",IF(H16<0.5,"Зона дифференциации","Переходит в ожидаемую норму"),IF(E16="Безразличное","Не делать при дефиците ресурсов",IF(E16="Обратное","Исключить или проверить риск отторжения","Требует проверки")))))) | K16: Реализовать на уровне рынка | L16: К. А. Хаджинова | M16: Линейное влияние: чем лучше реализовано, тем выше оценка NotaCode
A17: R011 | B17: API или платформа разработчика | C17: Автоматизировать генерацию диаграмм | D17: API Mermaid; пункт API в меню Mermaid Chart; API в Enterprise Storm; Developer platform Lucidchart; API calls Eraser. Категория Кано - экспертная классификация по распространённости и роли признака (опрос не проводился) | E17: Привлекательное | F17: 3 | G17: 5 | H17: =IF(G17="","",IFERROR(G17/MAX(1,COUNTIF('01_Конкуренты'!$B\$7:$B\$36,"?*")),"")) | I17: 5 | J17: =IF(B17="","",IF(E17="Обязательное",IF(H17>=0.6,"Минимальный рыночный стандарт","Потенциальный обязательный разрыв"),IF(E17="Линейное",IF(H17>=0.5,"Конкурентная норма с влиянием на выбор","Зона усиления ценности"),IF(E17="Привлекательное",IF(H17<0.5,"Зона дифференциации","Переходит в ожидаемую норму"),IF(E17="Безразличное","Не делать при дефиците ресурсов",IF(E17="Обратное","Исключить или проверить риск отторжения","Требует проверки")))))) | K17: Рассмотреть как дифференциатор Pro | L17: К. А. Хаджинова | M17: Дифференциатор; добавляет ценность при реализации; кандидат для Pro
A18: R012 | B18: Открытый код и сообщество | C18: Доверять инструменту и расширять его | D18: GitHub API, 30.09.2026; лицензия Apache 2.0 у draw.io. Категория Кано - экспертная классификация по распространённости и роли признака (опрос не проводился) | E18: Привлекательное | F18: 4 | G18: 3 | H18: =IF(G18="","",IFERROR(G18/MAX(1,COUNTIF('01_Конкуренты'!$B\$7:$B\$36,"?*")),"")) | I18: 3.33 | J18: =IF(B18="","",IF(E18="Обязательное",IF(H18>=0.6,"Минимальный рыночный стандарт","Потенциальный обязательный разрыв"),IF(E18="Линейное",IF(H18>=0.5,"Конкурентная норма с влиянием на выбор","Зона усиления ценности"),IF(E18="Привлекательное",IF(H18<0.5,"Зона дифференциации","Переходит в ожидаемую норму"),IF(E18="Безразличное","Не делать при дефиците ресурсов",IF(E18="Обратное","Исключить или проверить риск отторжения","Требует проверки")))))) | K18: Рассмотреть как дифференциатор Pro | L18: К. А. Хаджинова | M18: Дифференциатор; добавляет ценность при реализации; кандидат для Pro
... A35: R029 | B35: Признаки развития (ИИ-помощник, MCP, новые функции) | C35: Видеть, что продукт развивается | D35: MCP-интеграция (Storm); метки NEW: Lucid AI, Developer platform (Lucidchart); ИИ-кредиты (Mermaid Chart); AI-first (Eraser). Категория Кано - экспертная классификация по распространённости и роли признака (опрос не проводился) | E35: Привлекательное | F35: 3 | G35: 4 | H35: =IF(G35="","",IFERROR(G35/MAX(1,COUNTIF('01_Конкуренты'!$B\$7:$B\$36,"?*")),"")) | I35: 3.33 | J35: =IF(B35="","",IF(E35="Обязательное",IF(H35>=0.6,"Минимальный рыночный стандарт","Потенциальный обязательный разрыв"),IF(E35="Линейное",IF(H35>=0.5,"Конкурентная норма с влиянием на выбор","Зона усиления ценности"),IF(E35="Привлекательное",IF(H35<0.5,"Зона дифференциации","Переходит в ожидаемую норму"),IF(E35="Безразличное","Не делать при дефиците ресурсов",IF(E35="Обратное","Исключить или проверить риск отторжения","Требует проверки")))))) | K35: Рассмотреть как дифференциатор Pro | L35: К. А. Хаджинова | M35: Дифференциатор; добавляет ценность при реализации; кандидат для Pro
A36: R030 | B36: Несколько нотаций (UML, BPMN, ERD) в одном инструменте | C36: Работать с разными нотациями без смены инструмента | D36: Lucidchart: UML-, BPMN-шаблоны и ERD markup (lucid.co/lucidchart) | E36: Привлекательное | F36: 5 | G36: 1 | H36: =IF(G36="","",IFERROR(G36/MAX(1,COUNTIF('01_Конкуренты'!$B\$7:$B\$36,"?*")),"")) | J36: =IF(B36="","",IF(E36="Обязательное",IF(H36>=0.6,"Минимальный рыночный стандарт","Потенциальный обязательный разрыв"),IF(E36="Линейное",IF(H36>=0.5,"Конкурентная норма с влиянием на выбор","Зона усиления ценности"),IF(E36="Привлекательное",IF(H36<0.5,"Зона дифференциации","Переходит в ожидаемую норму"),IF(E36="Безразличное","Не делать при дефиците ресурсов",IF(E36="Обратное","Исключить или проверить риск отторжения","Требует проверки")))))) | K36: Рассмотреть как дифференциатор: полный набор нотаций проекта | L36: К. А. Хаджинова | M36: Дифференциатор; добавляет ценность при реализации; кандидат для Pro
A37: R031 | B37: Нотации IDEF0, DFD, сети Петри | C37: Строить диаграммы по учебным и отраслевым стандартам | D37: На просмотренных страницах 8 конкурентов не найдены (IDEF упомянут в блоге Storm) | E37: Привлекательное | F37: 5 | G37: 0 | H37: =IF(G37="","",IFERROR(G37/MAX(1,COUNTIF('01_Конкуренты'!$B\$7:$B\$36,"?*")),"")) | J37: =IF(B37="","",IF(E37="Обязательное",IF(H37>=0.6,"Минимальный рыночный стандарт","Потенциальный обязательный разрыв"),IF(E37="Линейное",IF(H37>=0.5,"Конкурентная норма с влиянием на выбор","Зона усиления ценности"),IF(E37="Привлекательное",IF(H37<0.5,"Зона дифференциации","Переходит в ожидаемую норму"),IF(E37="Безразличное","Не делать при дефиците ресурсов",IF(E37="Обратное","Исключить или проверить риск отторжения","Требует проверки")))))) | K37: Дифференциатор NotaCode: у конкурентов не найден | L37: К. А. Хаджинова | M37: Дифференциатор; добавляет ценность при реализации; кандидат для Pro
A38: R032 | B38: Проверка правил нотации при вводе | C38: Получать подсказки об ошибках в модели | E38: Неясное | F38: 4 | H38: =IF(G38="","",IFERROR(G38/MAX(1,COUNTIF('01_Конкуренты'!$B\$7:$B\$36,"?*")),"")) | J38: =IF(B38="","",IF(E38="Обязательное",IF(H38>=0.6,"Минимальный рыночный стандарт","Потенциальный обязательный разрыв"),IF(E38="Линейное",IF(H38>=0.5,"Конкурентная норма с влиянием на выбор","Зона усиления ценности"),IF(E38="Привлекательное",IF(H38<0.5,"Зона дифференциации","Переходит в ожидаемую норму"),IF(E38="Безразличное","Не делать при дефиците ресурсов",IF(E38="Обратное","Исключить или проверить риск отторжения","Требует проверки")))))) | L38: К. А. Хаджинова | M38: Недостаточно данных; требует дополнительного исследования
A39: R033 | B39: Импорт форматов PlantUML, Mermaid, D2, draw.io, BPMN XML | C39: Перенести существующие диаграммы | E39: Неясное | F39: 4 | H39: =IF(G39="","",IFERROR(G39/MAX(1,COUNTIF('01_Конкуренты'!$B\$7:$B\$36,"?*")),"")) | J39: =IF(B39="","",IF(E39="Обязательное",IF(H39>=0.6,"Минимальный рыночный стандарт","Потенциальный обязательный разрыв"),IF(E39="Линейное",IF(H39>=0.5,"Конкурентная норма с влиянием на выбор","Зона усиления ценности"),IF(E39="Привлекательное",IF(H39<0.5,"Зона дифференциации","Переходит в ожидаемую норму"),IF(E39="Безразличное","Не делать при дефиците ресурсов",IF(E39="Обратное","Исключить или проверить риск отторжения","Требует проверки")))))) | L39: К. А. Хаджинова | M39: Недостаточно данных; требует дополнительного исследования
A40: R034 | H40: =IF(G40="","",IFERROR(G40/MAX(1,COUNTIF('01_Конкуренты'!$B\$7:$B\$36,"?*")),"")) | J40: =IF(B40="","",IF(E40="Обязательное",IF(H40>=0.6,"Минимальный рыночный стандарт","Потенциальный обязательный разрыв"),IF(E40="Линейное",IF(H40>=0.5,"Конкурентная норма с влиянием на выбор","Зона усиления ценности"),IF(E40="Привлекательное",IF(H40<0.5,"Зона дифференциации","Переходит в ожидаемую норму"),IF(E40="Безразличное","Не делать при дефиците ресурсов",IF(E40="Обратное","Исключить или проверить риск отторжения","Требует проверки"))))))
A41: R035 | H41: =IF(G41="","",IFERROR(G41/MAX(1,COUNTIF('01_Конкуренты'!$B\$7:$B\$36,"?*")),"")) | J41: =IF(B41="","",IF(E41="Обязательное",IF(H41>=0.6,"Минимальный рыночный стандарт","Потенциальный обязательный разрыв"),IF(E41="Линейное",IF(H41>=0.5,"Конкурентная норма с влиянием на выбор","Зона усиления ценности"),IF(E41="Привлекательное",IF(H41<0.5,"Зона дифференциации","Переходит в ожидаемую норму"),IF(E41="Безразличное","Не делать при дефиците ресурсов",IF(E41="Обратное","Исключить или проверить риск отторжения","Требует проверки"))))))
A42: R036 | H42: =IF(G42="","",IFERROR(G42/MAX(1,COUNTIF('01_Конкуренты'!$B\$7:$B\$36,"?*")),"")) | J42: =IF(B42="","",IF(E42="Обязательное",IF(H42>=0.6,"Минимальный рыночный стандарт","Потенциальный обязательный разрыв"),IF(E42="Линейное",IF(H42>=0.5,"Конкурентная норма с влиянием на выбор","Зона усиления ценности"),IF(E42="Привлекательное",IF(H42<0.5,"Зона дифференциации","Переходит в ожидаемую норму"),IF(E42="Безразличное","Не делать при дефиците ресурсов",IF(E42="Обратное","Исключить или проверить риск отторжения","Требует проверки"))))))
A43: R037 | H43: =IF(G43="","",IFERROR(G43/MAX(1,COUNTIF('01_Конкуренты'!$B\$7:$B\$36,"?*")),"")) | J43: =IF(B43="","",IF(E43="Обязательное",IF(H43>=0.6,"Минимальный рыночный стандарт","Потенциальный обязательный разрыв"),IF(E43="Линейное",IF(H43>=0.5,"Конкурентная норма с влиянием на выбор","Зона усиления ценности"),IF(E43="Привлекательное",IF(H43<0.5,"Зона дифференциации","Переходит в ожидаемую норму"),IF(E43="Безразличное","Не делать при дефиците ресурсов",IF(E43="Обратное","Исключить или проверить риск отторжения","Требует проверки"))))))
A44: R038 | H44: =IF(G44="","",IFERROR(G44/MAX(1,COUNTIF('01_Конкуренты'!$B\$7:$B\$36,"?*")),"")) | J44: =IF(B44="","",IF(E44="Обязательное",IF(H44>=0.6,"Минимальный рыночный стандарт","Потенциальный обязательный разрыв"),IF(E44="Линейное",IF(H44>=0.5,"Конкурентная норма с влиянием на выбор","Зона усиления ценности"),IF(E44="Привлекательное",IF(H44<0.5,"Зона дифференциации","Переходит в ожидаемую норму"),IF(E44="Безразличное","Не делать при дефиците ресурсов",IF(E44="Обратное","Исключить или проверить риск отторжения","Требует проверки"))))))
A45: R039 | H45: =IF(G45="","",IFERROR(G45/MAX(1,COUNTIF('01_Конкуренты'!$B\$7:$B\$36,"?*")),"")) | J45: =IF(B45="","",IF(E45="Обязательное",IF(H45>=0.6,"Минимальный рыночный стандарт","Потенциальный обязательный разрыв"),IF(E45="Линейное",IF(H45>=0.5,"Конкурентная норма с влиянием на выбор","Зона усиления ценности"),IF(E45="Привлекательное",IF(H45<0.5,"Зона дифференциации","Переходит в ожидаемую норму"),IF(E45="Безразличное","Не делать при дефиците ресурсов",IF(E45="Обратное","Исключить или проверить риск отторжения","Требует проверки"))))))
A46: R040 | H46: =IF(G46="","",IFERROR(G46/MAX(1,COUNTIF('01_Конкуренты'!$B\$7:$B\$36,"?*")),"")) | J46: =IF(B46="","",IF(E46="Обязательное",IF(H46>=0.6,"Минимальный рыночный стандарт","Потенциальный обязательный разрыв"),IF(E46="Линейное",IF(H46>=0.5,"Конкурентная норма с влиянием на выбор","Зона усиления ценности"),IF(E46="Привлекательное",IF(H46<0.5,"Зона дифференциации","Переходит в ожидаемую норму"),IF(E46="Безразличное","Не делать при дефиците ресурсов",IF(E46="Обратное","Исключить или проверить риск отторжения","Требует проверки"))))))
A47: R041 | H47: =IF(G47="","",IFERROR(G47/MAX(1,COUNTIF('01_Конкуренты'!$B\$7:$B\$36,"?*")),"")) | J47: =IF(B47="","",IF(E47="Обязательное",IF(H47>=0.6,"Минимальный рыночный стандарт","Потенциальный обязательный разрыв"),IF(E47="Линейное",IF(H47>=0.5,"Конкурентная норма с влиянием на выбор","Зона усиления ценности"),IF(E47="Привлекательное",IF(H47<0.5,"Зона дифференциации","Переходит в ожидаемую норму"),IF(E47="Безразличное","Не делать при дефиците ресурсов",IF(E47="Обратное","Исключить или проверить риск отторжения","Требует проверки"))))))
A48: R042 | H48: =IF(G48="","",IFERROR(G48/MAX(1,COUNTIF('01_Конкуренты'!$B\$7:$B\$36,"?*")),"")) | J48: =IF(B48="","",IF(E48="Обязательное",IF(H48>=0.6,"Минимальный рыночный стандарт","Потенциальный обязательный разрыв"),IF(E48="Линейное",IF(H48>=0.5,"Конкурентная норма с влиянием на выбор","Зона усиления ценности"),IF(E48="Привлекательное",IF(H48<0.5,"Зона дифференциации","Переходит в ожидаемую норму"),IF(E48="Безразличное","Не делать при дефиците ресурсов",IF(E48="Обратное","Исключить или проверить риск отторжения","Требует проверки"))))))
A49: R043 | H49: =IF(G49="","",IFERROR(G49/MAX(1,COUNTIF('01_Конкуренты'!$B\$7:$B\$36,"?*")),"")) | J49: =IF(B49="","",IF(E49="Обязательное",IF(H49>=0.6,"Минимальный рыночный стандарт","Потенциальный обязательный разрыв"),IF(E49="Линейное",IF(H49>=0.5,"Конкурентная норма с влиянием на выбор","Зона усиления ценности"),IF(E49="Привлекательное",IF(H49<0.5,"Зона дифференциации","Переходит в ожидаемую норму"),IF(E49="Безразличное","Не делать при дефиците ресурсов",IF(E49="Обратное","Исключить или проверить риск отторжения","Требует проверки"))))))
A50: R044 | H50: =IF(G50="","",IFERROR(G50/MAX(1,COUNTIF('01_Конкуренты'!$B\$7:$B\$36,"?*")),"")) | J50: =IF(B50="","",IF(E50="Обязательное",IF(H50>=0.6,"Минимальный рыночный стандарт","Потенциальный обязательный разрыв"),IF(E50="Линейное",IF(H50>=0.5,"Конкурентная норма с влиянием на выбор","Зона усиления ценности"),IF(E50="Привлекательное",IF(H50<0.5,"Зона дифференциации","Переходит в ожидаемую норму"),IF(E50="Безразличное","Не делать при дефиците ресурсов",IF(E50="Обратное","Исключить или проверить риск отторжения","Требует проверки"))))))
A51: R045 | H51: =IF(G51="","",IFERROR(G51/MAX(1,COUNTIF('01_Конкуренты'!$B\$7:$B\$36,"?*")),"")) | J51: =IF(B51="","",IF(E51="Обязательное",IF(H51>=0.6,"Минимальный рыночный стандарт","Потенциальный обязательный разрыв"),IF(E51="Линейное",IF(H51>=0.5,"Конкурентная норма с влиянием на выбор","Зона усиления ценности"),IF(E51="Привлекательное",IF(H51<0.5,"Зона дифференциации","Переходит в ожидаемую норму"),IF(E51="Безразличное","Не делать при дефиците ресурсов",IF(E51="Обратное","Исключить или проверить риск отторжения","Требует проверки"))))))
... A206: R200 | H206: =IF(G206="","",IFERROR(G206/MAX(1,COUNTIF('01_Конкуренты'!$B\$7:$B\$36,"?*")),"")) | J206: =IF(B206="","",IF(E206="Обязательное",IF(H206>=0.6,"Минимальный рыночный стандарт","Потенциальный обязательный разрыв"),IF(E206="Линейное",IF(H206>=0.5,"Конкурентная норма с влиянием на выбор","Зона усиления ценности"),IF(E206="Привлекательное",IF(H206<0.5,"Зона дифференциации","Переходит в ожидаемую норму"),IF(E206="Безразличное","Не делать при дефиците ресурсов",IF(E206="Обратное","Исключить или проверить риск отторжения","Требует проверки"))))))

Sheet 05_Матрица_товара
A1: 05. Определение цифрового товара
A2: Используйте этот лист для итогового синтеза: какие элементы входят в цифровой товар, какие являются обязательными, а какие формируют отличие
A6: Блок определения | B6: Вопрос для анализа | C6: Вывод по рынку | D6: Доказательства | E6: Связь с Левиттом | F6: Связь с Кано | G6: Статус для своего товара | H6: Минимальная реализация | I6: Расширенная реализация | J6: Риск исключения | K6: Решение | L6: Комментарий
A7: Целевая пользовательская задача | B7: Какую основную задачу обещает решить товар? | C7: Рынок обещает три вида задач: диаграммы из текста (PlantUML, Mermaid, Mermaid Chart, Eraser), рисование в редакторе (draw.io, Lucidchart, Whimsical), управление процессами (Storm); ИИ-генерация есть у 5 из 8 | D7: Главные страницы и страницы ИИ (01.10.2026) | E7: 1. Базовая выгода | F7: Обязательное / Линейное | G7: Принять | H7: Построение диаграммы по текстовому описанию | I7: ИИ-генерация диаграммы по описанию | J7: Низкий | K7: Обязательно | L7: Основа продукта
A8: Пользовательский сегмент | B8: Для кого товар явно предназначен по сайту конкурентов? | C8: Явные аудитории: разработчики и технические писатели (PlantUML, Mermaid), команды и бизнес-пользователи (Mermaid Chart, Lucidchart, Whimsical), процессные аналитики (Storm), инженерные команды (Eraser) | D8: Главные страницы, ЛР4 карточки | E8: 1. Базовая выгода | F8: Линейное | G8: Принять | H8: Студенты и аналитики ПО | I8: Преподаватели и команды | J8: Низкий | K8: Обязательно | L8: Сегмент NotaCode: студенты (Free), аналитики и разработчики (Pro)
A9: Родовой товар | B9: Какой минимальный цифровой объект продается: сервис, приложение, платформа, курс, кабинет, база данных, подписка? | C9: Родовой товар: онлайн-редактор с кодом диаграммы (PlantUML server, Mermaid Live), облачный SaaS (Mermaid Chart, Lucidchart, Eraser, Whimsical, Storm) или бесплатное приложение (draw.io) | D9: Страницы продуктов и тарифов | E9: 2. Родовой товар | F9: Обязательное | G9: Принять | H9: Веб-IDE «диаграммы как код» (PWA) | I9: Настольный режим и отдельный сервер | J9: Низкий | K9: Обязательно | L9: Форма поставки NotaCode — PWA
A10: Ожидаемый состав | B10: Какие функции пользователь считает нормой рынка? | C10: Ожидаемый состав: UML (4 из 8), ERD (6 из 8), экспорт (8 из 8), документация (6 из 8), вход (5 из 8), шаблоны (3 из 8) | D10: Страницы документации и продуктов | E10: 3. Ожидаемый товар | F10: Обязательное | G10: Принять | H10: UML, BPMN, ERD, экспорт PNG/SVG/PDF, документация | I10: Шаблоны, история версий | J10: Средний | K10: Включить | L10: IDEF0, DFD, сети Петри у конкурентов не найдены: отличие NotaCode
A11: Интерфейс и доступ | B11: Как организован доступ: сайт, приложение, личный кабинет, мобильная версия, интеграции? | C11: Доступ: открытый код или Free-тариф у 8 из 8; вход и личный кабинет у 5 из 8; совместная работа у 6 из 8 | D11: Главные страницы и тарифы | E11: 3. Ожидаемый товар | F11: Обязательное / Линейное | G11: Принять | H11: Работа в браузере без установки, Free-доступ | I11: Совместное редактирование | J11: Низкий | K11: Включить | L11: Коллаборация — линейное требование
A12: Оплата и тарифы | B12: Какой способ оплаты и представления тарифов является нормой? | C12: Тарифы открыты у 5 из 8: Free плюс подписка 9–20 у.е. за пользователя в месяц (Mermaid Chart 10 и 20, Lucidchart 9 и 10, Eraser 15 и 45, Whimsical 10 и 20); цены при годовой оплате у 4 из 8 | D12: Страницы тарифов (01.10.2026) | E12: 3. Ожидаемый товар | F12: Обязательное | G12: Принять | H12: Free и Pro 40 у.е. в год (48 у.е. при 4 x 12 рядом) | I12: Командный тариф за пользователя | J12: Средний | K12: Включить | L12: Цена Pro ниже минимальных тарифов конкурентов (от 9 у.е. в месяц)
A13: Поддержка и сопровождение | B13: Какой уровень поддержки включен в товар? | C13: Поддержка: документация у 6 из 8, учебный центр у Lucidchart, раздел поддержки у Whimsical; чат поддержки не проверялся | D13: Страницы документации и поддержки | E13: 3. Ожидаемый товар | F13: Линейное | G13: Принять | H13: Документация и примеры | I13: Обучающие материалы для студентов | J13: Средний | K13: Включить | L13: Документация — обязательное требование
A14: Расширение ценности | B14: Какие дополнительные функции повышают ценность: персонализация, аналитика, рекомендации, автоматизация? | C14: Расширение ценности: ИИ у 5 из 8, API у 5 из 8, интеграции у 8 из 8, история версий у 5 из 8 | D14: Страницы тарифов и продуктов | E14: 4. Расширенный товар | F14: Линейное / Привлекательное | G14: Рассмотреть | H14: ИИ-помощник и экспорт | I14: API, интеграции, история версий | J14: Средний | K14: Рассмотреть | L14: ИИ — привлекательное требование
A15: Доверие и доказательства | B15: Какие элементы подтверждают надежность: кейсы, отзывы, сертификаты, политика безопасности, гарантии? | C15: Доверие: независимые отзывы у 7 из 8, данные о числе пользователей на сайте у 4 из 8, раздел о безопасности у 6 из 8, открытый код у 3 из 8 | D15: G2, Capterra, Trustpilot, страницы сайтов | E15: 4. Расширенный товар | F15: Линейное | G15: Принять | H15: Политика конфиденциальности, примеры | I15: Открытый репозиторий, отзывы | J15: Средний | K15: Включить | L15: Пока продукт до MVP: отзывов нет
A16: Потенциальное развитие | B16: Какие будущие возможности видны по дорожной карте, интеграциям, пробным функциям, технологиям? | C16: Потенциал: ИИ-помощник и MCP (Storm), Lucid AI и платформа разработчика (Lucidchart), ИИ-кредиты (Mermaid Chart) | D16: Страницы сайтов | E16: 5. Потенциальный товар | F16: Привлекательное | G16: Рассмотреть | H16: Не требуется в минимальной версии | I16: ИИ-помощник, платформа разработчика | J16: Средний | K16: Рассмотреть | L16: Развитие после MVP
A17: Граница товара | B17: Что входит в товар, а что остается услугой, сопровождением или маркетинговым обещанием? | C17: Граница товара: у всех восьми товар — сервис или библиотека; консультации и обучение не входят в тарифы Free и Pro | D17: Страницы тарифов | E17: Все уровни | F17: Все категории | G17: Принять | H17: Сервис без консультаций | I17: Платное обучение | J17: Низкий | K17: Принять | L17: Консультации вне границы товара
A18: Формулировка товара | B18: Сформулируйте итог: цифровой товар — это… для… который решает… за счет… | C18: Рынок: цифровой товар диаграмм — онлайн-редактор или библиотека с кодом диаграммы для разработчиков и аналитиков, бесплатный доступ и платная подписка, экспорт, документация | D18: Сводка по листам 03, 04, 07 | E18: Синтез | F18: Синтез | G18: Принять | H18: Цифровой товар NotaCode — это веб-IDE «диаграммы как код» для студентов и аналитиков ПО, который решает задачу построения и проверки диаграмм UML, BPMN, ERD, IDEF0 и DFD по текстовому описанию за счёт онлайн-редактора с экспортом, бесплатного уровня Free и подписки Pro 40 у.е. в год | K18: Принять

Sheet 06_Сравнение
A1: 06. Сравнительная оценка конкурентов
A2: Оцените каждый критерий по шкале 0–5. Вес показывает влияние критерия на товарную конкурентоспособность
A6: ID критерия | B6: Группа | C6: Критерий | D6: Вес | E6: C01 | F6: C02 | G6: C03 | H6: C04 | I6: C05 | J6: C06 | K6: C07 | L6: C08 | M6: Среднее | N6: Лучший балл | O6: Лидер
A7: P01 | B7: Сущность товара | C7: На сайте ясно понятно, какой цифровой товар предлагается | D7: 5 | E7: 5 | F7: 5 | G7: 5 | H7: 5 | I7: 5 | J7: 5 | K7: 5 | L7: 5 | M7: =IFERROR(AVERAGE(E7:L7),"") | N7: =IFERROR(MAX(E7:L7),"") | O7: =IF(N7="","",IFERROR(INDEX($E\$6:$L\$6,1,MATCH(N7,E7:L7,0)),""))
A8: P02 | B8: Сущность товара | C8: Целевая пользовательская задача сформулирована конкретно | D8: 5 | E8: 4 | F8: 4 | G8: 5 | H8: 4 | I8: 4 | J8: 4 | K8: 5 | L8: 4 | M8: =IFERROR(AVERAGE(E8:L8),"") | N8: =IFERROR(MAX(E8:L8),"") | O8: =IF(N8="","",IFERROR(INDEX($E\$6:$L\$6,1,MATCH(N8,E8:L8,0)),""))
A9: P03 | B9: Сущность товара | C9: Граница товара отделена от консультаций, сопровождения и маркетинговых обещаний | D9: 4 | E9: 4 | F9: 4 | G9: 4 | H9: 4 | I9: 4 | J9: 4 | K9: 4 | L9: 3 | M9: =IFERROR(AVERAGE(E9:L9),"") | N9: =IFERROR(MAX(E9:L9),"") | O9: =IF(N9="","",IFERROR(INDEX($E\$6:$L\$6,1,MATCH(N9,E9:L9,0)),""))
A10: P04 | B10: Функциональность | C10: Ключевые функции товара раскрыты через сценарии использования | D10: 5 | E10: 4 | F10: 4 | G10: 5 | H10: 5 | I10: 4 | J10: 5 | K10: 5 | L10: 4 | M10: =IFERROR(AVERAGE(E10:L10),"") | N10: =IFERROR(MAX(E10:L10),"") | O10: =IF(N10="","",IFERROR(INDEX($E\$6:$L\$6,1,MATCH(N10,E10:L10,0)),""))
A11: P05 | B11: Функциональность | C11: Есть демонстрация интерфейса, личного кабинета или результата работы | D11: 4 | E11: 4 | F11: 4 | G11: 4 | I11: 4 | J11: 5 | K11: 4 | L11: 4 | M11: =IFERROR(AVERAGE(E11:L11),"") | N11: =IFERROR(MAX(E11:L11),"") | O11: =IF(N11="","",IFERROR(INDEX($E\$6:$L\$6,1,MATCH(N11,E11:L11,0)),""))
A12: P06 | B12: Функциональность | C12: Есть пробный доступ, демоверсия, бесплатный фрагмент или понятный вход в использование | D12: 4 | E12: 5 | F12: 5 | G12: 5 | H12: 5 | I12: 5 | J12: 5 | K12: 5 | L12: 5 | M12: =IFERROR(AVERAGE(E12:L12),"") | N12: =IFERROR(MAX(E12:L12),"") | O12: =IF(N12="","",IFERROR(INDEX($E\$6:$L\$6,1,MATCH(N12,E12:L12,0)),""))
A13: P07 | B13: Ценность | C13: Показана измеримая выгода: экономия времени, денег, снижение риска, рост результата | D13: 5 | E13: 2 | F13: 2 | G13: 4 | H13: 3 | I13: 3 | J13: 4 | K13: 4 | L13: 3 | M13: =IFERROR(AVERAGE(E13:L13),"") | N13: =IFERROR(MAX(E13:L13),"") | O13: =IF(N13="","",IFERROR(INDEX($E\$6:$L\$6,1,MATCH(N13,E13:L13,0)),""))
A14: P08 | B14: Ценность | C14: Преимущества связаны с функциями товара, а не только с рекламными обещаниями | D14: 5 | E14: 3 | F14: 3 | G14: 4 | H14: 4 | I14: 4 | J14: 5 | K14: 5 | L14: 4 | M14: =IFERROR(AVERAGE(E14:L14),"") | N14: =IFERROR(MAX(E14:L14),"") | O14: =IF(N14="","",IFERROR(INDEX($E\$6:$L\$6,1,MATCH(N14,E14:L14,0)),""))
A15: P09 | B15: Ценность | C15: Есть сравнение тарифов, комплектаций или уровней доступа | D15: 4 | E15: 2 | F15: 1 | G15: 5 | H15: 5 | I15: 2 | J15: 5 | K15: 5 | L15: 5 | M15: =IFERROR(AVERAGE(E15:L15),"") | N15: =IFERROR(MAX(E15:L15),"") | O15: =IF(N15="","",IFERROR(INDEX($E\$6:$L\$6,1,MATCH(N15,E15:L15,0)),""))
A16: P10 | B16: Доверие | C16: Есть отзывы, кейсы, примеры клиентов или подтверждения результата | D16: 4 | E16: 1 | F16: 2 | G16: 4 | H16: 4 | I16: 3 | J16: 5 | K16: 4 | L16: 4 | M16: =IFERROR(AVERAGE(E16:L16),"") | N16: =IFERROR(MAX(E16:L16),"") | O16: =IF(N16="","",IFERROR(INDEX($E\$6:$L\$6,1,MATCH(N16,E16:L16,0)),""))
A17: P11 | B17: Доверие | C17: Раскрыты безопасность, обработка данных, юридические условия, гарантии | D17: 4 | E17: 2 | F17: 2 | G17: 4 | H17: 4 | I17: 5 | J17: 5 | K17: 4 | L17: 5 | M17: =IFERROR(AVERAGE(E17:L17),"") | N17: =IFERROR(MAX(E17:L17),"") | O17: =IF(N17="","",IFERROR(INDEX($E\$6:$L\$6,1,MATCH(N17,E17:L17,0)),""))
A18: P12 | B18: Доверие | C18: Есть прозрачные контакты, реквизиты, команда или сведения о поставщике | D18: 3 | E18: 2 | F18: 3 | G18: 3 | I18: 3 | M18: =IFERROR(AVERAGE(E18:L18),"") | N18: =IFERROR(MAX(E18:L18),"") | O18: =IF(N18="","",IFERROR(INDEX($E\$6:$L\$6,1,MATCH(N18,E18:L18,0)),""))
A19: P13 | B19: Интерфейс | C19: Путь пользователя к покупке/регистрации короткий и понятный | D19: 5 | E19: 4 | F19: 5 | G19: 5 | H19: 5 | I19: 5 | J19: 5 | K19: 5 | L19: 5 | M19: =IFERROR(AVERAGE(E19:L19),"") | N19: =IFERROR(MAX(E19:L19),"") | O19: =IF(N19="","",IFERROR(INDEX($E\$6:$L\$6,1,MATCH(N19,E19:L19,0)),""))
A20: P14 | B20: Интерфейс | C20: Призыв к действию соответствует стадии выбора: узнать, попробовать, купить, запросить демо | D20: 4 | E20: 3 | F20: 3 | G20: 5 | H20: 5 | I20: 4 | J20: 5 | K20: 5 | L20: 4 | M20: =IFERROR(AVERAGE(E20:L20),"") | N20: =IFERROR(MAX(E20:L20),"") | O20: =IF(N20="","",IFERROR(INDEX($E\$6:$L\$6,1,MATCH(N20,E20:L20,0)),""))
A21: P15 | B21: Интерфейс | C21: Навигация помогает понять состав товара без лишнего поиска | D21: 4 | E21: 3 | F21: 4 | G21: 4 | H21: 4 | I21: 4 | J21: 4 | K21: 4 | L21: 4 | M21: =IFERROR(AVERAGE(E21:L21),"") | N21: =IFERROR(MAX(E21:L21),"") | O21: =IF(N21="","",IFERROR(INDEX($E\$6:$L\$6,1,MATCH(N21,E21:L21,0)),""))
A22: P16 | B22: Тарифы и оплата | C22: Цена, состав тарифа и ограничения раскрыты ясно | D22: 5 | E22: 4 | F22: 3 | G22: 5 | H22: 5 | I22: 4 | J22: 5 | K22: 5 | L22: 5 | M22: =IFERROR(AVERAGE(E22:L22),"") | N22: =IFERROR(MAX(E22:L22),"") | O22: =IF(N22="","",IFERROR(INDEX($E\$6:$L\$6,1,MATCH(N22,E22:L22,0)),""))
A23: P17 | B23: Тарифы и оплата | C23: Оплата, возврат, пробный период или условия подключения объяснены без неопределенности | D23: 4 | E23: 2 | F23: 1 | G23: 4 | H23: 4 | I23: 2 | J23: 5 | K23: 4 | L23: 4 | M23: =IFERROR(AVERAGE(E23:L23),"") | N23: =IFERROR(MAX(E23:L23),"") | O23: =IF(N23="","",IFERROR(INDEX($E\$6:$L\$6,1,MATCH(N23,E23:L23,0)),""))
A24: P18 | B24: Сопровождение | C24: Поддержка и обучение встроены в товарное предложение | D24: 3 | E24: 2 | F24: 2 | G24: 4 | H24: 3 | I24: 3 | J24: 4 | K24: 3 | L24: 4 | M24: =IFERROR(AVERAGE(E24:L24),"") | N24: =IFERROR(MAX(E24:L24),"") | O24: =IF(N24="","",IFERROR(INDEX($E\$6:$L\$6,1,MATCH(N24,E24:L24,0)),""))
A25: P19 | B25: Сопровождение | C25: Есть база знаний, вопросы и ответы, инструкции или документация | D25: 3 | E25: 5 | F25: 5 | G25: 5 | I25: 4 | J25: 4 | K25: 4 | M25: =IFERROR(AVERAGE(E25:L25),"") | N25: =IFERROR(MAX(E25:L25),"") | O25: =IF(N25="","",IFERROR(INDEX($E\$6:$L\$6,1,MATCH(N25,E25:L25,0)),""))
A26: P20 | B26: Расширение товара | C26: Есть персонализация, рекомендации, интеграции, автоматизация или аналитика | D26: 4 | E26: 4 | F26: 5 | G26: 5 | H26: 5 | I26: 5 | J26: 5 | K26: 5 | L26: 4 | M26: =IFERROR(AVERAGE(E26:L26),"") | N26: =IFERROR(MAX(E26:L26),"") | O26: =IF(N26="","",IFERROR(INDEX($E\$6:$L\$6,1,MATCH(N26,E26:L26,0)),""))
A27: P21 | B27: Расширение товара | C27: Есть признаки будущего развития товара: дорожная карта, обновления, новые функции | D27: 3 | E27: 3 | F27: 3 | G27: 4 | H27: 3 | J27: 4 | K27: 4 | L27: 3 | M27: =IFERROR(AVERAGE(E27:L27),"") | N27: =IFERROR(MAX(E27:L27),"") | O27: =IF(N27="","",IFERROR(INDEX($E\$6:$L\$6,1,MATCH(N27,E27:L27,0)),""))
A28: P22 | B28: Дифференциация | C28: Есть уникальные или редкие товарные признаки | D28: 5 | E28: 3 | F28: 3 | G28: 4 | H28: 4 | I28: 4 | J28: 4 | K28: 5 | L28: 3 | M28: =IFERROR(AVERAGE(E28:L28),"") | N28: =IFERROR(MAX(E28:L28),"") | O28: =IF(N28="","",IFERROR(INDEX($E\$6:$L\$6,1,MATCH(N28,E28:L28,0)),""))
A29: P23 | B29: Дифференциация | C29: Отличия хорошо объяснены через пользовательскую ценность | D29: 5 | E29: 2 | F29: 2 | G29: 4 | H29: 4 | I29: 4 | J29: 4 | K29: 4 | L29: 4 | M29: =IFERROR(AVERAGE(E29:L29),"") | N29: =IFERROR(MAX(E29:L29),"") | O29: =IF(N29="","",IFERROR(INDEX($E\$6:$L\$6,1,MATCH(N29,E29:L29,0)),""))
A30: P24 | B30: Рыночный стандарт | C30: На сайте закрыты обязательные требования категории | D30: 5 | E30: 4 | F30: 4 | G30: 5 | H30: 4 | I30: 5 | J30: 5 | K30: 4 | L30: 3 | M30: =IFERROR(AVERAGE(E30:L30),"") | N30: =IFERROR(MAX(E30:L30),"") | O30: =IF(N30="","",IFERROR(INDEX($E\$6:$L\$6,1,MATCH(N30,E30:L30,0)),""))
A31: P25 | B31: Рыночный стандарт | C31: Предложение не уступает большинству конкурентов по базовым ожиданиям | D31: 5 | E31: 4 | F31: 4 | G31: 5 | H31: 4 | I31: 5 | J31: 5 | K31: 4 | L31: 4 | M31: =IFERROR(AVERAGE(E31:L31),"") | N31: =IFERROR(MAX(E31:L31),"") | O31: =IF(N31="","",IFERROR(INDEX($E\$6:$L\$6,1,MATCH(N31,E31:L31,0)),""))
A32: P26 | M32: =IFERROR(AVERAGE(E32:L32),"") | N32: =IFERROR(MAX(E32:L32),"") | O32: =IF(N32="","",IFERROR(INDEX($E\$6:$L\$6,1,MATCH(N32,E32:L32,0)),""))
A33: P27 | M33: =IFERROR(AVERAGE(E33:L33),"") | N33: =IFERROR(MAX(E33:L33),"") | O33: =IF(N33="","",IFERROR(INDEX($E\$6:$L\$6,1,MATCH(N33,E33:L33,0)),""))
A34: P28 | M34: =IFERROR(AVERAGE(E34:L34),"") | N34: =IFERROR(MAX(E34:L34),"") | O34: =IF(N34="","",IFERROR(INDEX($E\$6:$L\$6,1,MATCH(N34,E34:L34,0)),""))
A35: P29 | M35: =IFERROR(AVERAGE(E35:L35),"") | N35: =IFERROR(MAX(E35:L35),"") | O35: =IF(N35="","",IFERROR(INDEX($E\$6:$L\$6,1,MATCH(N35,E35:L35,0)),""))
A36: P30 | M36: =IFERROR(AVERAGE(E36:L36),"") | N36: =IFERROR(MAX(E36:L36),"") | O36: =IF(N36="","",IFERROR(INDEX($E\$6:$L\$6,1,MATCH(N36,E36:L36,0)),""))
A37: P31 | M37: =IFERROR(AVERAGE(E37:L37),"") | N37: =IFERROR(MAX(E37:L37),"") | O37: =IF(N37="","",IFERROR(INDEX($E\$6:$L\$6,1,MATCH(N37,E37:L37,0)),""))
A38: P32 | M38: =IFERROR(AVERAGE(E38:L38),"") | N38: =IFERROR(MAX(E38:L38),"") | O38: =IF(N38="","",IFERROR(INDEX($E\$6:$L\$6,1,MATCH(N38,E38:L38,0)),""))
A39: P33 | M39: =IFERROR(AVERAGE(E39:L39),"") | N39: =IFERROR(MAX(E39:L39),"") | O39: =IF(N39="","",IFERROR(INDEX($E\$6:$L\$6,1,MATCH(N39,E39:L39,0)),""))
A40: P34 | M40: =IFERROR(AVERAGE(E40:L40),"") | N40: =IFERROR(MAX(E40:L40),"") | O40: =IF(N40="","",IFERROR(INDEX($E\$6:$L\$6,1,MATCH(N40,E40:L40,0)),""))
A41: P35 | M41: =IFERROR(AVERAGE(E41:L41),"") | N41: =IFERROR(MAX(E41:L41),"") | O41: =IF(N41="","",IFERROR(INDEX($E\$6:$L\$6,1,MATCH(N41,E41:L41,0)),""))
A42: P36 | M42: =IFERROR(AVERAGE(E42:L42),"") | N42: =IFERROR(MAX(E42:L42),"") | O42: =IF(N42="","",IFERROR(INDEX($E\$6:$L\$6,1,MATCH(N42,E42:L42,0)),""))
A43: P37 | M43: =IFERROR(AVERAGE(E43:L43),"") | N43: =IFERROR(MAX(E43:L43),"") | O43: =IF(N43="","",IFERROR(INDEX($E\$6:$L\$6,1,MATCH(N43,E43:L43,0)),""))
... A86: P80 | M86: =IFERROR(AVERAGE(E86:L86),"") | N86: =IFERROR(MAX(E86:L86),"") | O86: =IF(N86="","",IFERROR(INDEX($E\$6:$L\$6,1,MATCH(N86,E86:L86,0)),""))
A90: Итоговый взвешенный балл | E90: =IFERROR(ROUND(SUMPRODUCT($D\$7:$D\$86,E\$7:E\$86)/SUMIF(E\$7:E\$86,">=0",$D\$7:$D\$86),2),"") | F90: =IFERROR(ROUND(SUMPRODUCT($D\$7:$D\$86,F\$7:F\$86)/SUMIF(F\$7:F\$86,">=0",$D\$7:$D\$86),2),"") | G90: =IFERROR(ROUND(SUMPRODUCT($D\$7:$D\$86,G\$7:G\$86)/SUMIF(G\$7:G\$86,">=0",$D\$7:$D\$86),2),"") | H90: =IFERROR(ROUND(SUMPRODUCT($D\$7:$D\$86,H\$7:H\$86)/SUMIF(H\$7:H\$86,">=0",$D\$7:$D\$86),2),"") | I90: =IFERROR(ROUND(SUMPRODUCT($D\$7:$D\$86,I\$7:I\$86)/SUMIF(I\$7:I\$86,">=0",$D\$7:$D\$86),2),"") | J90: =IFERROR(ROUND(SUMPRODUCT($D\$7:$D\$86,J\$7:J\$86)/SUMIF(J\$7:J\$86,">=0",$D\$7:$D\$86),2),"") | K90: =IFERROR(ROUND(SUMPRODUCT($D\$7:$D\$86,K\$7:K\$86)/SUMIF(K\$7:K\$86,">=0",$D\$7:$D\$86),2),"") | L90: =IFERROR(ROUND(SUMPRODUCT($D\$7:$D\$86,L\$7:L\$86)/SUMIF(L\$7:L\$86,">=0",$D\$7:$D\$86),2),"")
A91: Интерпретация | E91: =IF(E90="","",IF(E90>=4.2,"Лидерский уровень",IF(E90>=3.5,"Сильный уровень",IF(E90>=2.5,"Средний уровень","Слабый уровень")))) | F91: =IF(F90="","",IF(F90>=4.2,"Лидерский уровень",IF(F90>=3.5,"Сильный уровень",IF(F90>=2.5,"Средний уровень","Слабый уровень")))) | G91: =IF(G90="","",IF(G90>=4.2,"Лидерский уровень",IF(G90>=3.5,"Сильный уровень",IF(G90>=2.5,"Средний уровень","Слабый уровень")))) | H91: =IF(H90="","",IF(H90>=4.2,"Лидерский уровень",IF(H90>=3.5,"Сильный уровень",IF(H90>=2.5,"Средний уровень","Слабый уровень")))) | I91: =IF(I90="","",IF(I90>=4.2,"Лидерский уровень",IF(I90>=3.5,"Сильный уровень",IF(I90>=2.5,"Средний уровень","Слабый уровень")))) | J91: =IF(J90="","",IF(J90>=4.2,"Лидерский уровень",IF(J90>=3.5,"Сильный уровень",IF(J90>=2.5,"Средний уровень","Слабый уровень")))) | K91: =IF(K90="","",IF(K90>=4.2,"Лидерский уровень",IF(K90>=3.5,"Сильный уровень",IF(K90>=2.5,"Средний уровень","Слабый уровень")))) | L91: =IF(L90="","",IF(L90>=4.2,"Лидерский уровень",IF(L90>=3.5,"Сильный уровень",IF(L90>=2.5,"Средний уровень","Слабый уровень"))))

Sheet 07_Стандарт_рынка
A1: 07. Определение рыночного стандарта
A2: Лист позволяет отделить обязательную норму рынка от зон дифференциации и спорных признаков
A6: ID признака | B6: Признак / требование | C6: Источник | D6: Уровень Левитта | E6: Категория Кано | F6: Кол-во конкурентов | G6: Доля конкурентов | H6: Средняя сила 0–5 | I6: Статус | J6: Минимальная формулировка стандарта | K6: Что проверить дополнительно | L6: Комментарий
A7: S001 | B7: Описание диаграммы текстом (DSL) | C7: Главные страницы PlantUML, Mermaid, Mermaid Chart; «Diagram-as-code» в тарифе Free Eraser; «Diagram as code» на lucid.co/lucidchart | D7: 2. Родовой товар | E7: Обязательное | F7: 5 | G7: 63% | H7: 5 | I7: Рыночный стандарт | J7: Признак есть у 5 из 8 конкурентов; входит в минимальный состав товара
A8: S002 | B8: Бесплатный доступ или Free-тариф | C8: Открытый код или тариф Free на страницах 8 из 8 конкурентов | D8: 3. Ожидаемый товар | E8: Обязательное | F8: 8 | G8: 100% | H8: 5 | I8: Рыночный стандарт | J8: Признак есть у 8 из 8 конкурентов; входит в минимальный состав товара
A9: S003 | B9: Платная подписка по тарифным уровням | C9: Страницы тарифов Mermaid Chart, Storm, Lucidchart, Eraser, Whimsical | D9: 3. Ожидаемый товар | E9: Линейное | F9: 5 | G9: 63% | H9: 5 | I9: Рыночный стандарт | J9: Признак есть у 5 из 8 конкурентов; реализовать на уровне рынка
A10: S004 | B10: Открытая страница тарифов | C10: Страницы тарифов (01.10.2026) | D10: 3. Ожидаемый товар | E10: Обязательное | F10: 5 | G10: 63% | H10: 5 | I10: Рыночный стандарт | J10: Признак есть у 5 из 8 конкурентов; входит в минимальный состав товара
A11: S005 | B11: Корпоративный тариф (Enterprise или on-prem) | C11: Enterprise по запросу на страницах тарифов; Storm: on-prem от 990 тыс. BYN в год | D11: 4. Расширенный товар | E11: Безразличное | F11: 4 | G11: 50% | H11: 5 | I11: Низкий приоритет | J11: Признак есть у 4 из 8 конкурентов; не приоритет
A12: S006 | B12: Скидка или цена при годовой оплате | C12: Цены «billed annually» (Mermaid Chart, Lucidchart, Eraser), скидка 20 % (Storm) | D12: 3. Ожидаемый товар | E12: Линейное | F12: 4 | G12: 50% | H12: 5 | I12: Формирующаяся норма | J12: Признак есть у 4 из 8 конкурентов; реализовать на уровне рынка
A13: S007 | B13: Пробный период платного тарифа | C13: FAQ Lucidchart: пробный период 7 дней | D13: 3. Ожидаемый товар | E13: Безразличное | F13: 1 | G13: 13% | H13: 5 | I13: Низкий приоритет | J13: Признак есть у 1 из 8 конкурентов; не приоритет
A14: S008 | B14: Бесплатные гости или зрители | C14: Unlimited viewer seats (Mermaid Chart Premium); 100 гостей на участника (Storm); unlimited guests (Eraser, Whimsical) | D14: 4. Расширенный товар | E14: Привлекательное | F14: 4 | G14: 50% | H14: 5 | I14: Переходит в ожидаемое | J14: Признак есть у 4 из 8 конкурентов; кандидат на дифференциацию
A15: S009 | B15: ИИ-генерация или ИИ-помощник | C15: ИИ-кредиты (Mermaid Chart); ИИ-ассистент (Storm); Lucid AI; Eraser AI; ИИ в Whimsical | D15: 4. Расширенный товар | E15: Привлекательное | F15: 5 | G15: 63% | H15: 5 | I15: Переходит в ожидаемое | J15: Признак есть у 5 из 8 конкурентов; кандидат на дифференциацию
A16: S010 | B16: Интеграции с другими сервисами | C16: Разделы и упоминания интеграций на страницах 8 из 8 конкурентов | D16: 3. Ожидаемый товар | E16: Линейное | F16: 8 | G16: 100% | H16: 3.33 | I16: Рыночный стандарт | J16: Признак есть у 8 из 8 конкурентов; реализовать на уровне рынка
A17: S011 | B17: API или платформа разработчика | C17: API Mermaid; пункт API в меню Mermaid Chart; API в Enterprise Storm; Developer platform Lucidchart; API calls Eraser | D17: 4. Расширенный товар | E17: Привлекательное | F17: 5 | G17: 63% | H17: 5 | I17: Переходит в ожидаемое | J17: Признак есть у 5 из 8 конкурентов; кандидат на дифференциацию
A18: S012 | B18: Открытый код и сообщество | C18: GitHub API, 30.09.2026; лицензия Apache 2.0 у draw.io | D18: 4. Расширенный товар | E18: Привлекательное | F18: 3 | G18: 38% | H18: 3.33 | I18: Зона дифференциации | J18: Признак есть у 3 из 8 конкурентов; кандидат на дифференциацию
... A35: S029 | B35: Признаки развития (ИИ-помощник, MCP, новые функции) | C35: MCP-интеграция (Storm); метки NEW: Lucid AI, Developer platform (Lucidchart); ИИ-кредиты (Mermaid Chart); AI-first (Eraser) | D35: 5. Потенциальный товар | E35: Привлекательное | F35: 4 | G35: 50% | H35: 3.33 | I35: Переходит в ожидаемое | J35: Признак есть у 4 из 8 конкурентов; кандидат на дифференциацию
A36: S030 | G36: =IF(F36="","",IFERROR(F36/MAX(1,COUNTIF('01_Конкуренты'!$B\$7:$B\$36,"?*")),"")) | I36: =IF(B36="","",IF(OR(E36="Обязательное",E36="Линейное"),IF(G36>=0.6,"Рыночный стандарт",IF(G36>=0.35,"Формирующаяся норма","Проверить необходимость")),IF(E36="Привлекательное",IF(G36<0.5,"Зона дифференциации","Переходит в ожидаемое"),IF(E36="Безразличное","Низкий приоритет",IF(E36="Обратное","Риск отторжения","Требует проверки")))))
A37: S031 | G37: =IF(F37="","",IFERROR(F37/MAX(1,COUNTIF('01_Конкуренты'!$B\$7:$B\$36,"?*")),"")) | I37: =IF(B37="","",IF(OR(E37="Обязательное",E37="Линейное"),IF(G37>=0.6,"Рыночный стандарт",IF(G37>=0.35,"Формирующаяся норма","Проверить необходимость")),IF(E37="Привлекательное",IF(G37<0.5,"Зона дифференциации","Переходит в ожидаемое"),IF(E37="Безразличное","Низкий приоритет",IF(E37="Обратное","Риск отторжения","Требует проверки")))))
A38: S032 | G38: =IF(F38="","",IFERROR(F38/MAX(1,COUNTIF('01_Конкуренты'!$B\$7:$B\$36,"?*")),"")) | I38: =IF(B38="","",IF(OR(E38="Обязательное",E38="Линейное"),IF(G38>=0.6,"Рыночный стандарт",IF(G38>=0.35,"Формирующаяся норма","Проверить необходимость")),IF(E38="Привлекательное",IF(G38<0.5,"Зона дифференциации","Переходит в ожидаемое"),IF(E38="Безразличное","Низкий приоритет",IF(E38="Обратное","Риск отторжения","Требует проверки")))))
A39: S033 | G39: =IF(F39="","",IFERROR(F39/MAX(1,COUNTIF('01_Конкуренты'!$B\$7:$B\$36,"?*")),"")) | I39: =IF(B39="","",IF(OR(E39="Обязательное",E39="Линейное"),IF(G39>=0.6,"Рыночный стандарт",IF(G39>=0.35,"Формирующаяся норма","Проверить необходимость")),IF(E39="Привлекательное",IF(G39<0.5,"Зона дифференциации","Переходит в ожидаемое"),IF(E39="Безразличное","Низкий приоритет",IF(E39="Обратное","Риск отторжения","Требует проверки")))))
A40: S034 | G40: =IF(F40="","",IFERROR(F40/MAX(1,COUNTIF('01_Конкуренты'!$B\$7:$B\$36,"?*")),"")) | I40: =IF(B40="","",IF(OR(E40="Обязательное",E40="Линейное"),IF(G40>=0.6,"Рыночный стандарт",IF(G40>=0.35,"Формирующаяся норма","Проверить необходимость")),IF(E40="Привлекательное",IF(G40<0.5,"Зона дифференциации","Переходит в ожидаемое"),IF(E40="Безразличное","Низкий приоритет",IF(E40="Обратное","Риск отторжения","Требует проверки")))))
A41: S035 | G41: =IF(F41="","",IFERROR(F41/MAX(1,COUNTIF('01_Конкуренты'!$B\$7:$B\$36,"?*")),"")) | I41: =IF(B41="","",IF(OR(E41="Обязательное",E41="Линейное"),IF(G41>=0.6,"Рыночный стандарт",IF(G41>=0.35,"Формирующаяся норма","Проверить необходимость")),IF(E41="Привлекательное",IF(G41<0.5,"Зона дифференциации","Переходит в ожидаемое"),IF(E41="Безразличное","Низкий приоритет",IF(E41="Обратное","Риск отторжения","Требует проверки")))))
A42: S036 | G42: =IF(F42="","",IFERROR(F42/MAX(1,COUNTIF('01_Конкуренты'!$B\$7:$B\$36,"?*")),"")) | I42: =IF(B42="","",IF(OR(E42="Обязательное",E42="Линейное"),IF(G42>=0.6,"Рыночный стандарт",IF(G42>=0.35,"Формирующаяся норма","Проверить необходимость")),IF(E42="Привлекательное",IF(G42<0.5,"Зона дифференциации","Переходит в ожидаемое"),IF(E42="Безразличное","Низкий приоритет",IF(E42="Обратное","Риск отторжения","Требует проверки")))))
A43: S037 | G43: =IF(F43="","",IFERROR(F43/MAX(1,COUNTIF('01_Конкуренты'!$B\$7:$B\$36,"?*")),"")) | I43: =IF(B43="","",IF(OR(E43="Обязательное",E43="Линейное"),IF(G43>=0.6,"Рыночный стандарт",IF(G43>=0.35,"Формирующаяся норма","Проверить необходимость")),IF(E43="Привлекательное",IF(G43<0.5,"Зона дифференциации","Переходит в ожидаемое"),IF(E43="Безразличное","Низкий приоритет",IF(E43="Обратное","Риск отторжения","Требует проверки")))))
A44: S038 | G44: =IF(F44="","",IFERROR(F44/MAX(1,COUNTIF('01_Конкуренты'!$B\$7:$B\$36,"?*")),"")) | I44: =IF(B44="","",IF(OR(E44="Обязательное",E44="Линейное"),IF(G44>=0.6,"Рыночный стандарт",IF(G44>=0.35,"Формирующаяся норма","Проверить необходимость")),IF(E44="Привлекательное",IF(G44<0.5,"Зона дифференциации","Переходит в ожидаемое"),IF(E44="Безразличное","Низкий приоритет",IF(E44="Обратное","Риск отторжения","Требует проверки")))))
A45: S039 | G45: =IF(F45="","",IFERROR(F45/MAX(1,COUNTIF('01_Конкуренты'!$B\$7:$B\$36,"?*")),"")) | I45: =IF(B45="","",IF(OR(E45="Обязательное",E45="Линейное"),IF(G45>=0.6,"Рыночный стандарт",IF(G45>=0.35,"Формирующаяся норма","Проверить необходимость")),IF(E45="Привлекательное",IF(G45<0.5,"Зона дифференциации","Переходит в ожидаемое"),IF(E45="Безразличное","Низкий приоритет",IF(E45="Обратное","Риск отторжения","Требует проверки")))))
A46: S040 | G46: =IF(F46="","",IFERROR(F46/MAX(1,COUNTIF('01_Конкуренты'!$B\$7:$B\$36,"?*")),"")) | I46: =IF(B46="","",IF(OR(E46="Обязательное",E46="Линейное"),IF(G46>=0.6,"Рыночный стандарт",IF(G46>=0.35,"Формирующаяся норма","Проверить необходимость")),IF(E46="Привлекательное",IF(G46<0.5,"Зона дифференциации","Переходит в ожидаемое"),IF(E46="Безразличное","Низкий приоритет",IF(E46="Обратное","Риск отторжения","Требует проверки")))))
A47: S041 | G47: =IF(F47="","",IFERROR(F47/MAX(1,COUNTIF('01_Конкуренты'!$B\$7:$B\$36,"?*")),"")) | I47: =IF(B47="","",IF(OR(E47="Обязательное",E47="Линейное"),IF(G47>=0.6,"Рыночный стандарт",IF(G47>=0.35,"Формирующаяся норма","Проверить необходимость")),IF(E47="Привлекательное",IF(G47<0.5,"Зона дифференциации","Переходит в ожидаемое"),IF(E47="Безразличное","Низкий приоритет",IF(E47="Обратное","Риск отторжения","Требует проверки")))))
... A206: S200 | G206: =IF(F206="","",IFERROR(F206/MAX(1,COUNTIF('01_Конкуренты'!$B\$7:$B\$36,"?*")),"")) | I206: =IF(B206="","",IF(OR(E206="Обязательное",E206="Линейное"),IF(G206>=0.6,"Рыночный стандарт",IF(G206>=0.35,"Формирующаяся норма","Проверить необходимость")),IF(E206="Привлекательное",IF(G206<0.5,"Зона дифференциации","Переходит в ожидаемое"),IF(E206="Безразличное","Низкий приоритет",IF(E206="Обратное","Риск отторжения","Требует проверки")))))

Sheet 08_Преимущества
A1: 08. Выявление конкурентных преимуществ по товару
A2: Преимущество фиксируется только при наличии доказательства с сайта, пользовательской ценности и отличия от среднего рынка
A6: ID | B6: ID конкурента | C6: Признак преимущества | D6: Доказательство / URL | E6: Уровень Левитта | F6: Категория Кано | G6: Тип преимущества | H6: Редкость 1–5 | I6: Сила 1–5 | J6: Пользовательская ценность 1–5 | K6: Качество доказательства 1–5 | L6: Индекс преимущества | M6: Вывод | N6: Как использовать для своего товара
A7: A001 | B7: C07 | C7: ИИ-генерация и diagram-as-code в одном продукте | D7: «AI for diagrams that matter»; тариф Free включает diagram-as-code и 3 ИИ-диаграммы (eraser.io, 01.10.2026) | E7: 4. Расширенный товар | F7: Привлекательное | G7: Функциональное | H7: 4 | I7: 5 | J7: 4 | K7: 5 | L7: 4.45 | M7: Сильное преимущество | N7: Использовать как ориентир: совместить ИИ-генерацию и DSL-редактор в одном Free-тарифе NotaCode
A8: A002 | B8: C04 | C8: Девять модулей процессного управления и русскоязычный рынок с тарифами в рублях | D8: stormbpmn.com и /pricing, 01.10.2026; Россия 62,99 % трафика | E8: 4. Расширенный товар | F8: Привлекательное | G8: Интеграционное | H8: 5 | I8: 4 | J8: 4 | K8: 5 | L8: 4.45 | M8: Сильное преимущество | N8: Учесть при выходе на СНГ-рынок; тарифы в местной валюте снижают барьер входа
A9: A003 | B9: C06 | C9: Глубина товара и масштаб: 100 шаблонов в Free, Visio import, SAML, Fortune 500 | D9: lucid.app/pricing/lucidchart и lucid.co/lucidchart, 01.10.2026 | E9: 4. Расширенный товар | F9: Линейное | G9: Доверительное | H9: 2 | I9: 5 | J9: 4 | K9: 5 | L9: 3.95 | M9: Потенциальное преимущество | N9: Отразить как ориентир масштаба; NotaCode начинает с минимального набора шаблонов
A10: A004 | B10: C05 | C10: Бесплатное приложение без enterprise-тарифа, privacy-first, 100M+ пользователей | D10: drawio.com, 01.10.2026; GitHub (ЛР4) | E10: 3. Ожидаемый товар | F10: Привлекательное | G10: Экономическое | H10: 3 | I10: 5 | J10: 5 | K10: 4 | L10: 4.3 | M10: Сильное преимущество | N10: Ориентир для Free-уровня: полностью бесплатно без лимитов на нотации; открытый код
A11: A005 | B11: C02 | C11: Открытая экосистема интеграций и крупнейшее сообщество (90 489 звёзд) | D11: mermaid.js.org/ecosystem; GitHub (ЛР4) | E11: 4. Расширенный товар | F11: Привлекательное | G11: Сетевой эффект | H11: 3 | I11: 5 | J11: 4 | K11: 5 | L11: 4.2 | M11: Сильное преимущество | N11: Ориентир для сообщества: развивать открытый репозиторий NotaCode с первого дня
A12: A006 | B12: C01 | C12: Широкий набор UML-диаграмм и запуск на собственном сервере | D12: plantuml.com/running и /class-diagram, 01.10.2026 | E12: 2. Родовой товар | F12: Обязательное | G12: Функциональное | H12: 3 | I12: 4 | J12: 4 | K12: 4 | L12: 3.75 | M12: Потенциальное преимущество | N12: Диаграммы UML — обязательная норма; self-hosted — дифференциатор для Enterprise NotaCode
A13: A007 | B13: C03 | C13: Прозрачные тарифы и зрители без оплаты в Premium | D13: mermaid.ai/pricing, 01.10.2026 | E13: 3. Ожидаемый товар | F13: Привлекательное | G13: Экономическое | H13: 3 | I13: 4 | J13: 4 | K13: 5 | L13: 3.95 | M13: Потенциальное преимущество | N13: Модель зрителей без оплаты применима в NotaCode для расширения охвата без дохода
A14: A008 | B14: C08 | C14: Неограниченные гости и зрители на всех тарифах | D14: whimsical.com/pricing, 01.10.2026 | E14: 4. Расширенный товар | F14: Привлекательное | G14: Экономическое | H14: 3 | I14: 3 | J14: 3 | K14: 5 | L14: 3.4 | M14: Потенциальное преимущество | N14: Неограниченные зрители на Free снижают барьер для командного использования NotaCode
A15: A009 | B15: NotaCode | C15: Полный набор нотаций UML, BPMN, ERD, IDEF0, DFD, сети Петри в одном редакторе | D15: IDEF0, DFD и сети Петри отсутствуют у всех 8 проанализированных конкурентов (листы 03, 07) | E15: 3. Ожидаемый товар / 4. Расширенный товар | F15: Привлекательное | G15: Функциональное | H15: 5 | I15: 5 | J15: 5 | K15: 4 | L15: 4.8 | M15: Сильное преимущество | N15: Главный дифференциатор NotaCode; закрыть нишу академических и инженерных нотаций
A16: A010 | L16: =IF(OR(H16="",I16="",J16="",K16=""),"",ROUND(H16*0.25+I16*0.25+J16*0.3+K16*0.2,2)) | M16: =IF(L16="","",IF(L16>=4.2,"Сильное преимущество",IF(L16>=3.4,"Потенциальное преимущество",IF(L16>=2.5,"Слабое преимущество","Не считать преимуществом"))))
A17: A011 | L17: =IF(OR(H17="",I17="",J17="",K17=""),"",ROUND(H17*0.25+I17*0.25+J17*0.3+K17*0.2,2)) | M17: =IF(L17="","",IF(L17>=4.2,"Сильное преимущество",IF(L17>=3.4,"Потенциальное преимущество",IF(L17>=2.5,"Слабое преимущество","Не считать преимуществом"))))
A18: A012 | L18: =IF(OR(H18="",I18="",J18="",K18=""),"",ROUND(H18*0.25+I18*0.25+J18*0.3+K18*0.2,2)) | M18: =IF(L18="","",IF(L18>=4.2,"Сильное преимущество",IF(L18>=3.4,"Потенциальное преимущество",IF(L18>=2.5,"Слабое преимущество","Не считать преимуществом"))))
A19: A013 | L19: =IF(OR(H19="",I19="",J19="",K19=""),"",ROUND(H19*0.25+I19*0.25+J19*0.3+K19*0.2,2)) | M19: =IF(L19="","",IF(L19>=4.2,"Сильное преимущество",IF(L19>=3.4,"Потенциальное преимущество",IF(L19>=2.5,"Слабое преимущество","Не считать преимуществом"))))
A20: A014 | L20: =IF(OR(H20="",I20="",J20="",K20=""),"",ROUND(H20*0.25+I20*0.25+J20*0.3+K20*0.2,2)) | M20: =IF(L20="","",IF(L20>=4.2,"Сильное преимущество",IF(L20>=3.4,"Потенциальное преимущество",IF(L20>=2.5,"Слабое преимущество","Не считать преимуществом"))))
A21: A015 | L21: =IF(OR(H21="",I21="",J21="",K21=""),"",ROUND(H21*0.25+I21*0.25+J21*0.3+K21*0.2,2)) | M21: =IF(L21="","",IF(L21>=4.2,"Сильное преимущество",IF(L21>=3.4,"Потенциальное преимущество",IF(L21>=2.5,"Слабое преимущество","Не считать преимуществом"))))
A22: A016 | L22: =IF(OR(H22="",I22="",J22="",K22=""),"",ROUND(H22*0.25+I22*0.25+J22*0.3+K22*0.2,2)) | M22: =IF(L22="","",IF(L22>=4.2,"Сильное преимущество",IF(L22>=3.4,"Потенциальное преимущество",IF(L22>=2.5,"Слабое преимущество","Не считать преимуществом"))))
A23: A017 | L23: =IF(OR(H23="",I23="",J23="",K23=""),"",ROUND(H23*0.25+I23*0.25+J23*0.3+K23*0.2,2)) | M23: =IF(L23="","",IF(L23>=4.2,"Сильное преимущество",IF(L23>=3.4,"Потенциальное преимущество",IF(L23>=2.5,"Слабое преимущество","Не считать преимуществом"))))
A24: A018 | L24: =IF(OR(H24="",I24="",J24="",K24=""),"",ROUND(H24*0.25+I24*0.25+J24*0.3+K24*0.2,2)) | M24: =IF(L24="","",IF(L24>=4.2,"Сильное преимущество",IF(L24>=3.4,"Потенциальное преимущество",IF(L24>=2.5,"Слабое преимущество","Не считать преимуществом"))))
A25: A019 | L25: =IF(OR(H25="",I25="",J25="",K25=""),"",ROUND(H25*0.25+I25*0.25+J25*0.3+K25*0.2,2)) | M25: =IF(L25="","",IF(L25>=4.2,"Сильное преимущество",IF(L25>=3.4,"Потенциальное преимущество",IF(L25>=2.5,"Слабое преимущество","Не считать преимуществом"))))
A26: A020 | L26: =IF(OR(H26="",I26="",J26="",K26=""),"",ROUND(H26*0.25+I26*0.25+J26*0.3+K26*0.2,2)) | M26: =IF(L26="","",IF(L26>=4.2,"Сильное преимущество",IF(L26>=3.4,"Потенциальное преимущество",IF(L26>=2.5,"Слабое преимущество","Не считать преимуществом"))))
A27: A021 | L27: =IF(OR(H27="",I27="",J27="",K27=""),"",ROUND(H27*0.25+I27*0.25+J27*0.3+K27*0.2,2)) | M27: =IF(L27="","",IF(L27>=4.2,"Сильное преимущество",IF(L27>=3.4,"Потенциальное преимущество",IF(L27>=2.5,"Слабое преимущество","Не считать преимуществом"))))
... A206: A200 | L206: =IF(OR(H206="",I206="",J206="",K206=""),"",ROUND(H206*0.25+I206*0.25+J206*0.3+K206*0.2,2)) | M206: =IF(L206="","",IF(L206>=4.2,"Сильное преимущество",IF(L206>=3.4,"Потенциальное преимущество",IF(L206>=2.5,"Слабое преимущество","Не считать преимуществом"))))

Sheet 09_Дашборд
A1: 09. Дашборд анализа цифрового товара
A2: Сводные показатели обновляются после заполнения листов. Используйте лист для контроля полноты анализа и обсуждения итоговых выводов
A4: Показатель | B4: Значение | C4: Норма контроля | D4: Комментарий | F4: Категория Кано | G4: Количество | H4: Доля | J4: Уровень Левитта | K4: Кол-во признаков | L4: Средняя оценка
A5: Конкурентов в анализе | B5: =COUNTIF('01_Конкуренты'!$B\$7:$B\$36,"?*") | C5: 5–12 | D5: Меньше 5 — риск случайных выводов | F5: Обязательное | G5: =COUNTIF('04_Кано'!$E\$7:$E\$206,F5) | H5: =IFERROR(G5/SUM($G\$5:$G\$10),"") | J5: 1. Базовая выгода | K5: =COUNTIF('03_Левитт'!$D\$7:$D\$306,J5) | L5: =IFERROR(AVERAGEIF('03_Левитт'!$D\$7:$D\$306,J5,'03_Левитт'!$L\$7:$L\$306),"")
A6: Проверенных страниц | B6: =COUNTIF('02_Карта_сайтов'!$C\$7:$C\$206,"?*") | C6: 30+ | D6: Желательно несколько типов страниц по каждому конкуренту | F6: Линейное | G6: =COUNTIF('04_Кано'!$E\$7:$E\$206,F6) | H6: =IFERROR(G6/SUM($G\$5:$G\$10),"") | J6: 2. Родовой товар | K6: =COUNTIF('03_Левитт'!$D\$7:$D\$306,J6) | L6: =IFERROR(AVERAGEIF('03_Левитт'!$D\$7:$D\$306,J6,'03_Левитт'!$L\$7:$L\$306),"")
A7: Признаков по Левитту | B7: =COUNTIF('03_Левитт'!$E\$7:$E\$306,"?*") | C7: 40+ | D7: Нужны признаки по всем уровням товара | F7: Привлекательное | G7: =COUNTIF('04_Кано'!$E\$7:$E\$206,F7) | H7: =IFERROR(G7/SUM($G\$5:$G\$10),"") | J7: 3. Ожидаемый товар | K7: =COUNTIF('03_Левитт'!$D\$7:$D\$306,J7) | L7: =IFERROR(AVERAGEIF('03_Левитт'!$D\$7:$D\$306,J7,'03_Левитт'!$L\$7:$L\$306),"")
A8: Требований по Кано | B8: =COUNTIF('04_Кано'!$B\$7:$B\$206,"?*") | C8: 25+ | D8: Обязательные и привлекательные признаки должны быть разделены | F8: Безразличное | G8: =COUNTIF('04_Кано'!$E\$7:$E\$206,F8) | H8: =IFERROR(G8/SUM($G\$5:$G\$10),"") | J8: 4. Расширенный товар | K8: =COUNTIF('03_Левитт'!$D\$7:$D\$306,J8) | L8: =IFERROR(AVERAGEIF('03_Левитт'!$D\$7:$D\$306,J8,'03_Левитт'!$L\$7:$L\$306),"")
A9: Рыночных стандартов | B9: =COUNTIF('07_Стандарт_рынка'!$I\$7:$I\$206,"Рыночный стандарт") | C9: по факту | D9: Это минимальная планка цифрового товара | F9: Обратное | G9: =COUNTIF('04_Кано'!$E\$7:$E\$206,F9) | H9: =IFERROR(G9/SUM($G\$5:$G\$10),"") | J9: 5. Потенциальный товар | K9: =COUNTIF('03_Левитт'!$D\$7:$D\$306,J9) | L9: =IFERROR(AVERAGEIF('03_Левитт'!$D\$7:$D\$306,J9,'03_Левитт'!$L\$7:$L\$306),"")
A10: Зон дифференциации | B10: =COUNTIF('07_Стандарт_рынка'!$I\$7:$I\$206,"Зона дифференциации") | C10: по факту | D10: Это пространство для конкурентного отличия | F10: Неясное | G10: =COUNTIF('04_Кано'!$E\$7:$E\$206,F10) | H10: =IFERROR(G10/SUM($G\$5:$G\$10),"")
A11: Сильных преимуществ | B11: =COUNTIF('08_Преимущества'!$M\$7:$M\$206,"Сильное преимущество") | C11: по факту | D11: Проверять доказательства и воспроизводимость
A14: Итоговые баллы конкурентов
A15: C01 | B15: C02 | C15: C03 | D15: C04 | E15: C05 | F15: C06 | G15: C07 | H15: C08
A16: ='06_Сравнение'!E90 | B16: ='06_Сравнение'!F90 | C16: ='06_Сравнение'!G90 | D16: ='06_Сравнение'!H90 | E16: ='06_Сравнение'!I90 | F16: ='06_Сравнение'!J90 | G16: ='06_Сравнение'!K90 | H16: ='06_Сравнение'!L90
A17: ='06_Сравнение'!E91 | B17: ='06_Сравнение'!F91 | C17: ='06_Сравнение'!G91 | D17: ='06_Сравнение'!H91 | E17: ='06_Сравнение'!I91 | F17: ='06_Сравнение'!J91 | G17: ='06_Сравнение'!K91 | H17: ='06_Сравнение'!L91
A20: Итоговые управленческие выводы
A21: 1. Минимальный состав цифрового товара | B21: Минимальный состав: бесплатный доступ (8 из 8), экспорт (8 из 8), интеграции (8 из 8), UML (4 из 8), ERD (6 из 8), документация (6 из 8), открытая страница тарифов (5 из 8)
A22: 2. Признаки, которые нельзя игнорировать | B22: Нельзя игнорировать: Free-тариф, экспорт, понятные тарифы с ценой за пользователя в месяц, документация, ИИ-генерация (5 из 8) и интеграции
A23: 3. Главные зоны дифференциации | B23: Зоны дифференциации NotaCode: IDEF0, DFD и сети Петри на просмотренных сайтах не найдены; полный набор UML, BPMN, ERD найден только у Lucidchart; тарифы в рублях - только у Storm
A24: 4. Лучшие практики конкурентов | B24: Лучшие практики: прозрачные тарифы с ИИ-лимитами (Eraser, Mermaid Chart), шаблоны в бесплатном тарифе (Lucidchart), зрители без оплаты (Whimsical, Mermaid Chart), открытая экосистема (Mermaid)
A25: 5. Риски копирования конкурентов без проверки спроса | B25: Риск: копировать тарифы за пользователя без проверки спроса студентов; цена Pro 40 у.е. в год ниже минимальных тарифов конкурентов (от 9 у.е. в месяц), её нужно подтвердить опросом

Sheet 99_Справочники
A1: 99. Справочники для заполнения
A2: Лист содержит подсказки по классификациям, используемым в шаблоне
A4: Справочник | B4: Значение | C4: Пояснение
A5: Уровни Левитта | B5: 1. Базовая выгода | C5: Главная задача и ценность для пользователя
A6: Уровни Левитта | B6: 2. Родовой товар | C6: Минимальная форма товара: сервис, приложение, кабинет, база, подписка
A7: Уровни Левитта | B7: 3. Ожидаемый товар | C7: То, что пользователь считает нормой категории
A8: Уровни Левитта | B8: 4. Расширенный товар | C8: Дополнительные элементы, повышающие ценность и доверие
A9: Уровни Левитта | B9: 5. Потенциальный товар | C9: Будущие функции, развитие, интеграции, персонализация, данные
A10: Категории Кано | B10: Обязательное | C10: Отсутствие вызывает неудовлетворенность; наличие обычно воспринимается как норма
A11: Категории Кано | B11: Линейное | C11: Чем лучше реализовано, тем выше удовлетворенность и готовность выбрать товар
A12: Категории Кано | B12: Привлекательное | C12: Не ожидается большинством, но создает положительное отличие
A13: Категории Кано | B13: Безразличное | C13: Слабо влияет на выбор и удовлетворенность
A14: Категории Кано | B14: Обратное | C14: Может снижать удовлетворенность или создавать отторжение
A15: Категории Кано | B15: Неясное | C15: Недостаточно данных для классификации
... A24: Типы преимуществ | B24: Контентное | C24: Качество, глубина, эксклюзивность или регулярность материалов

Sheet 98_Журнал
A1: Журнал рабочей копии: источники, правила, ограничения
A3: Раздел | B3: Код | C3: Содержание
A4: Исправление шаблона | B4: Д-1 | C4: Лист 06_Сравнение, строки 90 и 91 (итоговый балл и интерпретация): формулы столбцов F-L ссылались на столбец E (баллы C01), поэтому итог был одинаковым (3,28) у всех конкурентов. Ссылки заменены на собственные столбцы (E-L); логика формулы сохранена
A5: Исправление шаблона | B5: Д-2 | C5: Лист 06_Сравнение, столбец O (Лидер) в пустых строках P26-P80: MAX пустого диапазона даёт 0, MATCH не находит значение, результат #Н/Д. Формула обёрнута в IFERROR (при пустых баллах - пустая ячейка)
A6: Источники | B6: И-1 | C6: Страницы 8 конкурентов (главные, тарифы, документация, интеграции, шаблоны, безопасность, блог): автоматическое извлечение текста 01.10.2026 (Материалы_собранные/sajty_konkurentov_stranicy_2026-10-01.json) и чтение во встроенном браузере (Lucidchart, тарифы Mermaid Chart); данные ЛР1-ЛР4 от 30.09.2026
A7: Выборка | B7: В-1 | C7: 8 компаний из 22 части A (поле «Переходит в части B и C»). Тип конкурента - итоговый уровень из части A
A8: Правило | B8: П-1 | C8: Признак засчитывается, если он найден на просмотренных страницах; отсутствие на просмотренных страницах не доказывает отсутствия у продукта (значения занижают долю)
A9: Правило | B9: П-2 | C9: Достоверность в 02_Карта_сайтов: 5 - страница прочитана целиком (тарифы, Lucidchart, Mermaid Chart) или данные GitHub API; 4 - автоматическое извлечение текста
A10: Правило | B10: П-3 | C10: 03_Левитт: сила реализации 3, если признак явно описан на странице (цена, тариф, функция), 2 - найден по ключевым словам; понятность 3 для SaaS-сайтов с отдельными разделами, 2 для остальных; влияние на ценность 1-5 - по типу признака
A11: Правило | B11: П-4 | C11: Категории Кано присвоены экспертно (по распространённости и роли признака для студентов и аналитиков ПО); опрос по методу Кано не проводился. Требования без данных помечены «Неясное»
A12: Правило | B12: П-5 | C12: 06_Сравнение: баллы 0-5 по 25 критериям поставлены по просмотренным страницам; пусто - критерий не подтверждён страницами. Итог - взвешенный балл шаблона
A13: Правило | B13: П-6 | C13: 08_Преимущества: редкость, сила, ценность и качество доказательства - экспертные оценки 1-5 по просмотренным страницам и данным ЛР4
A14: Нормы дашборда | B14: К-1 | C14: Страниц: 40 (норма 30+); признаков по Левитту: 153 (норма 40+); требований по Кано: 33 (норма 25+)
... A16: Ограничения | B16: О-1 | C16: Оценки экспертные; страницы просмотрены с одного устройства
